Workbook
Name solver_adj: 'Formação de Preço de Venda'!$G$14
Name solver_cvg: 0.0001
Name solver_drv: 1
Name solver_eng: 1
Name solver_est: 1
Name solver_itr: 2147483647
Name solver_mip: 2147483647
Name solver_mni: 30
Name solver_mrt: 0.075
Name solver_msl: 2
Name solver_neg: 1
Name solver_nod: 2147483647
Name solver_num: 0
Name solver_nwt: 1
Name solver_opt: 'Formação de Preço de Venda'!$BH$14
Name solver_pre: 0.000001
Name solver_rbv: 1
Name solver_rlx: 2
Name solver_rsd: 0
Name solver_scl: 1
Name solver_sho: 2
Name solver_ssz: 100
Name solver_tim: 2147483647
Name solver_tol: 0.01
Name solver_typ: 3
Name solver_val: 0.2
Name solver_ver: 3

Sheet Formação de Preço de Venda
AZ2: =SUM(AZ14:AZ455) -> 5867.17 | BA2: =SUM(BA14:BA455) -> 0 | BB2: =SUM(BB14:BB455) -> 0 | BC2: =SUM(BC14:BC455) -> 0 | BD2: =SUM(BD14:BD455) -> 910.3367 | BE2: =SUM(BE14:BE455) -> 650.2405 | BF2: =SUM(BF14:BF455) -> 7427.7472 | BG2: =SUM(BG14:BG455) -> 5577.0628 | BH2: =BG2/I2 -> #DIV/0!
A3: Preencher | B3: Fórmula | F3: Fórmula | G3: Preencher | H3: Preencher | I3: Fórmula | AZ3: Fórmula | BA3: Fórmula | BE3: Fórmula | BG3: Fórmula | BH3: Fórmula
A4: Código | B4: Descrição do Produto | D4: Tipo | E4: Tempo de ciclo (Qtd Hora) | F4: Preço de | G4: Preço | H4: Qtd | I4: Faturamento | AZ4: Decomposição do Preço Calculado
J5: 1. Materia prima | N5: TTL (1) | O5: 2.Processo | R5: TTL (2) | S5: 3.Embalagem | W5: TTL (3) | X5: 4.Refugo | Y5: TTL (4) | Z5: 5.Outras custos Industriais | AD5: TTL (5) | AE5: 6.Mark up | AF5: TTL (6) | AG5: 7.Outros Despesas (Indireto) - 15% | AL5: TTL (7) | AN5: 8.Impostos(Fora) | AP5: TTL (8) | AQ5: 9.Impostos(Dentro) | AT5: TTL (9) | AU5: 10.Comissao | AV5: TTL (10) | AW5: TTL (11) PRECO MINIMO SUGERIDO | BA5: Impostos
F6: Venda Mínimo | G6: Praticado | J6: Insumo | K6: Frete | L6: TCIF | M6: FTI | O6: Mao de obra direta (Hora/homem) | S6: Balde | T6: Pallet | U6: Filme | V6: Chapa tex | X6: Perda no processo | Z6: Energia | AA6: Agua | AB6: Equipamento Maquina | AC6: 0 | AE6: 0.25 | AG6: Mao de obra Ind | AH6: Frete Expedicao | AI6: Aluguel 2 | AJ6: IPTU | AK6: Comunicacao | AL6: 0.15 | AM6: CUSTO LIQUIDO TOTAL | AN6: IRPJ | AO6: CSLL | AQ6: ICMS (FMPES+UEA) | AR6: PIS | AS6: COFINS | AY6: DIFERENCA | BA6: PIS | BB6: COFINS | BC6: IPI | BD6: ICMS | BE6: Comissão | BF6: Custos Total | BG6: R$ Lucro | BH6: % Lucro Efetivo
S7: Galao | T7: 110 | U7: 110 | V7: 110 | AA7: Custo mês | AB7: Custo mês | AC7: 0 | AE7: 0.25 | AL7: 0 | AY7: CUSTO TOTAL | AZ7: Custos Diretos
S8: Balde | T8: 36 | U8: 36 | V8: 36 | AA8: 4000 | AB8: 3800 | AC8: 0 | AY8: VS
S9: Latao | T9: 40 | U9: 40 | V9: 36 | AA9: Qtd hora mês | AB9: Qtd hora mês | AC9: Qtd hora mês | AY9: PRECO PRATICADO
S10: Lata | T10: 36 | U10: 36 | V10: 36 | AA10: 192 | AB10: 192 | AC10: 192
O11: Operador | P11: Lider | Q11: Logistica | S11: Latinha | T11: 240 | U11: 110 | V11: 110 | Z11: KWH | AA11: C/ Hora | AB11: C/ Hora | AC11: C/ Hora
L12: 0.01 | M12: 0.01 | O12: 18.1 | P12: 28.29 | Q12: 28.29 | T12: 25 | U12: 43 | V12: 12 | X12: 0.01 | Z12: 0.83 | AA12: =AA8/AA10 -> 20.833333 | AB12: =AB8/AB10 -> 19.791667 | AC12: =AC8/AC10 -> 0 | AG12: =SUM('Despesas Fixas'!F46:F50,Salários!J7,Salários!J21) -> 65735.04 | AH12: =1740+800 -> 2540 | AI12: ='Despesas Fixas'!F9+'Despesas Fixas'!F10 -> 16980 | AJ12: =1410 -> 1410 | AK12: =388+61.61+15000+3212 -> 18661.61 | AN12: 0.012 | AO12: 0.0108 | AQ12: 0.0835 | AR12: 0 | AS12: 0 | AU12: 0.05 | BA12: 0 | BB12: 0 | BC12: 0 | BD12: 0.07 | BE12: 0.05
O13: 2 | P13: 1 | Q13: 1
A14: PRD00001 | B14: =IFERROR(VLOOKUP(A14,'Tabela de Produtos'!A:B,2,0),"Preencher Cód. Produto") -> BRAZIMIL MASSA CORRIDA 4,0KG | D14: Galao | E14: 100 | F14: =IF(A14=0,0,VLOOKUP(A14,'Tabela de Produtos'!A:W,23,0)) -> 8.3 | G14: 15.99 | H14: 1 | I14: =G14*H14 -> 15.99 | J14: =VLOOKUP(B14,'Tabela de Produtos'!B:M,12,FALSE()) -> 3 | K14: =VLOOKUP(B14,'Tabela de Produtos'!B:P,15,FALSE()) -> 1.24 | L14: =J14*1% -> 0.03 | M14: =J14*1% -> 0.03 | N14: =J14+K14+L14+M14 -> 4.3 | O14: =($O$12/E14)*$O$13 -> 0.362 | P14: =($P$12/E14)*$P$13 -> 0.2829 | Q14: =($Q$12/E14)*$Q$13 -> 0.2829 | R14: =O14+P14+Q14 -> 0.9278 | S14: =VLOOKUP(B14,'Tabela de Produtos'!B:N,13,FALSE()) -> 3.06 | T14: =$T$12/$T$7 -> 0.22727273 | U14: =$U$12/$U$7 -> 0.39090909 | V14: =$V$12/$V$7 -> 0.10909091 | W14: =S14+T14+U14+V14 -> 3.7872727 | X14: =(N14+R14+W14)*1% -> 0.090150727 | Y14: =X14 -> 0.090150727 | Z14: =$Z$12/E14 -> 0.0083 | AA14: =$AA$12/E14 -> 0.20833333 | AB14: =$AB$12/E14 -> 0.19791667 | AC14: =$AC$12/E14 -> 0 | AD14: =Z14+AA14+AB14+AC14 -> 0.41455 | AE14: =(AD14+Y14+W14+R14+N14)*$AE$7 -> 2.3799434 | AF14: =AE14 -> 2.3799434 | AL14: =(AD14+Y14+W14+R14+N14)*$AL$7 -> 0 | AM14: =AL14+AF14+AD14+Y14+W14+R14+N14 -> 11.899717 | AN14: =AM14*$AN$12 -> 0.1427966 | AO14: =AM14*$AO$12 -> 0.12851694 | AP14: =AO14+AN14 -> 0.27131354 | AQ14: =AM14*$AQ$12 -> 0.99362635 | AR14: =AM14*$AR$12 -> 0 | AS14: =AM14*$AS$12 -> 0 | AT14: =AQ14+AR14+AS14 -> 0.99362635 | AU14: =AM14*$AU$12 -> 0.59498584 | AV14: =AU14 -> 0.59498584 | AW14: =AM14+AP14+AT14+AV14 -> 13.759643 | AX14: =AY14/AW14 -> 0.16209414 | AY14: =I14-AW14 -> 2.2303574 | AZ14: =IFERROR(H14*VLOOKUP(A14,'Tabela de Produtos'!A:Q,17,0),0) -> 7.3 | BA14: =$I14*BA$12 -> 0 | BB14: =$I14*BB$12 -> 0 | BC14: =$I14*BC$12 -> 0 | BD14: =$I14*BD$12 -> 1.1193 | BE14: =I14*$BE$12 -> 0.7995 | BF14: =SUM(AZ14:BE14) -> 9.2188 | BG14: =I14-BF14 -> 6.7712 | BH14: =IF(F14="Cadastrar Ficha de Produção",0,IFERROR(BG14/I14,0)) -> 0.42346467
A15: PRD00002 | B15: =IFERROR(VLOOKUP(A15,'Tabela de Produtos'!A:B,2,0),"Preencher Cód. Produto") -> BRAZIMIL MASSA CORRIDA 20,0 KG | D15: Balde | E15: 33 | F15: =IF(A15=0,0,VLOOKUP(A15,'Tabela de Produtos'!A:W,23,0)) -> 33.88 | G15: 37.5 | H15: 1 | I15: =G15*H15 -> 37.5 | J15: =VLOOKUP(B15,'Tabela de Produtos'!B:M,12,FALSE()) -> 15 | K15: =VLOOKUP(B15,'Tabela de Produtos'!B:P,15,FALSE()) -> 6.2 | L15: =J15*1% -> 0.15 | M15: =J15*1% -> 0.15 | N15: =J15+K15+L15+M15 -> 21.5 | O15: =0.54*$O$13 -> 1.08 | P15: =0.85*$P$13 -> 0.85 | Q15: =0.85*$Q$13 -> 0.85 | R15: =O15+P15+Q15 -> 2.78 | S15: =VLOOKUP(B15,'Tabela de Produtos'!B:N,13,FALSE()) -> 8.61 | T15: =$T$12/$T$8 -> 0.69444444 | U15: =$U$12/$U$8 -> 1.1944444 | V15: =$V$12/$V$8 -> 0.33333333 | W15: =S15+T15+U15+V15 -> 10.832222 | X15: =(N15+R15+W15)*1% -> 0.35112222 | Y15: =X15 -> 0.35112222 | Z15: =$Z$12/E15 -> 0.025151515 | AA15: =$AA$12/E15 -> 0.63131313 | AB15: =$AB$12/E15 -> 0.59974747 | AC15: =$AC$12/E15 -> 0 | AD15: =Z15+AA15+AB15+AC15 -> 1.2562121 | AE15: =(AD15+Y15+W15+R15+N15)*$AE$7 -> 9.1798891 | AF15: =AE15 -> 9.1798891 | AL15: =(AD15+Y15+W15+R15+N15)*$AL$7 -> 0 | AM15: =AL15+AF15+AD15+Y15+W15+R15+N15 -> 45.899446 | AN15: =AM15*$AN$12 -> 0.55079335 | AO15: =AM15*$AO$12 -> 0.49571401 | AP15: =AO15+AN15 -> 1.0465074 | AQ15: =AM15*$AQ$12 -> 3.8326037 | AR15: =AM15*$AR$12 -> 0 | AS15: =AM15*$AS$12 -> 0 | AT15: =AQ15+AR15+AS15 -> 3.8326037 | AU15: =AM15*$AU$12 -> 2.2949723 | AV15: =AU15 -> 2.2949723 | AW15: =AM15+AP15+AT15+AV15 -> 53.073529 | AX15: =AY15/AW15 -> -0.29343308 | AY15: =I15-AW15 -> -15.573529 | AZ15: =IFERROR(H15*VLOOKUP(A15,'Tabela de Produtos'!A:Q,17,0),0) -> 29.81 | BA15: =$I15*BA$12 -> 0 | BB15: =$I15*BB$12 -> 0 | BC15: =$I15*BC$12 -> 0 | BD15: =$I15*BD$12 -> 2.625 | BE15: =I15*$BE$12 -> 1.875 | BF15: =SUM(AZ15:BE15) -> 34.31 | BG15: =I15-BF15 -> 3.19 | BH15: =IF(F15="Cadastrar Ficha de Produção",0,IFERROR(BG15/I15,0)) -> 0.085066667
A16: PRD00003 | B16: =IFERROR(VLOOKUP(A16,'Tabela de Produtos'!A:B,2,0),"Preencher Cód. Produto") -> BRAZIMIL SELADOR ACRILICO 3L | D16: Galao | E16: 100 | F16: =IF(A16=0,0,VLOOKUP(A16,'Tabela de Produtos'!A:W,23,0)) -> 7.54 | G16: 17.99 | H16: 1 | I16: =G16*H16 -> 17.99 | J16: =VLOOKUP(B16,'Tabela de Produtos'!B:M,12,FALSE()) -> 2.64 | K16: =VLOOKUP(B16,'Tabela de Produtos'!B:P,15,FALSE()) -> 0.93 | L16: =J16*1% -> 0.0264 | M16: =J16*1% -> 0.0264 | N16: =J16+K16+L16+M16 -> 3.6228 | O16: =($O$12/E16)*$O$13 -> 0.362 | P16: =($P$12/E16)*$P$13 -> 0.2829 | Q16: =($Q$12/E16)*$Q$13 -> 0.2829 | R16: =O16+P16+Q16 -> 0.9278 | S16: =VLOOKUP(B16,'Tabela de Produtos'!B:N,13,FALSE()) -> 3.06 | T16: =$T$12/$T$7 -> 0.22727273 | U16: =$U$12/$U$7 -> 0.39090909 | V16: =$V$12/$V$7 -> 0.10909091 | W16: =S16+T16+U16+V16 -> 3.7872727 | X16: =(N16+R16+W16)*1% -> 0.083378727 | Y16: =X16 -> 0.083378727 | Z16: =$Z$12/E16 -> 0.0083 | AA16: =$AA$12/E16 -> 0.20833333 | AB16: =$AB$12/E16 -> 0.19791667 | AC16: =$AC$12/E16 -> 0 | AD16: =Z16+AA16+AB16+AC16 -> 0.41455 | AE16: =(AD16+Y16+W16+R16+N16)*$AE$7 -> 2.2089504 | AF16: =AE16 -> 2.2089504 | AL16: =(AD16+Y16+W16+R16+N16)*$AL$7 -> 0 | AM16: =AL16+AF16+AD16+Y16+W16+R16+N16 -> 11.044752 | AN16: =AM16*$AN$12 -> 0.13253702 | AO16: =AM16*$AO$12 -> 0.11928332 | AP16: =AO16+AN16 -> 0.25182034 | AQ16: =AM16*$AQ$12 -> 0.92223678 | AR16: =AM16*$AR$12 -> 0 | AS16: =AM16*$AS$12 -> 0 | AT16: =AQ16+AR16+AS16 -> 0.92223678 | AU16: =AM16*$AU$12 -> 0.55223759 | AV16: =AU16 -> 0.55223759 | AW16: =AM16+AP16+AT16+AV16 -> 12.771047 | AX16: =AY16/AW16 -> 0.40865511 | AY16: =I16-AW16 -> 5.2189535 | AZ16: =IFERROR(H16*VLOOKUP(A16,'Tabela de Produtos'!A:Q,17,0),0) -> 6.63 | BA16: =$I16*BA$12 -> 0 | BB16: =$I16*BB$12 -> 0 | BC16: =$I16*BC$12 -> 0 | BD16: =$I16*BD$12 -> 1.2593 | BE16: =I16*$BE$12 -> 0.8995 | BF16: =SUM(AZ16:BE16) -> 8.7888 | BG16: =I16-BF16 -> 9.2012 | BH16: =IF(F16="Cadastrar Ficha de Produção",0,IFERROR(BG16/I16,0)) -> 0.51146192
A17: PRD00004 | B17: =IFERROR(VLOOKUP(A17,'Tabela de Produtos'!A:B,2,0),"Preencher Cód. Produto") -> BRAZIMIL SELADOR ACRILICO 15L | D17: Balde | E17: 28 | F17: =IF(A17=0,0,VLOOKUP(A17,'Tabela de Produtos'!A:W,23,0)) -> 30.07 | G17: 66.49 | H17: 1 | I17: =G17*H17 -> 66.49 | J17: =VLOOKUP(B17,'Tabela de Produtos'!B:M,12,FALSE()) -> 13.2 | K17: =VLOOKUP(B17,'Tabela de Produtos'!B:P,15,FALSE()) -> 4.65 | L17: =J17*1% -> 0.132 | M17: =J17*1% -> 0.132 | N17: =J17+K17+L17+M17 -> 18.114 | O17: =($O$12/E17)*$O$13 -> 1.2928571 | P17: =($P$12/E17)*$P$13 -> 1.0103571 | Q17: =($Q$12/E17)*$Q$13 -> 1.0103571 | R17: =O17+P17+Q17 -> 3.3135714 | S17: =VLOOKUP(B17,'Tabela de Produtos'!B:N,13,FALSE()) -> 8.61 | T17: =$T$12/$T$8 -> 0.69444444 | U17: =$U$12/$U$8 -> 1.1944444 | V17: =$V$12/$V$8 -> 0.33333333 | W17: =S17+T17+U17+V17 -> 10.832222 | X17: =(N17+R17+W17)*1% -> 0.32259794 | Y17: =X17 -> 0.32259794 | Z17: =$Z$12/E17 -> 0.029642857 | AA17: =$AA$12/E17 -> 0.74404762 | AB17: =$AB$12/E17 -> 0.70684524 | AC17: =$AC$12/E17 -> 0 | AD17: =Z17+AA17+AB17+AC17 -> 1.4805357 | AE17: =(AD17+Y17+W17+R17+N17)*$AE$7 -> 8.5157318 | AF17: =AE17 -> 8.5157318 | AL17: =(AD17+Y17+W17+R17+N17)*$AL$7 -> 0 | AM17: =AL17+AF17+AD17+Y17+W17+R17+N17 -> 42.578659 | AN17: =AM17*$AN$12 -> 0.51094391 | AO17: =AM17*$AO$12 -> 0.45984952 | AP17: =AO17+AN17 -> 0.97079343 | AQ17: =AM17*$AQ$12 -> 3.555318 | AR17: =AM17*$AR$12 -> 0 | AS17: =AM17*$AS$12 -> 0 | AT17: =AQ17+AR17+AS17 -> 3.555318 | AU17: =AM17*$AU$12 -> 2.128933 | AV17: =AU17 -> 2.128933 | AW17: =AM17+AP17+AT17+AV17 -> 49.233704 | AX17: =AY17/AW17 -> 0.35049763 | AY17: =I17-AW17 -> 17.256296 | AZ17: =IFERROR(H17*VLOOKUP(A17,'Tabela de Produtos'!A:Q,17,0),0) -> 26.46 | BA17: =$I17*BA$12 -> 0 | BB17: =$I17*BB$12 -> 0 | BC17: =$I17*BC$12 -> 0 | BD17: =$I17*BD$12 -> 4.6543 | BE17: =I17*$BE$12 -> 3.3245 | BF17: =SUM(AZ17:BE17) -> 34.4388 | BG17: =I17-BF17 -> 32.0512 | BH17: =IF(F17="Cadastrar Ficha de Produção",0,IFERROR(BG17/I17,0)) -> 0.48204542
A18: PRD00005 | B18: =IFERROR(VLOOKUP(A18,'Tabela de Produtos'!A:B,2,0),"Preencher Cód. Produto") -> BRAZIMIL SELADORA PARA MADEIRA 0,75L INCOLOR | F18: =IF(A18=0,0,VLOOKUP(A18,'Tabela de Produtos'!A:W,23,0)) -> Cadastrar Ficha de Produção | G18: 0 | H18: 1 | I18: =G18*H18 -> 0 | J18: =VLOOKUP(B18,'Tabela de Produtos'!B:M,12,FALSE()) -> 0 | AY18: =I18-AW18 -> 0 | AZ18: =IFERROR(H18*VLOOKUP(A18,'Tabela de Produtos'!A:Q,17,0),0) -> 0 | BA18: =$I18*BA$12 -> 0 | BB18: =$I18*BB$12 -> 0 | BC18: =$I18*BC$12 -> 0 | BD18: =$I18*BD$12 -> 0 | BE18: =I18*$BE$12 -> 0 | BF18: =SUM(AZ18:BE18) -> 0 | BG18: =I18-BF18 -> 0 | BH18: =IF(F18="Cadastrar Ficha de Produção",0,IFERROR(BG18/I18,0)) -> 0
A19: PRD00006 | B19: =IFERROR(VLOOKUP(A19,'Tabela de Produtos'!A:B,2,0),"Preencher Cód. Produto") -> BRAZIMIL SELADORA PARA MADEIRA 3L INCOLOR | D19: Galao | F19: =IF(A19=0,0,VLOOKUP(A19,'Tabela de Produtos'!A:W,23,0)) -> Cadastrar Ficha de Produção | G19: 0 | H19: 1 | I19: =G19*H19 -> 0 | J19: =VLOOKUP(B19,'Tabela de Produtos'!B:M,12,FALSE()) -> 0 | AY19: =I19-AW19 -> 0 | AZ19: =IFERROR(H19*VLOOKUP(A19,'Tabela de Produtos'!A:Q,17,0),0) -> 0 | BA19: =$I19*BA$12 -> 0 | BB19: =$I19*BB$12 -> 0 | BC19: =$I19*BC$12 -> 0 | BD19: =$I19*BD$12 -> 0 | BE19: =I19*$BE$12 -> 0 | BF19: =SUM(AZ19:BE19) -> 0 | BG19: =I19-BF19 -> 0 | BH19: =IF(F19="Cadastrar Ficha de Produção",0,IFERROR(BG19/I19,0)) -> 0
A20: PRD00007 | B20: =IFERROR(VLOOKUP(A20,'Tabela de Produtos'!A:B,2,0),"Preencher Cód. Produto") -> BRAZIMIL MASSA ACRÍLICA 4KG | D20: Galao | E20: 100 | F20: =IF(A20=0,0,VLOOKUP(A20,'Tabela de Produtos'!A:W,23,0)) -> 12.21 | G20: 19.99 | H20: 1 | I20: =G20*H20 -> 19.99 | J20: =VLOOKUP(B20,'Tabela de Produtos'!B:M,12,FALSE()) -> 6.44 | K20: =VLOOKUP(B20,'Tabela de Produtos'!B:P,15,FALSE()) -> 1.24 | L20: =J20*1% -> 0.0644 | M20: =J20*1% -> 0.0644 | N20: =J20+K20+L20+M20 -> 7.8088 | O20: =($O$12/E20)*$O$13 -> 0.362 | P20: =($P$12/E20)*$P$13 -> 0.2829 | Q20: =($Q$12/E20)*$Q$13 -> 0.2829 | R20: =O20+P20+Q20 -> 0.9278 | S20: =VLOOKUP(B20,'Tabela de Produtos'!B:N,13,FALSE()) -> 3.06 | T20: =$T$12/$T$7 -> 0.22727273 | U20: =$U$12/$U$7 -> 0.39090909 | V20: =$V$12/$V$7 -> 0.10909091 | W20: =S20+T20+U20+V20 -> 3.7872727 | X20: =(N20+R20+W20)*1% -> 0.12523873 | Y20: =X20 -> 0.12523873 | Z20: =$Z$12/E20 -> 0.0083 | AA20: =$AA$12/E20 -> 0.20833333 | AB20: =$AB$12/E20 -> 0.19791667 | AC20: =$AC$12/E20 -> 0 | AD20: =Z20+AA20+AB20+AC20 -> 0.41455 | AE20: =(AD20+Y20+W20+R20+N20)*$AE$7 -> 3.2659154 | AF20: =AE20 -> 3.2659154 | AL20: =(AD20+Y20+W20+R20+N20)*$AL$7 -> 0 | AM20: =AL20+AF20+AD20+Y20+W20+R20+N20 -> 16.329577 | AN20: =AM20*$AN$12 -> 0.19595492 | AO20: =AM20*$AO$12 -> 0.17635943 | AP20: =AO20+AN20 -> 0.37231435 | AQ20: =AM20*$AQ$12 -> 1.3635197 | AR20: =AM20*$AR$12 -> 0 | AS20: =AM20*$AS$12 -> 0 | AT20: =AQ20+AR20+AS20 -> 1.3635197 | AU20: =AM20*$AU$12 -> 0.81647884 | AV20: =AU20 -> 0.81647884 | AW20: =AM20+AP20+AT20+AV20 -> 18.88189 | AX20: =AY20/AW20 -> 0.05868641 | AY20: =I20-AW20 -> 1.1081103 | AZ20: =IFERROR(H20*VLOOKUP(A20,'Tabela de Produtos'!A:Q,17,0),0) -> 10.74 | BA20: =$I20*BA$12 -> 0 | BB20: =$I20*BB$12 -> 0 | BC20: =$I20*BC$12 -> 0 | BD20: =$I20*BD$12 -> 1.3993 | BE20: =I20*$BE$12 -> 0.9995 | BF20: =SUM(AZ20:BE20) -> 13.1388 | BG20: =I20-BF20 -> 6.8512 | BH20: =IF(F20="Cadastrar Ficha de Produção",0,IFERROR(BG20/I20,0)) -> 0.34273137
A21: PRD00008 | B21: =IFERROR(VLOOKUP(A21,'Tabela de Produtos'!A:B,2,0),"Preencher Cód. Produto") -> BRAZIMIL MASSA ACRÍLICA 20KG | D21: Balde | E21: 33 | F21: =IF(A21=0,0,VLOOKUP(A21,'Tabela de Produtos'!A:W,23,0)) -> 53.43 | G21: 72.9 | H21: 1 | I21: =G21*H21 -> 72.9 | J21: =VLOOKUP(B21,'Tabela de Produtos'!B:M,12,FALSE()) -> 32.2 | K21: =VLOOKUP(B21,'Tabela de Produtos'!B:P,15,FALSE()) -> 6.2 | L21: =J21*1% -> 0.322 | M21: =J21*1% -> 0.322 | N21: =J21+K21+L21+M21 -> 39.044 | O21: =0.54*$O$13 -> 1.08 | P21: =0.85*$P$13 -> 0.85 | Q21: =0.85*$Q$13 -> 0.85 | R21: =O21+P21+Q21 -> 2.78 | S21: =VLOOKUP(B21,'Tabela de Produtos'!B:N,13,FALSE()) -> 8.61 | T21: =$T$12/$T$8 -> 0.69444444 | U21: =$U$12/$U$8 -> 1.1944444 | V21: =$V$12/$V$8 -> 0.33333333 | W21: =S21+T21+U21+V21 -> 10.832222 | X21: =(N21+R21+W21)*1% -> 0.52656222 | Y21: =X21 -> 0.52656222 | Z21: =$Z$12/E21 -> 0.025151515 | AA21: =$AA$12/E21 -> 0.63131313 | AB21: =$AB$12/E21 -> 0.59974747 | AC21: =$AC$12/E21 -> 0 | AD21: =Z21+AA21+AB21+AC21 -> 1.2562121 | AE21: =(AD21+Y21+W21+R21+N21)*$AE$7 -> 13.609749 | AF21: =AE21 -> 13.609749 | AL21: =(AD21+Y21+W21+R21+N21)*$AL$7 -> 0 | AM21: =AL21+AF21+AD21+Y21+W21+R21+N21 -> 68.048746 | AN21: =AM21*$AN$12 -> 0.81658495 | AO21: =AM21*$AO$12 -> 0.73492645 | AP21: =AO21+AN21 -> 1.5515114 | AQ21: =AM21*$AQ$12 -> 5.6820703 | AR21: =AM21*$AR$12 -> 0 | AS21: =AM21*$AS$12 -> 0 | AT21: =AQ21+AR21+AS21 -> 5.6820703 | AU21: =AM21*$AU$12 -> 3.4024373 | AV21: =AU21 -> 3.4024373 | AW21: =AM21+AP21+AT21+AV21 -> 78.684765 | AX21: =AY21/AW21 -> -0.07351823 | AY21: =I21-AW21 -> -5.7847647 | AZ21: =IFERROR(H21*VLOOKUP(A21,'Tabela de Produtos'!A:Q,17,0),0) -> 47.01 | BA21: =$I21*BA$12 -> 0 | BB21: =$I21*BB$12 -> 0 | BC21: =$I21*BC$12 -> 0 | BD21: =$I21*BD$12 -> 5.103 | BE21: =I21*$BE$12 -> 3.645 | BF21: =SUM(AZ21:BE21) -> 55.758 | BG21: =I21-BF21 -> 17.142 | BH21: =IF(F21="Cadastrar Ficha de Produção",0,IFERROR(BG21/I21,0)) -> 0.23514403
A22: PRD00009 | B22: =IFERROR(VLOOKUP(A22,'Tabela de Produtos'!A:B,2,0),"Preencher Cód. Produto") -> BRAZIMIL LÁTEX ECONÔMICO INT FOSCO 3L BRANCO NEVE | D22: Galao | E22: 100 | F22: =IF(A22=0,0,VLOOKUP(A22,'Tabela de Produtos'!A:W,23,0)) -> 9.1 | G22: 17.99 | H22: 1 | I22: =G22*H22 -> 17.99 | J22: =VLOOKUP(B22,'Tabela de Produtos'!B:M,12,FALSE()) -> 3.63 | K22: =VLOOKUP(B22,'Tabela de Produtos'!B:P,15,FALSE()) -> 0.93 | L22: =J22*1% -> 0.0363 | M22: =J22*1% -> 0.0363 | N22: =J22+K22+L22+M22 -> 4.6326 | O22: =($O$12/E22)*$O$13 -> 0.362 | P22: =($P$12/E22)*$P$13 -> 0.2829 | Q22: =($Q$12/E22)*$Q$13 -> 0.2829 | R22: =O22+P22+Q22 -> 0.9278 | S22: =VLOOKUP(B22,'Tabela de Produtos'!B:N,13,FALSE()) -> 3.44 | T22: =$T$12/$T$7 -> 0.22727273 | U22: =$U$12/$U$7 -> 0.39090909 | V22: =$V$12/$V$7 -> 0.10909091 | W22: =S22+T22+U22+V22 -> 4.1672727 | X22: =(N22+R22+W22)*1% -> 0.097276727 | Y22: =X22 -> 0.097276727 | Z22: =$Z$12/E22 -> 0.0083 | AA22: =$AA$12/E22 -> 0.20833333 | AB22: =$AB$12/E22 -> 0.19791667 | AC22: =$AC$12/E22 -> 0 | AD22: =Z22+AA22+AB22+AC22 -> 0.41455 | AE22: =(AD22+Y22+W22+R22+N22)*$AE$7 -> 2.5598749 | AF22: =AE22 -> 2.5598749 | AL22: =(AD22+Y22+W22+R22+N22)*$AL$7 -> 0 | AM22: =AL22+AF22+AD22+Y22+W22+R22+N22 -> 12.799374 | AN22: =AM22*$AN$12 -> 0.15359249 | AO22: =AM22*$AO$12 -> 0.13823324 | AP22: =AO22+AN22 -> 0.29182573 | AQ22: =AM22*$AQ$12 -> 1.0687478 | AR22: =AM22*$AR$12 -> 0 | AS22: =AM22*$AS$12 -> 0 | AT22: =AQ22+AR22+AS22 -> 1.0687478 | AU22: =AM22*$AU$12 -> 0.63996872 | AV22: =AU22 -> 0.63996872 | AW22: =AM22+AP22+AT22+AV22 -> 14.799917 | AX22: =AY22/AW22 -> 0.2155474 | AY22: =I22-AW22 -> 3.1900835 | AZ22: =IFERROR(H22*VLOOKUP(A22,'Tabela de Produtos'!A:Q,17,0),0) -> 8 | BA22: =$I22*BA$12 -> 0 | BB22: =$I22*BB$12 -> 0 | BC22: =$I22*BC$12 -> 0 | BD22: =$I22*BD$12 -> 1.2593 | BE22: =I22*$BE$12 -> 0.8995 | BF22: =SUM(AZ22:BE22) -> 10.1588 | BG22: =I22-BF22 -> 7.8312 | BH22: =IF(F22="Cadastrar Ficha de Produção",0,IFERROR(BG22/I22,0)) -> 0.4353085
A23: PRD00010 | B23: =IFERROR(VLOOKUP(A23,'Tabela de Produtos'!A:B,2,0),"Preencher Cód. Produto") -> BRAZIMIL LÁTEX ECONÔMICO INT FOSCO 3L BRANCO GELO | D23: Galao | E23: 100 | F23: =IF(A23=0,0,VLOOKUP(A23,'Tabela de Produtos'!A:W,23,0)) -> 10.39 | G23: 17.99 | H23: 1 | I23: =G23*H23 -> 17.99 | J23: =VLOOKUP(B23,'Tabela de Produtos'!B:M,12,FALSE()) -> 4.77 | K23: =VLOOKUP(B23,'Tabela de Produtos'!B:P,15,FALSE()) -> 0.93 | L23: =J23*1% -> 0.0477 | M23: =J23*1% -> 0.0477 | N23: =J23+K23+L23+M23 -> 5.7954 | O23: =($O$12/E23)*$O$13 -> 0.362 | P23: =($P$12/E23)*$P$13 -> 0.2829 | Q23: =($Q$12/E23)*$Q$13 -> 0.2829 | R23: =O23+P23+Q23 -> 0.9278 | S23: =VLOOKUP(B23,'Tabela de Produtos'!B:N,13,FALSE()) -> 3.44 | T23: =$T$12/$T$7 -> 0.22727273 | U23: =$U$12/$U$7 -> 0.39090909 | V23: =$V$12/$V$7 -> 0.10909091 | W23: =S23+T23+U23+V23 -> 4.1672727 | X23: =(N23+R23+W23)*1% -> 0.10890473 | Y23: =X23 -> 0.10890473 | Z23: =$Z$12/E23 -> 0.0083 | AA23: =$AA$12/E23 -> 0.20833333 | AB23: =$AB$12/E23 -> 0.19791667 | AC23: =$AC$12/E23 -> 0 | AD23: =Z23+AA23+AB23+AC23 -> 0.41455 | AE23: =(AD23+Y23+W23+R23+N23)*$AE$7 -> 2.8534819 | AF23: =AE23 -> 2.8534819 | AL23: =(AD23+Y23+W23+R23+N23)*$AL$7 -> 0 | AM23: =AL23+AF23+AD23+Y23+W23+R23+N23 -> 14.267409 | AN23: =AM23*$AN$12 -> 0.17120891 | AO23: =AM23*$AO$12 -> 0.15408802 | AP23: =AO23+AN23 -> 0.32529693 | AQ23: =AM23*$AQ$12 -> 1.1913287 | AR23: =AM23*$AR$12 -> 0 | AS23: =AM23*$AS$12 -> 0 | AT23: =AQ23+AR23+AS23 -> 1.1913287 | AU23: =AM23*$AU$12 -> 0.71337047 | AV23: =AU23 -> 0.71337047 | AW23: =AM23+AP23+AT23+AV23 -> 16.497405 | AX23: =AY23/AW23 -> 0.090474506 | AY23: =I23-AW23 -> 1.4925946 | AZ23: =IFERROR(H23*VLOOKUP(A23,'Tabela de Produtos'!A:Q,17,0),0) -> 9.14 | BA23: =$I23*BA$12 -> 0 | BB23: =$I23*BB$12 -> 0 | BC23: =$I23*BC$12 -> 0 | BD23: =$I23*BD$12 -> 1.2593 | BE23: =I23*$BE$12 -> 0.8995 | BF23: =SUM(AZ23:BE23) -> 11.2988 | BG23: =I23-BF23 -> 6.6912 | BH23: =IF(F23="Cadastrar Ficha de Produção",0,IFERROR(BG23/I23,0)) -> 0.37193997
A24: PRD00011 | B24: =IFERROR(VLOOKUP(A24,'Tabela de Produtos'!A:B,2,0),"Preencher Cód. Produto") -> BRAZIMIL LÁTEX ECONÔMICO INT FOSCO 3L AREIA | D24: Galao | E24: 100 | F24: =IF(A24=0,0,VLOOKUP(A24,'Tabela de Produtos'!A:W,23,0)) -> 10.87 | G24: 17.99 | H24: 1 | I24: =G24*H24 -> 17.99 | J24: =VLOOKUP(B24,'Tabela de Produtos'!B:M,12,FALSE()) -> 5.19 | K24: =VLOOKUP(B24,'Tabela de Produtos'!B:P,15,FALSE()) -> 0.93 | L24: =J24*1% -> 0.0519 | M24: =J24*1% -> 0.0519 | N24: =J24+K24+L24+M24 -> 6.2238 | O24: =($O$12/E24)*$O$13 -> 0.362 | P24: =($P$12/E24)*$P$13 -> 0.2829 | Q24: =($Q$12/E24)*$Q$13 -> 0.2829 | R24: =O24+P24+Q24 -> 0.9278 | S24: =VLOOKUP(B24,'Tabela de Produtos'!B:N,13,FALSE()) -> 3.44 | T24: =$T$12/$T$7 -> 0.22727273 | U24: =$U$12/$U$7 -> 0.39090909 | V24: =$V$12/$V$7 -> 0.10909091 | W24: =S24+T24+U24+V24 -> 4.1672727 | X24: =(N24+R24+W24)*1% -> 0.11318873 | Y24: =X24 -> 0.11318873 | Z24: =$Z$12/E24 -> 0.0083 | AA24: =$AA$12/E24 -> 0.20833333 | AB24: =$AB$12/E24 -> 0.19791667 | AC24: =$AC$12/E24 -> 0 | AD24: =Z24+AA24+AB24+AC24 -> 0.41455 | AE24: =(AD24+Y24+W24+R24+N24)*$AE$7 -> 2.9616529 | AF24: =AE24 -> 2.9616529 | AL24: =(AD24+Y24+W24+R24+N24)*$AL$7 -> 0 | AM24: =AL24+AF24+AD24+Y24+W24+R24+N24 -> 14.808264 | AN24: =AM24*$AN$12 -> 0.17769917 | AO24: =AM24*$AO$12 -> 0.15992925 | AP24: =AO24+AN24 -> 0.33762843 | AQ24: =AM24*$AQ$12 -> 1.2364901 | AR24: =AM24*$AR$12 -> 0 | AS24: =AM24*$AS$12 -> 0 | AT24: =AQ24+AR24+AS24 -> 1.2364901 | AU24: =AM24*$AU$12 -> 0.74041322 | AV24: =AU24 -> 0.74041322 | AW24: =AM24+AP24+AT24+AV24 -> 17.122796 | AX24: =AY24/AW24 -> 0.050646166 | AY24: =I24-AW24 -> 0.86720397 | AZ24: =IFERROR(H24*VLOOKUP(A24,'Tabela de Produtos'!A:Q,17,0),0) -> 9.56 | BA24: =$I24*BA$12 -> 0 | BB24: =$I24*BB$12 -> 0 | BC24: =$I24*BC$12 -> 0 | BD24: =$I24*BD$12 -> 1.2593 | BE24: =I24*$BE$12 -> 0.8995 | BF24: =SUM(AZ24:BE24) -> 11.7188 | BG24: =I24-BF24 -> 6.2712 | BH24: =IF(F24="Cadastrar Ficha de Produção",0,IFERROR(BG24/I24,0)) -> 0.34859366
A25: PRD00012 | B25: =IFERROR(VLOOKUP(A25,'Tabela de Produtos'!A:B,2,0),"Preencher Cód. Produto") -> BRAZIMIL LÁTEX ECONÔMICO INT FOSCO 3L PALHA | D25: Galao | E25: 100 | F25: =IF(A25=0,0,VLOOKUP(A25,'Tabela de Produtos'!A:W,23,0)) -> 10.56 | G25: 17.99 | H25: 1 | I25: =G25*H25 -> 17.99 | J25: =VLOOKUP(B25,'Tabela de Produtos'!B:M,12,FALSE()) -> 4.92 | K25: =VLOOKUP(B25,'Tabela de Produtos'!B:P,15,FALSE()) -> 0.93 | L25: =J25*1% -> 0.0492 | M25: =J25*1% -> 0.0492 | N25: =J25+K25+L25+M25 -> 5.9484 | O25: =($O$12/E25)*$O$13 -> 0.362 | P25: =($P$12/E25)*$P$13 -> 0.2829 | Q25: =($Q$12/E25)*$Q$13 -> 0.2829 | R25: =O25+P25+Q25 -> 0.9278 | S25: =VLOOKUP(B25,'Tabela de Produtos'!B:N,13,FALSE()) -> 3.44 | T25: =$T$12/$T$7 -> 0.22727273 | U25: =$U$12/$U$7 -> 0.39090909 | V25: =$V$12/$V$7 -> 0.10909091 | W25: =S25+T25+U25+V25 -> 4.1672727 | X25: =(N25+R25+W25)*1% -> 0.11043473 | Y25: =X25 -> 0.11043473 | Z25: =$Z$12/E25 -> 0.0083 | AA25: =$AA$12/E25 -> 0.20833333 | AB25: =$AB$12/E25 -> 0.19791667 | AC25: =$AC$12/E25 -> 0 | AD25: =Z25+AA25+AB25+AC25 -> 0.41455 | AE25: =(AD25+Y25+W25+R25+N25)*$AE$7 -> 2.8921144 | AF25: =AE25 -> 2.8921144 | AL25: =(AD25+Y25+W25+R25+N25)*$AL$7 -> 0 | AM25: =AL25+AF25+AD25+Y25+W25+R25+N25 -> 14.460572 | AN25: =AM25*$AN$12 -> 0.17352686 | AO25: =AM25*$AO$12 -> 0.15617418 | AP25: =AO25+AN25 -> 0.32970104 | AQ25: =AM25*$AQ$12 -> 1.2074577 | AR25: =AM25*$AR$12 -> 0 | AS25: =AM25*$AS$12 -> 0 | AT25: =AQ25+AR25+AS25 -> 1.2074577 | AU25: =AM25*$AU$12 -> 0.72302859 | AV25: =AU25 -> 0.72302859 | AW25: =AM25+AP25+AT25+AV25 -> 16.720759 | AX25: =AY25/AW25 -> 0.075908085 | AY25: =I25-AW25 -> 1.2692408 | AZ25: =IFERROR(H25*VLOOKUP(A25,'Tabela de Produtos'!A:Q,17,0),0) -> 9.29 | BA25: =$I25*BA$12 -> 0 | BB25: =$I25*BB$12 -> 0 | BC25: =$I25*BC$12 -> 0 | BD25: =$I25*BD$12 -> 1.2593 | BE25: =I25*$BE$12 -> 0.8995 | BF25: =SUM(AZ25:BE25) -> 11.4488 | BG25: =I25-BF25 -> 6.5412 | BH25: =IF(F25="Cadastrar Ficha de Produção",0,IFERROR(BG25/I25,0)) -> 0.363602
A26: PRD00013 | B26: =IFERROR(VLOOKUP(A26,'Tabela de Produtos'!A:B,2,0),"Preencher Cód. Produto") -> BRAZIMIL LÁTEX ECONÔMICO INT FOSCO 3L VERDE PRIMAVERA | D26: Galao | E26: 100 | F26: =IF(A26=0,0,VLOOKUP(A26,'Tabela de Produtos'!A:W,23,0)) -> 11.52 | G26: 17.99 | H26: 1 | I26: =G26*H26 -> 17.99 | J26: =VLOOKUP(B26,'Tabela de Produtos'!B:M,12,FALSE()) -> 5.76 | K26: =VLOOKUP(B26,'Tabela de Produtos'!B:P,15,FALSE()) -> 0.93 | L26: =J26*1% -> 0.0576 | M26: =J26*1% -> 0.0576 | N26: =J26+K26+L26+M26 -> 6.8052 | O26: =($O$12/E26)*$O$13 -> 0.362 | P26: =($P$12/E26)*$P$13 -> 0.2829 | Q26: =($Q$12/E26)*$Q$13 -> 0.2829 | R26: =O26+P26+Q26 -> 0.9278 | S26: =VLOOKUP(B26,'Tabela de Produtos'!B:N,13,FALSE()) -> 3.44 | T26: =$T$12/$T$7 -> 0.22727273 | U26: =$U$12/$U$7 -> 0.39090909 | V26: =$V$12/$V$7 -> 0.10909091 | W26: =S26+T26+U26+V26 -> 4.1672727 | X26: =(N26+R26+W26)*1% -> 0.11900273 | Y26: =X26 -> 0.11900273 | Z26: =$Z$12/E26 -> 0.0083 | AA26: =$AA$12/E26 -> 0.20833333 | AB26: =$AB$12/E26 -> 0.19791667 | AC26: =$AC$12/E26 -> 0 | AD26: =Z26+AA26+AB26+AC26 -> 0.41455 | AE26: =(AD26+Y26+W26+R26+N26)*$AE$7 -> 3.1084564 | AF26: =AE26 -> 3.1084564 | AL26: =(AD26+Y26+W26+R26+N26)*$AL$7 -> 0 | AM26: =AL26+AF26+AD26+Y26+W26+R26+N26 -> 15.542282 | AN26: =AM26*$AN$12 -> 0.18650738 | AO26: =AM26*$AO$12 -> 0.16785664 | AP26: =AO26+AN26 -> 0.35436403 | AQ26: =AM26*$AQ$12 -> 1.2977805 | AR26: =AM26*$AR$12 -> 0 | AS26: =AM26*$AS$12 -> 0 | AT26: =AQ26+AR26+AS26 -> 1.2977805 | AU26: =AM26*$AU$12 -> 0.77711409 | AV26: =AU26 -> 0.77711409 | AW26: =AM26+AP26+AT26+AV26 -> 17.97154 | AX26: =AY26/AW26 -> 0.0010271537 | AY26: =I26-AW26 -> 0.018459534 | AZ26: =IFERROR(H26*VLOOKUP(A26,'Tabela de Produtos'!A:Q,17,0),0) -> 10.13 | BA26: =$I26*BA$12 -> 0 | BB26: =$I26*BB$12 -> 0 | BC26: =$I26*BC$12 -> 0 | BD26: =$I26*BD$12 -> 1.2593 | BE26: =I26*$BE$12 -> 0.8995 | BF26: =SUM(AZ26:BE26) -> 12.2888 | BG26: =I26-BF26 -> 5.7012 | BH26: =IF(F26="Cadastrar Ficha de Produção",0,IFERROR(BG26/I26,0)) -> 0.31690939
A27: PRD00014 | B27: =IFERROR(VLOOKUP(A27,'Tabela de Produtos'!A:B,2,0),"Preencher Cód. Produto") -> BRAZIMIL LÁTEX ECONÔMICO INT FOSCO 3L VERDE FOLHA | D27: Galao | E27: 100 | F27: =IF(A27=0,0,VLOOKUP(A27,'Tabela de Produtos'!A:W,23,0)) -> 12.78 | G27: 17.99 | H27: 1 | I27: =G27*H27 -> 17.99 | J27: =VLOOKUP(B27,'Tabela de Produtos'!B:M,12,FALSE()) -> 6.87 | K27: =VLOOKUP(B27,'Tabela de Produtos'!B:P,15,FALSE()) -> 0.93 | L27: =J27*1% -> 0.0687 | M27: =J27*1% -> 0.0687 | N27: =J27+K27+L27+M27 -> 7.9374 | O27: =($O$12/E27)*$O$13 -> 0.362 | P27: =($P$12/E27)*$P$13 -> 0.2829 | Q27: =($Q$12/E27)*$Q$13 -> 0.2829 | R27: =O27+P27+Q27 -> 0.9278 | S27: =VLOOKUP(B27,'Tabela de Produtos'!B:N,13,FALSE()) -> 3.44 | T27: =$T$12/$T$7 -> 0.22727273 | U27: =$U$12/$U$7 -> 0.39090909 | V27: =$V$12/$V$7 -> 0.10909091 | W27: =S27+T27+U27+V27 -> 4.1672727 | X27: =(N27+R27+W27)*1% -> 0.13032473 | Y27: =X27 -> 0.13032473 | Z27: =$Z$12/E27 -> 0.0083 | AA27: =$AA$12/E27 -> 0.20833333 | AB27: =$AB$12/E27 -> 0.19791667 | AC27: =$AC$12/E27 -> 0 | AD27: =Z27+AA27+AB27+AC27 -> 0.41455 | AE27: =(AD27+Y27+W27+R27+N27)*$AE$7 -> 3.3943369 | AF27: =AE27 -> 3.3943369 | AL27: =(AD27+Y27+W27+R27+N27)*$AL$7 -> 0 | AM27: =AL27+AF27+AD27+Y27+W27+R27+N27 -> 16.971684 | AN27: =AM27*$AN$12 -> 0.20366021 | AO27: =AM27*$AO$12 -> 0.18329419 | AP27: =AO27+AN27 -> 0.3869544 | AQ27: =AM27*$AQ$12 -> 1.4171356 | AR27: =AM27*$AR$12 -> 0 | AS27: =AM27*$AS$12 -> 0 | AT27: =AQ27+AR27+AS27 -> 1.4171356 | AU27: =AM27*$AU$12 -> 0.84858422 | AV27: =AU27 -> 0.84858422 | AW27: =AM27+AP27+AT27+AV27 -> 19.624359 | AX27: =AY27/AW27 -> -0.08328214 | AY27: =I27-AW27 -> -1.6343586 | AZ27: =IFERROR(H27*VLOOKUP(A27,'Tabela de Produtos'!A:Q,17,0),0) -> 11.24 | BA27: =$I27*BA$12 -> 0 | BB27: =$I27*BB$12 -> 0 | BC27: =$I27*BC$12 -> 0 | BD27: =$I27*BD$12 -> 1.2593 | BE27: =I27*$BE$12 -> 0.8995 | BF27: =SUM(AZ27:BE27) -> 13.3988 | BG27: =I27-BF27 -> 4.5912 | BH27: =IF(F27="Cadastrar Ficha de Produção",0,IFERROR(BG27/I27,0)) -> 0.25520845
A28: PRD00015 | B28: =IFERROR(VLOOKUP(A28,'Tabela de Produtos'!A:B,2,0),"Preencher Cód. Produto") -> BRAZIMIL LÁTEX ECONÔMICO INT FOSCO 3L AZUL CEU | D28: Galao | E28: 100 | F28: =IF(A28=0,0,VLOOKUP(A28,'Tabela de Produtos'!A:W,23,0)) -> 10.49 | G28: 17.99 | H28: 1 | I28: =G28*H28 -> 17.99 | J28: =VLOOKUP(B28,'Tabela de Produtos'!B:M,12,FALSE()) -> 4.86 | K28: =VLOOKUP(B28,'Tabela de Produtos'!B:P,15,FALSE()) -> 0.93 | L28: =J28*1% -> 0.0486 | M28: =J28*1% -> 0.0486 | N28: =J28+K28+L28+M28 -> 5.8872 | O28: =($O$12/E28)*$O$13 -> 0.362 | P28: =($P$12/E28)*$P$13 -> 0.2829 | Q28: =($Q$12/E28)*$Q$13 -> 0.2829 | R28: =O28+P28+Q28 -> 0.9278 | S28: =VLOOKUP(B28,'Tabela de Produtos'!B:N,13,FALSE()) -> 3.44 | T28: =$T$12/$T$7 -> 0.22727273 | U28: =$U$12/$U$7 -> 0.39090909 | V28: =$V$12/$V$7 -> 0.10909091 | W28: =S28+T28+U28+V28 -> 4.1672727 | X28: =(N28+R28+W28)*1% -> 0.10982273 | Y28: =X28 -> 0.10982273 | Z28: =$Z$12/E28 -> 0.0083 | AA28: =$AA$12/E28 -> 0.20833333 | AB28: =$AB$12/E28 -> 0.19791667 | AC28: =$AC$12/E28 -> 0 | AD28: =Z28+AA28+AB28+AC28 -> 0.41455 | AE28: =(AD28+Y28+W28+R28+N28)*$AE$7 -> 2.8766614 | AF28: =AE28 -> 2.8766614 | AL28: =(AD28+Y28+W28+R28+N28)*$AL$7 -> 0 | AM28: =AL28+AF28+AD28+Y28+W28+R28+N28 -> 14.383307 | AN28: =AM28*$AN$12 -> 0.17259968 | AO28: =AM28*$AO$12 -> 0.15533971 | AP28: =AO28+AN28 -> 0.3279394 | AQ28: =AM28*$AQ$12 -> 1.2010061 | AR28: =AM28*$AR$12 -> 0 | AS28: =AM28*$AS$12 -> 0 | AT28: =AQ28+AR28+AS28 -> 1.2010061 | AU28: =AM28*$AU$12 -> 0.71916534 | AV28: =AU28 -> 0.71916534 | AW28: =AM28+AP28+AT28+AV28 -> 16.631418 | AX28: =AY28/AW28 -> 0.081687704 | AY28: =I28-AW28 -> 1.3585823 | AZ28: =IFERROR(H28*VLOOKUP(A28,'Tabela de Produtos'!A:Q,17,0),0) -> 9.23 | BA28: =$I28*BA$12 -> 0 | BB28: =$I28*BB$12 -> 0 | BC28: =$I28*BC$12 -> 0 | BD28: =$I28*BD$12 -> 1.2593 | BE28: =I28*$BE$12 -> 0.8995 | BF28: =SUM(AZ28:BE28) -> 11.3888 | BG28: =I28-BF28 -> 6.6012 | BH28: =IF(F28="Cadastrar Ficha de Produção",0,IFERROR(BG28/I28,0)) -> 0.36693719
A29: PRD00016 | B29: =IFERROR(VLOOKUP(A29,'Tabela de Produtos'!A:B,2,0),"Preencher Cód. Produto") -> BRAZIMIL LÁTEX ECONÔMICO INT FOSCO 3L AZUL OCEANO | D29: Galao | E29: 100 | F29: =IF(A29=0,0,VLOOKUP(A29,'Tabela de Produtos'!A:W,23,0)) -> 11.82 | G29: 17.99 | H29: 1 | I29: =G29*H29 -> 17.99 | J29: =VLOOKUP(B29,'Tabela de Produtos'!B:M,12,FALSE()) -> 6.03 | K29: =VLOOKUP(B29,'Tabela de Produtos'!B:P,15,FALSE()) -> 0.93 | L29: =J29*1% -> 0.0603 | M29: =J29*1% -> 0.0603 | N29: =J29+K29+L29+M29 -> 7.0806 | O29: =($O$12/E29)*$O$13 -> 0.362 | P29: =($P$12/E29)*$P$13 -> 0.2829 | Q29: =($Q$12/E29)*$Q$13 -> 0.2829 | R29: =O29+P29+Q29 -> 0.9278 | S29: =VLOOKUP(B29,'Tabela de Produtos'!B:N,13,FALSE()) -> 3.44 | T29: =$T$12/$T$7 -> 0.22727273 | U29: =$U$12/$U$7 -> 0.39090909 | V29: =$V$12/$V$7 -> 0.10909091 | W29: =S29+T29+U29+V29 -> 4.1672727 | X29: =(N29+R29+W29)*1% -> 0.12175673 | Y29: =X29 -> 0.12175673 | Z29: =$Z$12/E29 -> 0.0083 | AA29: =$AA$12/E29 -> 0.20833333 | AB29: =$AB$12/E29 -> 0.19791667 | AC29: =$AC$12/E29 -> 0 | AD29: =Z29+AA29+AB29+AC29 -> 0.41455 | AE29: =(AD29+Y29+W29+R29+N29)*$AE$7 -> 3.1779949 | AF29: =AE29 -> 3.1779949 | AL29: =(AD29+Y29+W29+R29+N29)*$AL$7 -> 0 | AM29: =AL29+AF29+AD29+Y29+W29+R29+N29 -> 15.889974 | AN29: =AM29*$AN$12 -> 0.19067969 | AO29: =AM29*$AO$12 -> 0.17161172 | AP29: =AO29+AN29 -> 0.36229141 | AQ29: =AM29*$AQ$12 -> 1.3268129 | AR29: =AM29*$AR$12 -> 0 | AS29: =AM29*$AS$12 -> 0 | AT29: =AQ29+AR29+AS29 -> 1.3268129 | AU29: =AM29*$AU$12 -> 0.79449872 | AV29: =AU29 -> 0.79449872 | AW29: =AM29+AP29+AT29+AV29 -> 18.373577 | AX29: =AY29/AW29 -> -0.020876572 | AY29: =I29-AW29 -> -0.3835773 | AZ29: =IFERROR(H29*VLOOKUP(A29,'Tabela de Produtos'!A:Q,17,0),0) -> 10.4 | BA29: =$I29*BA$12 -> 0 | BB29: =$I29*BB$12 -> 0 | BC29: =$I29*BC$12 -> 0 | BD29: =$I29*BD$12 -> 1.2593 | BE29: =I29*$BE$12 -> 0.8995 | BF29: =SUM(AZ29:BE29) -> 12.5588 | BG29: =I29-BF29 -> 5.4312 | BH29: =IF(F29="Cadastrar Ficha de Produção",0,IFERROR(BG29/I29,0)) -> 0.30190106
A30: PRD00017 | B30: =IFERROR(VLOOKUP(A30,'Tabela de Produtos'!A:B,2,0),"Preencher Cód. Produto") -> BRAZIMIL LÁTEX ECONÔMICO INT FOSCO 3L AMARELO CANARIO | D30: Galao | E30: 100 | F30: =IF(A30=0,0,VLOOKUP(A30,'Tabela de Produtos'!A:W,23,0)) -> 10.8 | G30: 17.99 | H30: 1 | I30: =G30*H30 -> 17.99 | J30: =VLOOKUP(B30,'Tabela de Produtos'!B:M,12,FALSE()) -> 5.13 | K30: =VLOOKUP(B30,'Tabela de Produtos'!B:P,15,FALSE()) -> 0.93 | L30: =J30*1% -> 0.0513 | M30: =J30*1% -> 0.0513 | N30: =J30+K30+L30+M30 -> 6.1626 | O30: =($O$12/E30)*$O$13 -> 0.362 | P30: =($P$12/E30)*$P$13 -> 0.2829 | Q30: =($Q$12/E30)*$Q$13 -> 0.2829 | R30: =O30+P30+Q30 -> 0.9278 | S30: =VLOOKUP(B30,'Tabela de Produtos'!B:N,13,FALSE()) -> 3.44 | T30: =$T$12/$T$7 -> 0.22727273 | U30: =$U$12/$U$7 -> 0.39090909 | V30: =$V$12/$V$7 -> 0.10909091 | W30: =S30+T30+U30+V30 -> 4.1672727 | X30: =(N30+R30+W30)*1% -> 0.11257673 | Y30: =X30 -> 0.11257673 | Z30: =$Z$12/E30 -> 0.0083 | AA30: =$AA$12/E30 -> 0.20833333 | AB30: =$AB$12/E30 -> 0.19791667 | AC30: =$AC$12/E30 -> 0 | AD30: =Z30+AA30+AB30+AC30 -> 0.41455 | AE30: =(AD30+Y30+W30+R30+N30)*$AE$7 -> 2.9461999 | AF30: =AE30 -> 2.9461999 | AL30: =(AD30+Y30+W30+R30+N30)*$AL$7 -> 0 | AM30: =AL30+AF30+AD30+Y30+W30+R30+N30 -> 14.730999 | AN30: =AM30*$AN$12 -> 0.17677199 | AO30: =AM30*$AO$12 -> 0.15909479 | AP30: =AO30+AN30 -> 0.33586678 | AQ30: =AM30*$AQ$12 -> 1.2300384 | AR30: =AM30*$AR$12 -> 0 | AS30: =AM30*$AS$12 -> 0 | AT30: =AQ30+AR30+AS30 -> 1.2300384 | AU30: =AM30*$AU$12 -> 0.73654997 | AV30: =AU30 -> 0.73654997 | AW30: =AM30+AP30+AT30+AV30 -> 17.033455 | AX30: =AY30/AW30 -> 0.05615687 | AY30: =I30-AW30 -> 0.95654549 | AZ30: =IFERROR(H30*VLOOKUP(A30,'Tabela de Produtos'!A:Q,17,0),0) -> 9.5 | BA30: =$I30*BA$12 -> 0 | BB30: =$I30*BB$12 -> 0 | BC30: =$I30*BC$12 -> 0 | BD30: =$I30*BD$12 -> 1.2593 | BE30: =I30*$BE$12 -> 0.8995 | BF30: =SUM(AZ30:BE30) -> 11.6588 | BG30: =I30-BF30 -> 6.3312 | BH30: =IF(F30="Cadastrar Ficha de Produção",0,IFERROR(BG30/I30,0)) -> 0.35192885
A31: PRD00018 | B31: =IFERROR(VLOOKUP(A31,'Tabela de Produtos'!A:B,2,0),"Preencher Cód. Produto") -> BRAZIMIL LÁTEX ECONÔMICO INT FOSCO 3L CROMO SUAVE | D31: Galao | E31: 100 | F31: =IF(A31=0,0,VLOOKUP(A31,'Tabela de Produtos'!A:W,23,0)) -> 11.62 | G31: 17.99 | H31: 1 | I31: =G31*H31 -> 17.99 | J31: =VLOOKUP(B31,'Tabela de Produtos'!B:M,12,FALSE()) -> 5.85 | K31: =VLOOKUP(B31,'Tabela de Produtos'!B:P,15,FALSE()) -> 0.93 | L31: =J31*1% -> 0.0585 | M31: =J31*1% -> 0.0585 | N31: =J31+K31+L31+M31 -> 6.897 | O31: =($O$12/E31)*$O$13 -> 0.362 | P31: =($P$12/E31)*$P$13 -> 0.2829 | Q31: =($Q$12/E31)*$Q$13 -> 0.2829 | R31: =O31+P31+Q31 -> 0.9278 | S31: =VLOOKUP(B31,'Tabela de Produtos'!B:N,13,FALSE()) -> 3.44 | T31: =$T$12/$T$7 -> 0.22727273 | U31: =$U$12/$U$7 -> 0.39090909 | V31: =$V$12/$V$7 -> 0.10909091 | W31: =S31+T31+U31+V31 -> 4.1672727 | X31: =(N31+R31+W31)*1% -> 0.11992073 | Y31: =X31 -> 0.11992073 | Z31: =$Z$12/E31 -> 0.0083 | AA31: =$AA$12/E31 -> 0.20833333 | AB31: =$AB$12/E31 -> 0.19791667 | AC31: =$AC$12/E31 -> 0 | AD31: =Z31+AA31+AB31+AC31 -> 0.41455 | AE31: =(AD31+Y31+W31+R31+N31)*$AE$7 -> 3.1316359 | AF31: =AE31 -> 3.1316359 | AL31: =(AD31+Y31+W31+R31+N31)*$AL$7 -> 0 | AM31: =AL31+AF31+AD31+Y31+W31+R31+N31 -> 15.658179 | AN31: =AM31*$AN$12 -> 0.18789815 | AO31: =AM31*$AO$12 -> 0.16910834 | AP31: =AO31+AN31 -> 0.35700649 | AQ31: =AM31*$AQ$12 -> 1.307458 | AR31: =AM31*$AR$12 -> 0 | AS31: =AM31*$AS$12 -> 0 | AT31: =AQ31+AR31+AS31 -> 1.307458 | AU31: =AM31*$AU$12 -> 0.78290897 | AV31: =AU31 -> 0.78290897 | AW31: =AM31+AP31+AT31+AV31 -> 18.105553 | AX31: =AY31/AW31 -> -0.0063821717 | AY31: =I31-AW31 -> -0.11555275 | AZ31: =IFERROR(H31*VLOOKUP(A31,'Tabela de Produtos'!A:Q,17,0),0) -> 10.22 | BA31: =$I31*BA$12 -> 0 | BB31: =$I31*BB$12 -> 0 | BC31: =$I31*BC$12 -> 0 | BD31: =$I31*BD$12 -> 1.2593 | BE31: =I31*$BE$12 -> 0.8995 | BF31: =SUM(AZ31:BE31) -> 12.3788 | BG31: =I31-BF31 -> 5.6112 | BH31: =IF(F31="Cadastrar Ficha de Produção",0,IFERROR(BG31/I31,0)) -> 0.31190661
A32: PRD00019 | B32: =IFERROR(VLOOKUP(A32,'Tabela de Produtos'!A:B,2,0),"Preencher Cód. Produto") -> BRAZIMIL LÁTEX ECONÔMICO INT FOSCO 3L ROSA BEBE | D32: Galao | E32: 100 | F32: =IF(A32=0,0,VLOOKUP(A32,'Tabela de Produtos'!A:W,23,0)) -> 10.6 | G32: 17.99 | H32: 1 | I32: =G32*H32 -> 17.99 | J32: =VLOOKUP(B32,'Tabela de Produtos'!B:M,12,FALSE()) -> 4.95 | K32: =VLOOKUP(B32,'Tabela de Produtos'!B:P,15,FALSE()) -> 0.93 | L32: =J32*1% -> 0.0495 | M32: =J32*1% -> 0.0495 | N32: =J32+K32+L32+M32 -> 5.979 | O32: =($O$12/E32)*$O$13 -> 0.362 | P32: =($P$12/E32)*$P$13 -> 0.2829 | Q32: =($Q$12/E32)*$Q$13 -> 0.2829 | R32: =O32+P32+Q32 -> 0.9278 | S32: =VLOOKUP(B32,'Tabela de Produtos'!B:N,13,FALSE()) -> 3.44 | T32: =$T$12/$T$7 -> 0.22727273 | U32: =$U$12/$U$7 -> 0.39090909 | V32: =$V$12/$V$7 -> 0.10909091 | W32: =S32+T32+U32+V32 -> 4.1672727 | X32: =(N32+R32+W32)*1% -> 0.11074073 | Y32: =X32 -> 0.11074073 | Z32: =$Z$12/E32 -> 0.0083 | AA32: =$AA$12/E32 -> 0.20833333 | AB32: =$AB$12/E32 -> 0.19791667 | AC32: =$AC$12/E32 -> 0 | AD32: =Z32+AA32+AB32+AC32 -> 0.41455 | AE32: =(AD32+Y32+W32+R32+N32)*$AE$7 -> 2.8998409 | AF32: =AE32 -> 2.8998409 | AL32: =(AD32+Y32+W32+R32+N32)*$AL$7 -> 0 | AM32: =AL32+AF32+AD32+Y32+W32+R32+N32 -> 14.499204 | AN32: =AM32*$AN$12 -> 0.17399045 | AO32: =AM32*$AO$12 -> 0.15659141 | AP32: =AO32+AN32 -> 0.33058186 | AQ32: =AM32*$AQ$12 -> 1.2106836 | AR32: =AM32*$AR$12 -> 0 | AS32: =AM32*$AS$12 -> 0 | AT32: =AQ32+AR32+AS32 -> 1.2106836 | AU32: =AM32*$AU$12 -> 0.72496022 | AV32: =AU32 -> 0.72496022 | AW32: =AM32+AP32+AT32+AV32 -> 16.76543 | AX32: =AY32/AW32 -> 0.073041374 | AY32: =I32-AW32 -> 1.22457 | AZ32: =IFERROR(H32*VLOOKUP(A32,'Tabela de Produtos'!A:Q,17,0),0) -> 9.32 | BA32: =$I32*BA$12 -> 0 | BB32: =$I32*BB$12 -> 0 | BC32: =$I32*BC$12 -> 0 | BD32: =$I32*BD$12 -> 1.2593 | BE32: =I32*$BE$12 -> 0.8995 | BF32: =SUM(AZ32:BE32) -> 11.4788 | BG32: =I32-BF32 -> 6.5112 | BH32: =IF(F32="Cadastrar Ficha de Produção",0,IFERROR(BG32/I32,0)) -> 0.36193441
A33: PRD00020 | B33: =IFERROR(VLOOKUP(A33,'Tabela de Produtos'!A:B,2,0),"Preencher Cód. Produto") -> BRAZIMIL LÁTEX ECONÔMICO INT FOSCO 3L MARFIM | D33: Galao | E33: 100 | F33: =IF(A33=0,0,VLOOKUP(A33,'Tabela de Produtos'!A:W,23,0)) -> 10.63 | G33: 17.99 | H33: 1 | I33: =G33*H33 -> 17.99 | J33: =VLOOKUP(B33,'Tabela de Produtos'!B:M,12,FALSE()) -> 4.98 | K33: =VLOOKUP(B33,'Tabela de Produtos'!B:P,15,FALSE()) -> 0.93 | L33: =J33*1% -> 0.0498 | M33: =J33*1% -> 0.0498 | N33: =J33+K33+L33+M33 -> 6.0096 | O33: =($O$12/E33)*$O$13 -> 0.362 | P33: =($P$12/E33)*$P$13 -> 0.2829 | Q33: =($Q$12/E33)*$Q$13 -> 0.2829 | R33: =O33+P33+Q33 -> 0.9278 | S33: =VLOOKUP(B33,'Tabela de Produtos'!B:N,13,FALSE()) -> 3.44 | T33: =$T$12/$T$7 -> 0.22727273 | U33: =$U$12/$U$7 -> 0.39090909 | V33: =$V$12/$V$7 -> 0.10909091 | W33: =S33+T33+U33+V33 -> 4.1672727 | X33: =(N33+R33+W33)*1% -> 0.11104673 | Y33: =X33 -> 0.11104673 | Z33: =$Z$12/E33 -> 0.0083 | AA33: =$AA$12/E33 -> 0.20833333 | AB33: =$AB$12/E33 -> 0.19791667 | AC33: =$AC$12/E33 -> 0 | AD33: =Z33+AA33+AB33+AC33 -> 0.41455 | AE33: =(AD33+Y33+W33+R33+N33)*$AE$7 -> 2.9075674 | AF33: =AE33 -> 2.9075674 | AL33: =(AD33+Y33+W33+R33+N33)*$AL$7 -> 0 | AM33: =AL33+AF33+AD33+Y33+W33+R33+N33 -> 14.537837 | AN33: =AM33*$AN$12 -> 0.17445404 | AO33: =AM33*$AO$12 -> 0.15700864 | AP33: =AO33+AN33 -> 0.33146268 | AQ33: =AM33*$AQ$12 -> 1.2139094 | AR33: =AM33*$AR$12 -> 0 | AS33: =AM33*$AS$12 -> 0 | AT33: =AQ33+AR33+AS33 -> 1.2139094 | AU33: =AM33*$AU$12 -> 0.72689184 | AV33: =AU33 -> 0.72689184 | AW33: =AM33+AP33+AT33+AV33 -> 16.810101 | AX33: =AY33/AW33 -> 0.0701899 | AY33: =I33-AW33 -> 1.1798993 | AZ33: =IFERROR(H33*VLOOKUP(A33,'Tabela de Produtos'!A:Q,17,0),0) -> 9.35 | BA33: =$I33*BA$12 -> 0 | BB33: =$I33*BB$12 -> 0 | BC33: =$I33*BC$12 -> 0 | BD33: =$I33*BD$12 -> 1.2593 | BE33: =I33*$BE$12 -> 0.8995 | BF33: =SUM(AZ33:BE33) -> 11.5088 | BG33: =I33-BF33 -> 6.4812 | BH33: =IF(F33="Cadastrar Ficha de Produção",0,IFERROR(BG33/I33,0)) -> 0.36026681
... A36: PRD00023 | B36: =IFERROR(VLOOKUP(A36,'Tabela de Produtos'!A:B,2,0),"Preencher Cód. Produto") -> BRAZIMIL LÁTEX ECONÔMICO INT FOSCO 3L PEROLA | D36: Galao | E36: 100 | F36: =IF(A36=0,0,VLOOKUP(A36,'Tabela de Produtos'!A:W,23,0)) -> 10.56 | G36: 17.99 | H36: 1 | I36: =G36*H36 -> 17.99 | J36: =VLOOKUP(B36,'Tabela de Produtos'!B:M,12,FALSE()) -> 4.92 | K36: =VLOOKUP(B36,'Tabela de Produtos'!B:P,15,FALSE()) -> 0.93 | L36: =J36*1% -> 0.0492 | M36: =J36*1% -> 0.0492 | N36: =J36+K36+L36+M36 -> 5.9484 | O36: =($O$12/E36)*$O$13 -> 0.362 | P36: =($P$12/E36)*$P$13 -> 0.2829 | Q36: =($Q$12/E36)*$Q$13 -> 0.2829 | R36: =O36+P36+Q36 -> 0.9278 | S36: =VLOOKUP(B36,'Tabela de Produtos'!B:N,13,FALSE()) -> 3.44 | T36: =$T$12/$T$7 -> 0.22727273 | U36: =$U$12/$U$7 -> 0.39090909 | V36: =$V$12/$V$7 -> 0.10909091 | W36: =S36+T36+U36+V36 -> 4.1672727 | X36: =(N36+R36+W36)*1% -> 0.11043473 | Y36: =X36 -> 0.11043473 | Z36: =$Z$12/E36 -> 0.0083 | AA36: =$AA$12/E36 -> 0.20833333 | AB36: =$AB$12/E36 -> 0.19791667 | AC36: =$AC$12/E36 -> 0 | AD36: =Z36+AA36+AB36+AC36 -> 0.41455 | AE36: =(AD36+Y36+W36+R36+N36)*$AE$7 -> 2.8921144 | AF36: =AE36 -> 2.8921144 | AL36: =(AD36+Y36+W36+R36+N36)*$AL$7 -> 0 | AM36: =AL36+AF36+AD36+Y36+W36+R36+N36 -> 14.460572 | AN36: =AM36*$AN$12 -> 0.17352686 | AO36: =AM36*$AO$12 -> 0.15617418 | AP36: =AO36+AN36 -> 0.32970104 | AQ36: =AM36*$AQ$12 -> 1.2074577 | AR36: =AM36*$AR$12 -> 0 | AS36: =AM36*$AS$12 -> 0 | AT36: =AQ36+AR36+AS36 -> 1.2074577 | AU36: =AM36*$AU$12 -> 0.72302859 | AV36: =AU36 -> 0.72302859 | AW36: =AM36+AP36+AT36+AV36 -> 16.720759 | AX36: =AY36/AW36 -> 0.075908085 | AY36: =I36-AW36 -> 1.2692408 | AZ36: =IFERROR(H36*VLOOKUP(A36,'Tabela de Produtos'!A:Q,17,0),0) -> 9.29 | BA36: =$I36*BA$12 -> 0 | BB36: =$I36*BB$12 -> 0 | BC36: =$I36*BC$12 -> 0 | BD36: =$I36*BD$12 -> 1.2593 | BE36: =I36*$BE$12 -> 0.8995 | BF36: =SUM(AZ36:BE36) -> 11.4488 | BG36: =I36-BF36 -> 6.5412 | BH36: =IF(F36="Cadastrar Ficha de Produção",0,IFERROR(BG36/I36,0)) -> 0.363602
A37: PRD00024 | B37: =IFERROR(VLOOKUP(A37,'Tabela de Produtos'!A:B,2,0),"Preencher Cód. Produto") -> BRAZIMIL LÁTEX ECONÔMICO INT/EXT SEMIBRILHO 3L BRANCO NEVE | D37: Galao | F37: =IF(A37=0,0,VLOOKUP(A37,'Tabela de Produtos'!A:W,23,0)) -> Cadastrar Ficha de Produção | G37: 0 | H37: 1 | I37: =G37*H37 -> 0 | J37: =VLOOKUP(B37,'Tabela de Produtos'!B:M,12,FALSE()) -> 0 | AY37: =I37-AW37 -> 0 | AZ37: =IFERROR(H37*VLOOKUP(A37,'Tabela de Produtos'!A:Q,17,0),0) -> 0 | BA37: =$I37*BA$12 -> 0 | BB37: =$I37*BB$12 -> 0 | BC37: =$I37*BC$12 -> 0 | BD37: =$I37*BD$12 -> 0 | BE37: =I37*$BE$12 -> 0 | BF37: =SUM(AZ37:BE37) -> 0 | BG37: =I37-BF37 -> 0 | BH37: =IF(F37="Cadastrar Ficha de Produção",0,IFERROR(BG37/I37,0)) -> 0
A38: PRD00025 | B38: =IFERROR(VLOOKUP(A38,'Tabela de Produtos'!A:B,2,0),"Preencher Cód. Produto") -> BRAZIMIL LÁTEX ECONÔMICO INT/EXT SEMIBRILHO 3L BRANCO GELO | D38: Galao | F38: =IF(A38=0,0,VLOOKUP(A38,'Tabela de Produtos'!A:W,23,0)) -> Cadastrar Ficha de Produção | G38: 0 | H38: 1 | I38: =G38*H38 -> 0 | J38: =VLOOKUP(B38,'Tabela de Produtos'!B:M,12,FALSE()) -> 0 | AY38: =I38-AW38 -> 0 | AZ38: =IFERROR(H38*VLOOKUP(A38,'Tabela de Produtos'!A:Q,17,0),0) -> 0 | BA38: =$I38*BA$12 -> 0 | BB38: =$I38*BB$12 -> 0 | BC38: =$I38*BC$12 -> 0 | BD38: =$I38*BD$12 -> 0 | BE38: =I38*$BE$12 -> 0 | BF38: =SUM(AZ38:BE38) -> 0 | BG38: =I38-BF38 -> 0 | BH38: =IF(F38="Cadastrar Ficha de Produção",0,IFERROR(BG38/I38,0)) -> 0
A39: PRD00026 | B39: =IFERROR(VLOOKUP(A39,'Tabela de Produtos'!A:B,2,0),"Preencher Cód. Produto") -> BRAZIMIL LÁTEX ECONÔMICO INT/EXT SEMIBRILHO 3L AREIA | D39: Galao | F39: =IF(A39=0,0,VLOOKUP(A39,'Tabela de Produtos'!A:W,23,0)) -> Cadastrar Ficha de Produção | G39: 0 | H39: 1 | I39: =G39*H39 -> 0 | J39: =VLOOKUP(B39,'Tabela de Produtos'!B:M,12,FALSE()) -> 0 | AY39: =I39-AW39 -> 0 | AZ39: =IFERROR(H39*VLOOKUP(A39,'Tabela de Produtos'!A:Q,17,0),0) -> 0 | BA39: =$I39*BA$12 -> 0 | BB39: =$I39*BB$12 -> 0 | BC39: =$I39*BC$12 -> 0 | BD39: =$I39*BD$12 -> 0 | BE39: =I39*$BE$12 -> 0 | BF39: =SUM(AZ39:BE39) -> 0 | BG39: =I39-BF39 -> 0 | BH39: =IF(F39="Cadastrar Ficha de Produção",0,IFERROR(BG39/I39,0)) -> 0
A40: PRD00027 | B40: =IFERROR(VLOOKUP(A40,'Tabela de Produtos'!A:B,2,0),"Preencher Cód. Produto") -> BRAZIMIL LÁTEX ECONÔMICO INT/EXT SEMIBRILHO 3L PALHA | D40: Galao | F40: =IF(A40=0,0,VLOOKUP(A40,'Tabela de Produtos'!A:W,23,0)) -> Cadastrar Ficha de Produção | G40: 0 | H40: 1 | I40: =G40*H40 -> 0 | J40: =VLOOKUP(B40,'Tabela de Produtos'!B:M,12,FALSE()) -> 0 | AY40: =I40-AW40 -> 0 | AZ40: =IFERROR(H40*VLOOKUP(A40,'Tabela de Produtos'!A:Q,17,0),0) -> 0 | BA40: =$I40*BA$12 -> 0 | BB40: =$I40*BB$12 -> 0 | BC40: =$I40*BC$12 -> 0 | BD40: =$I40*BD$12 -> 0 | BE40: =I40*$BE$12 -> 0 | BF40: =SUM(AZ40:BE40) -> 0 | BG40: =I40-BF40 -> 0 | BH40: =IF(F40="Cadastrar Ficha de Produção",0,IFERROR(BG40/I40,0)) -> 0
A41: PRD00028 | B41: =IFERROR(VLOOKUP(A41,'Tabela de Produtos'!A:B,2,0),"Preencher Cód. Produto") -> BRAZIMIL LÁTEX ECONÔMICO INT/EXT SEMIBRILHO 3L VERDE PRIMAVERA | D41: Galao | F41: =IF(A41=0,0,VLOOKUP(A41,'Tabela de Produtos'!A:W,23,0)) -> Cadastrar Ficha de Produção | G41: 0 | H41: 1 | I41: =G41*H41 -> 0 | J41: =VLOOKUP(B41,'Tabela de Produtos'!B:M,12,FALSE()) -> 0 | AY41: =I41-AW41 -> 0 | AZ41: =IFERROR(H41*VLOOKUP(A41,'Tabela de Produtos'!A:Q,17,0),0) -> 0 | BA41: =$I41*BA$12 -> 0 | BB41: =$I41*BB$12 -> 0 | BC41: =$I41*BC$12 -> 0 | BD41: =$I41*BD$12 -> 0 | BE41: =I41*$BE$12 -> 0 | BF41: =SUM(AZ41:BE41) -> 0 | BG41: =I41-BF41 -> 0 | BH41: =IF(F41="Cadastrar Ficha de Produção",0,IFERROR(BG41/I41,0)) -> 0
A42: PRD00029 | B42: =IFERROR(VLOOKUP(A42,'Tabela de Produtos'!A:B,2,0),"Preencher Cód. Produto") -> BRAZIMIL LÁTEX ECONÔMICO INT/EXT SEMIBRILHO 3L VERDE FOLHA | D42: Galao | F42: =IF(A42=0,0,VLOOKUP(A42,'Tabela de Produtos'!A:W,23,0)) -> Cadastrar Ficha de Produção | G42: 0 | H42: 1 | I42: =G42*H42 -> 0 | J42: =VLOOKUP(B42,'Tabela de Produtos'!B:M,12,FALSE()) -> 0 | AY42: =I42-AW42 -> 0 | AZ42: =IFERROR(H42*VLOOKUP(A42,'Tabela de Produtos'!A:Q,17,0),0) -> 0 | BA42: =$I42*BA$12 -> 0 | BB42: =$I42*BB$12 -> 0 | BC42: =$I42*BC$12 -> 0 | BD42: =$I42*BD$12 -> 0 | BE42: =I42*$BE$12 -> 0 | BF42: =SUM(AZ42:BE42) -> 0 | BG42: =I42-BF42 -> 0 | BH42: =IF(F42="Cadastrar Ficha de Produção",0,IFERROR(BG42/I42,0)) -> 0
A43: PRD00030 | B43: =IFERROR(VLOOKUP(A43,'Tabela de Produtos'!A:B,2,0),"Preencher Cód. Produto") -> BRAZIMIL LÁTEX ECONÔMICO INT/EXT SEMIBRILHO 3L AZUL CEU | D43: Galao | F43: =IF(A43=0,0,VLOOKUP(A43,'Tabela de Produtos'!A:W,23,0)) -> Cadastrar Ficha de Produção | G43: 0 | H43: 1 | I43: =G43*H43 -> 0 | J43: =VLOOKUP(B43,'Tabela de Produtos'!B:M,12,FALSE()) -> 0 | AY43: =I43-AW43 -> 0 | AZ43: =IFERROR(H43*VLOOKUP(A43,'Tabela de Produtos'!A:Q,17,0),0) -> 0 | BA43: =$I43*BA$12 -> 0 | BB43: =$I43*BB$12 -> 0 | BC43: =$I43*BC$12 -> 0 | BD43: =$I43*BD$12 -> 0 | BE43: =I43*$BE$12 -> 0 | BF43: =SUM(AZ43:BE43) -> 0 | BG43: =I43-BF43 -> 0 | BH43: =IF(F43="Cadastrar Ficha de Produção",0,IFERROR(BG43/I43,0)) -> 0
A44: PRD00031 | B44: =IFERROR(VLOOKUP(A44,'Tabela de Produtos'!A:B,2,0),"Preencher Cód. Produto") -> BRAZIMIL LÁTEX ECONÔMICO INT/EXT SEMIBRILHO 3L AZUL OCEANO | D44: Galao | F44: =IF(A44=0,0,VLOOKUP(A44,'Tabela de Produtos'!A:W,23,0)) -> Cadastrar Ficha de Produção | G44: 0 | H44: 1 | I44: =G44*H44 -> 0 | J44: =VLOOKUP(B44,'Tabela de Produtos'!B:M,12,FALSE()) -> 0 | AY44: =I44-AW44 -> 0 | AZ44: =IFERROR(H44*VLOOKUP(A44,'Tabela de Produtos'!A:Q,17,0),0) -> 0 | BA44: =$I44*BA$12 -> 0 | BB44: =$I44*BB$12 -> 0 | BC44: =$I44*BC$12 -> 0 | BD44: =$I44*BD$12 -> 0 | BE44: =I44*$BE$12 -> 0 | BF44: =SUM(AZ44:BE44) -> 0 | BG44: =I44-BF44 -> 0 | BH44: =IF(F44="Cadastrar Ficha de Produção",0,IFERROR(BG44/I44,0)) -> 0
A45: PRD00032 | B45: =IFERROR(VLOOKUP(A45,'Tabela de Produtos'!A:B,2,0),"Preencher Cód. Produto") -> BRAZIMIL LÁTEX ECONÔMICO INT/EXT SEMIBRILHO 3L AMARELO CANARIO | D45: Galao | F45: =IF(A45=0,0,VLOOKUP(A45,'Tabela de Produtos'!A:W,23,0)) -> Cadastrar Ficha de Produção | G45: 0 | H45: 1 | I45: =G45*H45 -> 0 | J45: =VLOOKUP(B45,'Tabela de Produtos'!B:M,12,FALSE()) -> 0 | AY45: =I45-AW45 -> 0 | AZ45: =IFERROR(H45*VLOOKUP(A45,'Tabela de Produtos'!A:Q,17,0),0) -> 0 | BA45: =$I45*BA$12 -> 0 | BB45: =$I45*BB$12 -> 0 | BC45: =$I45*BC$12 -> 0 | BD45: =$I45*BD$12 -> 0 | BE45: =I45*$BE$12 -> 0 | BF45: =SUM(AZ45:BE45) -> 0 | BG45: =I45-BF45 -> 0 | BH45: =IF(F45="Cadastrar Ficha de Produção",0,IFERROR(BG45/I45,0)) -> 0
A46: PRD00033 | B46: =IFERROR(VLOOKUP(A46,'Tabela de Produtos'!A:B,2,0),"Preencher Cód. Produto") -> BRAZIMIL LÁTEX ECONÔMICO INT/EXT SEMIBRILHO 3L CROMO SUAVE | D46: Galao | F46: =IF(A46=0,0,VLOOKUP(A46,'Tabela de Produtos'!A:W,23,0)) -> Cadastrar Ficha de Produção | G46: 0 | H46: 1 | I46: =G46*H46 -> 0 | J46: =VLOOKUP(B46,'Tabela de Produtos'!B:M,12,FALSE()) -> 0 | AY46: =I46-AW46 -> 0 | AZ46: =IFERROR(H46*VLOOKUP(A46,'Tabela de Produtos'!A:Q,17,0),0) -> 0 | BA46: =$I46*BA$12 -> 0 | BB46: =$I46*BB$12 -> 0 | BC46: =$I46*BC$12 -> 0 | BD46: =$I46*BD$12 -> 0 | BE46: =I46*$BE$12 -> 0 | BF46: =SUM(AZ46:BE46) -> 0 | BG46: =I46-BF46 -> 0 | BH46: =IF(F46="Cadastrar Ficha de Produção",0,IFERROR(BG46/I46,0)) -> 0
A47: PRD00034 | B47: =IFERROR(VLOOKUP(A47,'Tabela de Produtos'!A:B,2,0),"Preencher Cód. Produto") -> BRAZIMIL LÁTEX ECONÔMICO INT/EXT SEMIBRILHO 3L ROSA BEBE | D47: Galao | F47: =IF(A47=0,0,VLOOKUP(A47,'Tabela de Produtos'!A:W,23,0)) -> Cadastrar Ficha de Produção | G47: 0 | H47: 1 | I47: =G47*H47 -> 0 | J47: =VLOOKUP(B47,'Tabela de Produtos'!B:M,12,FALSE()) -> 0 | AY47: =I47-AW47 -> 0 | AZ47: =IFERROR(H47*VLOOKUP(A47,'Tabela de Produtos'!A:Q,17,0),0) -> 0 | BA47: =$I47*BA$12 -> 0 | BB47: =$I47*BB$12 -> 0 | BC47: =$I47*BC$12 -> 0 | BD47: =$I47*BD$12 -> 0 | BE47: =I47*$BE$12 -> 0 | BF47: =SUM(AZ47:BE47) -> 0 | BG47: =I47-BF47 -> 0 | BH47: =IF(F47="Cadastrar Ficha de Produção",0,IFERROR(BG47/I47,0)) -> 0
A48: PRD00035 | B48: =IFERROR(VLOOKUP(A48,'Tabela de Produtos'!A:B,2,0),"Preencher Cód. Produto") -> BRAZIMIL LÁTEX ECONÔMICO INT/EXT SEMIBRILHO 3L MARFIM | D48: Galao | F48: =IF(A48=0,0,VLOOKUP(A48,'Tabela de Produtos'!A:W,23,0)) -> Cadastrar Ficha de Produção | G48: 0 | H48: 1 | I48: =G48*H48 -> 0 | J48: =VLOOKUP(B48,'Tabela de Produtos'!B:M,12,FALSE()) -> 0 | AY48: =I48-AW48 -> 0 | AZ48: =IFERROR(H48*VLOOKUP(A48,'Tabela de Produtos'!A:Q,17,0),0) -> 0 | BA48: =$I48*BA$12 -> 0 | BB48: =$I48*BB$12 -> 0 | BC48: =$I48*BC$12 -> 0 | BD48: =$I48*BD$12 -> 0 | BE48: =I48*$BE$12 -> 0 | BF48: =SUM(AZ48:BE48) -> 0 | BG48: =I48-BF48 -> 0 | BH48: =IF(F48="Cadastrar Ficha de Produção",0,IFERROR(BG48/I48,0)) -> 0
... A51: PRD00038 | B51: =IFERROR(VLOOKUP(A51,'Tabela de Produtos'!A:B,2,0),"Preencher Cód. Produto") -> BRAZIMIL LÁTEX ECONÔMICO INT/EXT SEMIBRILHO 3L PEROLA | D51: Galao | F51: =IF(A51=0,0,VLOOKUP(A51,'Tabela de Produtos'!A:W,23,0)) -> Cadastrar Ficha de Produção | G51: 0 | H51: 1 | I51: =G51*H51 -> 0 | J51: =VLOOKUP(B51,'Tabela de Produtos'!B:M,12,FALSE()) -> 0 | AY51: =I51-AW51 -> 0 | AZ51: =IFERROR(H51*VLOOKUP(A51,'Tabela de Produtos'!A:Q,17,0),0) -> 0 | BA51: =$I51*BA$12 -> 0 | BB51: =$I51*BB$12 -> 0 | BC51: =$I51*BC$12 -> 0 | BD51: =$I51*BD$12 -> 0 | BE51: =I51*$BE$12 -> 0 | BF51: =SUM(AZ51:BE51) -> 0 | BG51: =I51-BF51 -> 0 | BH51: =IF(F51="Cadastrar Ficha de Produção",0,IFERROR(BG51/I51,0)) -> 0
A52: PRD00039 | B52: =IFERROR(VLOOKUP(A52,'Tabela de Produtos'!A:B,2,0),"Preencher Cód. Produto") -> BRAZIMIL LÁTEX ECONÔMICO INT FOSCO 15L BRANCO NEVE | D52: Balde | E52: 28 | F52: =IF(A52=0,0,VLOOKUP(A52,'Tabela de Produtos'!A:W,23,0)) -> 35.7 | G52: 60 | H52: 1 | I52: =G52*H52 -> 60 | J52: =VLOOKUP(B52,'Tabela de Produtos'!B:M,12,FALSE()) -> 18.15 | K52: =VLOOKUP(B52,'Tabela de Produtos'!B:P,15,FALSE()) -> 4.65 | L52: =J52*1% -> 0.1815 | M52: =J52*1% -> 0.1815 | N52: =J52+K52+L52+M52 -> 23.163 | O52: =($O$12/E52)*$O$13 -> 1.2928571 | P52: =($P$12/E52)*$P$13 -> 1.0103571 | Q52: =($Q$12/E52)*$Q$13 -> 1.0103571 | R52: =O52+P52+Q52 -> 3.3135714 | S52: =VLOOKUP(B52,'Tabela de Produtos'!B:N,13,FALSE()) -> 8.61 | T52: =$T$12/$T$8 -> 0.69444444 | U52: =$U$12/$U$8 -> 1.1944444 | V52: =$V$12/$V$8 -> 0.33333333 | W52: =S52+T52+U52+V52 -> 10.832222 | X52: =(N52+R52+W52)*1% -> 0.37308794 | Y52: =X52 -> 0.37308794 | Z52: =$Z$12/E52 -> 0.029642857 | AA52: =$AA$12/E52 -> 0.74404762 | AB52: =$AB$12/E52 -> 0.70684524 | AC52: =$AC$12/E52 -> 0 | AD52: =Z52+AA52+AB52+AC52 -> 1.4805357 | AE52: =(AD52+Y52+W52+R52+N52)*$AE$7 -> 9.7906043 | AF52: =AE52 -> 9.7906043 | AL52: =(AD52+Y52+W52+R52+N52)*$AL$7 -> 0 | AM52: =AL52+AF52+AD52+Y52+W52+R52+N52 -> 48.953022 | AN52: =AM52*$AN$12 -> 0.58743626 | AO52: =AM52*$AO$12 -> 0.52869263 | AP52: =AO52+AN52 -> 1.1161289 | AQ52: =AM52*$AQ$12 -> 4.0875773 | AR52: =AM52*$AR$12 -> 0 | AS52: =AM52*$AS$12 -> 0 | AT52: =AQ52+AR52+AS52 -> 4.0875773 | AU52: =AM52*$AU$12 -> 2.4476511 | AV52: =AU52 -> 2.4476511 | AW52: =AM52+AP52+AT52+AV52 -> 56.604379 | AX52: =AY52/AW52 -> 0.059988664 | AY52: =I52-AW52 -> 3.3956211 | AZ52: =IFERROR(H52*VLOOKUP(A52,'Tabela de Produtos'!A:Q,17,0),0) -> 31.41 | BA52: =$I52*BA$12 -> 0 | BB52: =$I52*BB$12 -> 0 | BC52: =$I52*BC$12 -> 0 | BD52: =$I52*BD$12 -> 4.2 | BE52: =I52*$BE$12 -> 3 | BF52: =SUM(AZ52:BE52) -> 38.61 | BG52: =I52-BF52 -> 21.39 | BH52: =IF(F52="Cadastrar Ficha de Produção",0,IFERROR(BG52/I52,0)) -> 0.3565
A53: PRD00040 | B53: =IFERROR(VLOOKUP(A53,'Tabela de Produtos'!A:B,2,0),"Preencher Cód. Produto") -> BRAZIMIL LÁTEX ECONÔMICO INT FOSCO 15L BRANCO GELO | D53: Balde | E53: 28 | F53: =IF(A53=0,0,VLOOKUP(A53,'Tabela de Produtos'!A:W,23,0)) -> 42.18 | G53: 60 | H53: 1 | I53: =G53*H53 -> 60 | J53: =VLOOKUP(B53,'Tabela de Produtos'!B:M,12,FALSE()) -> 23.85 | K53: =VLOOKUP(B53,'Tabela de Produtos'!B:P,15,FALSE()) -> 4.65 | L53: =J53*1% -> 0.2385 | M53: =J53*1% -> 0.2385 | N53: =J53+K53+L53+M53 -> 28.977 | O53: =($O$12/E53)*$O$13 -> 1.2928571 | P53: =($P$12/E53)*$P$13 -> 1.0103571 | Q53: =($Q$12/E53)*$Q$13 -> 1.0103571 | R53: =O53+P53+Q53 -> 3.3135714 | S53: =VLOOKUP(B53,'Tabela de Produtos'!B:N,13,FALSE()) -> 8.61 | T53: =$T$12/$T$8 -> 0.69444444 | U53: =$U$12/$U$8 -> 1.1944444 | V53: =$V$12/$V$8 -> 0.33333333 | W53: =S53+T53+U53+V53 -> 10.832222 | X53: =(N53+R53+W53)*1% -> 0.43122794 | Y53: =X53 -> 0.43122794 | Z53: =$Z$12/E53 -> 0.029642857 | AA53: =$AA$12/E53 -> 0.74404762 | AB53: =$AB$12/E53 -> 0.70684524 | AC53: =$AC$12/E53 -> 0 | AD53: =Z53+AA53+AB53+AC53 -> 1.4805357 | AE53: =(AD53+Y53+W53+R53+N53)*$AE$7 -> 11.258639 | AF53: =AE53 -> 11.258639 | AL53: =(AD53+Y53+W53+R53+N53)*$AL$7 -> 0 | AM53: =AL53+AF53+AD53+Y53+W53+R53+N53 -> 56.293197 | AN53: =AM53*$AN$12 -> 0.67551836 | AO53: =AM53*$AO$12 -> 0.60796652 | AP53: =AO53+AN53 -> 1.2834849 | AQ53: =AM53*$AQ$12 -> 4.7004819 | AR53: =AM53*$AR$12 -> 0 | AS53: =AM53*$AS$12 -> 0 | AT53: =AQ53+AR53+AS53 -> 4.7004819 | AU53: =AM53*$AU$12 -> 2.8146598 | AV53: =AU53 -> 2.8146598 | AW53: =AM53+AP53+AT53+AV53 -> 65.091823 | AX53: =AY53/AW53 -> -0.078225236 | AY53: =I53-AW53 -> -5.0918233 | AZ53: =IFERROR(H53*VLOOKUP(A53,'Tabela de Produtos'!A:Q,17,0),0) -> 37.11 | BA53: =$I53*BA$12 -> 0 | BB53: =$I53*BB$12 -> 0 | BC53: =$I53*BC$12 -> 0 | BD53: =$I53*BD$12 -> 4.2 | BE53: =I53*$BE$12 -> 3 | BF53: =SUM(AZ53:BE53) -> 44.31 | BG53: =I53-BF53 -> 15.69 | BH53: =IF(F53="Cadastrar Ficha de Produção",0,IFERROR(BG53/I53,0)) -> 0.2615
A54: PRD00041 | B54: =IFERROR(VLOOKUP(A54,'Tabela de Produtos'!A:B,2,0),"Preencher Cód. Produto") -> BRAZIMIL LÁTEX ECONÔMICO INT FOSCO 15L AREIA | D54: Balde | E54: 28 | F54: =IF(A54=0,0,VLOOKUP(A54,'Tabela de Produtos'!A:W,23,0)) -> 44.56 | G54: 60 | H54: 1 | I54: =G54*H54 -> 60 | J54: =VLOOKUP(B54,'Tabela de Produtos'!B:M,12,FALSE()) -> 25.95 | K54: =VLOOKUP(B54,'Tabela de Produtos'!B:P,15,FALSE()) -> 4.65 | L54: =J54*1% -> 0.2595 | M54: =J54*1% -> 0.2595 | N54: =J54+K54+L54+M54 -> 31.119 | O54: =($O$12/E54)*$O$13 -> 1.2928571 | P54: =($P$12/E54)*$P$13 -> 1.0103571 | Q54: =($Q$12/E54)*$Q$13 -> 1.0103571 | R54: =O54+P54+Q54 -> 3.3135714 | S54: =VLOOKUP(B54,'Tabela de Produtos'!B:N,13,FALSE()) -> 8.61 | T54: =$T$12/$T$8 -> 0.69444444 | U54: =$U$12/$U$8 -> 1.1944444 | V54: =$V$12/$V$8 -> 0.33333333 | W54: =S54+T54+U54+V54 -> 10.832222 | X54: =(N54+R54+W54)*1% -> 0.45264794 | Y54: =X54 -> 0.45264794 | Z54: =$Z$12/E54 -> 0.029642857 | AA54: =$AA$12/E54 -> 0.74404762 | AB54: =$AB$12/E54 -> 0.70684524 | AC54: =$AC$12/E54 -> 0 | AD54: =Z54+AA54+AB54+AC54 -> 1.4805357 | AE54: =(AD54+Y54+W54+R54+N54)*$AE$7 -> 11.799494 | AF54: =AE54 -> 11.799494 | AL54: =(AD54+Y54+W54+R54+N54)*$AL$7 -> 0 | AM54: =AL54+AF54+AD54+Y54+W54+R54+N54 -> 58.997472 | AN54: =AM54*$AN$12 -> 0.70796966 | AO54: =AM54*$AO$12 -> 0.63717269 | AP54: =AO54+AN54 -> 1.3451424 | AQ54: =AM54*$AQ$12 -> 4.9262889 | AR54: =AM54*$AR$12 -> 0 | AS54: =AM54*$AS$12 -> 0 | AT54: =AQ54+AR54+AS54 -> 4.9262889 | AU54: =AM54*$AU$12 -> 2.9498736 | AV54: =AU54 -> 2.9498736 | AW54: =AM54+AP54+AT54+AV54 -> 68.218776 | AX54: =AY54/AW54 -> -0.12047675 | AY54: =I54-AW54 -> -8.2187764 | AZ54: =IFERROR(H54*VLOOKUP(A54,'Tabela de Produtos'!A:Q,17,0),0) -> 39.21 | BA54: =$I54*BA$12 -> 0 | BB54: =$I54*BB$12 -> 0 | BC54: =$I54*BC$12 -> 0 | BD54: =$I54*BD$12 -> 4.2 | BE54: =I54*$BE$12 -> 3 | BF54: =SUM(AZ54:BE54) -> 46.41 | BG54: =I54-BF54 -> 13.59 | BH54: =IF(F54="Cadastrar Ficha de Produção",0,IFERROR(BG54/I54,0)) -> 0.2265
A55: PRD00042 | B55: =IFERROR(VLOOKUP(A55,'Tabela de Produtos'!A:B,2,0),"Preencher Cód. Produto") -> BRAZIMIL LÁTEX ECONÔMICO INT FOSCO 15L PALHA | D55: Balde | E55: 28 | F55: =IF(A55=0,0,VLOOKUP(A55,'Tabela de Produtos'!A:W,23,0)) -> 43.03 | G55: 60 | H55: 1 | I55: =G55*H55 -> 60 | J55: =VLOOKUP(B55,'Tabela de Produtos'!B:M,12,FALSE()) -> 24.6 | K55: =VLOOKUP(B55,'Tabela de Produtos'!B:P,15,FALSE()) -> 4.65 | L55: =J55*1% -> 0.246 | M55: =J55*1% -> 0.246 | N55: =J55+K55+L55+M55 -> 29.742 | O55: =($O$12/E55)*$O$13 -> 1.2928571 | P55: =($P$12/E55)*$P$13 -> 1.0103571 | Q55: =($Q$12/E55)*$Q$13 -> 1.0103571 | R55: =O55+P55+Q55 -> 3.3135714 | S55: =VLOOKUP(B55,'Tabela de Produtos'!B:N,13,FALSE()) -> 8.61 | T55: =$T$12/$T$8 -> 0.69444444 | U55: =$U$12/$U$8 -> 1.1944444 | V55: =$V$12/$V$8 -> 0.33333333 | W55: =S55+T55+U55+V55 -> 10.832222 | X55: =(N55+R55+W55)*1% -> 0.43887794 | Y55: =X55 -> 0.43887794 | Z55: =$Z$12/E55 -> 0.029642857 | AA55: =$AA$12/E55 -> 0.74404762 | AB55: =$AB$12/E55 -> 0.70684524 | AC55: =$AC$12/E55 -> 0 | AD55: =Z55+AA55+AB55+AC55 -> 1.4805357 | AE55: =(AD55+Y55+W55+R55+N55)*$AE$7 -> 11.451802 | AF55: =AE55 -> 11.451802 | AL55: =(AD55+Y55+W55+R55+N55)*$AL$7 -> 0 | AM55: =AL55+AF55+AD55+Y55+W55+R55+N55 -> 57.259009 | AN55: =AM55*$AN$12 -> 0.68710811 | AO55: =AM55*$AO$12 -> 0.6183973 | AP55: =AO55+AN55 -> 1.3055054 | AQ55: =AM55*$AQ$12 -> 4.7811273 | AR55: =AM55*$AR$12 -> 0 | AS55: =AM55*$AS$12 -> 0 | AT55: =AQ55+AR55+AS55 -> 4.7811273 | AU55: =AM55*$AU$12 -> 2.8629505 | AV55: =AU55 -> 2.8629505 | AW55: =AM55+AP55+AT55+AV55 -> 66.208592 | AX55: =AY55/AW55 -> -0.09377321 | AY55: =I55-AW55 -> -6.2085923 | AZ55: =IFERROR(H55*VLOOKUP(A55,'Tabela de Produtos'!A:Q,17,0),0) -> 37.86 | BA55: =$I55*BA$12 -> 0 | BB55: =$I55*BB$12 -> 0 | BC55: =$I55*BC$12 -> 0 | BD55: =$I55*BD$12 -> 4.2 | BE55: =I55*$BE$12 -> 3 | BF55: =SUM(AZ55:BE55) -> 45.06 | BG55: =I55-BF55 -> 14.94 | BH55: =IF(F55="Cadastrar Ficha de Produção",0,IFERROR(BG55/I55,0)) -> 0.249
A56: PRD00043 | B56: =IFERROR(VLOOKUP(A56,'Tabela de Produtos'!A:B,2,0),"Preencher Cód. Produto") -> BRAZIMIL LÁTEX ECONÔMICO INT FOSCO 15L VERDE PRIMAVERA | D56: Balde | E56: 28 | F56: =IF(A56=0,0,VLOOKUP(A56,'Tabela de Produtos'!A:W,23,0)) -> 47.8 | G56: 60 | H56: 1 | I56: =G56*H56 -> 60 | J56: =VLOOKUP(B56,'Tabela de Produtos'!B:M,12,FALSE()) -> 28.8 | K56: =VLOOKUP(B56,'Tabela de Produtos'!B:P,15,FALSE()) -> 4.65 | L56: =J56*1% -> 0.288 | M56: =J56*1% -> 0.288 | N56: =J56+K56+L56+M56 -> 34.026 | O56: =($O$12/E56)*$O$13 -> 1.2928571 | P56: =($P$12/E56)*$P$13 -> 1.0103571 | Q56: =($Q$12/E56)*$Q$13 -> 1.0103571 | R56: =O56+P56+Q56 -> 3.3135714 | S56: =VLOOKUP(B56,'Tabela de Produtos'!B:N,13,FALSE()) -> 8.61 | T56: =$T$12/$T$8 -> 0.69444444 | U56: =$U$12/$U$8 -> 1.1944444 | V56: =$V$12/$V$8 -> 0.33333333 | W56: =S56+T56+U56+V56 -> 10.832222 | X56: =(N56+R56+W56)*1% -> 0.48171794 | Y56: =X56 -> 0.48171794 | Z56: =$Z$12/E56 -> 0.029642857 | AA56: =$AA$12/E56 -> 0.74404762 | AB56: =$AB$12/E56 -> 0.70684524 | AC56: =$AC$12/E56 -> 0 | AD56: =Z56+AA56+AB56+AC56 -> 1.4805357 | AE56: =(AD56+Y56+W56+R56+N56)*$AE$7 -> 12.533512 | AF56: =AE56 -> 12.533512 | AL56: =(AD56+Y56+W56+R56+N56)*$AL$7 -> 0 | AM56: =AL56+AF56+AD56+Y56+W56+R56+N56 -> 62.667559 | AN56: =AM56*$AN$12 -> 0.75201071 | AO56: =AM56*$AO$12 -> 0.67680964 | AP56: =AO56+AN56 -> 1.4288203 | AQ56: =AM56*$AQ$12 -> 5.2327412 | AR56: =AM56*$AR$12 -> 0 | AS56: =AM56*$AS$12 -> 0 | AT56: =AQ56+AR56+AS56 -> 5.2327412 | AU56: =AM56*$AU$12 -> 3.133378 | AV56: =AU56 -> 3.133378 | AW56: =AM56+AP56+AT56+AV56 -> 72.462499 | AX56: =AY56/AW56 -> -0.17198549 | AY56: =I56-AW56 -> -12.462499 | AZ56: =IFERROR(H56*VLOOKUP(A56,'Tabela de Produtos'!A:Q,17,0),0) -> 42.06 | BA56: =$I56*BA$12 -> 0 | BB56: =$I56*BB$12 -> 0 | BC56: =$I56*BC$12 -> 0 | BD56: =$I56*BD$12 -> 4.2 | BE56: =I56*$BE$12 -> 3 | BF56: =SUM(AZ56:BE56) -> 49.26 | BG56: =I56-BF56 -> 10.74 | BH56: =IF(F56="Cadastrar Ficha de Produção",0,IFERROR(BG56/I56,0)) -> 0.179
A57: PRD00044 | B57: =IFERROR(VLOOKUP(A57,'Tabela de Produtos'!A:B,2,0),"Preencher Cód. Produto") -> BRAZIMIL LÁTEX ECONÔMICO INT FOSCO 15L VERDE FOLHA | D57: Balde | E57: 28 | F57: =IF(A57=0,0,VLOOKUP(A57,'Tabela de Produtos'!A:W,23,0)) -> 54.11 | G57: 60 | H57: 1 | I57: =G57*H57 -> 60 | J57: =VLOOKUP(B57,'Tabela de Produtos'!B:M,12,FALSE()) -> 34.35 | K57: =VLOOKUP(B57,'Tabela de Produtos'!B:P,15,FALSE()) -> 4.65 | L57: =J57*1% -> 0.3435 | M57: =J57*1% -> 0.3435 | N57: =J57+K57+L57+M57 -> 39.687 | O57: =($O$12/E57)*$O$13 -> 1.2928571 | P57: =($P$12/E57)*$P$13 -> 1.0103571 | Q57: =($Q$12/E57)*$Q$13 -> 1.0103571 | R57: =O57+P57+Q57 -> 3.3135714 | S57: =VLOOKUP(B57,'Tabela de Produtos'!B:N,13,FALSE()) -> 8.61 | T57: =$T$12/$T$8 -> 0.69444444 | U57: =$U$12/$U$8 -> 1.1944444 | V57: =$V$12/$V$8 -> 0.33333333 | W57: =S57+T57+U57+V57 -> 10.832222 | X57: =(N57+R57+W57)*1% -> 0.53832794 | Y57: =X57 -> 0.53832794 | Z57: =$Z$12/E57 -> 0.029642857 | AA57: =$AA$12/E57 -> 0.74404762 | AB57: =$AB$12/E57 -> 0.70684524 | AC57: =$AC$12/E57 -> 0 | AD57: =Z57+AA57+AB57+AC57 -> 1.4805357 | AE57: =(AD57+Y57+W57+R57+N57)*$AE$7 -> 13.962914 | AF57: =AE57 -> 13.962914 | AL57: =(AD57+Y57+W57+R57+N57)*$AL$7 -> 0 | AM57: =AL57+AF57+AD57+Y57+W57+R57+N57 -> 69.814572 | AN57: =AM57*$AN$12 -> 0.83777486 | AO57: =AM57*$AO$12 -> 0.75399737 | AP57: =AO57+AN57 -> 1.5917722 | AQ57: =AM57*$AQ$12 -> 5.8295167 | AR57: =AM57*$AR$12 -> 0 | AS57: =AM57*$AS$12 -> 0 | AT57: =AQ57+AR57+AS57 -> 5.8295167 | AU57: =AM57*$AU$12 -> 3.4907286 | AV57: =AU57 -> 3.4907286 | AW57: =AM57+AP57+AT57+AV57 -> 80.726589 | AX57: =AY57/AW57 -> -0.25675046 | AY57: =I57-AW57 -> -20.726589 | AZ57: =IFERROR(H57*VLOOKUP(A57,'Tabela de Produtos'!A:Q,17,0),0) -> 47.61 | BA57: =$I57*BA$12 -> 0 | BB57: =$I57*BB$12 -> 0 | BC57: =$I57*BC$12 -> 0 | BD57: =$I57*BD$12 -> 4.2 | BE57: =I57*$BE$12 -> 3 | BF57: =SUM(AZ57:BE57) -> 54.81 | BG57: =I57-BF57 -> 5.19 | BH57: =IF(F57="Cadastrar Ficha de Produção",0,IFERROR(BG57/I57,0)) -> 0.0865
A58: PRD00045 | B58: =IFERROR(VLOOKUP(A58,'Tabela de Produtos'!A:B,2,0),"Preencher Cód. Produto") -> BRAZIMIL LÁTEX ECONÔMICO INT FOSCO 15L AZUL CEU | D58: Balde | E58: 28 | F58: =IF(A58=0,0,VLOOKUP(A58,'Tabela de Produtos'!A:W,23,0)) -> 42.69 | G58: 60 | H58: 1 | I58: =G58*H58 -> 60 | J58: =VLOOKUP(B58,'Tabela de Produtos'!B:M,12,FALSE()) -> 24.3 | K58: =VLOOKUP(B58,'Tabela de Produtos'!B:P,15,FALSE()) -> 4.65 | L58: =J58*1% -> 0.243 | M58: =J58*1% -> 0.243 | N58: =J58+K58+L58+M58 -> 29.436 | O58: =($O$12/E58)*$O$13 -> 1.2928571 | P58: =($P$12/E58)*$P$13 -> 1.0103571 | Q58: =($Q$12/E58)*$Q$13 -> 1.0103571 | R58: =O58+P58+Q58 -> 3.3135714 | S58: =VLOOKUP(B58,'Tabela de Produtos'!B:N,13,FALSE()) -> 8.61 | T58: =$T$12/$T$8 -> 0.69444444 | U58: =$U$12/$U$8 -> 1.1944444 | V58: =$V$12/$V$8 -> 0.33333333 | W58: =S58+T58+U58+V58 -> 10.832222 | X58: =(N58+R58+W58)*1% -> 0.43581794 | Y58: =X58 -> 0.43581794 | Z58: =$Z$12/E58 -> 0.029642857 | AA58: =$AA$12/E58 -> 0.74404762 | AB58: =$AB$12/E58 -> 0.70684524 | AC58: =$AC$12/E58 -> 0 | AD58: =Z58+AA58+AB58+AC58 -> 1.4805357 | AE58: =(AD58+Y58+W58+R58+N58)*$AE$7 -> 11.374537 | AF58: =AE58 -> 11.374537 | AL58: =(AD58+Y58+W58+R58+N58)*$AL$7 -> 0 | AM58: =AL58+AF58+AD58+Y58+W58+R58+N58 -> 56.872684 | AN58: =AM58*$AN$12 -> 0.68247221 | AO58: =AM58*$AO$12 -> 0.61422499 | AP58: =AO58+AN58 -> 1.2966972 | AQ58: =AM58*$AQ$12 -> 4.7488691 | AR58: =AM58*$AR$12 -> 0 | AS58: =AM58*$AS$12 -> 0 | AT58: =AQ58+AR58+AS58 -> 4.7488691 | AU58: =AM58*$AU$12 -> 2.8436342 | AV58: =AU58 -> 2.8436342 | AW58: =AM58+AP58+AT58+AV58 -> 65.761885 | AX58: =AY58/AW58 -> -0.087617389 | AY58: =I58-AW58 -> -5.7618847 | AZ58: =IFERROR(H58*VLOOKUP(A58,'Tabela de Produtos'!A:Q,17,0),0) -> 37.56 | BA58: =$I58*BA$12 -> 0 | BB58: =$I58*BB$12 -> 0 | BC58: =$I58*BC$12 -> 0 | BD58: =$I58*BD$12 -> 4.2 | BE58: =I58*$BE$12 -> 3 | BF58: =SUM(AZ58:BE58) -> 44.76 | BG58: =I58-BF58 -> 15.24 | BH58: =IF(F58="Cadastrar Ficha de Produção",0,IFERROR(BG58/I58,0)) -> 0.254
A59: PRD00046 | B59: =IFERROR(VLOOKUP(A59,'Tabela de Produtos'!A:B,2,0),"Preencher Cód. Produto") -> BRAZIMIL LÁTEX ECONÔMICO INT FOSCO 15L AZUL OCEANO | D59: Balde | E59: 28 | F59: =IF(A59=0,0,VLOOKUP(A59,'Tabela de Produtos'!A:W,23,0)) -> 49.33 | G59: 60 | H59: 1 | I59: =G59*H59 -> 60 | J59: =VLOOKUP(B59,'Tabela de Produtos'!B:M,12,FALSE()) -> 30.15 | K59: =VLOOKUP(B59,'Tabela de Produtos'!B:P,15,FALSE()) -> 4.65 | L59: =J59*1% -> 0.3015 | M59: =J59*1% -> 0.3015 | N59: =J59+K59+L59+M59 -> 35.403 | O59: =($O$12/E59)*$O$13 -> 1.2928571 | P59: =($P$12/E59)*$P$13 -> 1.0103571 | Q59: =($Q$12/E59)*$Q$13 -> 1.0103571 | R59: =O59+P59+Q59 -> 3.3135714 | S59: =VLOOKUP(B59,'Tabela de Produtos'!B:N,13,FALSE()) -> 8.61 | T59: =$T$12/$T$8 -> 0.69444444 | U59: =$U$12/$U$8 -> 1.1944444 | V59: =$V$12/$V$8 -> 0.33333333 | W59: =S59+T59+U59+V59 -> 10.832222 | X59: =(N59+R59+W59)*1% -> 0.49548794 | Y59: =X59 -> 0.49548794 | Z59: =$Z$12/E59 -> 0.029642857 | AA59: =$AA$12/E59 -> 0.74404762 | AB59: =$AB$12/E59 -> 0.70684524 | AC59: =$AC$12/E59 -> 0 | AD59: =Z59+AA59+AB59+AC59 -> 1.4805357 | AE59: =(AD59+Y59+W59+R59+N59)*$AE$7 -> 12.881204 | AF59: =AE59 -> 12.881204 | AL59: =(AD59+Y59+W59+R59+N59)*$AL$7 -> 0 | AM59: =AL59+AF59+AD59+Y59+W59+R59+N59 -> 64.406022 | AN59: =AM59*$AN$12 -> 0.77287226 | AO59: =AM59*$AO$12 -> 0.69558503 | AP59: =AO59+AN59 -> 1.4684573 | AQ59: =AM59*$AQ$12 -> 5.3779028 | AR59: =AM59*$AR$12 -> 0 | AS59: =AM59*$AS$12 -> 0 | AT59: =AQ59+AR59+AS59 -> 5.3779028 | AU59: =AM59*$AU$12 -> 3.2203011 | AV59: =AU59 -> 3.2203011 | AW59: =AM59+AP59+AT59+AV59 -> 74.472683 | AX59: =AY59/AW59 -> -0.19433546 | AY59: =I59-AW59 -> -14.472683 | AZ59: =IFERROR(H59*VLOOKUP(A59,'Tabela de Produtos'!A:Q,17,0),0) -> 43.41 | BA59: =$I59*BA$12 -> 0 | BB59: =$I59*BB$12 -> 0 | BC59: =$I59*BC$12 -> 0 | BD59: =$I59*BD$12 -> 4.2 | BE59: =I59*$BE$12 -> 3 | BF59: =SUM(AZ59:BE59) -> 50.61 | BG59: =I59-BF59 -> 9.39 | BH59: =IF(F59="Cadastrar Ficha de Produção",0,IFERROR(BG59/I59,0)) -> 0.1565
A60: PRD00047 | B60: =IFERROR(VLOOKUP(A60,'Tabela de Produtos'!A:B,2,0),"Preencher Cód. Produto") -> BRAZIMIL LÁTEX ECONÔMICO INT FOSCO 15L AMARELO CANARIO | D60: Balde | E60: 28 | F60: =IF(A60=0,0,VLOOKUP(A60,'Tabela de Produtos'!A:W,23,0)) -> 44.22 | G60: 60 | H60: 1 | I60: =G60*H60 -> 60 | J60: =VLOOKUP(B60,'Tabela de Produtos'!B:M,12,FALSE()) -> 25.65 | K60: =VLOOKUP(B60,'Tabela de Produtos'!B:P,15,FALSE()) -> 4.65 | L60: =J60*1% -> 0.2565 | M60: =J60*1% -> 0.2565 | N60: =J60+K60+L60+M60 -> 30.813 | O60: =($O$12/E60)*$O$13 -> 1.2928571 | P60: =($P$12/E60)*$P$13 -> 1.0103571 | Q60: =($Q$12/E60)*$Q$13 -> 1.0103571 | R60: =O60+P60+Q60 -> 3.3135714 | S60: =VLOOKUP(B60,'Tabela de Produtos'!B:N,13,FALSE()) -> 8.61 | T60: =$T$12/$T$8 -> 0.69444444 | U60: =$U$12/$U$8 -> 1.1944444 | V60: =$V$12/$V$8 -> 0.33333333 | W60: =S60+T60+U60+V60 -> 10.832222 | X60: =(N60+R60+W60)*1% -> 0.44958794 | Y60: =X60 -> 0.44958794 | Z60: =$Z$12/E60 -> 0.029642857 | AA60: =$AA$12/E60 -> 0.74404762 | AB60: =$AB$12/E60 -> 0.70684524 | AC60: =$AC$12/E60 -> 0 | AD60: =Z60+AA60+AB60+AC60 -> 1.4805357 | AE60: =(AD60+Y60+W60+R60+N60)*$AE$7 -> 11.722229 | AF60: =AE60 -> 11.722229 | AL60: =(AD60+Y60+W60+R60+N60)*$AL$7 -> 0 | AM60: =AL60+AF60+AD60+Y60+W60+R60+N60 -> 58.611147 | AN60: =AM60*$AN$12 -> 0.70333376 | AO60: =AM60*$AO$12 -> 0.63300038 | AP60: =AO60+AN60 -> 1.3363341 | AQ60: =AM60*$AQ$12 -> 4.8940307 | AR60: =AM60*$AR$12 -> 0 | AS60: =AM60*$AS$12 -> 0 | AT60: =AQ60+AR60+AS60 -> 4.8940307 | AU60: =AM60*$AU$12 -> 2.9305573 | AV60: =AU60 -> 2.9305573 | AW60: =AM60+AP60+AT60+AV60 -> 67.772069 | AX60: =AY60/AW60 -> -0.11467953 | AY60: =I60-AW60 -> -7.7720688 | AZ60: =IFERROR(H60*VLOOKUP(A60,'Tabela de Produtos'!A:Q,17,0),0) -> 38.91 | BA60: =$I60*BA$12 -> 0 | BB60: =$I60*BB$12 -> 0 | BC60: =$I60*BC$12 -> 0 | BD60: =$I60*BD$12 -> 4.2 | BE60: =I60*$BE$12 -> 3 | BF60: =SUM(AZ60:BE60) -> 46.11 | BG60: =I60-BF60 -> 13.89 | BH60: =IF(F60="Cadastrar Ficha de Produção",0,IFERROR(BG60/I60,0)) -> 0.2315
A61: PRD00048 | B61: =IFERROR(VLOOKUP(A61,'Tabela de Produtos'!A:B,2,0),"Preencher Cód. Produto") -> BRAZIMIL LÁTEX ECONÔMICO INT FOSCO 15L CROMO SUAVE | D61: Balde | E61: 28 | F61: =IF(A61=0,0,VLOOKUP(A61,'Tabela de Produtos'!A:W,23,0)) -> 48.31 | G61: 60 | H61: 1 | I61: =G61*H61 -> 60 | J61: =VLOOKUP(B61,'Tabela de Produtos'!B:M,12,FALSE()) -> 29.25 | K61: =VLOOKUP(B61,'Tabela de Produtos'!B:P,15,FALSE()) -> 4.65 | L61: =J61*1% -> 0.2925 | M61: =J61*1% -> 0.2925 | N61: =J61+K61+L61+M61 -> 34.485 | O61: =($O$12/E61)*$O$13 -> 1.2928571 | P61: =($P$12/E61)*$P$13 -> 1.0103571 | Q61: =($Q$12/E61)*$Q$13 -> 1.0103571 | R61: =O61+P61+Q61 -> 3.3135714 | S61: =VLOOKUP(B61,'Tabela de Produtos'!B:N,13,FALSE()) -> 8.61 | T61: =$T$12/$T$8 -> 0.69444444 | U61: =$U$12/$U$8 -> 1.1944444 | V61: =$V$12/$V$8 -> 0.33333333 | W61: =S61+T61+U61+V61 -> 10.832222 | X61: =(N61+R61+W61)*1% -> 0.48630794 | Y61: =X61 -> 0.48630794 | Z61: =$Z$12/E61 -> 0.029642857 | AA61: =$AA$12/E61 -> 0.74404762 | AB61: =$AB$12/E61 -> 0.70684524 | AC61: =$AC$12/E61 -> 0 | AD61: =Z61+AA61+AB61+AC61 -> 1.4805357 | AE61: =(AD61+Y61+W61+R61+N61)*$AE$7 -> 12.649409 | AF61: =AE61 -> 12.649409 | AL61: =(AD61+Y61+W61+R61+N61)*$AL$7 -> 0 | AM61: =AL61+AF61+AD61+Y61+W61+R61+N61 -> 63.247047 | AN61: =AM61*$AN$12 -> 0.75896456 | AO61: =AM61*$AO$12 -> 0.6830681 | AP61: =AO61+AN61 -> 1.4420327 | AQ61: =AM61*$AQ$12 -> 5.2811284 | AR61: =AM61*$AR$12 -> 0 | AS61: =AM61*$AS$12 -> 0 | AT61: =AQ61+AR61+AS61 -> 5.2811284 | AU61: =AM61*$AU$12 -> 3.1623523 | AV61: =AU61 -> 3.1623523 | AW61: =AM61+AP61+AT61+AV61 -> 73.13256 | AX61: =AY61/AW61 -> -0.179572 | AY61: =I61-AW61 -> -13.13256 | AZ61: =IFERROR(H61*VLOOKUP(A61,'Tabela de Produtos'!A:Q,17,0),0) -> 42.51 | BA61: =$I61*BA$12 -> 0 | BB61: =$I61*BB$12 -> 0 | BC61: =$I61*BC$12 -> 0 | BD61: =$I61*BD$12 -> 4.2 | BE61: =I61*$BE$12 -> 3 | BF61: =SUM(AZ61:BE61) -> 49.71 | BG61: =I61-BF61 -> 10.29 | BH61: =IF(F61="Cadastrar Ficha de Produção",0,IFERROR(BG61/I61,0)) -> 0.1715
A62: PRD00049 | B62: =IFERROR(VLOOKUP(A62,'Tabela de Produtos'!A:B,2,0),"Preencher Cód. Produto") -> BRAZIMIL LÁTEX ECONÔMICO INT FOSCO 15L ROSA BEBE | D62: Balde | E62: 28 | F62: =IF(A62=0,0,VLOOKUP(A62,'Tabela de Produtos'!A:W,23,0)) -> 43.2 | G62: 60 | H62: 1 | I62: =G62*H62 -> 60 | J62: =VLOOKUP(B62,'Tabela de Produtos'!B:M,12,FALSE()) -> 24.75 | K62: =VLOOKUP(B62,'Tabela de Produtos'!B:P,15,FALSE()) -> 4.65 | L62: =J62*1% -> 0.2475 | M62: =J62*1% -> 0.2475 | N62: =J62+K62+L62+M62 -> 29.895 | O62: =($O$12/E62)*$O$13 -> 1.2928571 | P62: =($P$12/E62)*$P$13 -> 1.0103571 | Q62: =($Q$12/E62)*$Q$13 -> 1.0103571 | R62: =O62+P62+Q62 -> 3.3135714 | S62: =VLOOKUP(B62,'Tabela de Produtos'!B:N,13,FALSE()) -> 8.61 | T62: =$T$12/$T$8 -> 0.69444444 | U62: =$U$12/$U$8 -> 1.1944444 | V62: =$V$12/$V$8 -> 0.33333333 | W62: =S62+T62+U62+V62 -> 10.832222 | X62: =(N62+R62+W62)*1% -> 0.44040794 | Y62: =X62 -> 0.44040794 | Z62: =$Z$12/E62 -> 0.029642857 | AA62: =$AA$12/E62 -> 0.74404762 | AB62: =$AB$12/E62 -> 0.70684524 | AC62: =$AC$12/E62 -> 0 | AD62: =Z62+AA62+AB62+AC62 -> 1.4805357 | AE62: =(AD62+Y62+W62+R62+N62)*$AE$7 -> 11.490434 | AF62: =AE62 -> 11.490434 | AL62: =(AD62+Y62+W62+R62+N62)*$AL$7 -> 0 | AM62: =AL62+AF62+AD62+Y62+W62+R62+N62 -> 57.452172 | AN62: =AM62*$AN$12 -> 0.68942606 | AO62: =AM62*$AO$12 -> 0.62048345 | AP62: =AO62+AN62 -> 1.3099095 | AQ62: =AM62*$AQ$12 -> 4.7972563 | AR62: =AM62*$AR$12 -> 0 | AS62: =AM62*$AS$12 -> 0 | AT62: =AQ62+AR62+AS62 -> 4.7972563 | AU62: =AM62*$AU$12 -> 2.8726086 | AV62: =AU62 -> 2.8726086 | AW62: =AM62+AP62+AT62+AV62 -> 66.431946 | AX62: =AY62/AW62 -> -0.096820076 | AY62: =I62-AW62 -> -6.4319461 | AZ62: =IFERROR(H62*VLOOKUP(A62,'Tabela de Produtos'!A:Q,17,0),0) -> 38.01 | BA62: =$I62*BA$12 -> 0 | BB62: =$I62*BB$12 -> 0 | BC62: =$I62*BC$12 -> 0 | BD62: =$I62*BD$12 -> 4.2 | BE62: =I62*$BE$12 -> 3 | BF62: =SUM(AZ62:BE62) -> 45.21 | BG62: =I62-BF62 -> 14.79 | BH62: =IF(F62="Cadastrar Ficha de Produção",0,IFERROR(BG62/I62,0)) -> 0.2465
A63: PRD00050 | B63: =IFERROR(VLOOKUP(A63,'Tabela de Produtos'!A:B,2,0),"Preencher Cód. Produto") -> BRAZIMIL LÁTEX ECONÔMICO INT FOSCO 15L MARFIM | D63: Balde | E63: 28 | F63: =IF(A63=0,0,VLOOKUP(A63,'Tabela de Produtos'!A:W,23,0)) -> 43.37 | G63: 60 | H63: 1 | I63: =G63*H63 -> 60 | J63: =VLOOKUP(B63,'Tabela de Produtos'!B:M,12,FALSE()) -> 24.9 | K63: =VLOOKUP(B63,'Tabela de Produtos'!B:P,15,FALSE()) -> 4.65 | L63: =J63*1% -> 0.249 | M63: =J63*1% -> 0.249 | N63: =J63+K63+L63+M63 -> 30.048 | O63: =($O$12/E63)*$O$13 -> 1.2928571 | P63: =($P$12/E63)*$P$13 -> 1.0103571 | Q63: =($Q$12/E63)*$Q$13 -> 1.0103571 | R63: =O63+P63+Q63 -> 3.3135714 | S63: =VLOOKUP(B63,'Tabela de Produtos'!B:N,13,FALSE()) -> 8.61 | T63: =$T$12/$T$8 -> 0.69444444 | U63: =$U$12/$U$8 -> 1.1944444 | V63: =$V$12/$V$8 -> 0.33333333 | W63: =S63+T63+U63+V63 -> 10.832222 | X63: =(N63+R63+W63)*1% -> 0.44193794 | Y63: =X63 -> 0.44193794 | Z63: =$Z$12/E63 -> 0.029642857 | AA63: =$AA$12/E63 -> 0.74404762 | AB63: =$AB$12/E63 -> 0.70684524 | AC63: =$AC$12/E63 -> 0 | AD63: =Z63+AA63+AB63+AC63 -> 1.4805357 | AE63: =(AD63+Y63+W63+R63+N63)*$AE$7 -> 11.529067 | AF63: =AE63 -> 11.529067 | AL63: =(AD63+Y63+W63+R63+N63)*$AL$7 -> 0 | AM63: =AL63+AF63+AD63+Y63+W63+R63+N63 -> 57.645334 | AN63: =AM63*$AN$12 -> 0.69174401 | AO63: =AM63*$AO$12 -> 0.62256961 | AP63: =AO63+AN63 -> 1.3143136 | AQ63: =AM63*$AQ$12 -> 4.8133854 | AR63: =AM63*$AR$12 -> 0 | AS63: =AM63*$AS$12 -> 0 | AT63: =AQ63+AR63+AS63 -> 4.8133854 | AU63: =AM63*$AU$12 -> 2.8822667 | AV63: =AU63 -> 2.8822667 | AW63: =AM63+AP63+AT63+AV63 -> 66.6553 | AX63: =AY63/AW63 -> -0.099846522 | AY63: =I63-AW63 -> -6.6552999 | AZ63: =IFERROR(H63*VLOOKUP(A63,'Tabela de Produtos'!A:Q,17,0),0) -> 38.16 | BA63: =$I63*BA$12 -> 0 | BB63: =$I63*BB$12 -> 0 | BC63: =$I63*BC$12 -> 0 | BD63: =$I63*BD$12 -> 4.2 | BE63: =I63*$BE$12 -> 3 | BF63: =SUM(AZ63:BE63) -> 45.36 | BG63: =I63-BF63 -> 14.64 | BH63: =IF(F63="Cadastrar Ficha de Produção",0,IFERROR(BG63/I63,0)) -> 0.244
... A66: PRD00053 | B66: =IFERROR(VLOOKUP(A66,'Tabela de Produtos'!A:B,2,0),"Preencher Cód. Produto") -> BRAZIMIL LÁTEX ECONÔMICO INT FOSCO 15L PEROLA | D66: Balde | E66: 28 | F66: =IF(A66=0,0,VLOOKUP(A66,'Tabela de Produtos'!A:W,23,0)) -> 43.03 | G66: 60 | H66: 1 | I66: =G66*H66 -> 60 | J66: =VLOOKUP(B66,'Tabela de Produtos'!B:M,12,FALSE()) -> 24.6 | K66: =VLOOKUP(B66,'Tabela de Produtos'!B:P,15,FALSE()) -> 4.65 | L66: =J66*1% -> 0.246 | M66: =J66*1% -> 0.246 | N66: =J66+K66+L66+M66 -> 29.742 | O66: =($O$12/E66)*$O$13 -> 1.2928571 | P66: =($P$12/E66)*$P$13 -> 1.0103571 | Q66: =($Q$12/E66)*$Q$13 -> 1.0103571 | R66: =O66+P66+Q66 -> 3.3135714 | S66: =VLOOKUP(B66,'Tabela de Produtos'!B:N,13,FALSE()) -> 8.61 | T66: =$T$12/$T$8 -> 0.69444444 | U66: =$U$12/$U$8 -> 1.1944444 | V66: =$V$12/$V$8 -> 0.33333333 | W66: =S66+T66+U66+V66 -> 10.832222 | X66: =(N66+R66+W66)*1% -> 0.43887794 | Y66: =X66 -> 0.43887794 | Z66: =$Z$12/E66 -> 0.029642857 | AA66: =$AA$12/E66 -> 0.74404762 | AB66: =$AB$12/E66 -> 0.70684524 | AC66: =$AC$12/E66 -> 0 | AD66: =Z66+AA66+AB66+AC66 -> 1.4805357 | AE66: =(AD66+Y66+W66+R66+N66)*$AE$7 -> 11.451802 | AF66: =AE66 -> 11.451802 | AL66: =(AD66+Y66+W66+R66+N66)*$AL$7 -> 0 | AM66: =AL66+AF66+AD66+Y66+W66+R66+N66 -> 57.259009 | AN66: =AM66*$AN$12 -> 0.68710811 | AO66: =AM66*$AO$12 -> 0.6183973 | AP66: =AO66+AN66 -> 1.3055054 | AQ66: =AM66*$AQ$12 -> 4.7811273 | AR66: =AM66*$AR$12 -> 0 | AS66: =AM66*$AS$12 -> 0 | AT66: =AQ66+AR66+AS66 -> 4.7811273 | AU66: =AM66*$AU$12 -> 2.8629505 | AV66: =AU66 -> 2.8629505 | AW66: =AM66+AP66+AT66+AV66 -> 66.208592 | AX66: =AY66/AW66 -> -0.09377321 | AY66: =I66-AW66 -> -6.2085923 | AZ66: =IFERROR(H66*VLOOKUP(A66,'Tabela de Produtos'!A:Q,17,0),0) -> 37.86 | BA66: =$I66*BA$12 -> 0 | BB66: =$I66*BB$12 -> 0 | BC66: =$I66*BC$12 -> 0 | BD66: =$I66*BD$12 -> 4.2 | BE66: =I66*$BE$12 -> 3 | BF66: =SUM(AZ66:BE66) -> 45.06 | BG66: =I66-BF66 -> 14.94 | BH66: =IF(F66="Cadastrar Ficha de Produção",0,IFERROR(BG66/I66,0)) -> 0.249
A67: PRD00054 | B67: =IFERROR(VLOOKUP(A67,'Tabela de Produtos'!A:B,2,0),"Preencher Cód. Produto") -> BRAZIMIL LÁTEX ECONÔMICO INT/EXT SEMIBRILHO 15L BRANCO NEVE | D67: Balde | F67: =IF(A67=0,0,VLOOKUP(A67,'Tabela de Produtos'!A:W,23,0)) -> Cadastrar Ficha de Produção | G67: 0 | H67: 1 | I67: =G67*H67 -> 0 | J67: =VLOOKUP(B67,'Tabela de Produtos'!B:M,12,FALSE()) -> 0 | AY67: =I67-AW67 -> 0 | AZ67: =IFERROR(H67*VLOOKUP(A67,'Tabela de Produtos'!A:Q,17,0),0) -> 0 | BA67: =$I67*BA$12 -> 0 | BB67: =$I67*BB$12 -> 0 | BC67: =$I67*BC$12 -> 0 | BD67: =$I67*BD$12 -> 0 | BE67: =I67*$BE$12 -> 0 | BF67: =SUM(AZ67:BE67) -> 0 | BG67: =I67-BF67 -> 0 | BH67: =IF(F67="Cadastrar Ficha de Produção",0,IFERROR(BG67/I67,0)) -> 0
A68: PRD00055 | B68: =IFERROR(VLOOKUP(A68,'Tabela de Produtos'!A:B,2,0),"Preencher Cód. Produto") -> BRAZIMIL LÁTEX ECONÔMICO INT/EXT SEMIBRILHO 15L BRANCO GELO | D68: Balde | F68: =IF(A68=0,0,VLOOKUP(A68,'Tabela de Produtos'!A:W,23,0)) -> Cadastrar Ficha de Produção | G68: 0 | H68: 1 | I68: =G68*H68 -> 0 | J68: =VLOOKUP(B68,'Tabela de Produtos'!B:M,12,FALSE()) -> 0 | AY68: =I68-AW68 -> 0 | AZ68: =IFERROR(H68*VLOOKUP(A68,'Tabela de Produtos'!A:Q,17,0),0) -> 0 | BA68: =$I68*BA$12 -> 0 | BB68: =$I68*BB$12 -> 0 | BC68: =$I68*BC$12 -> 0 | BD68: =$I68*BD$12 -> 0 | BE68: =I68*$BE$12 -> 0 | BF68: =SUM(AZ68:BE68) -> 0 | BG68: =I68-BF68 -> 0 | BH68: =IF(F68="Cadastrar Ficha de Produção",0,IFERROR(BG68/I68,0)) -> 0
A69: PRD00056 | B69: =IFERROR(VLOOKUP(A69,'Tabela de Produtos'!A:B,2,0),"Preencher Cód. Produto") -> BRAZIMIL LÁTEX ECONÔMICO INT/EXT SEMIBRILHO 15L AREIA | D69: Balde | F69: =IF(A69=0,0,VLOOKUP(A69,'Tabela de Produtos'!A:W,23,0)) -> Cadastrar Ficha de Produção | G69: 0 | H69: 1 | I69: =G69*H69 -> 0 | J69: =VLOOKUP(B69,'Tabela de Produtos'!B:M,12,FALSE()) -> 0 | AY69: =I69-AW69 -> 0 | AZ69: =IFERROR(H69*VLOOKUP(A69,'Tabela de Produtos'!A:Q,17,0),0) -> 0 | BA69: =$I69*BA$12 -> 0 | BB69: =$I69*BB$12 -> 0 | BC69: =$I69*BC$12 -> 0 | BD69: =$I69*BD$12 -> 0 | BE69: =I69*$BE$12 -> 0 | BF69: =SUM(AZ69:BE69) -> 0 | BG69: =I69-BF69 -> 0 | BH69: =IF(F69="Cadastrar Ficha de Produção",0,IFERROR(BG69/I69,0)) -> 0
A70: PRD00057 | B70: =IFERROR(VLOOKUP(A70,'Tabela de Produtos'!A:B,2,0),"Preencher Cód. Produto") -> BRAZIMIL LÁTEX ECONÔMICO INT/EXT SEMIBRILHO 15L PALHA | D70: Balde | F70: =IF(A70=0,0,VLOOKUP(A70,'Tabela de Produtos'!A:W,23,0)) -> Cadastrar Ficha de Produção | G70: 0 | H70: 1 | I70: =G70*H70 -> 0 | J70: =VLOOKUP(B70,'Tabela de Produtos'!B:M,12,FALSE()) -> 0 | AY70: =I70-AW70 -> 0 | AZ70: =IFERROR(H70*VLOOKUP(A70,'Tabela de Produtos'!A:Q,17,0),0) -> 0 | BA70: =$I70*BA$12 -> 0 | BB70: =$I70*BB$12 -> 0 | BC70: =$I70*BC$12 -> 0 | BD70: =$I70*BD$12 -> 0 | BE70: =I70*$BE$12 -> 0 | BF70: =SUM(AZ70:BE70) -> 0 | BG70: =I70-BF70 -> 0 | BH70: =IF(F70="Cadastrar Ficha de Produção",0,IFERROR(BG70/I70,0)) -> 0
A71: PRD00058 | B71: =IFERROR(VLOOKUP(A71,'Tabela de Produtos'!A:B,2,0),"Preencher Cód. Produto") -> BRAZIMIL LÁTEX ECONÔMICO INT/EXT SEMIBRILHO 15L VERDE PRIMAVERA | D71: Balde | F71: =IF(A71=0,0,VLOOKUP(A71,'Tabela de Produtos'!A:W,23,0)) -> Cadastrar Ficha de Produção | G71: 0 | H71: 1 | I71: =G71*H71 -> 0 | J71: =VLOOKUP(B71,'Tabela de Produtos'!B:M,12,FALSE()) -> 0 | AY71: =I71-AW71 -> 0 | AZ71: =IFERROR(H71*VLOOKUP(A71,'Tabela de Produtos'!A:Q,17,0),0) -> 0 | BA71: =$I71*BA$12 -> 0 | BB71: =$I71*BB$12 -> 0 | BC71: =$I71*BC$12 -> 0 | BD71: =$I71*BD$12 -> 0 | BE71: =I71*$BE$12 -> 0 | BF71: =SUM(AZ71:BE71) -> 0 | BG71: =I71-BF71 -> 0 | BH71: =IF(F71="Cadastrar Ficha de Produção",0,IFERROR(BG71/I71,0)) -> 0
A72: PRD00059 | B72: =IFERROR(VLOOKUP(A72,'Tabela de Produtos'!A:B,2,0),"Preencher Cód. Produto") -> BRAZIMIL LÁTEX ECONÔMICO INT/EXT SEMIBRILHO 15L VERDE FOLHA | D72: Balde | F72: =IF(A72=0,0,VLOOKUP(A72,'Tabela de Produtos'!A:W,23,0)) -> Cadastrar Ficha de Produção | G72: 0 | H72: 1 | I72: =G72*H72 -> 0 | J72: =VLOOKUP(B72,'Tabela de Produtos'!B:M,12,FALSE()) -> 0 | AY72: =I72-AW72 -> 0 | AZ72: =IFERROR(H72*VLOOKUP(A72,'Tabela de Produtos'!A:Q,17,0),0) -> 0 | BA72: =$I72*BA$12 -> 0 | BB72: =$I72*BB$12 -> 0 | BC72: =$I72*BC$12 -> 0 | BD72: =$I72*BD$12 -> 0 | BE72: =I72*$BE$12 -> 0 | BF72: =SUM(AZ72:BE72) -> 0 | BG72: =I72-BF72 -> 0 | BH72: =IF(F72="Cadastrar Ficha de Produção",0,IFERROR(BG72/I72,0)) -> 0
A73: PRD00060 | B73: =IFERROR(VLOOKUP(A73,'Tabela de Produtos'!A:B,2,0),"Preencher Cód. Produto") -> BRAZIMIL LÁTEX ECONÔMICO INT/EXT SEMIBRILHO 15L AZUL CEU | D73: Balde | F73: =IF(A73=0,0,VLOOKUP(A73,'Tabela de Produtos'!A:W,23,0)) -> Cadastrar Ficha de Produção | G73: 0 | H73: 1 | I73: =G73*H73 -> 0 | J73: =VLOOKUP(B73,'Tabela de Produtos'!B:M,12,FALSE()) -> 0 | AY73: =I73-AW73 -> 0 | AZ73: =IFERROR(H73*VLOOKUP(A73,'Tabela de Produtos'!A:Q,17,0),0) -> 0 | BA73: =$I73*BA$12 -> 0 | BB73: =$I73*BB$12 -> 0 | BC73: =$I73*BC$12 -> 0 | BD73: =$I73*BD$12 -> 0 | BE73: =I73*$BE$12 -> 0 | BF73: =SUM(AZ73:BE73) -> 0 | BG73: =I73-BF73 -> 0 | BH73: =IF(F73="Cadastrar Ficha de Produção",0,IFERROR(BG73/I73,0)) -> 0
A74: PRD00061 | B74: =IFERROR(VLOOKUP(A74,'Tabela de Produtos'!A:B,2,0),"Preencher Cód. Produto") -> BRAZIMIL LÁTEX ECONÔMICO INT/EXT SEMIBRILHO 15L AZUL OCEANO | D74: Balde | F74: =IF(A74=0,0,VLOOKUP(A74,'Tabela de Produtos'!A:W,23,0)) -> Cadastrar Ficha de Produção | G74: 0 | H74: 1 | I74: =G74*H74 -> 0 | J74: =VLOOKUP(B74,'Tabela de Produtos'!B:M,12,FALSE()) -> 0 | AY74: =I74-AW74 -> 0 | AZ74: =IFERROR(H74*VLOOKUP(A74,'Tabela de Produtos'!A:Q,17,0),0) -> 0 | BA74: =$I74*BA$12 -> 0 | BB74: =$I74*BB$12 -> 0 | BC74: =$I74*BC$12 -> 0 | BD74: =$I74*BD$12 -> 0 | BE74: =I74*$BE$12 -> 0 | BF74: =SUM(AZ74:BE74) -> 0 | BG74: =I74-BF74 -> 0 | BH74: =IF(F74="Cadastrar Ficha de Produção",0,IFERROR(BG74/I74,0)) -> 0
A75: PRD00062 | B75: =IFERROR(VLOOKUP(A75,'Tabela de Produtos'!A:B,2,0),"Preencher Cód. Produto") -> BRAZIMIL LÁTEX ECONÔMICO INT/EXT SEMIBRILHO 15L AMARELO CANARIO | D75: Balde | F75: =IF(A75=0,0,VLOOKUP(A75,'Tabela de Produtos'!A:W,23,0)) -> Cadastrar Ficha de Produção | G75: 0 | H75: 1 | I75: =G75*H75 -> 0 | J75: =VLOOKUP(B75,'Tabela de Produtos'!B:M,12,FALSE()) -> 0 | AY75: =I75-AW75 -> 0 | AZ75: =IFERROR(H75*VLOOKUP(A75,'Tabela de Produtos'!A:Q,17,0),0) -> 0 | BA75: =$I75*BA$12 -> 0 | BB75: =$I75*BB$12 -> 0 | BC75: =$I75*BC$12 -> 0 | BD75: =$I75*BD$12 -> 0 | BE75: =I75*$BE$12 -> 0 | BF75: =SUM(AZ75:BE75) -> 0 | BG75: =I75-BF75 -> 0 | BH75: =IF(F75="Cadastrar Ficha de Produção",0,IFERROR(BG75/I75,0)) -> 0
A76: PRD00063 | B76: =IFERROR(VLOOKUP(A76,'Tabela de Produtos'!A:B,2,0),"Preencher Cód. Produto") -> BRAZIMIL LÁTEX ECONÔMICO INT/EXT SEMIBRILHO 15L CROMO SUAVE | D76: Balde | F76: =IF(A76=0,0,VLOOKUP(A76,'Tabela de Produtos'!A:W,23,0)) -> Cadastrar Ficha de Produção | G76: 0 | H76: 1 | I76: =G76*H76 -> 0 | J76: =VLOOKUP(B76,'Tabela de Produtos'!B:M,12,FALSE()) -> 0 | AY76: =I76-AW76 -> 0 | AZ76: =IFERROR(H76*VLOOKUP(A76,'Tabela de Produtos'!A:Q,17,0),0) -> 0 | BA76: =$I76*BA$12 -> 0 | BB76: =$I76*BB$12 -> 0 | BC76: =$I76*BC$12 -> 0 | BD76: =$I76*BD$12 -> 0 | BE76: =I76*$BE$12 -> 0 | BF76: =SUM(AZ76:BE76) -> 0 | BG76: =I76-BF76 -> 0 | BH76: =IF(F76="Cadastrar Ficha de Produção",0,IFERROR(BG76/I76,0)) -> 0
A77: PRD00064 | B77: =IFERROR(VLOOKUP(A77,'Tabela de Produtos'!A:B,2,0),"Preencher Cód. Produto") -> BRAZIMIL LÁTEX ECONÔMICO INT/EXT SEMIBRILHO 15L ROSA BEBE | D77: Balde | F77: =IF(A77=0,0,VLOOKUP(A77,'Tabela de Produtos'!A:W,23,0)) -> Cadastrar Ficha de Produção | G77: 0 | H77: 1 | I77: =G77*H77 -> 0 | J77: =VLOOKUP(B77,'Tabela de Produtos'!B:M,12,FALSE()) -> 0 | AY77: =I77-AW77 -> 0 | AZ77: =IFERROR(H77*VLOOKUP(A77,'Tabela de Produtos'!A:Q,17,0),0) -> 0 | BA77: =$I77*BA$12 -> 0 | BB77: =$I77*BB$12 -> 0 | BC77: =$I77*BC$12 -> 0 | BD77: =$I77*BD$12 -> 0 | BE77: =I77*$BE$12 -> 0 | BF77: =SUM(AZ77:BE77) -> 0 | BG77: =I77-BF77 -> 0 | BH77: =IF(F77="Cadastrar Ficha de Produção",0,IFERROR(BG77/I77,0)) -> 0
A78: PRD00065 | B78: =IFERROR(VLOOKUP(A78,'Tabela de Produtos'!A:B,2,0),"Preencher Cód. Produto") -> BRAZIMIL LÁTEX ECONÔMICO INT/EXT SEMIBRILHO 15L MARFIM | D78: Balde | F78: =IF(A78=0,0,VLOOKUP(A78,'Tabela de Produtos'!A:W,23,0)) -> Cadastrar Ficha de Produção | G78: 0 | H78: 1 | I78: =G78*H78 -> 0 | J78: =VLOOKUP(B78,'Tabela de Produtos'!B:M,12,FALSE()) -> 0 | AY78: =I78-AW78 -> 0 | AZ78: =IFERROR(H78*VLOOKUP(A78,'Tabela de Produtos'!A:Q,17,0),0) -> 0 | BA78: =$I78*BA$12 -> 0 | BB78: =$I78*BB$12 -> 0 | BC78: =$I78*BC$12 -> 0 | BD78: =$I78*BD$12 -> 0 | BE78: =I78*$BE$12 -> 0 | BF78: =SUM(AZ78:BE78) -> 0 | BG78: =I78-BF78 -> 0 | BH78: =IF(F78="Cadastrar Ficha de Produção",0,IFERROR(BG78/I78,0)) -> 0
... A81: PRD00068 | B81: =IFERROR(VLOOKUP(A81,'Tabela de Produtos'!A:B,2,0),"Preencher Cód. Produto") -> BRAZIMIL LÁTEX ECONÔMICO INT/EXT SEMIBRILHO 15L PEROLA | D81: Balde | F81: =IF(A81=0,0,VLOOKUP(A81,'Tabela de Produtos'!A:W,23,0)) -> Cadastrar Ficha de Produção | G81: 0 | H81: 1 | I81: =G81*H81 -> 0 | J81: =VLOOKUP(B81,'Tabela de Produtos'!B:M,12,FALSE()) -> 0 | AY81: =I81-AW81 -> 0 | AZ81: =IFERROR(H81*VLOOKUP(A81,'Tabela de Produtos'!A:Q,17,0),0) -> 0 | BA81: =$I81*BA$12 -> 0 | BB81: =$I81*BB$12 -> 0 | BC81: =$I81*BC$12 -> 0 | BD81: =$I81*BD$12 -> 0 | BE81: =I81*$BE$12 -> 0 | BF81: =SUM(AZ81:BE81) -> 0 | BG81: =I81-BF81 -> 0 | BH81: =IF(F81="Cadastrar Ficha de Produção",0,IFERROR(BG81/I81,0)) -> 0
A82: PRD00069 | B82: =IFERROR(VLOOKUP(A82,'Tabela de Produtos'!A:B,2,0),"Preencher Cód. Produto") -> BRAZIMIL LÁTEX STANDARD INT/EXT FOSCO 3L BRANCO NEVE | D82: Galao | E82: 100 | F82: =IF(A82=0,0,VLOOKUP(A82,'Tabela de Produtos'!A:W,23,0)) -> 16.12 | G82: 41.9 | H82: 1 | I82: =G82*H82 -> 41.9 | J82: =VLOOKUP(B82,'Tabela de Produtos'!B:M,12,FALSE()) -> 9.81 | K82: =VLOOKUP(B82,'Tabela de Produtos'!B:P,15,FALSE()) -> 0.93 | L82: =J82*1% -> 0.0981 | M82: =J82*1% -> 0.0981 | N82: =J82+K82+L82+M82 -> 10.9362 | O82: =($O$12/E82)*$O$13 -> 0.362 | P82: =($P$12/E82)*$P$13 -> 0.2829 | Q82: =($Q$12/E82)*$Q$13 -> 0.2829 | R82: =O82+P82+Q82 -> 0.9278 | S82: =VLOOKUP(B82,'Tabela de Produtos'!B:N,13,FALSE()) -> 3.44 | T82: =$T$12/$T$7 -> 0.22727273 | U82: =$U$12/$U$7 -> 0.39090909 | V82: =$V$12/$V$7 -> 0.10909091 | W82: =S82+T82+U82+V82 -> 4.1672727 | X82: =(N82+R82+W82)*1% -> 0.16031273 | Y82: =X82 -> 0.16031273 | Z82: =$Z$12/E82 -> 0.0083 | AA82: =$AA$12/E82 -> 0.20833333 | AB82: =$AB$12/E82 -> 0.19791667 | AC82: =$AC$12/E82 -> 0 | AD82: =Z82+AA82+AB82+AC82 -> 0.41455 | AE82: =(AD82+Y82+W82+R82+N82)*$AE$7 -> 4.1515339 | AF82: =AE82 -> 4.1515339 | AL82: =(AD82+Y82+W82+R82+N82)*$AL$7 -> 0 | AM82: =AL82+AF82+AD82+Y82+W82+R82+N82 -> 20.757669 | AN82: =AM82*$AN$12 -> 0.24909203 | AO82: =AM82*$AO$12 -> 0.22418283 | AP82: =AO82+AN82 -> 0.47327486 | AQ82: =AM82*$AQ$12 -> 1.7332654 | AR82: =AM82*$AR$12 -> 0 | AS82: =AM82*$AS$12 -> 0 | AT82: =AQ82+AR82+AS82 -> 1.7332654 | AU82: =AM82*$AU$12 -> 1.0378835 | AV82: =AU82 -> 1.0378835 | AW82: =AM82+AP82+AT82+AV82 -> 24.002093 | AX82: =AY82/AW82 -> 0.74568109 | AY82: =I82-AW82 -> 17.897907 | AZ82: =IFERROR(H82*VLOOKUP(A82,'Tabela de Produtos'!A:Q,17,0),0) -> 14.18 | BA82: =$I82*BA$12 -> 0 | BB82: =$I82*BB$12 -> 0 | BC82: =$I82*BC$12 -> 0 | BD82: =$I82*BD$12 -> 2.933 | BE82: =I82*$BE$12 -> 2.095 | BF82: =SUM(AZ82:BE82) -> 19.208 | BG82: =I82-BF82 -> 22.692 | BH82: =IF(F82="Cadastrar Ficha de Produção",0,IFERROR(BG82/I82,0)) -> 0.54157518
A83: PRD00070 | B83: =IFERROR(VLOOKUP(A83,'Tabela de Produtos'!A:B,2,0),"Preencher Cód. Produto") -> BRAZIMIL LÁTEX STANDARD INT/EXT FOSCO 3L BRANCO GELO | D83: Galao | E83: 100 | F83: =IF(A83=0,0,VLOOKUP(A83,'Tabela de Produtos'!A:W,23,0)) -> 13.66 | G83: 41.9 | H83: 1 | I83: =G83*H83 -> 41.9 | J83: =VLOOKUP(B83,'Tabela de Produtos'!B:M,12,FALSE()) -> 7.65 | K83: =VLOOKUP(B83,'Tabela de Produtos'!B:P,15,FALSE()) -> 0.93 | L83: =J83*1% -> 0.0765 | M83: =J83*1% -> 0.0765 | N83: =J83+K83+L83+M83 -> 8.733 | O83: =($O$12/E83)*$O$13 -> 0.362 | P83: =($P$12/E83)*$P$13 -> 0.2829 | Q83: =($Q$12/E83)*$Q$13 -> 0.2829 | R83: =O83+P83+Q83 -> 0.9278 | S83: =VLOOKUP(B83,'Tabela de Produtos'!B:N,13,FALSE()) -> 3.44 | T83: =$T$12/$T$7 -> 0.22727273 | U83: =$U$12/$U$7 -> 0.39090909 | V83: =$V$12/$V$7 -> 0.10909091 | W83: =S83+T83+U83+V83 -> 4.1672727 | X83: =(N83+R83+W83)*1% -> 0.13828073 | Y83: =X83 -> 0.13828073 | Z83: =$Z$12/E83 -> 0.0083 | AA83: =$AA$12/E83 -> 0.20833333 | AB83: =$AB$12/E83 -> 0.19791667 | AC83: =$AC$12/E83 -> 0 | AD83: =Z83+AA83+AB83+AC83 -> 0.41455 | AE83: =(AD83+Y83+W83+R83+N83)*$AE$7 -> 3.5952259 | AF83: =AE83 -> 3.5952259 | AL83: =(AD83+Y83+W83+R83+N83)*$AL$7 -> 0 | AM83: =AL83+AF83+AD83+Y83+W83+R83+N83 -> 17.976129 | AN83: =AM83*$AN$12 -> 0.21571355 | AO83: =AM83*$AO$12 -> 0.1941422 | AP83: =AO83+AN83 -> 0.40985575 | AQ83: =AM83*$AQ$12 -> 1.5010068 | AR83: =AM83*$AR$12 -> 0 | AS83: =AM83*$AS$12 -> 0 | AT83: =AQ83+AR83+AS83 -> 1.5010068 | AU83: =AM83*$AU$12 -> 0.89880647 | AV83: =AU83 -> 0.89880647 | AW83: =AM83+AP83+AT83+AV83 -> 20.785798 | AX83: =AY83/AW83 -> 1.0157994 | AY83: =I83-AW83 -> 21.114202 | AZ83: =IFERROR(H83*VLOOKUP(A83,'Tabela de Produtos'!A:Q,17,0),0) -> 12.02 | BA83: =$I83*BA$12 -> 0 | BB83: =$I83*BB$12 -> 0 | BC83: =$I83*BC$12 -> 0 | BD83: =$I83*BD$12 -> 2.933 | BE83: =I83*$BE$12 -> 2.095 | BF83: =SUM(AZ83:BE83) -> 17.048 | BG83: =I83-BF83 -> 24.852 | BH83: =IF(F83="Cadastrar Ficha de Produção",0,IFERROR(BG83/I83,0)) -> 0.59312649
A84: PRD00071 | B84: =IFERROR(VLOOKUP(A84,'Tabela de Produtos'!A:B,2,0),"Preencher Cód. Produto") -> BRAZIMIL LÁTEX STANDARD INT/EXT FOSCO 3L FLAMINGO | D84: Galao | E84: 100 | F84: =IF(A84=0,0,VLOOKUP(A84,'Tabela de Produtos'!A:W,23,0)) -> 15.27 | G84: 41.9 | H84: 1 | I84: =G84*H84 -> 41.9 | J84: =VLOOKUP(B84,'Tabela de Produtos'!B:M,12,FALSE()) -> 9.06 | K84: =VLOOKUP(B84,'Tabela de Produtos'!B:P,15,FALSE()) -> 0.93 | L84: =J84*1% -> 0.0906 | M84: =J84*1% -> 0.0906 | N84: =J84+K84+L84+M84 -> 10.1712 | O84: =($O$12/E84)*$O$13 -> 0.362 | P84: =($P$12/E84)*$P$13 -> 0.2829 | Q84: =($Q$12/E84)*$Q$13 -> 0.2829 | R84: =O84+P84+Q84 -> 0.9278 | S84: =VLOOKUP(B84,'Tabela de Produtos'!B:N,13,FALSE()) -> 3.44 | T84: =$T$12/$T$7 -> 0.22727273 | U84: =$U$12/$U$7 -> 0.39090909 | V84: =$V$12/$V$7 -> 0.10909091 | W84: =S84+T84+U84+V84 -> 4.1672727 | X84: =(N84+R84+W84)*1% -> 0.15266273 | Y84: =X84 -> 0.15266273 | Z84: =$Z$12/E84 -> 0.0083 | AA84: =$AA$12/E84 -> 0.20833333 | AB84: =$AB$12/E84 -> 0.19791667 | AC84: =$AC$12/E84 -> 0 | AD84: =Z84+AA84+AB84+AC84 -> 0.41455 | AE84: =(AD84+Y84+W84+R84+N84)*$AE$7 -> 3.9583714 | AF84: =AE84 -> 3.9583714 | AL84: =(AD84+Y84+W84+R84+N84)*$AL$7 -> 0 | AM84: =AL84+AF84+AD84+Y84+W84+R84+N84 -> 19.791857 | AN84: =AM84*$AN$12 -> 0.23750228 | AO84: =AM84*$AO$12 -> 0.21375205 | AP84: =AO84+AN84 -> 0.45125434 | AQ84: =AM84*$AQ$12 -> 1.65262 | AR84: =AM84*$AR$12 -> 0 | AS84: =AM84*$AS$12 -> 0 | AT84: =AQ84+AR84+AS84 -> 1.65262 | AU84: =AM84*$AU$12 -> 0.98959284 | AV84: =AU84 -> 0.98959284 | AW84: =AM84+AP84+AT84+AV84 -> 22.885324 | AX84: =AY84/AW84 -> 0.83086767 | AY84: =I84-AW84 -> 19.014676 | AZ84: =IFERROR(H84*VLOOKUP(A84,'Tabela de Produtos'!A:Q,17,0),0) -> 13.43 | BA84: =$I84*BA$12 -> 0 | BB84: =$I84*BB$12 -> 0 | BC84: =$I84*BC$12 -> 0 | BD84: =$I84*BD$12 -> 2.933 | BE84: =I84*$BE$12 -> 2.095 | BF84: =SUM(AZ84:BE84) -> 18.458 | BG84: =I84-BF84 -> 23.442 | BH84: =IF(F84="Cadastrar Ficha de Produção",0,IFERROR(BG84/I84,0)) -> 0.55947494
A85: PRD00072 | B85: =IFERROR(VLOOKUP(A85,'Tabela de Produtos'!A:B,2,0),"Preencher Cód. Produto") -> BRAZIMIL LÁTEX STANDARD INT/EXT FOSCO 3L AREIA | D85: Galao | F85: =IF(A85=0,0,VLOOKUP(A85,'Tabela de Produtos'!A:W,23,0)) -> Cadastrar Ficha de Produção | G85: 25 | H85: 1 | I85: =G85*H85 -> 25 | J85: =VLOOKUP(B85,'Tabela de Produtos'!B:M,12,FALSE()) -> 0 | AY85: =I85-AW85 -> 25 | AZ85: =IFERROR(H85*VLOOKUP(A85,'Tabela de Produtos'!A:Q,17,0),0) -> 3.44 | BA85: =$I85*BA$12 -> 0 | BB85: =$I85*BB$12 -> 0 | BC85: =$I85*BC$12 -> 0 | BD85: =$I85*BD$12 -> 1.75 | BE85: =I85*$BE$12 -> 1.25 | BF85: =SUM(AZ85:BE85) -> 6.44 | BG85: =I85-BF85 -> 18.56 | BH85: =IF(F85="Cadastrar Ficha de Produção",0,IFERROR(BG85/I85,0)) -> 0
A86: PRD00073 | B86: =IFERROR(VLOOKUP(A86,'Tabela de Produtos'!A:B,2,0),"Preencher Cód. Produto") -> BRAZIMIL LÁTEX STANDARD INT/EXT FOSCO 3L MARFIM | D86: Galao | E86: 100 | F86: =IF(A86=0,0,VLOOKUP(A86,'Tabela de Produtos'!A:W,23,0)) -> 13.9 | G86: 41.9 | H86: 1 | I86: =G86*H86 -> 41.9 | J86: =VLOOKUP(B86,'Tabela de Produtos'!B:M,12,FALSE()) -> 7.86 | K86: =VLOOKUP(B86,'Tabela de Produtos'!B:P,15,FALSE()) -> 0.93 | L86: =J86*1% -> 0.0786 | M86: =J86*1% -> 0.0786 | N86: =J86+K86+L86+M86 -> 8.9472 | O86: =($O$12/E86)*$O$13 -> 0.362 | P86: =($P$12/E86)*$P$13 -> 0.2829 | Q86: =($Q$12/E86)*$Q$13 -> 0.2829 | R86: =O86+P86+Q86 -> 0.9278 | S86: =VLOOKUP(B86,'Tabela de Produtos'!B:N,13,FALSE()) -> 3.44 | T86: =$T$12/$T$7 -> 0.22727273 | U86: =$U$12/$U$7 -> 0.39090909 | V86: =$V$12/$V$7 -> 0.10909091 | W86: =S86+T86+U86+V86 -> 4.1672727 | X86: =(N86+R86+W86)*1% -> 0.14042273 | Y86: =X86 -> 0.14042273 | Z86: =$Z$12/E86 -> 0.0083 | AA86: =$AA$12/E86 -> 0.20833333 | AB86: =$AB$12/E86 -> 0.19791667 | AC86: =$AC$12/E86 -> 0 | AD86: =Z86+AA86+AB86+AC86 -> 0.41455 | AE86: =(AD86+Y86+W86+R86+N86)*$AE$7 -> 3.6493114 | AF86: =AE86 -> 3.6493114 | AL86: =(AD86+Y86+W86+R86+N86)*$AL$7 -> 0 | AM86: =AL86+AF86+AD86+Y86+W86+R86+N86 -> 18.246557 | AN86: =AM86*$AN$12 -> 0.21895868 | AO86: =AM86*$AO$12 -> 0.19706281 | AP86: =AO86+AN86 -> 0.4160215 | AQ86: =AM86*$AQ$12 -> 1.5235875 | AR86: =AM86*$AR$12 -> 0 | AS86: =AM86*$AS$12 -> 0 | AT86: =AQ86+AR86+AS86 -> 1.5235875 | AU86: =AM86*$AU$12 -> 0.91232784 | AV86: =AU86 -> 0.91232784 | AW86: =AM86+AP86+AT86+AV86 -> 21.098494 | AX86: =AY86/AW86 -> 0.98592377 | AY86: =I86-AW86 -> 20.801506 | AZ86: =IFERROR(H86*VLOOKUP(A86,'Tabela de Produtos'!A:Q,17,0),0) -> 12.23 | BA86: =$I86*BA$12 -> 0 | BB86: =$I86*BB$12 -> 0 | BC86: =$I86*BC$12 -> 0 | BD86: =$I86*BD$12 -> 2.933 | BE86: =I86*$BE$12 -> 2.095 | BF86: =SUM(AZ86:BE86) -> 17.258 | BG86: =I86-BF86 -> 24.642 | BH86: =IF(F86="Cadastrar Ficha de Produção",0,IFERROR(BG86/I86,0)) -> 0.58811456
A87: PRD00074 | B87: =IFERROR(VLOOKUP(A87,'Tabela de Produtos'!A:B,2,0),"Preencher Cód. Produto") -> BRAZIMIL LÁTEX STANDARD INT/EXT FOSCO 3L ROSA PETALA | D87: Galao | E87: 100 | F87: =IF(A87=0,0,VLOOKUP(A87,'Tabela de Produtos'!A:W,23,0)) -> 13.94 | G87: 41.9 | H87: 1 | I87: =G87*H87 -> 41.9 | J87: =VLOOKUP(B87,'Tabela de Produtos'!B:M,12,FALSE()) -> 7.89 | K87: =VLOOKUP(B87,'Tabela de Produtos'!B:P,15,FALSE()) -> 0.93 | L87: =J87*1% -> 0.0789 | M87: =J87*1% -> 0.0789 | N87: =J87+K87+L87+M87 -> 8.9778 | O87: =($O$12/E87)*$O$13 -> 0.362 | P87: =($P$12/E87)*$P$13 -> 0.2829 | Q87: =($Q$12/E87)*$Q$13 -> 0.2829 | R87: =O87+P87+Q87 -> 0.9278 | S87: =VLOOKUP(B87,'Tabela de Produtos'!B:N,13,FALSE()) -> 3.44 | T87: =$T$12/$T$7 -> 0.22727273 | U87: =$U$12/$U$7 -> 0.39090909 | V87: =$V$12/$V$7 -> 0.10909091 | W87: =S87+T87+U87+V87 -> 4.1672727 | X87: =(N87+R87+W87)*1% -> 0.14072873 | Y87: =X87 -> 0.14072873 | Z87: =$Z$12/E87 -> 0.0083 | AA87: =$AA$12/E87 -> 0.20833333 | AB87: =$AB$12/E87 -> 0.19791667 | AC87: =$AC$12/E87 -> 0 | AD87: =Z87+AA87+AB87+AC87 -> 0.41455 | AE87: =(AD87+Y87+W87+R87+N87)*$AE$7 -> 3.6570379 | AF87: =AE87 -> 3.6570379 | AL87: =(AD87+Y87+W87+R87+N87)*$AL$7 -> 0 | AM87: =AL87+AF87+AD87+Y87+W87+R87+N87 -> 18.285189 | AN87: =AM87*$AN$12 -> 0.21942227 | AO87: =AM87*$AO$12 -> 0.19748004 | AP87: =AO87+AN87 -> 0.41690232 | AQ87: =AM87*$AQ$12 -> 1.5268133 | AR87: =AM87*$AR$12 -> 0 | AS87: =AM87*$AS$12 -> 0 | AT87: =AQ87+AR87+AS87 -> 1.5268133 | AU87: =AM87*$AU$12 -> 0.91425947 | AV87: =AU87 -> 0.91425947 | AW87: =AM87+AP87+AT87+AV87 -> 21.143164 | AX87: =AY87/AW87 -> 0.98172796 | AY87: =I87-AW87 -> 20.756836 | AZ87: =IFERROR(H87*VLOOKUP(A87,'Tabela de Produtos'!A:Q,17,0),0) -> 12.26 | BA87: =$I87*BA$12 -> 0 | BB87: =$I87*BB$12 -> 0 | BC87: =$I87*BC$12 -> 0 | BD87: =$I87*BD$12 -> 2.933 | BE87: =I87*$BE$12 -> 2.095 | BF87: =SUM(AZ87:BE87) -> 17.288 | BG87: =I87-BF87 -> 24.612 | BH87: =IF(F87="Cadastrar Ficha de Produção",0,IFERROR(BG87/I87,0)) -> 0.58739857
A88: PRD00075 | B88: =IFERROR(VLOOKUP(A88,'Tabela de Produtos'!A:B,2,0),"Preencher Cód. Produto") -> BRAZIMIL LÁTEX STANDARD INT/EXT FOSCO 3L ACAI AMAZONICO | D88: Galao | F88: =IF(A88=0,0,VLOOKUP(A88,'Tabela de Produtos'!A:W,23,0)) -> Cadastrar Ficha de Produção | G88: 25 | H88: 1 | I88: =G88*H88 -> 25 | J88: =VLOOKUP(B88,'Tabela de Produtos'!B:M,12,FALSE()) -> 0 | AY88: =I88-AW88 -> 25 | AZ88: =IFERROR(H88*VLOOKUP(A88,'Tabela de Produtos'!A:Q,17,0),0) -> 3.44 | BA88: =$I88*BA$12 -> 0 | BB88: =$I88*BB$12 -> 0 | BC88: =$I88*BC$12 -> 0 | BD88: =$I88*BD$12 -> 1.75 | BE88: =I88*$BE$12 -> 1.25 | BF88: =SUM(AZ88:BE88) -> 6.44 | BG88: =I88-BF88 -> 18.56 | BH88: =IF(F88="Cadastrar Ficha de Produção",0,IFERROR(BG88/I88,0)) -> 0
A89: PRD00076 | B89: =IFERROR(VLOOKUP(A89,'Tabela de Produtos'!A:B,2,0),"Preencher Cód. Produto") -> BRAZIMIL LÁTEX STANDARD INT/EXT FOSCO 3L VERDE FOLHA | D89: Galao | F89: =IF(A89=0,0,VLOOKUP(A89,'Tabela de Produtos'!A:W,23,0)) -> Cadastrar Ficha de Produção | G89: 25 | H89: 1 | I89: =G89*H89 -> 25 | J89: =VLOOKUP(B89,'Tabela de Produtos'!B:M,12,FALSE()) -> 0 | AY89: =I89-AW89 -> 25 | AZ89: =IFERROR(H89*VLOOKUP(A89,'Tabela de Produtos'!A:Q,17,0),0) -> 3.44 | BA89: =$I89*BA$12 -> 0 | BB89: =$I89*BB$12 -> 0 | BC89: =$I89*BC$12 -> 0 | BD89: =$I89*BD$12 -> 1.75 | BE89: =I89*$BE$12 -> 1.25 | BF89: =SUM(AZ89:BE89) -> 6.44 | BG89: =I89-BF89 -> 18.56 | BH89: =IF(F89="Cadastrar Ficha de Produção",0,IFERROR(BG89/I89,0)) -> 0
A90: PRD00077 | B90: =IFERROR(VLOOKUP(A90,'Tabela de Produtos'!A:B,2,0),"Preencher Cód. Produto") -> BRAZIMIL LÁTEX STANDARD INT/EXT FOSCO 3L LARANJA | D90: Galao | F90: =IF(A90=0,0,VLOOKUP(A90,'Tabela de Produtos'!A:W,23,0)) -> Cadastrar Ficha de Produção | G90: 25 | H90: 1 | I90: =G90*H90 -> 25 | J90: =VLOOKUP(B90,'Tabela de Produtos'!B:M,12,FALSE()) -> 0 | AY90: =I90-AW90 -> 25 | AZ90: =IFERROR(H90*VLOOKUP(A90,'Tabela de Produtos'!A:Q,17,0),0) -> 3.44 | BA90: =$I90*BA$12 -> 0 | BB90: =$I90*BB$12 -> 0 | BC90: =$I90*BC$12 -> 0 | BD90: =$I90*BD$12 -> 1.75 | BE90: =I90*$BE$12 -> 1.25 | BF90: =SUM(AZ90:BE90) -> 6.44 | BG90: =I90-BF90 -> 18.56 | BH90: =IF(F90="Cadastrar Ficha de Produção",0,IFERROR(BG90/I90,0)) -> 0
A91: PRD00078 | B91: =IFERROR(VLOOKUP(A91,'Tabela de Produtos'!A:B,2,0),"Preencher Cód. Produto") -> BRAZIMIL LÁTEX STANDARD INT/EXT FOSCO 3L AZUL CARIBE | D91: Galao | E91: 100 | F91: =IF(A91=0,0,VLOOKUP(A91,'Tabela de Produtos'!A:W,23,0)) -> 13.9 | G91: 41.9 | H91: 1 | I91: =G91*H91 -> 41.9 | J91: =VLOOKUP(B91,'Tabela de Produtos'!B:M,12,FALSE()) -> 7.86 | K91: =VLOOKUP(B91,'Tabela de Produtos'!B:P,15,FALSE()) -> 0.93 | L91: =J91*1% -> 0.0786 | M91: =J91*1% -> 0.0786 | N91: =J91+K91+L91+M91 -> 8.9472 | O91: =($O$12/E91)*$O$13 -> 0.362 | P91: =($P$12/E91)*$P$13 -> 0.2829 | Q91: =($Q$12/E91)*$Q$13 -> 0.2829 | R91: =O91+P91+Q91 -> 0.9278 | S91: =VLOOKUP(B91,'Tabela de Produtos'!B:N,13,FALSE()) -> 3.44 | T91: =$T$12/$T$7 -> 0.22727273 | U91: =$U$12/$U$7 -> 0.39090909 | V91: =$V$12/$V$7 -> 0.10909091 | W91: =S91+T91+U91+V91 -> 4.1672727 | X91: =(N91+R91+W91)*1% -> 0.14042273 | Y91: =X91 -> 0.14042273 | Z91: =$Z$12/E91 -> 0.0083 | AA91: =$AA$12/E91 -> 0.20833333 | AB91: =$AB$12/E91 -> 0.19791667 | AC91: =$AC$12/E91 -> 0 | AD91: =Z91+AA91+AB91+AC91 -> 0.41455 | AE91: =(AD91+Y91+W91+R91+N91)*$AE$7 -> 3.6493114 | AF91: =AE91 -> 3.6493114 | AL91: =(AD91+Y91+W91+R91+N91)*$AL$7 -> 0 | AM91: =AL91+AF91+AD91+Y91+W91+R91+N91 -> 18.246557 | AN91: =AM91*$AN$12 -> 0.21895868 | AO91: =AM91*$AO$12 -> 0.19706281 | AP91: =AO91+AN91 -> 0.4160215 | AQ91: =AM91*$AQ$12 -> 1.5235875 | AR91: =AM91*$AR$12 -> 0 | AS91: =AM91*$AS$12 -> 0 | AT91: =AQ91+AR91+AS91 -> 1.5235875 | AU91: =AM91*$AU$12 -> 0.91232784 | AV91: =AU91 -> 0.91232784 | AW91: =AM91+AP91+AT91+AV91 -> 21.098494 | AX91: =AY91/AW91 -> 0.98592377 | AY91: =I91-AW91 -> 20.801506 | AZ91: =IFERROR(H91*VLOOKUP(A91,'Tabela de Produtos'!A:Q,17,0),0) -> 12.23 | BA91: =$I91*BA$12 -> 0 | BB91: =$I91*BB$12 -> 0 | BC91: =$I91*BC$12 -> 0 | BD91: =$I91*BD$12 -> 2.933 | BE91: =I91*$BE$12 -> 2.095 | BF91: =SUM(AZ91:BE91) -> 17.258 | BG91: =I91-BF91 -> 24.642 | BH91: =IF(F91="Cadastrar Ficha de Produção",0,IFERROR(BG91/I91,0)) -> 0.58811456
A92: PRD00079 | B92: =IFERROR(VLOOKUP(A92,'Tabela de Produtos'!A:B,2,0),"Preencher Cód. Produto") -> BRAZIMIL LÁTEX STANDARD INT/EXT FOSCO 3L VERDE LIMA | D92: Galao | E92: 100 | F92: =IF(A92=0,0,VLOOKUP(A92,'Tabela de Produtos'!A:W,23,0)) -> 14.48 | G92: 41.9 | H92: 1 | I92: =G92*H92 -> 41.9 | J92: =VLOOKUP(B92,'Tabela de Produtos'!B:M,12,FALSE()) -> 8.37 | K92: =VLOOKUP(B92,'Tabela de Produtos'!B:P,15,FALSE()) -> 0.93 | L92: =J92*1% -> 0.0837 | M92: =J92*1% -> 0.0837 | N92: =J92+K92+L92+M92 -> 9.4674 | O92: =($O$12/E92)*$O$13 -> 0.362 | P92: =($P$12/E92)*$P$13 -> 0.2829 | Q92: =($Q$12/E92)*$Q$13 -> 0.2829 | R92: =O92+P92+Q92 -> 0.9278 | S92: =VLOOKUP(B92,'Tabela de Produtos'!B:N,13,FALSE()) -> 3.44 | T92: =$T$12/$T$7 -> 0.22727273 | U92: =$U$12/$U$7 -> 0.39090909 | V92: =$V$12/$V$7 -> 0.10909091 | W92: =S92+T92+U92+V92 -> 4.1672727 | X92: =(N92+R92+W92)*1% -> 0.14562473 | Y92: =X92 -> 0.14562473 | Z92: =$Z$12/E92 -> 0.0083 | AA92: =$AA$12/E92 -> 0.20833333 | AB92: =$AB$12/E92 -> 0.19791667 | AC92: =$AC$12/E92 -> 0 | AD92: =Z92+AA92+AB92+AC92 -> 0.41455 | AE92: =(AD92+Y92+W92+R92+N92)*$AE$7 -> 3.7806619 | AF92: =AE92 -> 3.7806619 | AL92: =(AD92+Y92+W92+R92+N92)*$AL$7 -> 0 | AM92: =AL92+AF92+AD92+Y92+W92+R92+N92 -> 18.903309 | AN92: =AM92*$AN$12 -> 0.22683971 | AO92: =AM92*$AO$12 -> 0.20415574 | AP92: =AO92+AN92 -> 0.43099545 | AQ92: =AM92*$AQ$12 -> 1.5784263 | AR92: =AM92*$AR$12 -> 0 | AS92: =AM92*$AS$12 -> 0 | AT92: =AQ92+AR92+AS92 -> 1.5784263 | AU92: =AM92*$AU$12 -> 0.94516547 | AV92: =AU92 -> 0.94516547 | AW92: =AM92+AP92+AT92+AV92 -> 21.857897 | AX92: =AY92/AW92 -> 0.91692736 | AY92: =I92-AW92 -> 20.042103 | AZ92: =IFERROR(H92*VLOOKUP(A92,'Tabela de Produtos'!A:Q,17,0),0) -> 12.74 | BA92: =$I92*BA$12 -> 0 | BB92: =$I92*BB$12 -> 0 | BC92: =$I92*BC$12 -> 0 | BD92: =$I92*BD$12 -> 2.933 | BE92: =I92*$BE$12 -> 2.095 | BF92: =SUM(AZ92:BE92) -> 17.768 | BG92: =I92-BF92 -> 24.132 | BH92: =IF(F92="Cadastrar Ficha de Produção",0,IFERROR(BG92/I92,0)) -> 0.57594272
A93: PRD00080 | B93: =IFERROR(VLOOKUP(A93,'Tabela de Produtos'!A:B,2,0),"Preencher Cód. Produto") -> BRAZIMIL LÁTEX STANDARD INT/EXT FOSCO 3L PEROLA | D93: Galao | F93: =IF(A93=0,0,VLOOKUP(A93,'Tabela de Produtos'!A:W,23,0)) -> Cadastrar Ficha de Produção | G93: 25 | H93: 1 | I93: =G93*H93 -> 25 | J93: =VLOOKUP(B93,'Tabela de Produtos'!B:M,12,FALSE()) -> 0 | AY93: =I93-AW93 -> 25 | AZ93: =IFERROR(H93*VLOOKUP(A93,'Tabela de Produtos'!A:Q,17,0),0) -> 3.44 | BA93: =$I93*BA$12 -> 0 | BB93: =$I93*BB$12 -> 0 | BC93: =$I93*BC$12 -> 0 | BD93: =$I93*BD$12 -> 1.75 | BE93: =I93*$BE$12 -> 1.25 | BF93: =SUM(AZ93:BE93) -> 6.44 | BG93: =I93-BF93 -> 18.56 | BH93: =IF(F93="Cadastrar Ficha de Produção",0,IFERROR(BG93/I93,0)) -> 0
A94: PRD00081 | B94: =IFERROR(VLOOKUP(A94,'Tabela de Produtos'!A:B,2,0),"Preencher Cód. Produto") -> BRAZIMIL LÁTEX STANDARD INT/EXT FOSCO 3L AZUL INTENSO | D94: Galao | E94: 100 | F94: =IF(A94=0,0,VLOOKUP(A94,'Tabela de Produtos'!A:W,23,0)) -> 15.64 | G94: 41.9 | H94: 1 | I94: =G94*H94 -> 41.9 | J94: =VLOOKUP(B94,'Tabela de Produtos'!B:M,12,FALSE()) -> 9.39 | K94: =VLOOKUP(B94,'Tabela de Produtos'!B:P,15,FALSE()) -> 0.93 | L94: =J94*1% -> 0.0939 | M94: =J94*1% -> 0.0939 | N94: =J94+K94+L94+M94 -> 10.5078 | O94: =($O$12/E94)*$O$13 -> 0.362 | P94: =($P$12/E94)*$P$13 -> 0.2829 | Q94: =($Q$12/E94)*$Q$13 -> 0.2829 | R94: =O94+P94+Q94 -> 0.9278 | S94: =VLOOKUP(B94,'Tabela de Produtos'!B:N,13,FALSE()) -> 3.44 | T94: =$T$12/$T$7 -> 0.22727273 | U94: =$U$12/$U$7 -> 0.39090909 | V94: =$V$12/$V$7 -> 0.10909091 | W94: =S94+T94+U94+V94 -> 4.1672727 | X94: =(N94+R94+W94)*1% -> 0.15602873 | Y94: =X94 -> 0.15602873 | Z94: =$Z$12/E94 -> 0.0083 | AA94: =$AA$12/E94 -> 0.20833333 | AB94: =$AB$12/E94 -> 0.19791667 | AC94: =$AC$12/E94 -> 0 | AD94: =Z94+AA94+AB94+AC94 -> 0.41455 | AE94: =(AD94+Y94+W94+R94+N94)*$AE$7 -> 4.0433629 | AF94: =AE94 -> 4.0433629 | AL94: =(AD94+Y94+W94+R94+N94)*$AL$7 -> 0 | AM94: =AL94+AF94+AD94+Y94+W94+R94+N94 -> 20.216814 | AN94: =AM94*$AN$12 -> 0.24260177 | AO94: =AM94*$AO$12 -> 0.21834159 | AP94: =AO94+AN94 -> 0.46094337 | AQ94: =AM94*$AQ$12 -> 1.688104 | AR94: =AM94*$AR$12 -> 0 | AS94: =AM94*$AS$12 -> 0 | AT94: =AQ94+AR94+AS94 -> 1.688104 | AU94: =AM94*$AU$12 -> 1.0108407 | AV94: =AU94 -> 1.0108407 | AW94: =AM94+AP94+AT94+AV94 -> 23.376702 | AX94: =AY94/AW94 -> 0.79238283 | AY94: =I94-AW94 -> 18.523298 | AZ94: =IFERROR(H94*VLOOKUP(A94,'Tabela de Produtos'!A:Q,17,0),0) -> 13.76 | BA94: =$I94*BA$12 -> 0 | BB94: =$I94*BB$12 -> 0 | BC94: =$I94*BC$12 -> 0 | BD94: =$I94*BD$12 -> 2.933 | BE94: =I94*$BE$12 -> 2.095 | BF94: =SUM(AZ94:BE94) -> 18.788 | BG94: =I94-BF94 -> 23.112 | BH94: =IF(F94="Cadastrar Ficha de Produção",0,IFERROR(BG94/I94,0)) -> 0.55159905
A95: PRD00082 | B95: =IFERROR(VLOOKUP(A95,'Tabela de Produtos'!A:B,2,0),"Preencher Cód. Produto") -> BRAZIMIL LÁTEX STANDARD INT/EXT FOSCO 3L LILAS | D95: Galao | F95: =IF(A95=0,0,VLOOKUP(A95,'Tabela de Produtos'!A:W,23,0)) -> Cadastrar Ficha de Produção | G95: 25 | H95: 1 | I95: =G95*H95 -> 25 | J95: =VLOOKUP(B95,'Tabela de Produtos'!B:M,12,FALSE()) -> 0 | AY95: =I95-AW95 -> 25 | AZ95: =IFERROR(H95*VLOOKUP(A95,'Tabela de Produtos'!A:Q,17,0),0) -> 3.44 | BA95: =$I95*BA$12 -> 0 | BB95: =$I95*BB$12 -> 0 | BC95: =$I95*BC$12 -> 0 | BD95: =$I95*BD$12 -> 1.75 | BE95: =I95*$BE$12 -> 1.25 | BF95: =SUM(AZ95:BE95) -> 6.44 | BG95: =I95-BF95 -> 18.56 | BH95: =IF(F95="Cadastrar Ficha de Produção",0,IFERROR(BG95/I95,0)) -> 0
A96: PRD00083 | B96: =IFERROR(VLOOKUP(A96,'Tabela de Produtos'!A:B,2,0),"Preencher Cód. Produto") -> BRAZIMIL LÁTEX STANDARD INT/EXT FOSCO 3L VERMELHO GARANTIDO | D96: Galao | F96: =IF(A96=0,0,VLOOKUP(A96,'Tabela de Produtos'!A:W,23,0)) -> Cadastrar Ficha de Produção | G96: 25 | H96: 1 | I96: =G96*H96 -> 25 | J96: =VLOOKUP(B96,'Tabela de Produtos'!B:M,12,FALSE()) -> 0 | AY96: =I96-AW96 -> 25 | AZ96: =IFERROR(H96*VLOOKUP(A96,'Tabela de Produtos'!A:Q,17,0),0) -> 3.44 | BA96: =$I96*BA$12 -> 0 | BB96: =$I96*BB$12 -> 0 | BC96: =$I96*BC$12 -> 0 | BD96: =$I96*BD$12 -> 1.75 | BE96: =I96*$BE$12 -> 1.25 | BF96: =SUM(AZ96:BE96) -> 6.44 | BG96: =I96-BF96 -> 18.56 | BH96: =IF(F96="Cadastrar Ficha de Produção",0,IFERROR(BG96/I96,0)) -> 0
A97: PRD00084 | B97: =IFERROR(VLOOKUP(A97,'Tabela de Produtos'!A:B,2,0),"Preencher Cód. Produto") -> BRAZIMIL LÁTEX STANDARD INT/EXT FOSCO 3L AZUL CAPRICHOSO | D97: Galao | F97: =IF(A97=0,0,VLOOKUP(A97,'Tabela de Produtos'!A:W,23,0)) -> Cadastrar Ficha de Produção | G97: 25 | H97: 1 | I97: =G97*H97 -> 25 | J97: =VLOOKUP(B97,'Tabela de Produtos'!B:M,12,FALSE()) -> 0 | AY97: =I97-AW97 -> 25 | AZ97: =IFERROR(H97*VLOOKUP(A97,'Tabela de Produtos'!A:Q,17,0),0) -> 3.44 | BA97: =$I97*BA$12 -> 0 | BB97: =$I97*BB$12 -> 0 | BC97: =$I97*BC$12 -> 0 | BD97: =$I97*BD$12 -> 1.75 | BE97: =I97*$BE$12 -> 1.25 | BF97: =SUM(AZ97:BE97) -> 6.44 | BG97: =I97-BF97 -> 18.56 | BH97: =IF(F97="Cadastrar Ficha de Produção",0,IFERROR(BG97/I97,0)) -> 0
A98: PRD00085 | B98: =IFERROR(VLOOKUP(A98,'Tabela de Produtos'!A:B,2,0),"Preencher Cód. Produto") -> BRAZIMIL LÁTEX STANDARD INT/EXT FOSCO 3L CINZA MEDIO | D98: Galao | E98: 100 | F98: =IF(A98=0,0,VLOOKUP(A98,'Tabela de Produtos'!A:W,23,0)) -> 13.7 | G98: 41.9 | H98: 1 | I98: =G98*H98 -> 41.9 | J98: =VLOOKUP(B98,'Tabela de Produtos'!B:M,12,FALSE()) -> 7.68 | K98: =VLOOKUP(B98,'Tabela de Produtos'!B:P,15,FALSE()) -> 0.93 | L98: =J98*1% -> 0.0768 | M98: =J98*1% -> 0.0768 | N98: =J98+K98+L98+M98 -> 8.7636 | O98: =($O$12/E98)*$O$13 -> 0.362 | P98: =($P$12/E98)*$P$13 -> 0.2829 | Q98: =($Q$12/E98)*$Q$13 -> 0.2829 | R98: =O98+P98+Q98 -> 0.9278 | S98: =VLOOKUP(B98,'Tabela de Produtos'!B:N,13,FALSE()) -> 3.44 | T98: =$T$12/$T$7 -> 0.22727273 | U98: =$U$12/$U$7 -> 0.39090909 | V98: =$V$12/$V$7 -> 0.10909091 | W98: =S98+T98+U98+V98 -> 4.1672727 | X98: =(N98+R98+W98)*1% -> 0.13858673 | Y98: =X98 -> 0.13858673 | Z98: =$Z$12/E98 -> 0.0083 | AA98: =$AA$12/E98 -> 0.20833333 | AB98: =$AB$12/E98 -> 0.19791667 | AC98: =$AC$12/E98 -> 0 | AD98: =Z98+AA98+AB98+AC98 -> 0.41455 | AE98: =(AD98+Y98+W98+R98+N98)*$AE$7 -> 3.6029524 | AF98: =AE98 -> 3.6029524 | AL98: =(AD98+Y98+W98+R98+N98)*$AL$7 -> 0 | AM98: =AL98+AF98+AD98+Y98+W98+R98+N98 -> 18.014762 | AN98: =AM98*$AN$12 -> 0.21617714 | AO98: =AM98*$AO$12 -> 0.19455943 | AP98: =AO98+AN98 -> 0.41073657 | AQ98: =AM98*$AQ$12 -> 1.5042326 | AR98: =AM98*$AR$12 -> 0 | AS98: =AM98*$AS$12 -> 0 | AT98: =AQ98+AR98+AS98 -> 1.5042326 | AU98: =AM98*$AU$12 -> 0.90073809 | AV98: =AU98 -> 0.90073809 | AW98: =AM98+AP98+AT98+AV98 -> 20.830469 | AX98: =AY98/AW98 -> 1.0114765 | AY98: =I98-AW98 -> 21.069531 | AZ98: =IFERROR(H98*VLOOKUP(A98,'Tabela de Produtos'!A:Q,17,0),0) -> 12.05 | BA98: =$I98*BA$12 -> 0 | BB98: =$I98*BB$12 -> 0 | BC98: =$I98*BC$12 -> 0 | BD98: =$I98*BD$12 -> 2.933 | BE98: =I98*$BE$12 -> 2.095 | BF98: =SUM(AZ98:BE98) -> 17.078 | BG98: =I98-BF98 -> 24.822 | BH98: =IF(F98="Cadastrar Ficha de Produção",0,IFERROR(BG98/I98,0)) -> 0.5924105
A99: PRD00086 | B99: =IFERROR(VLOOKUP(A99,'Tabela de Produtos'!A:B,2,0),"Preencher Cód. Produto") -> BRAZIMIL LÁTEX STANDARD INT/EXT FOSCO 3L CINZA INTENSO | D99: Galao | E99: 100 | F99: =IF(A99=0,0,VLOOKUP(A99,'Tabela de Produtos'!A:W,23,0)) -> 13.77 | G99: 41.9 | H99: 1 | I99: =G99*H99 -> 41.9 | J99: =VLOOKUP(B99,'Tabela de Produtos'!B:M,12,FALSE()) -> 7.74 | K99: =VLOOKUP(B99,'Tabela de Produtos'!B:P,15,FALSE()) -> 0.93 | L99: =J99*1% -> 0.0774 | M99: =J99*1% -> 0.0774 | N99: =J99+K99+L99+M99 -> 8.8248 | O99: =($O$12/E99)*$O$13 -> 0.362 | P99: =($P$12/E99)*$P$13 -> 0.2829 | Q99: =($Q$12/E99)*$Q$13 -> 0.2829 | R99: =O99+P99+Q99 -> 0.9278 | S99: =VLOOKUP(B99,'Tabela de Produtos'!B:N,13,FALSE()) -> 3.44 | T99: =$T$12/$T$7 -> 0.22727273 | U99: =$U$12/$U$7 -> 0.39090909 | V99: =$V$12/$V$7 -> 0.10909091 | W99: =S99+T99+U99+V99 -> 4.1672727 | X99: =(N99+R99+W99)*1% -> 0.13919873 | Y99: =X99 -> 0.13919873 | Z99: =$Z$12/E99 -> 0.0083 | AA99: =$AA$12/E99 -> 0.20833333 | AB99: =$AB$12/E99 -> 0.19791667 | AC99: =$AC$12/E99 -> 0 | AD99: =Z99+AA99+AB99+AC99 -> 0.41455 | AE99: =(AD99+Y99+W99+R99+N99)*$AE$7 -> 3.6184054 | AF99: =AE99 -> 3.6184054 | AL99: =(AD99+Y99+W99+R99+N99)*$AL$7 -> 0 | AM99: =AL99+AF99+AD99+Y99+W99+R99+N99 -> 18.092027 | AN99: =AM99*$AN$12 -> 0.21710432 | AO99: =AM99*$AO$12 -> 0.19539389 | AP99: =AO99+AN99 -> 0.41249821 | AQ99: =AM99*$AQ$12 -> 1.5106842 | AR99: =AM99*$AR$12 -> 0 | AS99: =AM99*$AS$12 -> 0 | AT99: =AQ99+AR99+AS99 -> 1.5106842 | AU99: =AM99*$AU$12 -> 0.90460134 | AV99: =AU99 -> 0.90460134 | AW99: =AM99+AP99+AT99+AV99 -> 20.919811 | AX99: =AY99/AW99 -> 1.0028862 | AY99: =I99-AW99 -> 20.980189 | AZ99: =IFERROR(H99*VLOOKUP(A99,'Tabela de Produtos'!A:Q,17,0),0) -> 12.11 | BA99: =$I99*BA$12 -> 0 | BB99: =$I99*BB$12 -> 0 | BC99: =$I99*BC$12 -> 0 | BD99: =$I99*BD$12 -> 2.933 | BE99: =I99*$BE$12 -> 2.095 | BF99: =SUM(AZ99:BE99) -> 17.138 | BG99: =I99-BF99 -> 24.762 | BH99: =IF(F99="Cadastrar Ficha de Produção",0,IFERROR(BG99/I99,0)) -> 0.59097852
A100: PRD00087 | B100: =IFERROR(VLOOKUP(A100,'Tabela de Produtos'!A:B,2,0),"Preencher Cód. Produto") -> BRAZIMIL LÁTEX STANDARD INT/EXT SEMIBRILHO 3L BRANCO NEVE | D100: Galao | E100: 100 | F100: =IF(A100=0,0,VLOOKUP(A100,'Tabela de Produtos'!A:W,23,0)) -> 29.82 | G100: 46.9 | H100: 1 | I100: =G100*H100 -> 46.9 | J100: =VLOOKUP(B100,'Tabela de Produtos'!B:M,12,FALSE()) -> 21.87 | K100: =VLOOKUP(B100,'Tabela de Produtos'!B:P,15,FALSE()) -> 0.93 | L100: =J100*1% -> 0.2187 | M100: =J100*1% -> 0.2187 | N100: =J100+K100+L100+M100 -> 23.2374 | O100: =($O$12/E100)*$O$13 -> 0.362 | P100: =($P$12/E100)*$P$13 -> 0.2829 | Q100: =($Q$12/E100)*$Q$13 -> 0.2829 | R100: =O100+P100+Q100 -> 0.9278 | S100: =VLOOKUP(B100,'Tabela de Produtos'!B:N,13,FALSE()) -> 3.44 | T100: =$T$12/$T$7 -> 0.22727273 | U100: =$U$12/$U$7 -> 0.39090909 | V100: =$V$12/$V$7 -> 0.10909091 | W100: =S100+T100+U100+V100 -> 4.1672727 | X100: =(N100+R100+W100)*1% -> 0.28332473 | Y100: =X100 -> 0.28332473 | Z100: =$Z$12/E100 -> 0.0083 | AA100: =$AA$12/E100 -> 0.20833333 | AB100: =$AB$12/E100 -> 0.19791667 | AC100: =$AC$12/E100 -> 0 | AD100: =Z100+AA100+AB100+AC100 -> 0.41455 | AE100: =(AD100+Y100+W100+R100+N100)*$AE$7 -> 7.2575869 | AF100: =AE100 -> 7.2575869 | AL100: =(AD100+Y100+W100+R100+N100)*$AL$7 -> 0 | AM100: =AL100+AF100+AD100+Y100+W100+R100+N100 -> 36.287934 | AN100: =AM100*$AN$12 -> 0.43545521 | AO100: =AM100*$AO$12 -> 0.39190969 | AP100: =AO100+AN100 -> 0.8273649 | AQ100: =AM100*$AQ$12 -> 3.0300425 | AR100: =AM100*$AR$12 -> 0 | AS100: =AM100*$AS$12 -> 0 | AT100: =AQ100+AR100+AS100 -> 3.0300425 | AU100: =AM100*$AU$12 -> 1.8143967 | AV100: =AU100 -> 1.8143967 | AW100: =AM100+AP100+AT100+AV100 -> 41.959738 | AX100: =AY100/AW100 -> 0.11773814 | AY100: =I100-AW100 -> 4.9402615 | AZ100: =IFERROR(H100*VLOOKUP(A100,'Tabela de Produtos'!A:Q,17,0),0) -> 26.24 | BA100: =$I100*BA$12 -> 0 | BB100: =$I100*BB$12 -> 0 | BC100: =$I100*BC$12 -> 0 | BD100: =$I100*BD$12 -> 3.283 | BE100: =I100*$BE$12 -> 2.345 | BF100: =SUM(AZ100:BE100) -> 31.868 | BG100: =I100-BF100 -> 15.032 | BH100: =IF(F100="Cadastrar Ficha de Produção",0,IFERROR(BG100/I100,0)) -> 0.32051173
A101: PRD00088 | B101: =IFERROR(VLOOKUP(A101,'Tabela de Produtos'!A:B,2,0),"Preencher Cód. Produto") -> BRAZIMIL LÁTEX STANDARD INT/EXT SEMIBRILHO 3L BRANCO GELO | D101: Galao | E101: 100 | F101: =IF(A101=0,0,VLOOKUP(A101,'Tabela de Produtos'!A:W,23,0)) -> 33.88 | G101: 46.9 | H101: 1 | I101: =G101*H101 -> 46.9 | J101: =VLOOKUP(B101,'Tabela de Produtos'!B:M,12,FALSE()) -> 25.44 | K101: =VLOOKUP(B101,'Tabela de Produtos'!B:P,15,FALSE()) -> 0.93 | L101: =J101*1% -> 0.2544 | M101: =J101*1% -> 0.2544 | N101: =J101+K101+L101+M101 -> 26.8788 | O101: =($O$12/E101)*$O$13 -> 0.362 | P101: =($P$12/E101)*$P$13 -> 0.2829 | Q101: =($Q$12/E101)*$Q$13 -> 0.2829 | R101: =O101+P101+Q101 -> 0.9278 | S101: =VLOOKUP(B101,'Tabela de Produtos'!B:N,13,FALSE()) -> 3.44 | T101: =$T$12/$T$7 -> 0.22727273 | U101: =$U$12/$U$7 -> 0.39090909 | V101: =$V$12/$V$7 -> 0.10909091 | W101: =S101+T101+U101+V101 -> 4.1672727 | X101: =(N101+R101+W101)*1% -> 0.31973873 | Y101: =X101 -> 0.31973873 | Z101: =$Z$12/E101 -> 0.0083 | AA101: =$AA$12/E101 -> 0.20833333 | AB101: =$AB$12/E101 -> 0.19791667 | AC101: =$AC$12/E101 -> 0 | AD101: =Z101+AA101+AB101+AC101 -> 0.41455 | AE101: =(AD101+Y101+W101+R101+N101)*$AE$7 -> 8.1770404 | AF101: =AE101 -> 8.1770404 | AL101: =(AD101+Y101+W101+R101+N101)*$AL$7 -> 0 | AM101: =AL101+AF101+AD101+Y101+W101+R101+N101 -> 40.885202 | AN101: =AM101*$AN$12 -> 0.49062242 | AO101: =AM101*$AO$12 -> 0.44156018 | AP101: =AO101+AN101 -> 0.9321826 | AQ101: =AM101*$AQ$12 -> 3.4139144 | AR101: =AM101*$AR$12 -> 0 | AS101: =AM101*$AS$12 -> 0 | AT101: =AQ101+AR101+AS101 -> 3.4139144 | AU101: =AM101*$AU$12 -> 2.0442601 | AV101: =AU101 -> 2.0442601 | AW101: =AM101+AP101+AT101+AV101 -> 47.275559 | AX101: =AY101/AW101 -> -0.0079440386 | AY101: =I101-AW101 -> -0.37555886 | AZ101: =IFERROR(H101*VLOOKUP(A101,'Tabela de Produtos'!A:Q,17,0),0) -> 29.81 | BA101: =$I101*BA$12 -> 0 | BB101: =$I101*BB$12 -> 0 | BC101: =$I101*BC$12 -> 0 | BD101: =$I101*BD$12 -> 3.283 | BE101: =I101*$BE$12 -> 2.345 | BF101: =SUM(AZ101:BE101) -> 35.438 | BG101: =I101-BF101 -> 11.462 | BH101: =IF(F101="Cadastrar Ficha de Produção",0,IFERROR(BG101/I101,0)) -> 0.24439232
A102: PRD00089 | B102: =IFERROR(VLOOKUP(A102,'Tabela de Produtos'!A:B,2,0),"Preencher Cód. Produto") -> BRAZIMIL LÁTEX STANDARD INT/EXT SEMIBRILHO 3L FLAMINGO | D102: Galao | E102: 100 | F102: =IF(A102=0,0,VLOOKUP(A102,'Tabela de Produtos'!A:W,23,0)) -> 33.91 | G102: 46.9 | H102: 1 | I102: =G102*H102 -> 46.9 | J102: =VLOOKUP(B102,'Tabela de Produtos'!B:M,12,FALSE()) -> 25.47 | K102: =VLOOKUP(B102,'Tabela de Produtos'!B:P,15,FALSE()) -> 0.93 | L102: =J102*1% -> 0.2547 | M102: =J102*1% -> 0.2547 | N102: =J102+K102+L102+M102 -> 26.9094 | O102: =($O$12/E102)*$O$13 -> 0.362 | P102: =($P$12/E102)*$P$13 -> 0.2829 | Q102: =($Q$12/E102)*$Q$13 -> 0.2829 | R102: =O102+P102+Q102 -> 0.9278 | S102: =VLOOKUP(B102,'Tabela de Produtos'!B:N,13,FALSE()) -> 3.44 | T102: =$T$12/$T$7 -> 0.22727273 | U102: =$U$12/$U$7 -> 0.39090909 | V102: =$V$12/$V$7 -> 0.10909091 | W102: =S102+T102+U102+V102 -> 4.1672727 | X102: =(N102+R102+W102)*1% -> 0.32004473 | Y102: =X102 -> 0.32004473 | Z102: =$Z$12/E102 -> 0.0083 | AA102: =$AA$12/E102 -> 0.20833333 | AB102: =$AB$12/E102 -> 0.19791667 | AC102: =$AC$12/E102 -> 0 | AD102: =Z102+AA102+AB102+AC102 -> 0.41455 | AE102: =(AD102+Y102+W102+R102+N102)*$AE$7 -> 8.1847669 | AF102: =AE102 -> 8.1847669 | AL102: =(AD102+Y102+W102+R102+N102)*$AL$7 -> 0 | AM102: =AL102+AF102+AD102+Y102+W102+R102+N102 -> 40.923834 | AN102: =AM102*$AN$12 -> 0.49108601 | AO102: =AM102*$AO$12 -> 0.44197741 | AP102: =AO102+AN102 -> 0.93306342 | AQ102: =AM102*$AQ$12 -> 3.4171402 | AR102: =AM102*$AR$12 -> 0 | AS102: =AM102*$AS$12 -> 0 | AT102: =AQ102+AR102+AS102 -> 3.4171402 | AU102: =AM102*$AU$12 -> 2.0461917 | AV102: =AU102 -> 2.0461917 | AW102: =AM102+AP102+AT102+AV102 -> 47.32023 | AX102: =AY102/AW102 -> -0.0088805491 | AY102: =I102-AW102 -> -0.42022962 | AZ102: =IFERROR(H102*VLOOKUP(A102,'Tabela de Produtos'!A:Q,17,0),0) -> 29.84 | BA102: =$I102*BA$12 -> 0 | BB102: =$I102*BB$12 -> 0 | BC102: =$I102*BC$12 -> 0 | BD102: =$I102*BD$12 -> 3.283 | BE102: =I102*$BE$12 -> 2.345 | BF102: =SUM(AZ102:BE102) -> 35.468 | BG102: =I102-BF102 -> 11.432 | BH102: =IF(F102="Cadastrar Ficha de Produção",0,IFERROR(BG102/I102,0)) -> 0.24375267
A103: PRD00090 | B103: =IFERROR(VLOOKUP(A103,'Tabela de Produtos'!A:B,2,0),"Preencher Cód. Produto") -> BRAZIMIL LÁTEX STANDARD INT/EXT SEMIBRILHO 3L AREIA | D103: Galao | E103: 100 | F103: =IF(A103=0,0,VLOOKUP(A103,'Tabela de Produtos'!A:W,23,0)) -> 32.48 | G103: 46.9 | H103: 1 | I103: =G103*H103 -> 46.9 | J103: =VLOOKUP(B103,'Tabela de Produtos'!B:M,12,FALSE()) -> 24.21 | K103: =VLOOKUP(B103,'Tabela de Produtos'!B:P,15,FALSE()) -> 0.93 | L103: =J103*1% -> 0.2421 | M103: =J103*1% -> 0.2421 | N103: =J103+K103+L103+M103 -> 25.6242 | O103: =($O$12/E103)*$O$13 -> 0.362 | P103: =($P$12/E103)*$P$13 -> 0.2829 | Q103: =($Q$12/E103)*$Q$13 -> 0.2829 | R103: =O103+P103+Q103 -> 0.9278 | S103: =VLOOKUP(B103,'Tabela de Produtos'!B:N,13,FALSE()) -> 3.44 | T103: =$T$12/$T$7 -> 0.22727273 | U103: =$U$12/$U$7 -> 0.39090909 | V103: =$V$12/$V$7 -> 0.10909091 | W103: =S103+T103+U103+V103 -> 4.1672727 | X103: =(N103+R103+W103)*1% -> 0.30719273 | Y103: =X103 -> 0.30719273 | Z103: =$Z$12/E103 -> 0.0083 | AA103: =$AA$12/E103 -> 0.20833333 | AB103: =$AB$12/E103 -> 0.19791667 | AC103: =$AC$12/E103 -> 0 | AD103: =Z103+AA103+AB103+AC103 -> 0.41455 | AE103: =(AD103+Y103+W103+R103+N103)*$AE$7 -> 7.8602539 | AF103: =AE103 -> 7.8602539 | AL103: =(AD103+Y103+W103+R103+N103)*$AL$7 -> 0 | AM103: =AL103+AF103+AD103+Y103+W103+R103+N103 -> 39.301269 | AN103: =AM103*$AN$12 -> 0.47161523 | AO103: =AM103*$AO$12 -> 0.42445371 | AP103: =AO103+AN103 -> 0.89606894 | AQ103: =AM103*$AQ$12 -> 3.281656 | AR103: =AM103*$AR$12 -> 0 | AS103: =AM103*$AS$12 -> 0 | AT103: =AQ103+AR103+AS103 -> 3.281656 | AU103: =AM103*$AU$12 -> 1.9650635 | AV103: =AU103 -> 1.9650635 | AW103: =AM103+AP103+AT103+AV103 -> 45.444058 | AX103: =AY103/AW103 -> 0.032038122 | AY103: =I103-AW103 -> 1.4559423 | AZ103: =IFERROR(H103*VLOOKUP(A103,'Tabela de Produtos'!A:Q,17,0),0) -> 28.58 | BA103: =$I103*BA$12 -> 0 | BB103: =$I103*BB$12 -> 0 | BC103: =$I103*BC$12 -> 0 | BD103: =$I103*BD$12 -> 3.283 | BE103: =I103*$BE$12 -> 2.345 | BF103: =SUM(AZ103:BE103) -> 34.208 | BG103: =I103-BF103 -> 12.692 | BH103: =IF(F103="Cadastrar Ficha de Produção",0,IFERROR(BG103/I103,0)) -> 0.27061834
A104: PRD00091 | B104: =IFERROR(VLOOKUP(A104,'Tabela de Produtos'!A:B,2,0),"Preencher Cód. Produto") -> BRAZIMIL LÁTEX STANDARD INT/EXT SEMIBRILHO 3L MARFIM | D104: Galao | E104: 100 | F104: =IF(A104=0,0,VLOOKUP(A104,'Tabela de Produtos'!A:W,23,0)) -> 34.02 | G104: 46.9 | H104: 1 | I104: =G104*H104 -> 46.9 | J104: =VLOOKUP(B104,'Tabela de Produtos'!B:M,12,FALSE()) -> 25.56 | K104: =VLOOKUP(B104,'Tabela de Produtos'!B:P,15,FALSE()) -> 0.93 | L104: =J104*1% -> 0.2556 | M104: =J104*1% -> 0.2556 | N104: =J104+K104+L104+M104 -> 27.0012 | O104: =($O$12/E104)*$O$13 -> 0.362 | P104: =($P$12/E104)*$P$13 -> 0.2829 | Q104: =($Q$12/E104)*$Q$13 -> 0.2829 | R104: =O104+P104+Q104 -> 0.9278 | S104: =VLOOKUP(B104,'Tabela de Produtos'!B:N,13,FALSE()) -> 3.44 | T104: =$T$12/$T$7 -> 0.22727273 | U104: =$U$12/$U$7 -> 0.39090909 | V104: =$V$12/$V$7 -> 0.10909091 | W104: =S104+T104+U104+V104 -> 4.1672727 | X104: =(N104+R104+W104)*1% -> 0.32096273 | Y104: =X104 -> 0.32096273 | Z104: =$Z$12/E104 -> 0.0083 | AA104: =$AA$12/E104 -> 0.20833333 | AB104: =$AB$12/E104 -> 0.19791667 | AC104: =$AC$12/E104 -> 0 | AD104: =Z104+AA104+AB104+AC104 -> 0.41455 | AE104: =(AD104+Y104+W104+R104+N104)*$AE$7 -> 8.2079464 | AF104: =AE104 -> 8.2079464 | AL104: =(AD104+Y104+W104+R104+N104)*$AL$7 -> 0 | AM104: =AL104+AF104+AD104+Y104+W104+R104+N104 -> 41.039732 | AN104: =AM104*$AN$12 -> 0.49247678 | AO104: =AM104*$AO$12 -> 0.4432291 | AP104: =AO104+AN104 -> 0.93570589 | AQ104: =AM104*$AQ$12 -> 3.4268176 | AR104: =AM104*$AR$12 -> 0 | AS104: =AM104*$AS$12 -> 0 | AT104: =AQ104+AR104+AS104 -> 3.4268176 | AU104: =AM104*$AU$12 -> 2.0519866 | AV104: =AU104 -> 2.0519866 | AW104: =AM104+AP104+AT104+AV104 -> 47.454242 | AX104: =AY104/AW104 -> -0.011679502 | AY104: =I104-AW104 -> -0.5542419 | AZ104: =IFERROR(H104*VLOOKUP(A104,'Tabela de Produtos'!A:Q,17,0),0) -> 29.93 | BA104: =$I104*BA$12 -> 0 | BB104: =$I104*BB$12 -> 0 | BC104: =$I104*BC$12 -> 0 | BD104: =$I104*BD$12 -> 3.283 | BE104: =I104*$BE$12 -> 2.345 | BF104: =SUM(AZ104:BE104) -> 35.558 | BG104: =I104-BF104 -> 11.342 | BH104: =IF(F104="Cadastrar Ficha de Produção",0,IFERROR(BG104/I104,0)) -> 0.24183369
A105: PRD00092 | B105: =IFERROR(VLOOKUP(A105,'Tabela de Produtos'!A:B,2,0),"Preencher Cód. Produto") -> BRAZIMIL LÁTEX STANDARD INT/EXT SEMIBRILHO 3L ROSA PETALA | D105: Galao | E105: 100 | F105: =IF(A105=0,0,VLOOKUP(A105,'Tabela de Produtos'!A:W,23,0)) -> 32.24 | G105: 46.9 | H105: 1 | I105: =G105*H105 -> 46.9 | J105: =VLOOKUP(B105,'Tabela de Produtos'!B:M,12,FALSE()) -> 24 | K105: =VLOOKUP(B105,'Tabela de Produtos'!B:P,15,FALSE()) -> 0.93 | L105: =J105*1% -> 0.24 | M105: =J105*1% -> 0.24 | N105: =J105+K105+L105+M105 -> 25.41 | O105: =($O$12/E105)*$O$13 -> 0.362 | P105: =($P$12/E105)*$P$13 -> 0.2829 | Q105: =($Q$12/E105)*$Q$13 -> 0.2829 | R105: =O105+P105+Q105 -> 0.9278 | S105: =VLOOKUP(B105,'Tabela de Produtos'!B:N,13,FALSE()) -> 3.44 | T105: =$T$12/$T$7 -> 0.22727273 | U105: =$U$12/$U$7 -> 0.39090909 | V105: =$V$12/$V$7 -> 0.10909091 | W105: =S105+T105+U105+V105 -> 4.1672727 | X105: =(N105+R105+W105)*1% -> 0.30505073 | Y105: =X105 -> 0.30505073 | Z105: =$Z$12/E105 -> 0.0083 | AA105: =$AA$12/E105 -> 0.20833333 | AB105: =$AB$12/E105 -> 0.19791667 | AC105: =$AC$12/E105 -> 0 | AD105: =Z105+AA105+AB105+AC105 -> 0.41455 | AE105: =(AD105+Y105+W105+R105+N105)*$AE$7 -> 7.8061684 | AF105: =AE105 -> 7.8061684 | AL105: =(AD105+Y105+W105+R105+N105)*$AL$7 -> 0 | AM105: =AL105+AF105+AD105+Y105+W105+R105+N105 -> 39.030842 | AN105: =AM105*$AN$12 -> 0.4683701 | AO105: =AM105*$AO$12 -> 0.42153309 | AP105: =AO105+AN105 -> 0.88990319 | AQ105: =AM105*$AQ$12 -> 3.2590753 | AR105: =AM105*$AR$12 -> 0 | AS105: =AM105*$AS$12 -> 0 | AT105: =AQ105+AR105+AS105 -> 3.2590753 | AU105: =AM105*$AU$12 -> 1.9515421 | AV105: =AU105 -> 1.9515421 | AW105: =AM105+AP105+AT105+AV105 -> 45.131362 | AX105: =AY105/AW105 -> 0.03918866 | AY105: =I105-AW105 -> 1.7686376 | AZ105: =IFERROR(H105*VLOOKUP(A105,'Tabela de Produtos'!A:Q,17,0),0) -> 28.37 | BA105: =$I105*BA$12 -> 0 | BB105: =$I105*BB$12 -> 0 | BC105: =$I105*BC$12 -> 0 | BD105: =$I105*BD$12 -> 3.283 | BE105: =I105*$BE$12 -> 2.345 | BF105: =SUM(AZ105:BE105) -> 33.998 | BG105: =I105-BF105 -> 12.902 | BH105: =IF(F105="Cadastrar Ficha de Produção",0,IFERROR(BG105/I105,0)) -> 0.27509595
A106: PRD00093 | B106: =IFERROR(VLOOKUP(A106,'Tabela de Produtos'!A:B,2,0),"Preencher Cód. Produto") -> BRAZIMIL LÁTEX STANDARD INT/EXT SEMIBRILHO 3L ACAI AMAZONICO | D106: Galao | E106: 100 | F106: =IF(A106=0,0,VLOOKUP(A106,'Tabela de Produtos'!A:W,23,0)) -> 29.65 | G106: 46.9 | H106: 1 | I106: =G106*H106 -> 46.9 | J106: =VLOOKUP(B106,'Tabela de Produtos'!B:M,12,FALSE()) -> 21.72 | K106: =VLOOKUP(B106,'Tabela de Produtos'!B:P,15,FALSE()) -> 0.93 | L106: =J106*1% -> 0.2172 | M106: =J106*1% -> 0.2172 | N106: =J106+K106+L106+M106 -> 23.0844 | O106: =($O$12/E106)*$O$13 -> 0.362 | P106: =($P$12/E106)*$P$13 -> 0.2829 | Q106: =($Q$12/E106)*$Q$13 -> 0.2829 | R106: =O106+P106+Q106 -> 0.9278 | S106: =VLOOKUP(B106,'Tabela de Produtos'!B:N,13,FALSE()) -> 3.44 | T106: =$T$12/$T$7 -> 0.22727273 | U106: =$U$12/$U$7 -> 0.39090909 | V106: =$V$12/$V$7 -> 0.10909091 | W106: =S106+T106+U106+V106 -> 4.1672727 | X106: =(N106+R106+W106)*1% -> 0.28179473 | Y106: =X106 -> 0.28179473 | Z106: =$Z$12/E106 -> 0.0083 | AA106: =$AA$12/E106 -> 0.20833333 | AB106: =$AB$12/E106 -> 0.19791667 | AC106: =$AC$12/E106 -> 0 | AD106: =Z106+AA106+AB106+AC106 -> 0.41455 | AE106: =(AD106+Y106+W106+R106+N106)*$AE$7 -> 7.2189544 | AF106: =AE106 -> 7.2189544 | AL106: =(AD106+Y106+W106+R106+N106)*$AL$7 -> 0 | AM106: =AL106+AF106+AD106+Y106+W106+R106+N106 -> 36.094772 | AN106: =AM106*$AN$12 -> 0.43313726 | AO106: =AM106*$AO$12 -> 0.38982354 | AP106: =AO106+AN106 -> 0.8229608 | AQ106: =AM106*$AQ$12 -> 3.0139134 | AR106: =AM106*$AR$12 -> 0 | AS106: =AM106*$AS$12 -> 0 | AT106: =AQ106+AR106+AS106 -> 3.0139134 | AU106: =AM106*$AU$12 -> 1.8047386 | AV106: =AU106 -> 1.8047386 | AW106: =AM106+AP106+AT106+AV106 -> 41.736385 | AX106: =AY106/AW106 -> 0.12371976 | AY106: =I106-AW106 -> 5.1636153 | AZ106: =IFERROR(H106*VLOOKUP(A106,'Tabela de Produtos'!A:Q,17,0),0) -> 26.09 | BA106: =$I106*BA$12 -> 0 | BB106: =$I106*BB$12 -> 0 | BC106: =$I106*BC$12 -> 0 | BD106: =$I106*BD$12 -> 3.283 | BE106: =I106*$BE$12 -> 2.345 | BF106: =SUM(AZ106:BE106) -> 31.718 | BG106: =I106-BF106 -> 15.182 | BH106: =IF(F106="Cadastrar Ficha de Produção",0,IFERROR(BG106/I106,0)) -> 0.32371002
A107: PRD00094 | B107: =IFERROR(VLOOKUP(A107,'Tabela de Produtos'!A:B,2,0),"Preencher Cód. Produto") -> BRAZIMIL LÁTEX STANDARD INT/EXT SEMIBRILHO 3L VERDE FOLHA | D107: Galao | E107: 100 | F107: =IF(A107=0,0,VLOOKUP(A107,'Tabela de Produtos'!A:W,23,0)) -> 32 | G107: 46.9 | H107: 1 | I107: =G107*H107 -> 46.9 | J107: =VLOOKUP(B107,'Tabela de Produtos'!B:M,12,FALSE()) -> 23.79 | K107: =VLOOKUP(B107,'Tabela de Produtos'!B:P,15,FALSE()) -> 0.93 | L107: =J107*1% -> 0.2379 | M107: =J107*1% -> 0.2379 | N107: =J107+K107+L107+M107 -> 25.1958 | O107: =($O$12/E107)*$O$13 -> 0.362 | P107: =($P$12/E107)*$P$13 -> 0.2829 | Q107: =($Q$12/E107)*$Q$13 -> 0.2829 | R107: =O107+P107+Q107 -> 0.9278 | S107: =VLOOKUP(B107,'Tabela de Produtos'!B:N,13,FALSE()) -> 3.44 | T107: =$T$12/$T$7 -> 0.22727273 | U107: =$U$12/$U$7 -> 0.39090909 | V107: =$V$12/$V$7 -> 0.10909091 | W107: =S107+T107+U107+V107 -> 4.1672727 | X107: =(N107+R107+W107)*1% -> 0.30290873 | Y107: =X107 -> 0.30290873 | Z107: =$Z$12/E107 -> 0.0083 | AA107: =$AA$12/E107 -> 0.20833333 | AB107: =$AB$12/E107 -> 0.19791667 | AC107: =$AC$12/E107 -> 0 | AD107: =Z107+AA107+AB107+AC107 -> 0.41455 | AE107: =(AD107+Y107+W107+R107+N107)*$AE$7 -> 7.7520829 | AF107: =AE107 -> 7.7520829 | AL107: =(AD107+Y107+W107+R107+N107)*$AL$7 -> 0 | AM107: =AL107+AF107+AD107+Y107+W107+R107+N107 -> 38.760414 | AN107: =AM107*$AN$12 -> 0.46512497 | AO107: =AM107*$AO$12 -> 0.41861247 | AP107: =AO107+AN107 -> 0.88373745 | AQ107: =AM107*$AQ$12 -> 3.2364946 | AR107: =AM107*$AR$12 -> 0 | AS107: =AM107*$AS$12 -> 0 | AT107: =AQ107+AR107+AS107 -> 3.2364946 | AU107: =AM107*$AU$12 -> 1.9380207 | AV107: =AU107 -> 1.9380207 | AW107: =AM107+AP107+AT107+AV107 -> 44.818667 | AX107: =AY107/AW107 -> 0.046438974 | AY107: =I107-AW107 -> 2.0813329 | AZ107: =IFERROR(H107*VLOOKUP(A107,'Tabela de Produtos'!A:Q,17,0),0) -> 28.16 | BA107: =$I107*BA$12 -> 0 | BB107: =$I107*BB$12 -> 0 | BC107: =$I107*BC$12 -> 0 | BD107: =$I107*BD$12 -> 3.283 | BE107: =I107*$BE$12 -> 2.345 | BF107: =SUM(AZ107:BE107) -> 33.788 | BG107: =I107-BF107 -> 13.112 | BH107: =IF(F107="Cadastrar Ficha de Produção",0,IFERROR(BG107/I107,0)) -> 0.27957356
A108: PRD00095 | B108: =IFERROR(VLOOKUP(A108,'Tabela de Produtos'!A:B,2,0),"Preencher Cód. Produto") -> BRAZIMIL LÁTEX STANDARD INT/EXT SEMIBRILHO 3L LARANJA | D108: Galao | E108: 100 | F108: =IF(A108=0,0,VLOOKUP(A108,'Tabela de Produtos'!A:W,23,0)) -> 31.43 | G108: 46.9 | H108: 1 | I108: =G108*H108 -> 46.9 | J108: =VLOOKUP(B108,'Tabela de Produtos'!B:M,12,FALSE()) -> 23.28 | K108: =VLOOKUP(B108,'Tabela de Produtos'!B:P,15,FALSE()) -> 0.93 | L108: =J108*1% -> 0.2328 | M108: =J108*1% -> 0.2328 | N108: =J108+K108+L108+M108 -> 24.6756 | O108: =($O$12/E108)*$O$13 -> 0.362 | P108: =($P$12/E108)*$P$13 -> 0.2829 | Q108: =($Q$12/E108)*$Q$13 -> 0.2829 | R108: =O108+P108+Q108 -> 0.9278 | S108: =VLOOKUP(B108,'Tabela de Produtos'!B:N,13,FALSE()) -> 3.44 | T108: =$T$12/$T$7 -> 0.22727273 | U108: =$U$12/$U$7 -> 0.39090909 | V108: =$V$12/$V$7 -> 0.10909091 | W108: =S108+T108+U108+V108 -> 4.1672727 | X108: =(N108+R108+W108)*1% -> 0.29770673 | Y108: =X108 -> 0.29770673 | Z108: =$Z$12/E108 -> 0.0083 | AA108: =$AA$12/E108 -> 0.20833333 | AB108: =$AB$12/E108 -> 0.19791667 | AC108: =$AC$12/E108 -> 0 | AD108: =Z108+AA108+AB108+AC108 -> 0.41455 | AE108: =(AD108+Y108+W108+R108+N108)*$AE$7 -> 7.6207324 | AF108: =AE108 -> 7.6207324 | AL108: =(AD108+Y108+W108+R108+N108)*$AL$7 -> 0 | AM108: =AL108+AF108+AD108+Y108+W108+R108+N108 -> 38.103662 | AN108: =AM108*$AN$12 -> 0.45724394 | AO108: =AM108*$AO$12 -> 0.41151955 | AP108: =AO108+AN108 -> 0.86876349 | AQ108: =AM108*$AQ$12 -> 3.1816558 | AR108: =AM108*$AR$12 -> 0 | AS108: =AM108*$AS$12 -> 0 | AT108: =AQ108+AR108+AS108 -> 3.1816558 | AU108: =AM108*$AU$12 -> 1.9051831 | AV108: =AU108 -> 1.9051831 | AW108: =AM108+AP108+AT108+AV108 -> 44.059264 | AX108: =AY108/AW108 -> 0.064475336 | AY108: =I108-AW108 -> 2.8407358 | AZ108: =IFERROR(H108*VLOOKUP(A108,'Tabela de Produtos'!A:Q,17,0),0) -> 27.65 | BA108: =$I108*BA$12 -> 0 | BB108: =$I108*BB$12 -> 0 | BC108: =$I108*BC$12 -> 0 | BD108: =$I108*BD$12 -> 3.283 | BE108: =I108*$BE$12 -> 2.345 | BF108: =SUM(AZ108:BE108) -> 33.278 | BG108: =I108-BF108 -> 13.622 | BH108: =IF(F108="Cadastrar Ficha de Produção",0,IFERROR(BG108/I108,0)) -> 0.29044776
A109: PRD00096 | B109: =IFERROR(VLOOKUP(A109,'Tabela de Produtos'!A:B,2,0),"Preencher Cód. Produto") -> BRAZIMIL LÁTEX STANDARD INT/EXT SEMIBRILHO 3L AZUL CARIBE | D109: Galao | E109: 100 | F109: =IF(A109=0,0,VLOOKUP(A109,'Tabela de Produtos'!A:W,23,0)) -> 32.55 | G109: 46.9 | H109: 1 | I109: =G109*H109 -> 46.9 | J109: =VLOOKUP(B109,'Tabela de Produtos'!B:M,12,FALSE()) -> 24.27 | K109: =VLOOKUP(B109,'Tabela de Produtos'!B:P,15,FALSE()) -> 0.93 | L109: =J109*1% -> 0.2427 | M109: =J109*1% -> 0.2427 | N109: =J109+K109+L109+M109 -> 25.6854 | O109: =($O$12/E109)*$O$13 -> 0.362 | P109: =($P$12/E109)*$P$13 -> 0.2829 | Q109: =($Q$12/E109)*$Q$13 -> 0.2829 | R109: =O109+P109+Q109 -> 0.9278 | S109: =VLOOKUP(B109,'Tabela de Produtos'!B:N,13,FALSE()) -> 3.44 | T109: =$T$12/$T$7 -> 0.22727273 | U109: =$U$12/$U$7 -> 0.39090909 | V109: =$V$12/$V$7 -> 0.10909091 | W109: =S109+T109+U109+V109 -> 4.1672727 | X109: =(N109+R109+W109)*1% -> 0.30780473 | Y109: =X109 -> 0.30780473 | Z109: =$Z$12/E109 -> 0.0083 | AA109: =$AA$12/E109 -> 0.20833333 | AB109: =$AB$12/E109 -> 0.19791667 | AC109: =$AC$12/E109 -> 0 | AD109: =Z109+AA109+AB109+AC109 -> 0.41455 | AE109: =(AD109+Y109+W109+R109+N109)*$AE$7 -> 7.8757069 | AF109: =AE109 -> 7.8757069 | AL109: =(AD109+Y109+W109+R109+N109)*$AL$7 -> 0 | AM109: =AL109+AF109+AD109+Y109+W109+R109+N109 -> 39.378534 | AN109: =AM109*$AN$12 -> 0.47254241 | AO109: =AM109*$AO$12 -> 0.42528817 | AP109: =AO109+AN109 -> 0.89783058 | AQ109: =AM109*$AQ$12 -> 3.2881076 | AR109: =AM109*$AR$12 -> 0 | AS109: =AM109*$AS$12 -> 0 | AT109: =AQ109+AR109+AS109 -> 3.2881076 | AU109: =AM109*$AU$12 -> 1.9689267 | AV109: =AU109 -> 1.9689267 | AW109: =AM109+AP109+AT109+AV109 -> 45.533399 | AX109: =AY109/AW109 -> 0.030013151 | AY109: =I109-AW109 -> 1.3666008 | AZ109: =IFERROR(H109*VLOOKUP(A109,'Tabela de Produtos'!A:Q,17,0),0) -> 28.64 | BA109: =$I109*BA$12 -> 0 | BB109: =$I109*BB$12 -> 0 | BC109: =$I109*BC$12 -> 0 | BD109: =$I109*BD$12 -> 3.283 | BE109: =I109*$BE$12 -> 2.345 | BF109: =SUM(AZ109:BE109) -> 34.268 | BG109: =I109-BF109 -> 12.632 | BH109: =IF(F109="Cadastrar Ficha de Produção",0,IFERROR(BG109/I109,0)) -> 0.26933902
...

Sheet Grfico
C1: TOTAL
B2: BRAZIMIL LÁTEX ECONÔMICO INT FOSCO 15L BRANCO NEVE | C2: =SUM(C4:C13) -> 56.604379
B3: Tipo | C3: Custo
B4: 1. Materia prima | C4: ='Formação de Preço de Venda'!N52 -> 23.163 | D4: =C4/$C$2 -> 0.40920862
B5: 3.Embalagem | C5: ='Formação de Preço de Venda'!W52 -> 10.832222 | D5: =C5/$C$2 -> 0.19136721
B6: 6.Mark up | C6: ='Formação de Preço de Venda'!AF52 -> 9.7906043 | D6: =C6/$C$2 -> 0.17296549
B7: 7.Outros Despesas (Indireto) - 15% | C7: ='Formação de Preço de Venda'!AL52 -> 0 | D7: =C7/$C$2 -> 0
B8: 9.Impostos(Dentro) | C8: ='Formação de Preço de Venda'!AT52 -> 4.0875773 | D8: =C8/$C$2 -> 0.072213093
B9: 5.Outras custos Industriais | C9: ='Formação de Preço de Venda'!AD52 -> 1.4805357 | D9: =C9/$C$2 -> 0.026155851
B10: 2.Processo | C10: ='Formação de Preço de Venda'!R52 -> 3.3135714 | D10: =C10/$C$2 -> 0.058539136
B11: 10.Comissao | C11: ='Formação de Preço de Venda'!AV52 -> 2.4476511 | D11: =C11/$C$2 -> 0.043241373
B12: 8.Impostos(Fora) | C12: ='Formação de Preço de Venda'!AP52 -> 1.1161289 | D12: =C12/$C$2 -> 0.019718066
B13: 4.Refugo | C13: ='Formação de Preço de Venda'!Y52 -> 0.37308794 | D13: =C13/$C$2 -> 0.0065911497

Sheet Tabela de Produtos
P1: 0.31 | R1: ='Formação de Preço de Venda'!$BE$12 -> 0.05 | S1: =SUM('Formação de Preço de Venda'!$BA$12:$BD$12) -> 0.07 | AB1: ⚠️ CORREÇÃO METODOLÓGICA — Custeio Variável MC Correta = PLV − CV (I+E+F) | PLV = Preço × (1 − Comissão − Imposto) Comissão e Imposto são deduções do preço — NÃO fazem parte do custo variável do produto
AB2: 🟢 MC ≥ 35% = Saudável | 🟡 MC 20–35% = Atenção | 🔴 MC < 20% = Crítico | ⬛ MC < 0% = Prejuízo
A3: CÓDIGO | B3: DESCRIÇÃO | C3: GRUPO | D3: PROD. INTERM. | E3: ACABAMENTO | F3: COR | G3: EM PRODUÇÃO? | H3: EMBALAGEM | I3: MEDIDA | J3: FATOR CONV DENS | K3: Status Insumo | L3: Status Embalagem | M3: CUSTO INSUMOS (I) | N3: CUSTO EMBAL. (E) | O3: CUSTO (I+E) ← | P3: FRETE (F) | Q3: (I+E+F+CP) ← | R3: COMISSÃO FINAL | S3: IMPOSTO FINAL | T3: CUSTO TT FINAL | U3: PREÇO FINAL | V3: MARGEM FINAL | W3: PREÇO MÍNIMO | X3: CUSTO VARIÁVEL (método antigo) [inclui comissão+imposto] | Y3: MC UNITÁRIA (método antigo) [Preço − Custo TT] | Z3: MC % (método antigo) [MC / Preço Bruto] | AA3: CUSTOS FIXOS TOTAIS | AB3: CV UNITÁRIO CORRETO (I+E+F apenas) | AC3: PLV (Preço Líq. de Venda) | AD3: MC UNITÁRIA CORRETA (PLV − CV) | AE3: MC % CORRETA (MC/PLV) | AF3: PREÇO SUSTENTÁVEL (cobre CF também)
A4: PRD00001 | B4: BRAZIMIL MASSA CORRIDA 4,0KG | C4: MASSA CORRIDA | D4: PI00001 | E4: N/A | F4: N/A | G4: SIM | H4: 4 | I4: KG | J4: =IF(I4="KG",1,1.27) -> 1 | K4: =IFERROR(IF(VLOOKUP(D4,'Ficha de Produção'!C:C,1,0)=D4,"OK","Custo Produção Não Cadastrado"),"Custo Produção Não Cadastrado") -> OK | L4: =IFERROR(IF(VLOOKUP(A4,'Ficha de Embalagens'!A:A,1,0)=A4,"OK","Ficha de Embalagens Não Cadastrada"),"Ficha de Embalagens Não Cadastrada") -> OK | M4: =SUMIFS('Ficha de Produção'!N:N,'Ficha de Produção'!C:C,D4)*H4 -> 3 | N4: =SUMIFS('Ficha de Embalagens'!F:F,'Ficha de Embalagens'!A:A,A4) -> 3.06 | O4: =SUM(M4:N4) -> 6.06 | P4: =IF(AND(K4="OK",L4="OK"),H4*$P$1,0) -> 1.24 | Q4: =P4+O4 -> 7.3 | R4: =U4*$R$1 -> 0.7995 | S4: =$S$1*U4 -> 1.1193 | T4: =+Q4+R4+S4 -> 9.2188 | U4: 15.99 | V4: =IF(M4=0,"Cadastrar Ficha de Produção",IF(AND(M4>0,U4=""),"Cadastrar Preço Final",IFERROR((U4-T4)/U4,""))) -> 0.42346467 | W4: =IF(M4=0,"Cadastrar Ficha de Produção",ROUNDUP(Q4/(1-$R$1-$S$1),2)) -> 8.3 | X4: =SUM(Q4,R4,S4) -> 9.2188 | Y4: =U4-X4 -> 6.7712 | Z4: =Y4/U4 -> 0.42346467 | AA4: =SUM('Despesas Fixas'!F4,'Custos de Produção'!K4,Salários!J21) -> 55345.981 | AB4: =IF(Q4=0,"",Q4) -> 7.3 | AC4: =IF(U4="","",U4*(1-$R$1-$S$1)) -> 14.0712 | AD4: =IF(OR(AB4="",AC4=""),"",AC4-AB4) -> 6.7712 | AE4: =IF(OR(AD4="",AC4=0),"",AD4/AC4) -> 0.48120985 | AF4: =IF(Q4=0,"",ROUNDUP((Q4+IF(AA4="",0,AA4/1200))/(1-$R$1-$S$1),2)) -> 60.71
A5: PRD00002 | B5: BRAZIMIL MASSA CORRIDA 20,0 KG | C5: MASSA CORRIDA | D5: PI00001 | E5: N/A | F5: N/A | G5: SIM | H5: 20 | I5: KG | J5: =IF(I5="KG",1,1.27) -> 1 | K5: =IFERROR(IF(VLOOKUP(D5,'Ficha de Produção'!C:C,1,0)=D5,"OK","Custo Produção Não Cadastrado"),"Custo Produção Não Cadastrado") -> OK | L5: =IFERROR(IF(VLOOKUP(A5,'Ficha de Embalagens'!A:A,1,0)=A5,"OK","Ficha de Embalagens Não Cadastrada"),"Ficha de Embalagens Não Cadastrada") -> OK | M5: =SUMIFS('Ficha de Produção'!N:N,'Ficha de Produção'!C:C,D5)*H5 -> 15 | N5: =SUMIFS('Ficha de Embalagens'!F:F,'Ficha de Embalagens'!A:A,A5) -> 8.61 | O5: =SUM(M5:N5) -> 23.61 | P5: =IF(AND(K5="OK",L5="OK"),H5*$P$1,0) -> 6.2 | Q5: =P5+O5 -> 29.81 | R5: =U5*$R$1 -> 1.945 | S5: =$S$1*U5 -> 2.723 | T5: =+Q5+R5+S5 -> 34.478 | U5: 38.9 | V5: =IF(M5=0,"Cadastrar Ficha de Produção",IF(AND(M5>0,U5=""),"Cadastrar Preço Final",IFERROR((U5-T5)/U5,""))) -> 0.11367609 | W5: =IF(M5=0,"Cadastrar Ficha de Produção",ROUNDUP(Q5/(1-$R$1-$S$1),2)) -> 33.88 | AB5: =IF(Q5=0,"",Q5) -> 29.81 | AC5: =IF(U5="","",U5*(1-$R$1-$S$1)) -> 34.232 | AD5: =IF(OR(AB5="",AC5=""),"",AC5-AB5) -> 4.422 | AE5: =IF(OR(AD5="",AC5=0),"",AD5/AC5) -> 0.12917738 | AF5: =IF(Q5=0,"",ROUNDUP((Q5+IF(AA5="",0,AA5/1200))/(1-$R$1-$S$1),2)) -> 33.88
A6: PRD00003 | B6: BRAZIMIL SELADOR ACRILICO 3L | C6: SELADOR | D6: PI00002 | E6: ACRÍLICO | F6: N/A | G6: SIM | H6: 3 | I6: L | J6: =IF(I6="KG",1,1.27) -> 1.27 | K6: =IFERROR(IF(VLOOKUP(D6,'Ficha de Produção'!C:C,1,0)=D6,"OK","Custo Produção Não Cadastrado"),"Custo Produção Não Cadastrado") -> OK | L6: =IFERROR(IF(VLOOKUP(A6,'Ficha de Embalagens'!A:A,1,0)=A6,"OK","Ficha de Embalagens Não Cadastrada"),"Ficha de Embalagens Não Cadastrada") -> OK | M6: =SUMIFS('Ficha de Produção'!N:N,'Ficha de Produção'!C:C,D6)*H6 -> 2.64 | N6: =SUMIFS('Ficha de Embalagens'!F:F,'Ficha de Embalagens'!A:A,A6) -> 3.06 | O6: =SUM(M6:N6) -> 5.7 | P6: =IF(AND(K6="OK",L6="OK"),H6*$P$1,0) -> 0.93 | Q6: =P6+O6 -> 6.63 | R6: =U6*$R$1 -> 0.8495 | S6: =$S$1*U6 -> 1.1893 | T6: =+Q6+R6+S6 -> 8.6688 | U6: 16.99 | V6: =IF(M6=0,"Cadastrar Ficha de Produção",IF(AND(M6>0,U6=""),"Cadastrar Preço Final",IFERROR((U6-T6)/U6,""))) -> 0.48977045 | W6: =IF(M6=0,"Cadastrar Ficha de Produção",ROUNDUP(Q6/(1-$R$1-$S$1),2)) -> 7.54 | AB6: =IF(Q6=0,"",Q6) -> 6.63 | AC6: =IF(U6="","",U6*(1-$R$1-$S$1)) -> 14.9512 | AD6: =IF(OR(AB6="",AC6=""),"",AC6-AB6) -> 8.3212 | AE6: =IF(OR(AD6="",AC6=0),"",AD6/AC6) -> 0.55655733 | AF6: =IF(Q6=0,"",ROUNDUP((Q6+IF(AA6="",0,AA6/1200))/(1-$R$1-$S$1),2)) -> 7.54
A7: PRD00004 | B7: BRAZIMIL SELADOR ACRILICO 15L | C7: SELADOR | D7: PI00002 | E7: ACRÍLICO | F7: N/A | G7: SIM | H7: 15 | I7: L | J7: =IF(I7="KG",1,1.27) -> 1.27 | K7: =IFERROR(IF(VLOOKUP(D7,'Ficha de Produção'!C:C,1,0)=D7,"OK","Custo Produção Não Cadastrado"),"Custo Produção Não Cadastrado") -> OK | L7: =IFERROR(IF(VLOOKUP(A7,'Ficha de Embalagens'!A:A,1,0)=A7,"OK","Ficha de Embalagens Não Cadastrada"),"Ficha de Embalagens Não Cadastrada") -> OK | M7: =SUMIFS('Ficha de Produção'!N:N,'Ficha de Produção'!C:C,D7)*H7 -> 13.2 | N7: =SUMIFS('Ficha de Embalagens'!F:F,'Ficha de Embalagens'!A:A,A7) -> 8.61 | O7: =SUM(M7:N7) -> 21.81 | P7: =IF(AND(K7="OK",L7="OK"),H7*$P$1,0) -> 4.65 | Q7: =P7+O7 -> 26.46 | R7: =U7*$R$1 -> 3.3245 | S7: =$S$1*U7 -> 4.6543 | T7: =+Q7+R7+S7 -> 34.4388 | U7: 66.49 | V7: =IF(M7=0,"Cadastrar Ficha de Produção",IF(AND(M7>0,U7=""),"Cadastrar Preço Final",IFERROR((U7-T7)/U7,""))) -> 0.48204542 | W7: =IF(M7=0,"Cadastrar Ficha de Produção",ROUNDUP(Q7/(1-$R$1-$S$1),2)) -> 30.07 | AB7: =IF(Q7=0,"",Q7) -> 26.46 | AC7: =IF(U7="","",U7*(1-$R$1-$S$1)) -> 58.5112 | AD7: =IF(OR(AB7="",AC7=""),"",AC7-AB7) -> 32.0512 | AE7: =IF(OR(AD7="",AC7=0),"",AD7/AC7) -> 0.54777889 | AF7: =IF(Q7=0,"",ROUNDUP((Q7+IF(AA7="",0,AA7/1200))/(1-$R$1-$S$1),2)) -> 30.07
A8: PRD00005 | B8: BRAZIMIL SELADORA PARA MADEIRA 0,75L INCOLOR | C8: SELADOR | E8: PARA MADEIRA | F8: INCOLOR | G8: NÃO | H8: 0.75 | I8: L | J8: =IF(I8="KG",1,1.27) -> 1.27 | K8: =IFERROR(IF(VLOOKUP(D8,'Ficha de Produção'!C:C,1,0)=D8,"OK","Custo Produção Não Cadastrado"),"Custo Produção Não Cadastrado") -> Custo Produção Não Cadastrado | L8: =IFERROR(IF(VLOOKUP(A8,'Ficha de Embalagens'!A:A,1,0)=A8,"OK","Ficha de Embalagens Não Cadastrada"),"Ficha de Embalagens Não Cadastrada") -> Ficha de Embalagens Não Cadastrada | M8: =SUMIFS('Ficha de Produção'!N:N,'Ficha de Produção'!C:C,D8)*H8 -> 0 | N8: =SUMIFS('Ficha de Embalagens'!F:F,'Ficha de Embalagens'!A:A,A8) -> 0 | O8: =SUM(M8:N8) -> 0 | P8: =IF(AND(K8="OK",L8="OK"),H8*$P$1,0) -> 0 | Q8: =P8+O8 -> 0 | R8: =U8*$R$1 -> 0 | S8: =$S$1*U8 -> 0 | T8: =+Q8+R8+S8 -> 0 | V8: =IF(M8=0,"Cadastrar Ficha de Produção",IF(AND(M8>0,U8=""),"Cadastrar Preço Final",IFERROR((U8-T8)/U8,""))) -> Cadastrar Ficha de Produção | W8: =IF(M8=0,"Cadastrar Ficha de Produção",ROUNDUP(Q8/(1-$R$1-$S$1),2)) -> Cadastrar Ficha de Produção | AB8: =IF(Q8=0,"",Q8) | AC8: =IF(U8="","",U8*(1-$R$1-$S$1)) | AD8: =IF(OR(AB8="",AC8=""),"",AC8-AB8) | AE8: =IF(OR(AD8="",AC8=0),"",AD8/AC8) | AF8: =IF(Q8=0,"",ROUNDUP((Q8+IF(AA8="",0,AA8/1200))/(1-$R$1-$S$1),2))
A9: PRD00006 | B9: BRAZIMIL SELADORA PARA MADEIRA 3L INCOLOR | C9: SELADOR | E9: PARA MADEIRA | F9: INCOLOR | G9: NÃO | H9: 3 | I9: L | J9: =IF(I9="KG",1,1.27) -> 1.27 | K9: =IFERROR(IF(VLOOKUP(D9,'Ficha de Produção'!C:C,1,0)=D9,"OK","Custo Produção Não Cadastrado"),"Custo Produção Não Cadastrado") -> Custo Produção Não Cadastrado | L9: =IFERROR(IF(VLOOKUP(A9,'Ficha de Embalagens'!A:A,1,0)=A9,"OK","Ficha de Embalagens Não Cadastrada"),"Ficha de Embalagens Não Cadastrada") -> Ficha de Embalagens Não Cadastrada | M9: =SUMIFS('Ficha de Produção'!N:N,'Ficha de Produção'!C:C,D9)*H9 -> 0 | N9: =SUMIFS('Ficha de Embalagens'!F:F,'Ficha de Embalagens'!A:A,A9) -> 0 | O9: =SUM(M9:N9) -> 0 | P9: =IF(AND(K9="OK",L9="OK"),H9*$P$1,0) -> 0 | Q9: =P9+O9 -> 0 | R9: =U9*$R$1 -> 0 | S9: =$S$1*U9 -> 0 | T9: =+Q9+R9+S9 -> 0 | V9: =IF(M9=0,"Cadastrar Ficha de Produção",IF(AND(M9>0,U9=""),"Cadastrar Preço Final",IFERROR((U9-T9)/U9,""))) -> Cadastrar Ficha de Produção | W9: =IF(M9=0,"Cadastrar Ficha de Produção",ROUNDUP(Q9/(1-$R$1-$S$1),2)) -> Cadastrar Ficha de Produção | AB9: =IF(Q9=0,"",Q9) | AC9: =IF(U9="","",U9*(1-$R$1-$S$1)) | AD9: =IF(OR(AB9="",AC9=""),"",AC9-AB9) | AE9: =IF(OR(AD9="",AC9=0),"",AD9/AC9) | AF9: =IF(Q9=0,"",ROUNDUP((Q9+IF(AA9="",0,AA9/1200))/(1-$R$1-$S$1),2))
A10: PRD00007 | B10: BRAZIMIL MASSA ACRÍLICA 4KG | C10: MASSA ACRÍLICA | D10: PI00004 | E10: ACRÍLICO | F10: N/A | G10: SIM | H10: 4 | I10: KG | J10: =IF(I10="KG",1,1.27) -> 1 | K10: =IFERROR(IF(VLOOKUP(D10,'Ficha de Produção'!C:C,1,0)=D10,"OK","Custo Produção Não Cadastrado"),"Custo Produção Não Cadastrado") -> OK | L10: =IFERROR(IF(VLOOKUP(A10,'Ficha de Embalagens'!A:A,1,0)=A10,"OK","Ficha de Embalagens Não Cadastrada"),"Ficha de Embalagens Não Cadastrada") -> OK | M10: =SUMIFS('Ficha de Produção'!N:N,'Ficha de Produção'!C:C,D10)*H10 -> 6.44 | N10: =SUMIFS('Ficha de Embalagens'!F:F,'Ficha de Embalagens'!A:A,A10) -> 3.06 | O10: =SUM(M10:N10) -> 9.5 | P10: =IF(AND(K10="OK",L10="OK"),H10*$P$1,0) -> 1.24 | Q10: =P10+O10 -> 10.74 | R10: =U10*$R$1 -> 0.9995 | S10: =$S$1*U10 -> 1.3993 | T10: =+Q10+R10+S10 -> 13.1388 | U10: 19.99 | V10: =IF(M10=0,"Cadastrar Ficha de Produção",IF(AND(M10>0,U10=""),"Cadastrar Preço Final",IFERROR((U10-T10)/U10,""))) -> 0.34273137 | W10: =IF(M10=0,"Cadastrar Ficha de Produção",ROUNDUP(Q10/(1-$R$1-$S$1),2)) -> 12.21 | AB10: =IF(Q10=0,"",Q10) -> 10.74 | AC10: =IF(U10="","",U10*(1-$R$1-$S$1)) -> 17.5912 | AD10: =IF(OR(AB10="",AC10=""),"",AC10-AB10) -> 6.8512 | AE10: =IF(OR(AD10="",AC10=0),"",AD10/AC10) -> 0.38946746 | AF10: =IF(Q10=0,"",ROUNDUP((Q10+IF(AA10="",0,AA10/1200))/(1-$R$1-$S$1),2)) -> 12.21
A11: PRD00008 | B11: BRAZIMIL MASSA ACRÍLICA 20KG | C11: MASSA ACRÍLICA | D11: PI00004 | E11: ACRÍLICO | F11: N/A | G11: SIM | H11: 20 | I11: KG | J11: =IF(I11="KG",1,1.27) -> 1 | K11: =IFERROR(IF(VLOOKUP(D11,'Ficha de Produção'!C:C,1,0)=D11,"OK","Custo Produção Não Cadastrado"),"Custo Produção Não Cadastrado") -> OK | L11: =IFERROR(IF(VLOOKUP(A11,'Ficha de Embalagens'!A:A,1,0)=A11,"OK","Ficha de Embalagens Não Cadastrada"),"Ficha de Embalagens Não Cadastrada") -> OK | M11: =SUMIFS('Ficha de Produção'!N:N,'Ficha de Produção'!C:C,D11)*H11 -> 32.2 | N11: =SUMIFS('Ficha de Embalagens'!F:F,'Ficha de Embalagens'!A:A,A11) -> 8.61 | O11: =SUM(M11:N11) -> 40.81 | P11: =IF(AND(K11="OK",L11="OK"),H11*$P$1,0) -> 6.2 | Q11: =P11+O11 -> 47.01 | R11: =U11*$R$1 -> 3.495 | S11: =$S$1*U11 -> 4.893 | T11: =+Q11+R11+S11 -> 55.398 | U11: 69.9 | V11: =IF(M11=0,"Cadastrar Ficha de Produção",IF(AND(M11>0,U11=""),"Cadastrar Preço Final",IFERROR((U11-T11)/U11,""))) -> 0.20746781 | W11: =IF(M11=0,"Cadastrar Ficha de Produção",ROUNDUP(Q11/(1-$R$1-$S$1),2)) -> 53.43 | AB11: =IF(Q11=0,"",Q11) -> 47.01 | AC11: =IF(U11="","",U11*(1-$R$1-$S$1)) -> 61.512 | AD11: =IF(OR(AB11="",AC11=""),"",AC11-AB11) -> 14.502 | AE11: =IF(OR(AD11="",AC11=0),"",AD11/AC11) -> 0.23575888 | AF11: =IF(Q11=0,"",ROUNDUP((Q11+IF(AA11="",0,AA11/1200))/(1-$R$1-$S$1),2)) -> 53.43
A12: PRD00009 | B12: BRAZIMIL LÁTEX ECONÔMICO INT FOSCO 3L BRANCO NEVE | C12: LATEX | D12: PI00005 | E12: FOSCO | F12: BRANCO NEVE | G12: SIM | H12: 3 | I12: L | J12: =IF(I12="KG",1,1.27) -> 1.27 | K12: =IFERROR(IF(VLOOKUP(D12,'Ficha de Produção'!C:C,1,0)=D12,"OK","Custo Produção Não Cadastrado"),"Custo Produção Não Cadastrado") -> OK | L12: =IFERROR(IF(VLOOKUP(A12,'Ficha de Embalagens'!A:A,1,0)=A12,"OK","Ficha de Embalagens Não Cadastrada"),"Ficha de Embalagens Não Cadastrada") -> OK | M12: =SUMIFS('Ficha de Produção'!N:N,'Ficha de Produção'!C:C,D12)*H12 -> 3.63 | N12: =SUMIFS('Ficha de Embalagens'!F:F,'Ficha de Embalagens'!A:A,A12) -> 3.44 | O12: =SUM(M12:N12) -> 7.07 | P12: =IF(AND(K12="OK",L12="OK"),H12*$P$1,0) -> 0.93 | Q12: =P12+O12 -> 8 | R12: =U12*$R$1 -> 0.8995 | S12: =$S$1*U12 -> 1.2593 | T12: =+Q12+R12+S12 -> 10.1588 | U12: 17.99 | V12: =IF(M12=0,"Cadastrar Ficha de Produção",IF(AND(M12>0,U12=""),"Cadastrar Preço Final",IFERROR((U12-T12)/U12,""))) -> 0.4353085 | W12: =IF(M12=0,"Cadastrar Ficha de Produção",ROUNDUP(Q12/(1-$R$1-$S$1),2)) -> 9.1 | AB12: =IF(Q12=0,"",Q12) -> 8 | AC12: =IF(U12="","",U12*(1-$R$1-$S$1)) -> 15.8312 | AD12: =IF(OR(AB12="",AC12=""),"",AC12-AB12) -> 7.8312 | AE12: =IF(OR(AD12="",AC12=0),"",AD12/AC12) -> 0.49466876 | AF12: =IF(Q12=0,"",ROUNDUP((Q12+IF(AA12="",0,AA12/1200))/(1-$R$1-$S$1),2)) -> 9.1
A13: PRD00010 | B13: BRAZIMIL LÁTEX ECONÔMICO INT FOSCO 3L BRANCO GELO | C13: LATEX | D13: PI00006 | E13: FOSCO | F13: BRANCO GELO | G13: SIM | H13: 3 | I13: L | J13: =IF(I13="KG",1,1.27) -> 1.27 | K13: =IFERROR(IF(VLOOKUP(D13,'Ficha de Produção'!C:C,1,0)=D13,"OK","Custo Produção Não Cadastrado"),"Custo Produção Não Cadastrado") -> OK | L13: =IFERROR(IF(VLOOKUP(A13,'Ficha de Embalagens'!A:A,1,0)=A13,"OK","Ficha de Embalagens Não Cadastrada"),"Ficha de Embalagens Não Cadastrada") -> OK | M13: =SUMIFS('Ficha de Produção'!N:N,'Ficha de Produção'!C:C,D13)*H13 -> 4.77 | N13: =SUMIFS('Ficha de Embalagens'!F:F,'Ficha de Embalagens'!A:A,A13) -> 3.44 | O13: =SUM(M13:N13) -> 8.21 | P13: =IF(AND(K13="OK",L13="OK"),H13*$P$1,0) -> 0.93 | Q13: =P13+O13 -> 9.14 | R13: =U13*$R$1 -> 0.8995 | S13: =$S$1*U13 -> 1.2593 | T13: =+Q13+R13+S13 -> 11.2988 | U13: 17.99 | V13: =IF(M13=0,"Cadastrar Ficha de Produção",IF(AND(M13>0,U13=""),"Cadastrar Preço Final",IFERROR((U13-T13)/U13,""))) -> 0.37193997 | W13: =IF(M13=0,"Cadastrar Ficha de Produção",ROUNDUP(Q13/(1-$R$1-$S$1),2)) -> 10.39 | AB13: =IF(Q13=0,"",Q13) -> 9.14 | AC13: =IF(U13="","",U13*(1-$R$1-$S$1)) -> 15.8312 | AD13: =IF(OR(AB13="",AC13=""),"",AC13-AB13) -> 6.6912 | AE13: =IF(OR(AD13="",AC13=0),"",AD13/AC13) -> 0.42265905 | AF13: =IF(Q13=0,"",ROUNDUP((Q13+IF(AA13="",0,AA13/1200))/(1-$R$1-$S$1),2)) -> 10.39
A14: PRD00011 | B14: BRAZIMIL LÁTEX ECONÔMICO INT FOSCO 3L AREIA | C14: LATEX | D14: PI00007 | E14: FOSCO | F14: AREIA | G14: SIM | H14: 3 | I14: L | J14: =IF(I14="KG",1,1.27) -> 1.27 | K14: =IFERROR(IF(VLOOKUP(D14,'Ficha de Produção'!C:C,1,0)=D14,"OK","Custo Produção Não Cadastrado"),"Custo Produção Não Cadastrado") -> OK | L14: =IFERROR(IF(VLOOKUP(A14,'Ficha de Embalagens'!A:A,1,0)=A14,"OK","Ficha de Embalagens Não Cadastrada"),"Ficha de Embalagens Não Cadastrada") -> OK | M14: =SUMIFS('Ficha de Produção'!N:N,'Ficha de Produção'!C:C,D14)*H14 -> 5.19 | N14: =SUMIFS('Ficha de Embalagens'!F:F,'Ficha de Embalagens'!A:A,A14) -> 3.44 | O14: =SUM(M14:N14) -> 8.63 | P14: =IF(AND(K14="OK",L14="OK"),H14*$P$1,0) -> 0.93 | Q14: =P14+O14 -> 9.56 | R14: =U14*$R$1 -> 0.8995 | S14: =$S$1*U14 -> 1.2593 | T14: =+Q14+R14+S14 -> 11.7188 | U14: 17.99 | V14: =IF(M14=0,"Cadastrar Ficha de Produção",IF(AND(M14>0,U14=""),"Cadastrar Preço Final",IFERROR((U14-T14)/U14,""))) -> 0.34859366 | W14: =IF(M14=0,"Cadastrar Ficha de Produção",ROUNDUP(Q14/(1-$R$1-$S$1),2)) -> 10.87 | AB14: =IF(Q14=0,"",Q14) -> 9.56 | AC14: =IF(U14="","",U14*(1-$R$1-$S$1)) -> 15.8312 | AD14: =IF(OR(AB14="",AC14=""),"",AC14-AB14) -> 6.2712 | AE14: =IF(OR(AD14="",AC14=0),"",AD14/AC14) -> 0.39612916 | AF14: =IF(Q14=0,"",ROUNDUP((Q14+IF(AA14="",0,AA14/1200))/(1-$R$1-$S$1),2)) -> 10.87
A15: PRD00012 | B15: BRAZIMIL LÁTEX ECONÔMICO INT FOSCO 3L PALHA | C15: LATEX | D15: PI00008 | E15: FOSCO | F15: PALHA | G15: SIM | H15: 3 | I15: L | J15: =IF(I15="KG",1,1.27) -> 1.27 | K15: =IFERROR(IF(VLOOKUP(D15,'Ficha de Produção'!C:C,1,0)=D15,"OK","Custo Produção Não Cadastrado"),"Custo Produção Não Cadastrado") -> OK | L15: =IFERROR(IF(VLOOKUP(A15,'Ficha de Embalagens'!A:A,1,0)=A15,"OK","Ficha de Embalagens Não Cadastrada"),"Ficha de Embalagens Não Cadastrada") -> OK | M15: =SUMIFS('Ficha de Produção'!N:N,'Ficha de Produção'!C:C,D15)*H15 -> 4.92 | N15: =SUMIFS('Ficha de Embalagens'!F:F,'Ficha de Embalagens'!A:A,A15) -> 3.44 | O15: =SUM(M15:N15) -> 8.36 | P15: =IF(AND(K15="OK",L15="OK"),H15*$P$1,0) -> 0.93 | Q15: =P15+O15 -> 9.29 | R15: =U15*$R$1 -> 0.8995 | S15: =$S$1*U15 -> 1.2593 | T15: =+Q15+R15+S15 -> 11.4488 | U15: 17.99 | V15: =IF(M15=0,"Cadastrar Ficha de Produção",IF(AND(M15>0,U15=""),"Cadastrar Preço Final",IFERROR((U15-T15)/U15,""))) -> 0.363602 | W15: =IF(M15=0,"Cadastrar Ficha de Produção",ROUNDUP(Q15/(1-$R$1-$S$1),2)) -> 10.56 | AB15: =IF(Q15=0,"",Q15) -> 9.29 | AC15: =IF(U15="","",U15*(1-$R$1-$S$1)) -> 15.8312 | AD15: =IF(OR(AB15="",AC15=""),"",AC15-AB15) -> 6.5412 | AE15: =IF(OR(AD15="",AC15=0),"",AD15/AC15) -> 0.41318409 | AF15: =IF(Q15=0,"",ROUNDUP((Q15+IF(AA15="",0,AA15/1200))/(1-$R$1-$S$1),2)) -> 10.56
A16: PRD00013 | B16: BRAZIMIL LÁTEX ECONÔMICO INT FOSCO 3L VERDE PRIMAVERA | C16: LATEX | D16: PI00009 | E16: FOSCO | F16: VERDE PRIMAVERA | G16: SIM | H16: 3 | I16: L | J16: =IF(I16="KG",1,1.27) -> 1.27 | K16: =IFERROR(IF(VLOOKUP(D16,'Ficha de Produção'!C:C,1,0)=D16,"OK","Custo Produção Não Cadastrado"),"Custo Produção Não Cadastrado") -> OK | L16: =IFERROR(IF(VLOOKUP(A16,'Ficha de Embalagens'!A:A,1,0)=A16,"OK","Ficha de Embalagens Não Cadastrada"),"Ficha de Embalagens Não Cadastrada") -> OK | M16: =SUMIFS('Ficha de Produção'!N:N,'Ficha de Produção'!C:C,D16)*H16 -> 5.76 | N16: =SUMIFS('Ficha de Embalagens'!F:F,'Ficha de Embalagens'!A:A,A16) -> 3.44 | O16: =SUM(M16:N16) -> 9.2 | P16: =IF(AND(K16="OK",L16="OK"),H16*$P$1,0) -> 0.93 | Q16: =P16+O16 -> 10.13 | R16: =U16*$R$1 -> 0.8995 | S16: =$S$1*U16 -> 1.2593 | T16: =+Q16+R16+S16 -> 12.2888 | U16: 17.99 | V16: =IF(M16=0,"Cadastrar Ficha de Produção",IF(AND(M16>0,U16=""),"Cadastrar Preço Final",IFERROR((U16-T16)/U16,""))) -> 0.31690939 | W16: =IF(M16=0,"Cadastrar Ficha de Produção",ROUNDUP(Q16/(1-$R$1-$S$1),2)) -> 11.52 | AB16: =IF(Q16=0,"",Q16) -> 10.13 | AC16: =IF(U16="","",U16*(1-$R$1-$S$1)) -> 15.8312 | AD16: =IF(OR(AB16="",AC16=""),"",AC16-AB16) -> 5.7012 | AE16: =IF(OR(AD16="",AC16=0),"",AD16/AC16) -> 0.36012431 | AF16: =IF(Q16=0,"",ROUNDUP((Q16+IF(AA16="",0,AA16/1200))/(1-$R$1-$S$1),2)) -> 11.52
A17: PRD00014 | B17: BRAZIMIL LÁTEX ECONÔMICO INT FOSCO 3L VERDE FOLHA | C17: LATEX | D17: PI00010 | E17: FOSCO | F17: VERDE FOLHA | G17: SIM | H17: 3 | I17: L | J17: =IF(I17="KG",1,1.27) -> 1.27 | K17: =IFERROR(IF(VLOOKUP(D17,'Ficha de Produção'!C:C,1,0)=D17,"OK","Custo Produção Não Cadastrado"),"Custo Produção Não Cadastrado") -> OK | L17: =IFERROR(IF(VLOOKUP(A17,'Ficha de Embalagens'!A:A,1,0)=A17,"OK","Ficha de Embalagens Não Cadastrada"),"Ficha de Embalagens Não Cadastrada") -> OK | M17: =SUMIFS('Ficha de Produção'!N:N,'Ficha de Produção'!C:C,D17)*H17 -> 6.87 | N17: =SUMIFS('Ficha de Embalagens'!F:F,'Ficha de Embalagens'!A:A,A17) -> 3.44 | O17: =SUM(M17:N17) -> 10.31 | P17: =IF(AND(K17="OK",L17="OK"),H17*$P$1,0) -> 0.93 | Q17: =P17+O17 -> 11.24 | R17: =U17*$R$1 -> 0.8995 | S17: =$S$1*U17 -> 1.2593 | T17: =+Q17+R17+S17 -> 13.3988 | U17: 17.99 | V17: =IF(M17=0,"Cadastrar Ficha de Produção",IF(AND(M17>0,U17=""),"Cadastrar Preço Final",IFERROR((U17-T17)/U17,""))) -> 0.25520845 | W17: =IF(M17=0,"Cadastrar Ficha de Produção",ROUNDUP(Q17/(1-$R$1-$S$1),2)) -> 12.78 | AB17: =IF(Q17=0,"",Q17) -> 11.24 | AC17: =IF(U17="","",U17*(1-$R$1-$S$1)) -> 15.8312 | AD17: =IF(OR(AB17="",AC17=""),"",AC17-AB17) -> 4.5912 | AE17: =IF(OR(AD17="",AC17=0),"",AD17/AC17) -> 0.2900096 | AF17: =IF(Q17=0,"",ROUNDUP((Q17+IF(AA17="",0,AA17/1200))/(1-$R$1-$S$1),2)) -> 12.78
A18: PRD00015 | B18: BRAZIMIL LÁTEX ECONÔMICO INT FOSCO 3L AZUL CEU | C18: LATEX | D18: PI00011 | E18: FOSCO | F18: AZUL CEU | G18: SIM | H18: 3 | I18: L | J18: =IF(I18="KG",1,1.27) -> 1.27 | K18: =IFERROR(IF(VLOOKUP(D18,'Ficha de Produção'!C:C,1,0)=D18,"OK","Custo Produção Não Cadastrado"),"Custo Produção Não Cadastrado") -> OK | L18: =IFERROR(IF(VLOOKUP(A18,'Ficha de Embalagens'!A:A,1,0)=A18,"OK","Ficha de Embalagens Não Cadastrada"),"Ficha de Embalagens Não Cadastrada") -> OK | M18: =SUMIFS('Ficha de Produção'!N:N,'Ficha de Produção'!C:C,D18)*H18 -> 4.86 | N18: =SUMIFS('Ficha de Embalagens'!F:F,'Ficha de Embalagens'!A:A,A18) -> 3.44 | O18: =SUM(M18:N18) -> 8.3 | P18: =IF(AND(K18="OK",L18="OK"),H18*$P$1,0) -> 0.93 | Q18: =P18+O18 -> 9.23 | R18: =U18*$R$1 -> 0.8995 | S18: =$S$1*U18 -> 1.2593 | T18: =+Q18+R18+S18 -> 11.3888 | U18: 17.99 | V18: =IF(M18=0,"Cadastrar Ficha de Produção",IF(AND(M18>0,U18=""),"Cadastrar Preço Final",IFERROR((U18-T18)/U18,""))) -> 0.36693719 | W18: =IF(M18=0,"Cadastrar Ficha de Produção",ROUNDUP(Q18/(1-$R$1-$S$1),2)) -> 10.49 | AB18: =IF(Q18=0,"",Q18) -> 9.23 | AC18: =IF(U18="","",U18*(1-$R$1-$S$1)) -> 15.8312 | AD18: =IF(OR(AB18="",AC18=""),"",AC18-AB18) -> 6.6012 | AE18: =IF(OR(AD18="",AC18=0),"",AD18/AC18) -> 0.41697408 | AF18: =IF(Q18=0,"",ROUNDUP((Q18+IF(AA18="",0,AA18/1200))/(1-$R$1-$S$1),2)) -> 10.49
A19: PRD00016 | B19: BRAZIMIL LÁTEX ECONÔMICO INT FOSCO 3L AZUL OCEANO | C19: LATEX | D19: PI00012 | E19: FOSCO | F19: AZUL OCEANO | G19: SIM | H19: 3 | I19: L | J19: =IF(I19="KG",1,1.27) -> 1.27 | K19: =IFERROR(IF(VLOOKUP(D19,'Ficha de Produção'!C:C,1,0)=D19,"OK","Custo Produção Não Cadastrado"),"Custo Produção Não Cadastrado") -> OK | L19: =IFERROR(IF(VLOOKUP(A19,'Ficha de Embalagens'!A:A,1,0)=A19,"OK","Ficha de Embalagens Não Cadastrada"),"Ficha de Embalagens Não Cadastrada") -> OK | M19: =SUMIFS('Ficha de Produção'!N:N,'Ficha de Produção'!C:C,D19)*H19 -> 6.03 | N19: =SUMIFS('Ficha de Embalagens'!F:F,'Ficha de Embalagens'!A:A,A19) -> 3.44 | O19: =SUM(M19:N19) -> 9.47 | P19: =IF(AND(K19="OK",L19="OK"),H19*$P$1,0) -> 0.93 | Q19: =P19+O19 -> 10.4 | R19: =U19*$R$1 -> 0.8995 | S19: =$S$1*U19 -> 1.2593 | T19: =+Q19+R19+S19 -> 12.5588 | U19: 17.99 | V19: =IF(M19=0,"Cadastrar Ficha de Produção",IF(AND(M19>0,U19=""),"Cadastrar Preço Final",IFERROR((U19-T19)/U19,""))) -> 0.30190106 | W19: =IF(M19=0,"Cadastrar Ficha de Produção",ROUNDUP(Q19/(1-$R$1-$S$1),2)) -> 11.82 | AB19: =IF(Q19=0,"",Q19) -> 10.4 | AC19: =IF(U19="","",U19*(1-$R$1-$S$1)) -> 15.8312 | AD19: =IF(OR(AB19="",AC19=""),"",AC19-AB19) -> 5.4312 | AE19: =IF(OR(AD19="",AC19=0),"",AD19/AC19) -> 0.34306938 | AF19: =IF(Q19=0,"",ROUNDUP((Q19+IF(AA19="",0,AA19/1200))/(1-$R$1-$S$1),2)) -> 11.82
A20: PRD00017 | B20: BRAZIMIL LÁTEX ECONÔMICO INT FOSCO 3L AMARELO CANARIO | C20: LATEX | D20: PI00013 | E20: FOSCO | F20: AMARELO CANARIO | G20: SIM | H20: 3 | I20: L | J20: =IF(I20="KG",1,1.27) -> 1.27 | K20: =IFERROR(IF(VLOOKUP(D20,'Ficha de Produção'!C:C,1,0)=D20,"OK","Custo Produção Não Cadastrado"),"Custo Produção Não Cadastrado") -> OK | L20: =IFERROR(IF(VLOOKUP(A20,'Ficha de Embalagens'!A:A,1,0)=A20,"OK","Ficha de Embalagens Não Cadastrada"),"Ficha de Embalagens Não Cadastrada") -> OK | M20: =SUMIFS('Ficha de Produção'!N:N,'Ficha de Produção'!C:C,D20)*H20 -> 5.13 | N20: =SUMIFS('Ficha de Embalagens'!F:F,'Ficha de Embalagens'!A:A,A20) -> 3.44 | O20: =SUM(M20:N20) -> 8.57 | P20: =IF(AND(K20="OK",L20="OK"),H20*$P$1,0) -> 0.93 | Q20: =P20+O20 -> 9.5 | R20: =U20*$R$1 -> 0.8995 | S20: =$S$1*U20 -> 1.2593 | T20: =+Q20+R20+S20 -> 11.6588 | U20: 17.99 | V20: =IF(M20=0,"Cadastrar Ficha de Produção",IF(AND(M20>0,U20=""),"Cadastrar Preço Final",IFERROR((U20-T20)/U20,""))) -> 0.35192885 | W20: =IF(M20=0,"Cadastrar Ficha de Produção",ROUNDUP(Q20/(1-$R$1-$S$1),2)) -> 10.8 | AB20: =IF(Q20=0,"",Q20) -> 9.5 | AC20: =IF(U20="","",U20*(1-$R$1-$S$1)) -> 15.8312 | AD20: =IF(OR(AB20="",AC20=""),"",AC20-AB20) -> 6.3312 | AE20: =IF(OR(AD20="",AC20=0),"",AD20/AC20) -> 0.39991915 | AF20: =IF(Q20=0,"",ROUNDUP((Q20+IF(AA20="",0,AA20/1200))/(1-$R$1-$S$1),2)) -> 10.8
A21: PRD00018 | B21: BRAZIMIL LÁTEX ECONÔMICO INT FOSCO 3L CROMO SUAVE | C21: LATEX | D21: PI00014 | E21: FOSCO | F21: CROMO SUAVE | G21: SIM | H21: 3 | I21: L | J21: =IF(I21="KG",1,1.27) -> 1.27 | K21: =IFERROR(IF(VLOOKUP(D21,'Ficha de Produção'!C:C,1,0)=D21,"OK","Custo Produção Não Cadastrado"),"Custo Produção Não Cadastrado") -> OK | L21: =IFERROR(IF(VLOOKUP(A21,'Ficha de Embalagens'!A:A,1,0)=A21,"OK","Ficha de Embalagens Não Cadastrada"),"Ficha de Embalagens Não Cadastrada") -> OK | M21: =SUMIFS('Ficha de Produção'!N:N,'Ficha de Produção'!C:C,D21)*H21 -> 5.85 | N21: =SUMIFS('Ficha de Embalagens'!F:F,'Ficha de Embalagens'!A:A,A21) -> 3.44 | O21: =SUM(M21:N21) -> 9.29 | P21: =IF(AND(K21="OK",L21="OK"),H21*$P$1,0) -> 0.93 | Q21: =P21+O21 -> 10.22 | R21: =U21*$R$1 -> 0.8995 | S21: =$S$1*U21 -> 1.2593 | T21: =+Q21+R21+S21 -> 12.3788 | U21: 17.99 | V21: =IF(M21=0,"Cadastrar Ficha de Produção",IF(AND(M21>0,U21=""),"Cadastrar Preço Final",IFERROR((U21-T21)/U21,""))) -> 0.31190661 | W21: =IF(M21=0,"Cadastrar Ficha de Produção",ROUNDUP(Q21/(1-$R$1-$S$1),2)) -> 11.62 | AB21: =IF(Q21=0,"",Q21) -> 10.22 | AC21: =IF(U21="","",U21*(1-$R$1-$S$1)) -> 15.8312 | AD21: =IF(OR(AB21="",AC21=""),"",AC21-AB21) -> 5.6112 | AE21: =IF(OR(AD21="",AC21=0),"",AD21/AC21) -> 0.35443933 | AF21: =IF(Q21=0,"",ROUNDUP((Q21+IF(AA21="",0,AA21/1200))/(1-$R$1-$S$1),2)) -> 11.62
... A26: PRD00023 | B26: BRAZIMIL LÁTEX ECONÔMICO INT FOSCO 3L PEROLA | C26: LATEX | D26: PI00019 | E26: FOSCO | F26: PEROLA | G26: SIM | H26: 3 | I26: L | J26: =IF(I26="KG",1,1.27) -> 1.27 | K26: =IFERROR(IF(VLOOKUP(D26,'Ficha de Produção'!C:C,1,0)=D26,"OK","Custo Produção Não Cadastrado"),"Custo Produção Não Cadastrado") -> OK | L26: =IFERROR(IF(VLOOKUP(A26,'Ficha de Embalagens'!A:A,1,0)=A26,"OK","Ficha de Embalagens Não Cadastrada"),"Ficha de Embalagens Não Cadastrada") -> OK | M26: =SUMIFS('Ficha de Produção'!N:N,'Ficha de Produção'!C:C,D26)*H26 -> 4.92 | N26: =SUMIFS('Ficha de Embalagens'!F:F,'Ficha de Embalagens'!A:A,A26) -> 3.44 | O26: =SUM(M26:N26) -> 8.36 | P26: =IF(AND(K26="OK",L26="OK"),H26*$P$1,0) -> 0.93 | Q26: =P26+O26 -> 9.29 | R26: =U26*$R$1 -> 0.8995 | S26: =$S$1*U26 -> 1.2593 | T26: =+Q26+R26+S26 -> 11.4488 | U26: 17.99 | V26: =IF(M26=0,"Cadastrar Ficha de Produção",IF(AND(M26>0,U26=""),"Cadastrar Preço Final",IFERROR((U26-T26)/U26,""))) -> 0.363602 | W26: =IF(M26=0,"Cadastrar Ficha de Produção",ROUNDUP(Q26/(1-$R$1-$S$1),2)) -> 10.56 | AB26: =IF(Q26=0,"",Q26) -> 9.29 | AC26: =IF(U26="","",U26*(1-$R$1-$S$1)) -> 15.8312 | AD26: =IF(OR(AB26="",AC26=""),"",AC26-AB26) -> 6.5412 | AE26: =IF(OR(AD26="",AC26=0),"",AD26/AC26) -> 0.41318409 | AF26: =IF(Q26=0,"",ROUNDUP((Q26+IF(AA26="",0,AA26/1200))/(1-$R$1-$S$1),2)) -> 10.56
A27: PRD00024 | B27: BRAZIMIL LÁTEX ECONÔMICO INT/EXT SEMIBRILHO 3L BRANCO NEVE | C27: LATEX | E27: SEMIBRILHO | F27: BRANCO NEVE | G27: NÃO | H27: 3 | I27: L | J27: =IF(I27="KG",1,1.27) -> 1.27 | K27: =IFERROR(IF(VLOOKUP(D27,'Ficha de Produção'!C:C,1,0)=D27,"OK","Custo Produção Não Cadastrado"),"Custo Produção Não Cadastrado") -> Custo Produção Não Cadastrado | L27: =IFERROR(IF(VLOOKUP(A27,'Ficha de Embalagens'!A:A,1,0)=A27,"OK","Ficha de Embalagens Não Cadastrada"),"Ficha de Embalagens Não Cadastrada") -> Ficha de Embalagens Não Cadastrada | M27: =SUMIFS('Ficha de Produção'!N:N,'Ficha de Produção'!C:C,D27)*H27 -> 0 | N27: =SUMIFS('Ficha de Embalagens'!F:F,'Ficha de Embalagens'!A:A,A27) -> 0 | O27: =SUM(M27:N27) -> 0 | P27: =IF(AND(K27="OK",L27="OK"),H27*$P$1,0) -> 0 | Q27: =P27+O27 -> 0 | R27: =U27*$R$1 -> 0 | S27: =$S$1*U27 -> 0 | T27: =+Q27+R27+S27 -> 0 | V27: =IF(M27=0,"Cadastrar Ficha de Produção",IF(AND(M27>0,U27=""),"Cadastrar Preço Final",IFERROR((U27-T27)/U27,""))) -> Cadastrar Ficha de Produção | W27: =IF(M27=0,"Cadastrar Ficha de Produção",ROUNDUP(Q27/(1-$R$1-$S$1),2)) -> Cadastrar Ficha de Produção | AB27: =IF(Q27=0,"",Q27) | AC27: =IF(U27="","",U27*(1-$R$1-$S$1)) | AD27: =IF(OR(AB27="",AC27=""),"",AC27-AB27) | AE27: =IF(OR(AD27="",AC27=0),"",AD27/AC27) | AF27: =IF(Q27=0,"",ROUNDUP((Q27+IF(AA27="",0,AA27/1200))/(1-$R$1-$S$1),2))
A28: PRD00025 | B28: BRAZIMIL LÁTEX ECONÔMICO INT/EXT SEMIBRILHO 3L BRANCO GELO | C28: LATEX | E28: SEMIBRILHO | F28: BRANCO GELO | G28: NÃO | H28: 3 | I28: L | J28: =IF(I28="KG",1,1.27) -> 1.27 | K28: =IFERROR(IF(VLOOKUP(D28,'Ficha de Produção'!C:C,1,0)=D28,"OK","Custo Produção Não Cadastrado"),"Custo Produção Não Cadastrado") -> Custo Produção Não Cadastrado | L28: =IFERROR(IF(VLOOKUP(A28,'Ficha de Embalagens'!A:A,1,0)=A28,"OK","Ficha de Embalagens Não Cadastrada"),"Ficha de Embalagens Não Cadastrada") -> Ficha de Embalagens Não Cadastrada | M28: =SUMIFS('Ficha de Produção'!N:N,'Ficha de Produção'!C:C,D28)*H28 -> 0 | N28: =SUMIFS('Ficha de Embalagens'!F:F,'Ficha de Embalagens'!A:A,A28) -> 0 | O28: =SUM(M28:N28) -> 0 | P28: =IF(AND(K28="OK",L28="OK"),H28*$P$1,0) -> 0 | Q28: =P28+O28 -> 0 | R28: =U28*$R$1 -> 0 | S28: =$S$1*U28 -> 0 | T28: =+Q28+R28+S28 -> 0 | V28: =IF(M28=0,"Cadastrar Ficha de Produção",IF(AND(M28>0,U28=""),"Cadastrar Preço Final",IFERROR((U28-T28)/U28,""))) -> Cadastrar Ficha de Produção | W28: =IF(M28=0,"Cadastrar Ficha de Produção",ROUNDUP(Q28/(1-$R$1-$S$1),2)) -> Cadastrar Ficha de Produção | AB28: =IF(Q28=0,"",Q28) | AC28: =IF(U28="","",U28*(1-$R$1-$S$1)) | AD28: =IF(OR(AB28="",AC28=""),"",AC28-AB28) | AE28: =IF(OR(AD28="",AC28=0),"",AD28/AC28) | AF28: =IF(Q28=0,"",ROUNDUP((Q28+IF(AA28="",0,AA28/1200))/(1-$R$1-$S$1),2))
A29: PRD00026 | B29: BRAZIMIL LÁTEX ECONÔMICO INT/EXT SEMIBRILHO 3L AREIA | C29: LATEX | E29: SEMIBRILHO | F29: AREIA | G29: NÃO | H29: 3 | I29: L | J29: =IF(I29="KG",1,1.27) -> 1.27 | K29: =IFERROR(IF(VLOOKUP(D29,'Ficha de Produção'!C:C,1,0)=D29,"OK","Custo Produção Não Cadastrado"),"Custo Produção Não Cadastrado") -> Custo Produção Não Cadastrado | L29: =IFERROR(IF(VLOOKUP(A29,'Ficha de Embalagens'!A:A,1,0)=A29,"OK","Ficha de Embalagens Não Cadastrada"),"Ficha de Embalagens Não Cadastrada") -> Ficha de Embalagens Não Cadastrada | M29: =SUMIFS('Ficha de Produção'!N:N,'Ficha de Produção'!C:C,D29)*H29 -> 0 | N29: =SUMIFS('Ficha de Embalagens'!F:F,'Ficha de Embalagens'!A:A,A29) -> 0 | O29: =SUM(M29:N29) -> 0 | P29: =IF(AND(K29="OK",L29="OK"),H29*$P$1,0) -> 0 | Q29: =P29+O29 -> 0 | R29: =U29*$R$1 -> 0 | S29: =$S$1*U29 -> 0 | T29: =+Q29+R29+S29 -> 0 | V29: =IF(M29=0,"Cadastrar Ficha de Produção",IF(AND(M29>0,U29=""),"Cadastrar Preço Final",IFERROR((U29-T29)/U29,""))) -> Cadastrar Ficha de Produção | W29: =IF(M29=0,"Cadastrar Ficha de Produção",ROUNDUP(Q29/(1-$R$1-$S$1),2)) -> Cadastrar Ficha de Produção | AB29: =IF(Q29=0,"",Q29) | AC29: =IF(U29="","",U29*(1-$R$1-$S$1)) | AD29: =IF(OR(AB29="",AC29=""),"",AC29-AB29) | AE29: =IF(OR(AD29="",AC29=0),"",AD29/AC29) | AF29: =IF(Q29=0,"",ROUNDUP((Q29+IF(AA29="",0,AA29/1200))/(1-$R$1-$S$1),2))
A30: PRD00027 | B30: BRAZIMIL LÁTEX ECONÔMICO INT/EXT SEMIBRILHO 3L PALHA | C30: LATEX | E30: SEMIBRILHO | F30: PALHA | G30: NÃO | H30: 3 | I30: L | J30: =IF(I30="KG",1,1.27) -> 1.27 | K30: =IFERROR(IF(VLOOKUP(D30,'Ficha de Produção'!C:C,1,0)=D30,"OK","Custo Produção Não Cadastrado"),"Custo Produção Não Cadastrado") -> Custo Produção Não Cadastrado | L30: =IFERROR(IF(VLOOKUP(A30,'Ficha de Embalagens'!A:A,1,0)=A30,"OK","Ficha de Embalagens Não Cadastrada"),"Ficha de Embalagens Não Cadastrada") -> Ficha de Embalagens Não Cadastrada | M30: =SUMIFS('Ficha de Produção'!N:N,'Ficha de Produção'!C:C,D30)*H30 -> 0 | N30: =SUMIFS('Ficha de Embalagens'!F:F,'Ficha de Embalagens'!A:A,A30) -> 0 | O30: =SUM(M30:N30) -> 0 | P30: =IF(AND(K30="OK",L30="OK"),H30*$P$1,0) -> 0 | Q30: =P30+O30 -> 0 | R30: =U30*$R$1 -> 0 | S30: =$S$1*U30 -> 0 | T30: =+Q30+R30+S30 -> 0 | V30: =IF(M30=0,"Cadastrar Ficha de Produção",IF(AND(M30>0,U30=""),"Cadastrar Preço Final",IFERROR((U30-T30)/U30,""))) -> Cadastrar Ficha de Produção | W30: =IF(M30=0,"Cadastrar Ficha de Produção",ROUNDUP(Q30/(1-$R$1-$S$1),2)) -> Cadastrar Ficha de Produção | AB30: =IF(Q30=0,"",Q30) | AC30: =IF(U30="","",U30*(1-$R$1-$S$1)) | AD30: =IF(OR(AB30="",AC30=""),"",AC30-AB30) | AE30: =IF(OR(AD30="",AC30=0),"",AD30/AC30) | AF30: =IF(Q30=0,"",ROUNDUP((Q30+IF(AA30="",0,AA30/1200))/(1-$R$1-$S$1),2))
A31: PRD00028 | B31: BRAZIMIL LÁTEX ECONÔMICO INT/EXT SEMIBRILHO 3L VERDE PRIMAVERA | C31: LATEX | E31: SEMIBRILHO | F31: VERDE PRIMAVERA | G31: NÃO | H31: 3 | I31: L | J31: =IF(I31="KG",1,1.27) -> 1.27 | K31: =IFERROR(IF(VLOOKUP(D31,'Ficha de Produção'!C:C,1,0)=D31,"OK","Custo Produção Não Cadastrado"),"Custo Produção Não Cadastrado") -> Custo Produção Não Cadastrado | L31: =IFERROR(IF(VLOOKUP(A31,'Ficha de Embalagens'!A:A,1,0)=A31,"OK","Ficha de Embalagens Não Cadastrada"),"Ficha de Embalagens Não Cadastrada") -> Ficha de Embalagens Não Cadastrada | M31: =SUMIFS('Ficha de Produção'!N:N,'Ficha de Produção'!C:C,D31)*H31 -> 0 | N31: =SUMIFS('Ficha de Embalagens'!F:F,'Ficha de Embalagens'!A:A,A31) -> 0 | O31: =SUM(M31:N31) -> 0 | P31: =IF(AND(K31="OK",L31="OK"),H31*$P$1,0) -> 0 | Q31: =P31+O31 -> 0 | R31: =U31*$R$1 -> 0 | S31: =$S$1*U31 -> 0 | T31: =+Q31+R31+S31 -> 0 | V31: =IF(M31=0,"Cadastrar Ficha de Produção",IF(AND(M31>0,U31=""),"Cadastrar Preço Final",IFERROR((U31-T31)/U31,""))) -> Cadastrar Ficha de Produção | W31: =IF(M31=0,"Cadastrar Ficha de Produção",ROUNDUP(Q31/(1-$R$1-$S$1),2)) -> Cadastrar Ficha de Produção | AB31: =IF(Q31=0,"",Q31) | AC31: =IF(U31="","",U31*(1-$R$1-$S$1)) | AD31: =IF(OR(AB31="",AC31=""),"",AC31-AB31) | AE31: =IF(OR(AD31="",AC31=0),"",AD31/AC31) | AF31: =IF(Q31=0,"",ROUNDUP((Q31+IF(AA31="",0,AA31/1200))/(1-$R$1-$S$1),2))
A32: PRD00029 | B32: BRAZIMIL LÁTEX ECONÔMICO INT/EXT SEMIBRILHO 3L VERDE FOLHA | C32: LATEX | E32: SEMIBRILHO | F32: VERDE FOLHA | G32: NÃO | H32: 3 | I32: L | J32: =IF(I32="KG",1,1.27) -> 1.27 | K32: =IFERROR(IF(VLOOKUP(D32,'Ficha de Produção'!C:C,1,0)=D32,"OK","Custo Produção Não Cadastrado"),"Custo Produção Não Cadastrado") -> Custo Produção Não Cadastrado | L32: =IFERROR(IF(VLOOKUP(A32,'Ficha de Embalagens'!A:A,1,0)=A32,"OK","Ficha de Embalagens Não Cadastrada"),"Ficha de Embalagens Não Cadastrada") -> Ficha de Embalagens Não Cadastrada | M32: =SUMIFS('Ficha de Produção'!N:N,'Ficha de Produção'!C:C,D32)*H32 -> 0 | N32: =SUMIFS('Ficha de Embalagens'!F:F,'Ficha de Embalagens'!A:A,A32) -> 0 | O32: =SUM(M32:N32) -> 0 | P32: =IF(AND(K32="OK",L32="OK"),H32*$P$1,0) -> 0 | Q32: =P32+O32 -> 0 | R32: =U32*$R$1 -> 0 | S32: =$S$1*U32 -> 0 | T32: =+Q32+R32+S32 -> 0 | V32: =IF(M32=0,"Cadastrar Ficha de Produção",IF(AND(M32>0,U32=""),"Cadastrar Preço Final",IFERROR((U32-T32)/U32,""))) -> Cadastrar Ficha de Produção | W32: =IF(M32=0,"Cadastrar Ficha de Produção",ROUNDUP(Q32/(1-$R$1-$S$1),2)) -> Cadastrar Ficha de Produção | AB32: =IF(Q32=0,"",Q32) | AC32: =IF(U32="","",U32*(1-$R$1-$S$1)) | AD32: =IF(OR(AB32="",AC32=""),"",AC32-AB32) | AE32: =IF(OR(AD32="",AC32=0),"",AD32/AC32) | AF32: =IF(Q32=0,"",ROUNDUP((Q32+IF(AA32="",0,AA32/1200))/(1-$R$1-$S$1),2))
A33: PRD00030 | B33: BRAZIMIL LÁTEX ECONÔMICO INT/EXT SEMIBRILHO 3L AZUL CEU | C33: LATEX | E33: SEMIBRILHO | F33: AZUL CEU | G33: NÃO | H33: 3 | I33: L | J33: =IF(I33="KG",1,1.27) -> 1.27 | K33: =IFERROR(IF(VLOOKUP(D33,'Ficha de Produção'!C:C,1,0)=D33,"OK","Custo Produção Não Cadastrado"),"Custo Produção Não Cadastrado") -> Custo Produção Não Cadastrado | L33: =IFERROR(IF(VLOOKUP(A33,'Ficha de Embalagens'!A:A,1,0)=A33,"OK","Ficha de Embalagens Não Cadastrada"),"Ficha de Embalagens Não Cadastrada") -> Ficha de Embalagens Não Cadastrada | M33: =SUMIFS('Ficha de Produção'!N:N,'Ficha de Produção'!C:C,D33)*H33 -> 0 | N33: =SUMIFS('Ficha de Embalagens'!F:F,'Ficha de Embalagens'!A:A,A33) -> 0 | O33: =SUM(M33:N33) -> 0 | P33: =IF(AND(K33="OK",L33="OK"),H33*$P$1,0) -> 0 | Q33: =P33+O33 -> 0 | R33: =U33*$R$1 -> 0 | S33: =$S$1*U33 -> 0 | T33: =+Q33+R33+S33 -> 0 | V33: =IF(M33=0,"Cadastrar Ficha de Produção",IF(AND(M33>0,U33=""),"Cadastrar Preço Final",IFERROR((U33-T33)/U33,""))) -> Cadastrar Ficha de Produção | W33: =IF(M33=0,"Cadastrar Ficha de Produção",ROUNDUP(Q33/(1-$R$1-$S$1),2)) -> Cadastrar Ficha de Produção | AB33: =IF(Q33=0,"",Q33) | AC33: =IF(U33="","",U33*(1-$R$1-$S$1)) | AD33: =IF(OR(AB33="",AC33=""),"",AC33-AB33) | AE33: =IF(OR(AD33="",AC33=0),"",AD33/AC33) | AF33: =IF(Q33=0,"",ROUNDUP((Q33+IF(AA33="",0,AA33/1200))/(1-$R$1-$S$1),2))
A34: PRD00031 | B34: BRAZIMIL LÁTEX ECONÔMICO INT/EXT SEMIBRILHO 3L AZUL OCEANO | C34: LATEX | E34: SEMIBRILHO | F34: AZUL OCEANO | G34: NÃO | H34: 3 | I34: L | J34: =IF(I34="KG",1,1.27) -> 1.27 | K34: =IFERROR(IF(VLOOKUP(D34,'Ficha de Produção'!C:C,1,0)=D34,"OK","Custo Produção Não Cadastrado"),"Custo Produção Não Cadastrado") -> Custo Produção Não Cadastrado | L34: =IFERROR(IF(VLOOKUP(A34,'Ficha de Embalagens'!A:A,1,0)=A34,"OK","Ficha de Embalagens Não Cadastrada"),"Ficha de Embalagens Não Cadastrada") -> Ficha de Embalagens Não Cadastrada | M34: =SUMIFS('Ficha de Produção'!N:N,'Ficha de Produção'!C:C,D34)*H34 -> 0 | N34: =SUMIFS('Ficha de Embalagens'!F:F,'Ficha de Embalagens'!A:A,A34) -> 0 | O34: =SUM(M34:N34) -> 0 | P34: =IF(AND(K34="OK",L34="OK"),H34*$P$1,0) -> 0 | Q34: =P34+O34 -> 0 | R34: =U34*$R$1 -> 0 | S34: =$S$1*U34 -> 0 | T34: =+Q34+R34+S34 -> 0 | V34: =IF(M34=0,"Cadastrar Ficha de Produção",IF(AND(M34>0,U34=""),"Cadastrar Preço Final",IFERROR((U34-T34)/U34,""))) -> Cadastrar Ficha de Produção | W34: =IF(M34=0,"Cadastrar Ficha de Produção",ROUNDUP(Q34/(1-$R$1-$S$1),2)) -> Cadastrar Ficha de Produção | AB34: =IF(Q34=0,"",Q34) | AC34: =IF(U34="","",U34*(1-$R$1-$S$1)) | AD34: =IF(OR(AB34="",AC34=""),"",AC34-AB34) | AE34: =IF(OR(AD34="",AC34=0),"",AD34/AC34) | AF34: =IF(Q34=0,"",ROUNDUP((Q34+IF(AA34="",0,AA34/1200))/(1-$R$1-$S$1),2))
A35: PRD00032 | B35: BRAZIMIL LÁTEX ECONÔMICO INT/EXT SEMIBRILHO 3L AMARELO CANARIO | C35: LATEX | E35: SEMIBRILHO | F35: AMARELO CANARIO | G35: NÃO | H35: 3 | I35: L | J35: =IF(I35="KG",1,1.27) -> 1.27 | K35: =IFERROR(IF(VLOOKUP(D35,'Ficha de Produção'!C:C,1,0)=D35,"OK","Custo Produção Não Cadastrado"),"Custo Produção Não Cadastrado") -> Custo Produção Não Cadastrado | L35: =IFERROR(IF(VLOOKUP(A35,'Ficha de Embalagens'!A:A,1,0)=A35,"OK","Ficha de Embalagens Não Cadastrada"),"Ficha de Embalagens Não Cadastrada") -> Ficha de Embalagens Não Cadastrada | M35: =SUMIFS('Ficha de Produção'!N:N,'Ficha de Produção'!C:C,D35)*H35 -> 0 | N35: =SUMIFS('Ficha de Embalagens'!F:F,'Ficha de Embalagens'!A:A,A35) -> 0 | O35: =SUM(M35:N35) -> 0 | P35: =IF(AND(K35="OK",L35="OK"),H35*$P$1,0) -> 0 | Q35: =P35+O35 -> 0 | R35: =U35*$R$1 -> 0 | S35: =$S$1*U35 -> 0 | T35: =+Q35+R35+S35 -> 0 | V35: =IF(M35=0,"Cadastrar Ficha de Produção",IF(AND(M35>0,U35=""),"Cadastrar Preço Final",IFERROR((U35-T35)/U35,""))) -> Cadastrar Ficha de Produção | W35: =IF(M35=0,"Cadastrar Ficha de Produção",ROUNDUP(Q35/(1-$R$1-$S$1),2)) -> Cadastrar Ficha de Produção | AB35: =IF(Q35=0,"",Q35) | AC35: =IF(U35="","",U35*(1-$R$1-$S$1)) | AD35: =IF(OR(AB35="",AC35=""),"",AC35-AB35) | AE35: =IF(OR(AD35="",AC35=0),"",AD35/AC35) | AF35: =IF(Q35=0,"",ROUNDUP((Q35+IF(AA35="",0,AA35/1200))/(1-$R$1-$S$1),2))
A36: PRD00033 | B36: BRAZIMIL LÁTEX ECONÔMICO INT/EXT SEMIBRILHO 3L CROMO SUAVE | C36: LATEX | E36: SEMIBRILHO | F36: CROMO SUAVE | G36: NÃO | H36: 3 | I36: L | J36: =IF(I36="KG",1,1.27) -> 1.27 | K36: =IFERROR(IF(VLOOKUP(D36,'Ficha de Produção'!C:C,1,0)=D36,"OK","Custo Produção Não Cadastrado"),"Custo Produção Não Cadastrado") -> Custo Produção Não Cadastrado | L36: =IFERROR(IF(VLOOKUP(A36,'Ficha de Embalagens'!A:A,1,0)=A36,"OK","Ficha de Embalagens Não Cadastrada"),"Ficha de Embalagens Não Cadastrada") -> Ficha de Embalagens Não Cadastrada | M36: =SUMIFS('Ficha de Produção'!N:N,'Ficha de Produção'!C:C,D36)*H36 -> 0 | N36: =SUMIFS('Ficha de Embalagens'!F:F,'Ficha de Embalagens'!A:A,A36) -> 0 | O36: =SUM(M36:N36) -> 0 | P36: =IF(AND(K36="OK",L36="OK"),H36*$P$1,0) -> 0 | Q36: =P36+O36 -> 0 | R36: =U36*$R$1 -> 0 | S36: =$S$1*U36 -> 0 | T36: =+Q36+R36+S36 -> 0 | V36: =IF(M36=0,"Cadastrar Ficha de Produção",IF(AND(M36>0,U36=""),"Cadastrar Preço Final",IFERROR((U36-T36)/U36,""))) -> Cadastrar Ficha de Produção | W36: =IF(M36=0,"Cadastrar Ficha de Produção",ROUNDUP(Q36/(1-$R$1-$S$1),2)) -> Cadastrar Ficha de Produção | AB36: =IF(Q36=0,"",Q36) | AC36: =IF(U36="","",U36*(1-$R$1-$S$1)) | AD36: =IF(OR(AB36="",AC36=""),"",AC36-AB36) | AE36: =IF(OR(AD36="",AC36=0),"",AD36/AC36) | AF36: =IF(Q36=0,"",ROUNDUP((Q36+IF(AA36="",0,AA36/1200))/(1-$R$1-$S$1),2))
A37: PRD00034 | B37: BRAZIMIL LÁTEX ECONÔMICO INT/EXT SEMIBRILHO 3L ROSA BEBE | C37: LATEX | E37: SEMIBRILHO | F37: ROSA BEBE | G37: NÃO | H37: 3 | I37: L | J37: =IF(I37="KG",1,1.27) -> 1.27 | K37: =IFERROR(IF(VLOOKUP(D37,'Ficha de Produção'!C:C,1,0)=D37,"OK","Custo Produção Não Cadastrado"),"Custo Produção Não Cadastrado") -> Custo Produção Não Cadastrado | L37: =IFERROR(IF(VLOOKUP(A37,'Ficha de Embalagens'!A:A,1,0)=A37,"OK","Ficha de Embalagens Não Cadastrada"),"Ficha de Embalagens Não Cadastrada") -> Ficha de Embalagens Não Cadastrada | M37: =SUMIFS('Ficha de Produção'!N:N,'Ficha de Produção'!C:C,D37)*H37 -> 0 | N37: =SUMIFS('Ficha de Embalagens'!F:F,'Ficha de Embalagens'!A:A,A37) -> 0 | O37: =SUM(M37:N37) -> 0 | P37: =IF(AND(K37="OK",L37="OK"),H37*$P$1,0) -> 0 | Q37: =P37+O37 -> 0 | R37: =U37*$R$1 -> 0 | S37: =$S$1*U37 -> 0 | T37: =+Q37+R37+S37 -> 0 | V37: =IF(M37=0,"Cadastrar Ficha de Produção",IF(AND(M37>0,U37=""),"Cadastrar Preço Final",IFERROR((U37-T37)/U37,""))) -> Cadastrar Ficha de Produção | W37: =IF(M37=0,"Cadastrar Ficha de Produção",ROUNDUP(Q37/(1-$R$1-$S$1),2)) -> Cadastrar Ficha de Produção | AB37: =IF(Q37=0,"",Q37) | AC37: =IF(U37="","",U37*(1-$R$1-$S$1)) | AD37: =IF(OR(AB37="",AC37=""),"",AC37-AB37) | AE37: =IF(OR(AD37="",AC37=0),"",AD37/AC37) | AF37: =IF(Q37=0,"",ROUNDUP((Q37+IF(AA37="",0,AA37/1200))/(1-$R$1-$S$1),2))
A38: PRD00035 | B38: BRAZIMIL LÁTEX ECONÔMICO INT/EXT SEMIBRILHO 3L MARFIM | C38: LATEX | E38: SEMIBRILHO | F38: MARFIM | G38: NÃO | H38: 3 | I38: L | J38: =IF(I38="KG",1,1.27) -> 1.27 | K38: =IFERROR(IF(VLOOKUP(D38,'Ficha de Produção'!C:C,1,0)=D38,"OK","Custo Produção Não Cadastrado"),"Custo Produção Não Cadastrado") -> Custo Produção Não Cadastrado | L38: =IFERROR(IF(VLOOKUP(A38,'Ficha de Embalagens'!A:A,1,0)=A38,"OK","Ficha de Embalagens Não Cadastrada"),"Ficha de Embalagens Não Cadastrada") -> Ficha de Embalagens Não Cadastrada | M38: =SUMIFS('Ficha de Produção'!N:N,'Ficha de Produção'!C:C,D38)*H38 -> 0 | N38: =SUMIFS('Ficha de Embalagens'!F:F,'Ficha de Embalagens'!A:A,A38) -> 0 | O38: =SUM(M38:N38) -> 0 | P38: =IF(AND(K38="OK",L38="OK"),H38*$P$1,0) -> 0 | Q38: =P38+O38 -> 0 | R38: =U38*$R$1 -> 0 | S38: =$S$1*U38 -> 0 | T38: =+Q38+R38+S38 -> 0 | V38: =IF(M38=0,"Cadastrar Ficha de Produção",IF(AND(M38>0,U38=""),"Cadastrar Preço Final",IFERROR((U38-T38)/U38,""))) -> Cadastrar Ficha de Produção | W38: =IF(M38=0,"Cadastrar Ficha de Produção",ROUNDUP(Q38/(1-$R$1-$S$1),2)) -> Cadastrar Ficha de Produção | AB38: =IF(Q38=0,"",Q38) | AC38: =IF(U38="","",U38*(1-$R$1-$S$1)) | AD38: =IF(OR(AB38="",AC38=""),"",AC38-AB38) | AE38: =IF(OR(AD38="",AC38=0),"",AD38/AC38) | AF38: =IF(Q38=0,"",ROUNDUP((Q38+IF(AA38="",0,AA38/1200))/(1-$R$1-$S$1),2))
... A41: PRD00038 | B41: BRAZIMIL LÁTEX ECONÔMICO INT/EXT SEMIBRILHO 3L PEROLA | C41: LATEX | E41: SEMIBRILHO | F41: PEROLA | G41: NÃO | H41: 3 | I41: L | J41: =IF(I41="KG",1,1.27) -> 1.27 | K41: =IFERROR(IF(VLOOKUP(D41,'Ficha de Produção'!C:C,1,0)=D41,"OK","Custo Produção Não Cadastrado"),"Custo Produção Não Cadastrado") -> Custo Produção Não Cadastrado | L41: =IFERROR(IF(VLOOKUP(A41,'Ficha de Embalagens'!A:A,1,0)=A41,"OK","Ficha de Embalagens Não Cadastrada"),"Ficha de Embalagens Não Cadastrada") -> Ficha de Embalagens Não Cadastrada | M41: =SUMIFS('Ficha de Produção'!N:N,'Ficha de Produção'!C:C,D41)*H41 -> 0 | N41: =SUMIFS('Ficha de Embalagens'!F:F,'Ficha de Embalagens'!A:A,A41) -> 0 | O41: =SUM(M41:N41) -> 0 | P41: =IF(AND(K41="OK",L41="OK"),H41*$P$1,0) -> 0 | Q41: =P41+O41 -> 0 | R41: =U41*$R$1 -> 0 | S41: =$S$1*U41 -> 0 | T41: =+Q41+R41+S41 -> 0 | V41: =IF(M41=0,"Cadastrar Ficha de Produção",IF(AND(M41>0,U41=""),"Cadastrar Preço Final",IFERROR((U41-T41)/U41,""))) -> Cadastrar Ficha de Produção | W41: =IF(M41=0,"Cadastrar Ficha de Produção",ROUNDUP(Q41/(1-$R$1-$S$1),2)) -> Cadastrar Ficha de Produção | AB41: =IF(Q41=0,"",Q41) | AC41: =IF(U41="","",U41*(1-$R$1-$S$1)) | AD41: =IF(OR(AB41="",AC41=""),"",AC41-AB41) | AE41: =IF(OR(AD41="",AC41=0),"",AD41/AC41) | AF41: =IF(Q41=0,"",ROUNDUP((Q41+IF(AA41="",0,AA41/1200))/(1-$R$1-$S$1),2))
A42: PRD00039 | B42: BRAZIMIL LÁTEX ECONÔMICO INT FOSCO 15L BRANCO NEVE | C42: LATEX | D42: PI00005 | E42: FOSCO | F42: BRANCO NEVE | G42: SIM | H42: 15 | I42: L | J42: =IF(I42="KG",1,1.27) -> 1.27 | K42: =IFERROR(IF(VLOOKUP(D42,'Ficha de Produção'!C:C,1,0)=D42,"OK","Custo Produção Não Cadastrado"),"Custo Produção Não Cadastrado") -> OK | L42: =IFERROR(IF(VLOOKUP(A42,'Ficha de Embalagens'!A:A,1,0)=A42,"OK","Ficha de Embalagens Não Cadastrada"),"Ficha de Embalagens Não Cadastrada") -> OK | M42: =SUMIFS('Ficha de Produção'!N:N,'Ficha de Produção'!C:C,D42)*H42 -> 18.15 | N42: =SUMIFS('Ficha de Embalagens'!F:F,'Ficha de Embalagens'!A:A,A42) -> 8.61 | O42: =SUM(M42:N42) -> 26.76 | P42: =IF(AND(K42="OK",L42="OK"),H42*$P$1,0) -> 4.65 | Q42: =P42+O42 -> 31.41 | R42: =U42*$R$1 -> 3.495 | S42: =$S$1*U42 -> 4.893 | T42: =+Q42+R42+S42 -> 39.798 | U42: 69.9 | V42: =IF(M42=0,"Cadastrar Ficha de Produção",IF(AND(M42>0,U42=""),"Cadastrar Preço Final",IFERROR((U42-T42)/U42,""))) -> 0.43064378 | W42: =IF(M42=0,"Cadastrar Ficha de Produção",ROUNDUP(Q42/(1-$R$1-$S$1),2)) -> 35.7 | AB42: =IF(Q42=0,"",Q42) -> 31.41 | AC42: =IF(U42="","",U42*(1-$R$1-$S$1)) -> 61.512 | AD42: =IF(OR(AB42="",AC42=""),"",AC42-AB42) -> 30.102 | AE42: =IF(OR(AD42="",AC42=0),"",AD42/AC42) -> 0.48936793 | AF42: =IF(Q42=0,"",ROUNDUP((Q42+IF(AA42="",0,AA42/1200))/(1-$R$1-$S$1),2)) -> 35.7
A43: PRD00040 | B43: BRAZIMIL LÁTEX ECONÔMICO INT FOSCO 15L BRANCO GELO | C43: LATEX | D43: PI00006 | E43: FOSCO | F43: BRANCO GELO | G43: SIM | H43: 15 | I43: L | J43: =IF(I43="KG",1,1.27) -> 1.27 | K43: =IFERROR(IF(VLOOKUP(D43,'Ficha de Produção'!C:C,1,0)=D43,"OK","Custo Produção Não Cadastrado"),"Custo Produção Não Cadastrado") -> OK | L43: =IFERROR(IF(VLOOKUP(A43,'Ficha de Embalagens'!A:A,1,0)=A43,"OK","Ficha de Embalagens Não Cadastrada"),"Ficha de Embalagens Não Cadastrada") -> OK | M43: =SUMIFS('Ficha de Produção'!N:N,'Ficha de Produção'!C:C,D43)*H43 -> 23.85 | N43: =SUMIFS('Ficha de Embalagens'!F:F,'Ficha de Embalagens'!A:A,A43) -> 8.61 | O43: =SUM(M43:N43) -> 32.46 | P43: =IF(AND(K43="OK",L43="OK"),H43*$P$1,0) -> 4.65 | Q43: =P43+O43 -> 37.11 | R43: =U43*$R$1 -> 3.495 | S43: =$S$1*U43 -> 4.893 | T43: =+Q43+R43+S43 -> 45.498 | U43: 69.9 | V43: =IF(M43=0,"Cadastrar Ficha de Produção",IF(AND(M43>0,U43=""),"Cadastrar Preço Final",IFERROR((U43-T43)/U43,""))) -> 0.34909871 | W43: =IF(M43=0,"Cadastrar Ficha de Produção",ROUNDUP(Q43/(1-$R$1-$S$1),2)) -> 42.18 | AB43: =IF(Q43=0,"",Q43) -> 37.11 | AC43: =IF(U43="","",U43*(1-$R$1-$S$1)) -> 61.512 | AD43: =IF(OR(AB43="",AC43=""),"",AC43-AB43) -> 24.402 | AE43: =IF(OR(AD43="",AC43=0),"",AD43/AC43) -> 0.39670308 | AF43: =IF(Q43=0,"",ROUNDUP((Q43+IF(AA43="",0,AA43/1200))/(1-$R$1-$S$1),2)) -> 42.18
A44: PRD00041 | B44: BRAZIMIL LÁTEX ECONÔMICO INT FOSCO 15L AREIA | C44: LATEX | D44: PI00007 | E44: FOSCO | F44: AREIA | G44: SIM | H44: 15 | I44: L | J44: =IF(I44="KG",1,1.27) -> 1.27 | K44: =IFERROR(IF(VLOOKUP(D44,'Ficha de Produção'!C:C,1,0)=D44,"OK","Custo Produção Não Cadastrado"),"Custo Produção Não Cadastrado") -> OK | L44: =IFERROR(IF(VLOOKUP(A44,'Ficha de Embalagens'!A:A,1,0)=A44,"OK","Ficha de Embalagens Não Cadastrada"),"Ficha de Embalagens Não Cadastrada") -> OK | M44: =SUMIFS('Ficha de Produção'!N:N,'Ficha de Produção'!C:C,D44)*H44 -> 25.95 | N44: =SUMIFS('Ficha de Embalagens'!F:F,'Ficha de Embalagens'!A:A,A44) -> 8.61 | O44: =SUM(M44:N44) -> 34.56 | P44: =IF(AND(K44="OK",L44="OK"),H44*$P$1,0) -> 4.65 | Q44: =P44+O44 -> 39.21 | R44: =U44*$R$1 -> 3.495 | S44: =$S$1*U44 -> 4.893 | T44: =+Q44+R44+S44 -> 47.598 | U44: 69.9 | V44: =IF(M44=0,"Cadastrar Ficha de Produção",IF(AND(M44>0,U44=""),"Cadastrar Preço Final",IFERROR((U44-T44)/U44,""))) -> 0.31905579 | W44: =IF(M44=0,"Cadastrar Ficha de Produção",ROUNDUP(Q44/(1-$R$1-$S$1),2)) -> 44.56 | AB44: =IF(Q44=0,"",Q44) -> 39.21 | AC44: =IF(U44="","",U44*(1-$R$1-$S$1)) -> 61.512 | AD44: =IF(OR(AB44="",AC44=""),"",AC44-AB44) -> 22.302 | AE44: =IF(OR(AD44="",AC44=0),"",AD44/AC44) -> 0.3625634 | AF44: =IF(Q44=0,"",ROUNDUP((Q44+IF(AA44="",0,AA44/1200))/(1-$R$1-$S$1),2)) -> 44.56
A45: PRD00042 | B45: BRAZIMIL LÁTEX ECONÔMICO INT FOSCO 15L PALHA | C45: LATEX | D45: PI00008 | E45: FOSCO | F45: PALHA | G45: SIM | H45: 15 | I45: L | J45: =IF(I45="KG",1,1.27) -> 1.27 | K45: =IFERROR(IF(VLOOKUP(D45,'Ficha de Produção'!C:C,1,0)=D45,"OK","Custo Produção Não Cadastrado"),"Custo Produção Não Cadastrado") -> OK | L45: =IFERROR(IF(VLOOKUP(A45,'Ficha de Embalagens'!A:A,1,0)=A45,"OK","Ficha de Embalagens Não Cadastrada"),"Ficha de Embalagens Não Cadastrada") -> OK | M45: =SUMIFS('Ficha de Produção'!N:N,'Ficha de Produção'!C:C,D45)*H45 -> 24.6 | N45: =SUMIFS('Ficha de Embalagens'!F:F,'Ficha de Embalagens'!A:A,A45) -> 8.61 | O45: =SUM(M45:N45) -> 33.21 | P45: =IF(AND(K45="OK",L45="OK"),H45*$P$1,0) -> 4.65 | Q45: =P45+O45 -> 37.86 | R45: =U45*$R$1 -> 3.495 | S45: =$S$1*U45 -> 4.893 | T45: =+Q45+R45+S45 -> 46.248 | U45: 69.9 | V45: =IF(M45=0,"Cadastrar Ficha de Produção",IF(AND(M45>0,U45=""),"Cadastrar Preço Final",IFERROR((U45-T45)/U45,""))) -> 0.3383691 | W45: =IF(M45=0,"Cadastrar Ficha de Produção",ROUNDUP(Q45/(1-$R$1-$S$1),2)) -> 43.03 | AB45: =IF(Q45=0,"",Q45) -> 37.86 | AC45: =IF(U45="","",U45*(1-$R$1-$S$1)) -> 61.512 | AD45: =IF(OR(AB45="",AC45=""),"",AC45-AB45) -> 23.652 | AE45: =IF(OR(AD45="",AC45=0),"",AD45/AC45) -> 0.38451034 | AF45: =IF(Q45=0,"",ROUNDUP((Q45+IF(AA45="",0,AA45/1200))/(1-$R$1-$S$1),2)) -> 43.03
A46: PRD00043 | B46: BRAZIMIL LÁTEX ECONÔMICO INT FOSCO 15L VERDE PRIMAVERA | C46: LATEX | D46: PI00009 | E46: FOSCO | F46: VERDE PRIMAVERA | G46: SIM | H46: 15 | I46: L | J46: =IF(I46="KG",1,1.27) -> 1.27 | K46: =IFERROR(IF(VLOOKUP(D46,'Ficha de Produção'!C:C,1,0)=D46,"OK","Custo Produção Não Cadastrado"),"Custo Produção Não Cadastrado") -> OK | L46: =IFERROR(IF(VLOOKUP(A46,'Ficha de Embalagens'!A:A,1,0)=A46,"OK","Ficha de Embalagens Não Cadastrada"),"Ficha de Embalagens Não Cadastrada") -> OK | M46: =SUMIFS('Ficha de Produção'!N:N,'Ficha de Produção'!C:C,D46)*H46 -> 28.8 | N46: =SUMIFS('Ficha de Embalagens'!F:F,'Ficha de Embalagens'!A:A,A46) -> 8.61 | O46: =SUM(M46:N46) -> 37.41 | P46: =IF(AND(K46="OK",L46="OK"),H46*$P$1,0) -> 4.65 | Q46: =P46+O46 -> 42.06 | R46: =U46*$R$1 -> 3.495 | S46: =$S$1*U46 -> 4.893 | T46: =+Q46+R46+S46 -> 50.448 | U46: 69.9 | V46: =IF(M46=0,"Cadastrar Ficha de Produção",IF(AND(M46>0,U46=""),"Cadastrar Preço Final",IFERROR((U46-T46)/U46,""))) -> 0.27828326 | W46: =IF(M46=0,"Cadastrar Ficha de Produção",ROUNDUP(Q46/(1-$R$1-$S$1),2)) -> 47.8 | AB46: =IF(Q46=0,"",Q46) -> 42.06 | AC46: =IF(U46="","",U46*(1-$R$1-$S$1)) -> 61.512 | AD46: =IF(OR(AB46="",AC46=""),"",AC46-AB46) -> 19.452 | AE46: =IF(OR(AD46="",AC46=0),"",AD46/AC46) -> 0.31623098 | AF46: =IF(Q46=0,"",ROUNDUP((Q46+IF(AA46="",0,AA46/1200))/(1-$R$1-$S$1),2)) -> 47.8
A47: PRD00044 | B47: BRAZIMIL LÁTEX ECONÔMICO INT FOSCO 15L VERDE FOLHA | C47: LATEX | D47: PI00010 | E47: FOSCO | F47: VERDE FOLHA | G47: SIM | H47: 15 | I47: L | J47: =IF(I47="KG",1,1.27) -> 1.27 | K47: =IFERROR(IF(VLOOKUP(D47,'Ficha de Produção'!C:C,1,0)=D47,"OK","Custo Produção Não Cadastrado"),"Custo Produção Não Cadastrado") -> OK | L47: =IFERROR(IF(VLOOKUP(A47,'Ficha de Embalagens'!A:A,1,0)=A47,"OK","Ficha de Embalagens Não Cadastrada"),"Ficha de Embalagens Não Cadastrada") -> OK | M47: =SUMIFS('Ficha de Produção'!N:N,'Ficha de Produção'!C:C,D47)*H47 -> 34.35 | N47: =SUMIFS('Ficha de Embalagens'!F:F,'Ficha de Embalagens'!A:A,A47) -> 8.61 | O47: =SUM(M47:N47) -> 42.96 | P47: =IF(AND(K47="OK",L47="OK"),H47*$P$1,0) -> 4.65 | Q47: =P47+O47 -> 47.61 | R47: =U47*$R$1 -> 3.495 | S47: =$S$1*U47 -> 4.893 | T47: =+Q47+R47+S47 -> 55.998 | U47: 69.9 | V47: =IF(M47=0,"Cadastrar Ficha de Produção",IF(AND(M47>0,U47=""),"Cadastrar Preço Final",IFERROR((U47-T47)/U47,""))) -> 0.19888412 | W47: =IF(M47=0,"Cadastrar Ficha de Produção",ROUNDUP(Q47/(1-$R$1-$S$1),2)) -> 54.11 | AB47: =IF(Q47=0,"",Q47) -> 47.61 | AC47: =IF(U47="","",U47*(1-$R$1-$S$1)) -> 61.512 | AD47: =IF(OR(AB47="",AC47=""),"",AC47-AB47) -> 13.902 | AE47: =IF(OR(AD47="",AC47=0),"",AD47/AC47) -> 0.22600468 | AF47: =IF(Q47=0,"",ROUNDUP((Q47+IF(AA47="",0,AA47/1200))/(1-$R$1-$S$1),2)) -> 54.11
A48: PRD00045 | B48: BRAZIMIL LÁTEX ECONÔMICO INT FOSCO 15L AZUL CEU | C48: LATEX | D48: PI00011 | E48: FOSCO | F48: AZUL CEU | G48: SIM | H48: 15 | I48: L | J48: =IF(I48="KG",1,1.27) -> 1.27 | K48: =IFERROR(IF(VLOOKUP(D48,'Ficha de Produção'!C:C,1,0)=D48,"OK","Custo Produção Não Cadastrado"),"Custo Produção Não Cadastrado") -> OK | L48: =IFERROR(IF(VLOOKUP(A48,'Ficha de Embalagens'!A:A,1,0)=A48,"OK","Ficha de Embalagens Não Cadastrada"),"Ficha de Embalagens Não Cadastrada") -> OK | M48: =SUMIFS('Ficha de Produção'!N:N,'Ficha de Produção'!C:C,D48)*H48 -> 24.3 | N48: =SUMIFS('Ficha de Embalagens'!F:F,'Ficha de Embalagens'!A:A,A48) -> 8.61 | O48: =SUM(M48:N48) -> 32.91 | P48: =IF(AND(K48="OK",L48="OK"),H48*$P$1,0) -> 4.65 | Q48: =P48+O48 -> 37.56 | R48: =U48*$R$1 -> 3.495 | S48: =$S$1*U48 -> 4.893 | T48: =+Q48+R48+S48 -> 45.948 | U48: 69.9 | V48: =IF(M48=0,"Cadastrar Ficha de Produção",IF(AND(M48>0,U48=""),"Cadastrar Preço Final",IFERROR((U48-T48)/U48,""))) -> 0.34266094 | W48: =IF(M48=0,"Cadastrar Ficha de Produção",ROUNDUP(Q48/(1-$R$1-$S$1),2)) -> 42.69 | AB48: =IF(Q48=0,"",Q48) -> 37.56 | AC48: =IF(U48="","",U48*(1-$R$1-$S$1)) -> 61.512 | AD48: =IF(OR(AB48="",AC48=""),"",AC48-AB48) -> 23.952 | AE48: =IF(OR(AD48="",AC48=0),"",AD48/AC48) -> 0.38938744 | AF48: =IF(Q48=0,"",ROUNDUP((Q48+IF(AA48="",0,AA48/1200))/(1-$R$1-$S$1),2)) -> 42.69
A49: PRD00046 | B49: BRAZIMIL LÁTEX ECONÔMICO INT FOSCO 15L AZUL OCEANO | C49: LATEX | D49: PI00012 | E49: FOSCO | F49: AZUL OCEANO | G49: SIM | H49: 15 | I49: L | J49: =IF(I49="KG",1,1.27) -> 1.27 | K49: =IFERROR(IF(VLOOKUP(D49,'Ficha de Produção'!C:C,1,0)=D49,"OK","Custo Produção Não Cadastrado"),"Custo Produção Não Cadastrado") -> OK | L49: =IFERROR(IF(VLOOKUP(A49,'Ficha de Embalagens'!A:A,1,0)=A49,"OK","Ficha de Embalagens Não Cadastrada"),"Ficha de Embalagens Não Cadastrada") -> OK | M49: =SUMIFS('Ficha de Produção'!N:N,'Ficha de Produção'!C:C,D49)*H49 -> 30.15 | N49: =SUMIFS('Ficha de Embalagens'!F:F,'Ficha de Embalagens'!A:A,A49) -> 8.61 | O49: =SUM(M49:N49) -> 38.76 | P49: =IF(AND(K49="OK",L49="OK"),H49*$P$1,0) -> 4.65 | Q49: =P49+O49 -> 43.41 | R49: =U49*$R$1 -> 3.495 | S49: =$S$1*U49 -> 4.893 | T49: =+Q49+R49+S49 -> 51.798 | U49: 69.9 | V49: =IF(M49=0,"Cadastrar Ficha de Produção",IF(AND(M49>0,U49=""),"Cadastrar Preço Final",IFERROR((U49-T49)/U49,""))) -> 0.25896996 | W49: =IF(M49=0,"Cadastrar Ficha de Produção",ROUNDUP(Q49/(1-$R$1-$S$1),2)) -> 49.33 | AB49: =IF(Q49=0,"",Q49) -> 43.41 | AC49: =IF(U49="","",U49*(1-$R$1-$S$1)) -> 61.512 | AD49: =IF(OR(AB49="",AC49=""),"",AC49-AB49) -> 18.102 | AE49: =IF(OR(AD49="",AC49=0),"",AD49/AC49) -> 0.29428404 | AF49: =IF(Q49=0,"",ROUNDUP((Q49+IF(AA49="",0,AA49/1200))/(1-$R$1-$S$1),2)) -> 49.33
A50: PRD00047 | B50: BRAZIMIL LÁTEX ECONÔMICO INT FOSCO 15L AMARELO CANARIO | C50: LATEX | D50: PI00013 | E50: FOSCO | F50: AMARELO CANARIO | G50: SIM | H50: 15 | I50: L | J50: =IF(I50="KG",1,1.27) -> 1.27 | K50: =IFERROR(IF(VLOOKUP(D50,'Ficha de Produção'!C:C,1,0)=D50,"OK","Custo Produção Não Cadastrado"),"Custo Produção Não Cadastrado") -> OK | L50: =IFERROR(IF(VLOOKUP(A50,'Ficha de Embalagens'!A:A,1,0)=A50,"OK","Ficha de Embalagens Não Cadastrada"),"Ficha de Embalagens Não Cadastrada") -> OK | M50: =SUMIFS('Ficha de Produção'!N:N,'Ficha de Produção'!C:C,D50)*H50 -> 25.65 | N50: =SUMIFS('Ficha de Embalagens'!F:F,'Ficha de Embalagens'!A:A,A50) -> 8.61 | O50: =SUM(M50:N50) -> 34.26 | P50: =IF(AND(K50="OK",L50="OK"),H50*$P$1,0) -> 4.65 | Q50: =P50+O50 -> 38.91 | R50: =U50*$R$1 -> 3.495 | S50: =$S$1*U50 -> 4.893 | T50: =+Q50+R50+S50 -> 47.298 | U50: 69.9 | V50: =IF(M50=0,"Cadastrar Ficha de Produção",IF(AND(M50>0,U50=""),"Cadastrar Preço Final",IFERROR((U50-T50)/U50,""))) -> 0.32334764 | W50: =IF(M50=0,"Cadastrar Ficha de Produção",ROUNDUP(Q50/(1-$R$1-$S$1),2)) -> 44.22 | AB50: =IF(Q50=0,"",Q50) -> 38.91 | AC50: =IF(U50="","",U50*(1-$R$1-$S$1)) -> 61.512 | AD50: =IF(OR(AB50="",AC50=""),"",AC50-AB50) -> 22.602 | AE50: =IF(OR(AD50="",AC50=0),"",AD50/AC50) -> 0.3674405 | AF50: =IF(Q50=0,"",ROUNDUP((Q50+IF(AA50="",0,AA50/1200))/(1-$R$1-$S$1),2)) -> 44.22
A51: PRD00048 | B51: BRAZIMIL LÁTEX ECONÔMICO INT FOSCO 15L CROMO SUAVE | C51: LATEX | D51: PI00014 | E51: FOSCO | F51: CROMO SUAVE | G51: SIM | H51: 15 | I51: L | J51: =IF(I51="KG",1,1.27) -> 1.27 | K51: =IFERROR(IF(VLOOKUP(D51,'Ficha de Produção'!C:C,1,0)=D51,"OK","Custo Produção Não Cadastrado"),"Custo Produção Não Cadastrado") -> OK | L51: =IFERROR(IF(VLOOKUP(A51,'Ficha de Embalagens'!A:A,1,0)=A51,"OK","Ficha de Embalagens Não Cadastrada"),"Ficha de Embalagens Não Cadastrada") -> OK | M51: =SUMIFS('Ficha de Produção'!N:N,'Ficha de Produção'!C:C,D51)*H51 -> 29.25 | N51: =SUMIFS('Ficha de Embalagens'!F:F,'Ficha de Embalagens'!A:A,A51) -> 8.61 | O51: =SUM(M51:N51) -> 37.86 | P51: =IF(AND(K51="OK",L51="OK"),H51*$P$1,0) -> 4.65 | Q51: =P51+O51 -> 42.51 | R51: =U51*$R$1 -> 3.495 | S51: =$S$1*U51 -> 4.893 | T51: =+Q51+R51+S51 -> 50.898 | U51: 69.9 | V51: =IF(M51=0,"Cadastrar Ficha de Produção",IF(AND(M51>0,U51=""),"Cadastrar Preço Final",IFERROR((U51-T51)/U51,""))) -> 0.27184549 | W51: =IF(M51=0,"Cadastrar Ficha de Produção",ROUNDUP(Q51/(1-$R$1-$S$1),2)) -> 48.31 | AB51: =IF(Q51=0,"",Q51) -> 42.51 | AC51: =IF(U51="","",U51*(1-$R$1-$S$1)) -> 61.512 | AD51: =IF(OR(AB51="",AC51=""),"",AC51-AB51) -> 19.002 | AE51: =IF(OR(AD51="",AC51=0),"",AD51/AC51) -> 0.30891533 | AF51: =IF(Q51=0,"",ROUNDUP((Q51+IF(AA51="",0,AA51/1200))/(1-$R$1-$S$1),2)) -> 48.31
A52: PRD00049 | B52: BRAZIMIL LÁTEX ECONÔMICO INT FOSCO 15L ROSA BEBE | C52: LATEX | D52: PI00015 | E52: FOSCO | F52: ROSA BEBE | G52: SIM | H52: 15 | I52: L | J52: =IF(I52="KG",1,1.27) -> 1.27 | K52: =IFERROR(IF(VLOOKUP(D52,'Ficha de Produção'!C:C,1,0)=D52,"OK","Custo Produção Não Cadastrado"),"Custo Produção Não Cadastrado") -> OK | L52: =IFERROR(IF(VLOOKUP(A52,'Ficha de Embalagens'!A:A,1,0)=A52,"OK","Ficha de Embalagens Não Cadastrada"),"Ficha de Embalagens Não Cadastrada") -> OK | M52: =SUMIFS('Ficha de Produção'!N:N,'Ficha de Produção'!C:C,D52)*H52 -> 24.75 | N52: =SUMIFS('Ficha de Embalagens'!F:F,'Ficha de Embalagens'!A:A,A52) -> 8.61 | O52: =SUM(M52:N52) -> 33.36 | P52: =IF(AND(K52="OK",L52="OK"),H52*$P$1,0) -> 4.65 | Q52: =P52+O52 -> 38.01 | R52: =U52*$R$1 -> 3.495 | S52: =$S$1*U52 -> 4.893 | T52: =+Q52+R52+S52 -> 46.398 | U52: 69.9 | V52: =IF(M52=0,"Cadastrar Ficha de Produção",IF(AND(M52>0,U52=""),"Cadastrar Preço Final",IFERROR((U52-T52)/U52,""))) -> 0.33622318 | W52: =IF(M52=0,"Cadastrar Ficha de Produção",ROUNDUP(Q52/(1-$R$1-$S$1),2)) -> 43.2 | AB52: =IF(Q52=0,"",Q52) -> 38.01 | AC52: =IF(U52="","",U52*(1-$R$1-$S$1)) -> 61.512 | AD52: =IF(OR(AB52="",AC52=""),"",AC52-AB52) -> 23.502 | AE52: =IF(OR(AD52="",AC52=0),"",AD52/AC52) -> 0.38207179 | AF52: =IF(Q52=0,"",ROUNDUP((Q52+IF(AA52="",0,AA52/1200))/(1-$R$1-$S$1),2)) -> 43.2
A53: PRD00050 | B53: BRAZIMIL LÁTEX ECONÔMICO INT FOSCO 15L MARFIM | C53: LATEX | D53: PI00016 | E53: FOSCO | F53: MARFIM | G53: SIM | H53: 15 | I53: L | J53: =IF(I53="KG",1,1.27) -> 1.27 | K53: =IFERROR(IF(VLOOKUP(D53,'Ficha de Produção'!C:C,1,0)=D53,"OK","Custo Produção Não Cadastrado"),"Custo Produção Não Cadastrado") -> OK | L53: =IFERROR(IF(VLOOKUP(A53,'Ficha de Embalagens'!A:A,1,0)=A53,"OK","Ficha de Embalagens Não Cadastrada"),"Ficha de Embalagens Não Cadastrada") -> OK | M53: =SUMIFS('Ficha de Produção'!N:N,'Ficha de Produção'!C:C,D53)*H53 -> 24.9 | N53: =SUMIFS('Ficha de Embalagens'!F:F,'Ficha de Embalagens'!A:A,A53) -> 8.61 | O53: =SUM(M53:N53) -> 33.51 | P53: =IF(AND(K53="OK",L53="OK"),H53*$P$1,0) -> 4.65 | Q53: =P53+O53 -> 38.16 | R53: =U53*$R$1 -> 3.495 | S53: =$S$1*U53 -> 4.893 | T53: =+Q53+R53+S53 -> 46.548 | U53: 69.9 | V53: =IF(M53=0,"Cadastrar Ficha de Produção",IF(AND(M53>0,U53=""),"Cadastrar Preço Final",IFERROR((U53-T53)/U53,""))) -> 0.33407725 | W53: =IF(M53=0,"Cadastrar Ficha de Produção",ROUNDUP(Q53/(1-$R$1-$S$1),2)) -> 43.37 | AB53: =IF(Q53=0,"",Q53) -> 38.16 | AC53: =IF(U53="","",U53*(1-$R$1-$S$1)) -> 61.512 | AD53: =IF(OR(AB53="",AC53=""),"",AC53-AB53) -> 23.352 | AE53: =IF(OR(AD53="",AC53=0),"",AD53/AC53) -> 0.37963324 | AF53: =IF(Q53=0,"",ROUNDUP((Q53+IF(AA53="",0,AA53/1200))/(1-$R$1-$S$1),2)) -> 43.37
... A56: PRD00053 | B56: BRAZIMIL LÁTEX ECONÔMICO INT FOSCO 15L PEROLA | C56: LATEX | D56: PI00019 | E56: FOSCO | F56: PEROLA | G56: SIM | H56: 15 | I56: L | J56: =IF(I56="KG",1,1.27) -> 1.27 | K56: =IFERROR(IF(VLOOKUP(D56,'Ficha de Produção'!C:C,1,0)=D56,"OK","Custo Produção Não Cadastrado"),"Custo Produção Não Cadastrado") -> OK | L56: =IFERROR(IF(VLOOKUP(A56,'Ficha de Embalagens'!A:A,1,0)=A56,"OK","Ficha de Embalagens Não Cadastrada"),"Ficha de Embalagens Não Cadastrada") -> OK | M56: =SUMIFS('Ficha de Produção'!N:N,'Ficha de Produção'!C:C,D56)*H56 -> 24.6 | N56: =SUMIFS('Ficha de Embalagens'!F:F,'Ficha de Embalagens'!A:A,A56) -> 8.61 | O56: =SUM(M56:N56) -> 33.21 | P56: =IF(AND(K56="OK",L56="OK"),H56*$P$1,0) -> 4.65 | Q56: =P56+O56 -> 37.86 | R56: =U56*$R$1 -> 3.495 | S56: =$S$1*U56 -> 4.893 | T56: =+Q56+R56+S56 -> 46.248 | U56: 69.9 | V56: =IF(M56=0,"Cadastrar Ficha de Produção",IF(AND(M56>0,U56=""),"Cadastrar Preço Final",IFERROR((U56-T56)/U56,""))) -> 0.3383691 | W56: =IF(M56=0,"Cadastrar Ficha de Produção",ROUNDUP(Q56/(1-$R$1-$S$1),2)) -> 43.03 | AB56: =IF(Q56=0,"",Q56) -> 37.86 | AC56: =IF(U56="","",U56*(1-$R$1-$S$1)) -> 61.512 | AD56: =IF(OR(AB56="",AC56=""),"",AC56-AB56) -> 23.652 | AE56: =IF(OR(AD56="",AC56=0),"",AD56/AC56) -> 0.38451034 | AF56: =IF(Q56=0,"",ROUNDUP((Q56+IF(AA56="",0,AA56/1200))/(1-$R$1-$S$1),2)) -> 43.03
A57: PRD00054 | B57: BRAZIMIL LÁTEX ECONÔMICO INT/EXT SEMIBRILHO 15L BRANCO NEVE | C57: LATEX | E57: SEMIBRILHO | F57: BRANCO NEVE | G57: NÃO | H57: 15 | I57: L | J57: =IF(I57="KG",1,1.27) -> 1.27 | K57: =IFERROR(IF(VLOOKUP(D57,'Ficha de Produção'!C:C,1,0)=D57,"OK","Custo Produção Não Cadastrado"),"Custo Produção Não Cadastrado") -> Custo Produção Não Cadastrado | L57: =IFERROR(IF(VLOOKUP(A57,'Ficha de Embalagens'!A:A,1,0)=A57,"OK","Ficha de Embalagens Não Cadastrada"),"Ficha de Embalagens Não Cadastrada") -> Ficha de Embalagens Não Cadastrada | M57: =SUMIFS('Ficha de Produção'!N:N,'Ficha de Produção'!C:C,D57)*H57 -> 0 | N57: =SUMIFS('Ficha de Embalagens'!F:F,'Ficha de Embalagens'!A:A,A57) -> 0 | O57: =SUM(M57:N57) -> 0 | P57: =IF(AND(K57="OK",L57="OK"),H57*$P$1,0) -> 0 | Q57: =P57+O57 -> 0 | R57: =U57*$R$1 -> 0 | S57: =$S$1*U57 -> 0 | T57: =+Q57+R57+S57 -> 0 | V57: =IF(M57=0,"Cadastrar Ficha de Produção",IF(AND(M57>0,U57=""),"Cadastrar Preço Final",IFERROR((U57-T57)/U57,""))) -> Cadastrar Ficha de Produção | W57: =IF(M57=0,"Cadastrar Ficha de Produção",ROUNDUP(Q57/(1-$R$1-$S$1),2)) -> Cadastrar Ficha de Produção | AB57: =IF(Q57=0,"",Q57) | AC57: =IF(U57="","",U57*(1-$R$1-$S$1)) | AD57: =IF(OR(AB57="",AC57=""),"",AC57-AB57) | AE57: =IF(OR(AD57="",AC57=0),"",AD57/AC57) | AF57: =IF(Q57=0,"",ROUNDUP((Q57+IF(AA57="",0,AA57/1200))/(1-$R$1-$S$1),2))
