Workbook

Sheet Frete_Regiao-Impostos
A1: REPRESENTANTE | B1: FRETE TON | C1: IMPOSTOS | D1: ESTADO | E1: GRUPO ST | G1: TRIBUTAÇÃO P/ LUCRO PRESUMIDO!
H2: C
G3: PARAIBA | H3: =SUM(H4:H6) -> 0.2365
G4: Icms | H4: 0.2
G5: Pis | H5: 0.0065
G6: Cofins | H6: 0.03
H8: I
G9: INTERESTADUAL | H9: =SUM(H10:H12) -> 0.1565
G10: Icms | H10: 0.12
G11: Pis | H11: 0.0065
G12: Cofins | H12: 0.03
G14: MANUAS | H14: I (AM)
G15: INTERESTADUAL | H15: =SUM(H16:H18) -> 0.12
G16: Icms | H16: 0.12 | I16: ATENÇÃO: DESONERAÇÃO
G18: Desconto
G20: Exportação | H20: E
H21: =SUM(H22:H24) -> 0
G22: Icms | H22: 0
G23: Pis | H23: 0
G24: Cofins | H24: 0
A25: Manaus CIF | B25: 100 | C25: 0.07 | D25: AM | E25: GRUPO 4
A27: Manaus - FOB | B27: 0 | C27: 0.07 | D27: AM | E27: GRUPO 4
A28: Manaus - INTERIOR PIS COFINS | B28: 0 | C28: 0.1065 | D28: AM | E28: GRUPO 4 | G28: =2000/14 -> 142.85714
A29: Manaus - INTERIOR S/ PIS COFINS | B29: 0 | C29: 0.07 | D29: AM | E29: GRUPO 4

Sheet Sim_Preço
A2: Juros desconto duplicata | B2: X | C2: 0 | AJ2: % Comissão
A3: Representante | B3: Estado | C3: Grupo | AJ3: Vínculo planilha Frete_Regiao => Base p/ o Filtro "Representante-A4"
A4: Manaus CIF | B4: =VLOOKUP(A4,'Frete_Regiao-Impostos'!A1:D62,4,FALSE) -> AM | C4: =VLOOKUP(A4,'Frete_Regiao-Impostos'!A1:E62,5,FALSE) -> GRUPO 4 | E4: Fórmula | F4: Fórmula | I4: Digitado | N4: RESULTADO EM R$
A5: Impostos | B5: =VLOOKUP(A4,AF10:$AH$187,3,0) -> 0.07 | C5: PESO (Kg) | E5: Se "X" | F5: Se "X" | I5: Se "X" | O5: =N15/E15 -> 0.47981726 | X5: RESUMO DA VENDA
A6: Frete | B6: =VLOOKUP(A4,$AF$10:$AG$187,2,0) -> 100 | C6: =SUMPRODUCT(C12:C125,AP12:AP125) -> 0 | D6: MC Geral | E6: Considera | F6: Considera | I6: Considera
A7: Frete acima não é base p/ cálculo da MC => | B7: VALOR PEDIDO | C7: =SUMPRODUCT(B12:B133,C12:C133) -> 0 | D7: =+AB9 | E7: =IF($B$6<=$B$7,"X","") -> X | F7: =IF($B$6>$B$7,"X","") | I7: X | M7: Despesas | N7: =SUMPRODUCT(C12:C133,N12:N133) -> 0 | O7: Margem | Q7: CALCULO DO PREÇO FINAL PARA O CLIENTE
B8: Preço | D8: 9 | E8: Preço | F8: Preço | G8: Custo | I8: Comissão | J8: Comissão | K8: Desc. duplicata | L8: Desc. duplicata | M8: Custo | N8: Margem | O8: R$/TON | Q8: Alíquota | R8: Valor | S8: =HLOOKUP(B4,'MVA-IPI'!B137:AB142,2,FALSE) -> 0.12 | T8: MVA | U8: Base | V8: =HLOOKUP( B4,'MVA-IPI'!B137:AB142,3,FALSE) -> 0.2 | X8: PRODUTO | Y8: QTDE | Z8: MARGEM | AA8: RLV | AB8: MARGEM | AC8: MC Guia | AD8: Comissão | AE8: Comissão | AF8: REPRESENTANTE | AG8: FRETE TON | AH8: IMPOSTOS | AI8: ESTADO
A9: Produto | B9: Produto | C9: QTDE | D9: % | E9: Líquido | F9: Liq-Frete | G9: MP/ME | H9: Frete | I9: % | J9: R$ | K9: % | L9: R$ | M9: Variável | N9: R$ | O9: R$/HL | P9: Conversão | Q9: IPI | R9: IPI | S9: ICMS Normal | T9: ST | U9: ICMS ST | V9: ICMS ST | X9: TOTAL | Z9: =Z10+Z48+Z76+Z108 -> 0 | AA9: =AA10+AA48+AA76+AA108 -> 0 | AB9: =IF(ISERROR(Z9/AA9),"",Z9/AA9) | AC9: 0.18 | AE9: % | AH9: ICMS+PIS+COFINS
A10: TINTAS BASE ÁGUA | D10: =AB10 | X10: TINTAS BASE ÁGUA | Z10: =Z11+Z16+Z21+Z24+Z27+Z30+Z33+Z36+Z39+Z42+Z44+Z46 -> 0 | AA10: =AA11+AA16+AA21+AA24+AA27+AA30+AA33+AA36+AA39+AA42+AA44+AA46 -> 0 | AB10: =IF(ISERROR(Z10/AA10),"",Z10/AA10) | AC10: 0.25 | AF10: =+'Frete_Regiao-Impostos'!A2 -> 0 | AG10: =+'Frete_Regiao-Impostos'!B2 -> 0 | AH10: =+'Frete_Regiao-Impostos'!C2 -> 0 | AI10: =+'Frete_Regiao-Impostos'!D2 -> 0
A11: BRAZIMIL ECONOMICA 3,0L | D11: =AB11 | X11: =A11 -> BRAZIMIL ECONOMICA 3,0L | Z11: =SUM(Z12:Z15) -> 0 | AA11: =SUM(AA12:AA15) -> 0 | AB11: =IF(ISERROR(Z11/AA11),"",Z11/AA11) | AC11: 0.25 | AF11: =+'Frete_Regiao-Impostos'!A3 -> 0 | AG11: =+'Frete_Regiao-Impostos'!B3 -> 0 | AH11: =+'Frete_Regiao-Impostos'!C3 -> 0 | AI11: =+'Frete_Regiao-Impostos'!D3 -> 0 | AP11: PESO
A12: BRAZIMIL ECONÔMICA 3,0L REFIL BRANCO NEVE | B12: 9.5 | D12: =IF($F$7="x",IF(F12=0,0,N12/F12),IF($E$7="x",IF(F12=0,0,N12/E12),"")) -> 0.39340313 | E12: =+B12*(-B$5+100%) -> 8.835 | F12: =IF(B12=0,0,E12-H12) -> 8.45 | G12: =VLOOKUP(A12,Custo!A:B,2,0) -> 4.4992833 | H12: =(VLOOKUP(A12,Peso!$A$10:$B$148,2,0))*($B$6/1000) -> 0.385 | I12: =IF($I$7="X",AE12,0%) -> 0.05 | J12: =+B12*I12 -> 0.475 | K12: =IF($B$2="X",$C$2,0) -> 0 | L12: =+B12*K12 -> 0 | M12: =+G12+H12+J12+L12 -> 5.3592833 | N12: =+E12-M12 -> 3.4757167 | O12: =IF(ISERROR((N12/P12)*1000),"",(N12/P12)*1000) | Q12: =VLOOKUP(A12,'MVA-IPI'!A:AD,30,FALSE) -> 0 | R12: =IF($B$4="AM",0,IF($B$4="AP",0,IF($B$4="RR",0,(B12*Q12)))) -> 0 | S12: =IF($B$4="AP",(B12/0.88*$S$8),IF(T12=0%,0,IF($B$4="AM",(B12/0.88*$S$8),IF(T12=0%,0,IF($B$4="RR",(B12/0.88*$S$8),IF(T12=0%,0,B12*$S$8)))))) -> 0 | T12: =IF($C$4="GRUPO 1",VLOOKUP(A12,'MVA-grupos'!$A$9:$B$128,2,FALSE),IF($C$4="GRUPO 2",VLOOKUP(A12,'MVA-grupos'!$A$9:$D$128,4,FALSE),IF($C$4="GRUPO 3",VLOOKUP(A12,'MVA-grupos'!$A$10:$F$128,6,FALSE),IF($C$4="Grupo 4",VLOOKUP(A12,'MVA-grupos'!$A$9:$H$128,8,FALSE))))) -> 0 | U12: =IF(T12=0%,0,(B12+R12)*T12+(B12+R12)) -> 0 | V12: =(U12*$V$8)-S12 -> 0 | X12: =A12 -> BRAZIMIL ECONÔMICA 3,0L REFIL BRANCO NEVE | Y12: =+C12 -> 0 | Z12: =IF(ISERROR(Y12*N12),"",Y12*N12) -> 0 | AA12: =IF(ISERROR(IF(E$7="X",Y12*E12,Y12*F12)),"",IF(E$7="X",Y12*E12,Y12*F12)) -> 0 | AB12: =IF(ISERROR(Z12/AA12),"",Z12/AA12) | AE12: 0.05 | AF12: =+'Frete_Regiao-Impostos'!A4 -> 0 | AG12: =+'Frete_Regiao-Impostos'!B4 -> 0 | AH12: =+'Frete_Regiao-Impostos'!C4 -> 0 | AI12: =+'Frete_Regiao-Impostos'!D4 -> 0 | AP12: =Peso!B12 -> 3.85
A13: BRAZIMIL ECONÔMICA 3,0L REFIL COR | B13: 9.5 | D13: =IF($F$7="x",IF(F13=0,0,N13/F13),IF($E$7="x",IF(F13=0,0,N13/E13),"")) -> 0.45755276 | E13: =+B13*(-B$5+100%) -> 8.835 | F13: =IF(B13=0,0,E13-H13) -> 8.5 | G13: =VLOOKUP(A13,Custo!A:B,2,0) -> 3.9825213 | H13: =(VLOOKUP(A13,Peso!$A$10:$B$148,2,0))*($B$6/1000) -> 0.335 | I13: =IF($I$7="X",AE13,0%) -> 0.05 | J13: =+B13*I13 -> 0.475 | K13: =IF($B$2="X",$C$2,0) -> 0 | L13: =+B13*K13 -> 0 | M13: =+G13+H13+J13+L13 -> 4.7925213 | N13: =+E13-M13 -> 4.0424787 | O13: =IF(ISERROR((N13/P13)*1000),"",(N13/P13)*1000) | Q13: =VLOOKUP(A13,'MVA-IPI'!A:AD,30,FALSE) -> 0 | R13: =IF($B$4="AM",0,IF($B$4="AP",0,IF($B$4="RR",0,(B13*Q13)))) -> 0 | S13: =IF($B$4="AP",(B13/0.88*$S$8),IF(T13=0%,0,IF($B$4="AM",(B13/0.88*$S$8),IF(T13=0%,0,IF($B$4="RR",(B13/0.88*$S$8),IF(T13=0%,0,B13*$S$8)))))) -> 0 | T13: =IF($C$4="GRUPO 1",VLOOKUP(A13,'MVA-grupos'!$A$9:$B$128,2,FALSE),IF($C$4="GRUPO 2",VLOOKUP(A13,'MVA-grupos'!$A$9:$D$128,4,FALSE),IF($C$4="GRUPO 3",VLOOKUP(A13,'MVA-grupos'!$A$10:$F$128,6,FALSE),IF($C$4="Grupo 4",VLOOKUP(A13,'MVA-grupos'!$A$9:$H$128,8,FALSE))))) -> 0 | U13: =IF(T13=0%,0,(B13+R13)*T13+(B13+R13)) -> 0 | V13: =(U13*$V$8)-S13 -> 0 | X13: =A13 -> BRAZIMIL ECONÔMICA 3,0L REFIL COR | Y13: =+C13 -> 0 | Z13: =IF(ISERROR(Y13*N13),"",Y13*N13) -> 0 | AA13: =IF(ISERROR(IF(E$7="X",Y13*E13,Y13*F13)),"",IF(E$7="X",Y13*E13,Y13*F13)) -> 0 | AB13: =IF(ISERROR(Z13/AA13),"",Z13/AA13) | AE13: 0.05 | AF13: =+'Frete_Regiao-Impostos'!A5 -> 0 | AG13: =+'Frete_Regiao-Impostos'!B5 -> 0 | AH13: =+'Frete_Regiao-Impostos'!C5 -> 0 | AI13: =+'Frete_Regiao-Impostos'!D5 -> 0 | AP13: =Peso!B13 -> 3.35
A14: BRAZIMIL ECONÔMICA 3,0L GALÃO BRANCO NEVE | B14: 17.99 | D14: =IF($F$7="x",IF(F14=0,0,N14/F14),IF($E$7="x",IF(F14=0,0,N14/E14),"")) -> 0.44594169 | E14: =+B14*(-B$5+100%) -> 16.7307 | F14: =IF(B14=0,0,E14-H14) -> 16.3307 | G14: =VLOOKUP(A14,Custo!A:B,2,0) -> 7.9702833 | H14: =(VLOOKUP(A14,Peso!$A$10:$B$148,2,0))*($B$6/1000) -> 0.4 | I14: =IF($I$7="X",AE14,0%) -> 0.05 | J14: =+B14*I14 -> 0.8995 | K14: =IF($B$2="X",$C$2,0) -> 0 | L14: =+B14*K14 -> 0 | M14: =+G14+H14+J14+L14 -> 9.2697833 | N14: =+E14-M14 -> 7.4609167 | O14: =IF(ISERROR((N14/P14)*1000),"",(N14/P14)*1000) | Q14: =VLOOKUP(A14,'MVA-IPI'!A:AD,30,FALSE) -> 0 | R14: =IF($B$4="AM",0,IF($B$4="AP",0,IF($B$4="RR",0,(B14*Q14)))) -> 0 | S14: =IF($B$4="AP",(B14/0.88*$S$8),IF(T14=0%,0,IF($B$4="AM",(B14/0.88*$S$8),IF(T14=0%,0,IF($B$4="RR",(B14/0.88*$S$8),IF(T14=0%,0,B14*$S$8)))))) -> 0 | T14: =IF($C$4="GRUPO 1",VLOOKUP(A14,'MVA-grupos'!$A$9:$B$128,2,FALSE),IF($C$4="GRUPO 2",VLOOKUP(A14,'MVA-grupos'!$A$9:$D$128,4,FALSE),IF($C$4="GRUPO 3",VLOOKUP(A14,'MVA-grupos'!$A$10:$F$128,6,FALSE),IF($C$4="Grupo 4",VLOOKUP(A14,'MVA-grupos'!$A$9:$H$128,8,FALSE))))) -> 0 | U14: =IF(T14=0%,0,(B14+R14)*T14+(B14+R14)) -> 0 | V14: =(U14*$V$8)-S14 -> 0 | X14: =A14 -> BRAZIMIL ECONÔMICA 3,0L GALÃO BRANCO NEVE | Y14: =+C14 -> 0 | Z14: =IF(ISERROR(Y14*N14),"",Y14*N14) -> 0 | AA14: =IF(ISERROR(IF(E$7="X",Y14*E14,Y14*F14)),"",IF(E$7="X",Y14*E14,Y14*F14)) -> 0 | AB14: =IF(ISERROR(Z14/AA14),"",Z14/AA14) | AE14: 0.05 | AF14: =+'Frete_Regiao-Impostos'!A6 -> 0 | AG14: =+'Frete_Regiao-Impostos'!B6 -> 0 | AH14: =+'Frete_Regiao-Impostos'!C6 -> 0 | AI14: =+'Frete_Regiao-Impostos'!D6 -> 0 | AP14: =Peso!B14 -> 4
A15: BRAZIMIL ECONÔMICA 3,0L GALÃO COR | B15: 17.99 | D15: =IF($F$7="x",IF(F15=0,0,N15/F15),IF($E$7="x",IF(F15=0,0,N15/E15),"")) -> 0.47981726 | E15: =+B15*(-B$5+100%) -> 16.7307 | F15: =IF(B15=0,0,E15-H15) -> 16.3807 | G15: =VLOOKUP(A15,Custo!A:B,2,0) -> 7.4535213 | H15: =(VLOOKUP(A15,Peso!$A$10:$B$148,2,0))*($B$6/1000) -> 0.35 | I15: =IF($I$7="X",AE15,0%) -> 0.05 | J15: =+B15*I15 -> 0.8995 | K15: =IF($B$2="X",$C$2,0) -> 0 | L15: =+B15*K15 -> 0 | M15: =+G15+H15+J15+L15 -> 8.7030213 | N15: =+E15-M15 -> 8.0276787 | O15: =IF(ISERROR((N15/P15)*1000),"",(N15/P15)*1000) | Q15: =VLOOKUP(A15,'MVA-IPI'!A:AD,30,FALSE) -> 0 | R15: =IF($B$4="AM",0,IF($B$4="AP",0,IF($B$4="RR",0,(B15*Q15)))) -> 0 | S15: =IF($B$4="AP",(B15/0.88*$S$8),IF(T15=0%,0,IF($B$4="AM",(B15/0.88*$S$8),IF(T15=0%,0,IF($B$4="RR",(B15/0.88*$S$8),IF(T15=0%,0,B15*$S$8)))))) -> 0 | T15: =IF($C$4="GRUPO 1",VLOOKUP(A15,'MVA-grupos'!$A$9:$B$128,2,FALSE),IF($C$4="GRUPO 2",VLOOKUP(A15,'MVA-grupos'!$A$9:$D$128,4,FALSE),IF($C$4="GRUPO 3",VLOOKUP(A15,'MVA-grupos'!$A$10:$F$128,6,FALSE),IF($C$4="Grupo 4",VLOOKUP(A15,'MVA-grupos'!$A$9:$H$128,8,FALSE))))) -> 0 | U15: =IF(T15=0%,0,(B15+R15)*T15+(B15+R15)) -> 0 | V15: =(U15*$V$8)-S15 -> 0 | X15: =A15 -> BRAZIMIL ECONÔMICA 3,0L GALÃO COR | Y15: =+C15 -> 0 | Z15: =IF(ISERROR(Y15*N15),"",Y15*N15) -> 0 | AA15: =IF(ISERROR(IF(E$7="X",Y15*E15,Y15*F15)),"",IF(E$7="X",Y15*E15,Y15*F15)) -> 0 | AB15: =IF(ISERROR(Z15/AA15),"",Z15/AA15) | AE15: 0.05 | AF15: =+'Frete_Regiao-Impostos'!A7 -> 0 | AG15: =+'Frete_Regiao-Impostos'!B7 -> 0 | AH15: =+'Frete_Regiao-Impostos'!C7 -> 0 | AI15: =+'Frete_Regiao-Impostos'!D7 -> 0 | AP15: =Peso!B15 -> 3.5
A16: BRAZIMIL ECONÔMICA 15L | D16: =AB16 | X16: =A16 -> BRAZIMIL ECONÔMICA 15L | Z16: =SUM(Z17:Z20) -> 0 | AA16: =SUM(AA17:AA20) -> 0 | AB16: =IF(ISERROR(Z16/AA16),"",Z16/AA16) | AC16: 0.25 | AF16: =+'Frete_Regiao-Impostos'!A8 -> 0 | AG16: =+'Frete_Regiao-Impostos'!B8 -> 0 | AH16: =+'Frete_Regiao-Impostos'!C8 -> 0 | AI16: =+'Frete_Regiao-Impostos'!D8 -> 0 | AP16: =Peso!B16 -> 0
A17: BRAZIMIL ECONÔMICA 15L PPQ BRANCO NEVE | D17: =IF($F$7="x",IF(F17=0,0,N17/F17),IF($E$7="x",IF(F17=0,0,N17/E17),"")) -> 0 | E17: =+B17*(-B$5+100%) -> 0 | F17: =IF(B17=0,0,E17-H17) -> 0 | G17: =VLOOKUP(A17,Custo!A:B,2,0) -> 0 | H17: =(VLOOKUP(A17,Peso!$A$10:$B$148,2,0))*($B$6/1000) -> 1.87 | I17: =IF($I$7="X",AE17,0%) -> 0.06 | J17: =+B17*I17 -> 0 | M17: =+G17+H17+J17 -> 1.87 | N17: =+E17-M17 -> -1.87 | O17: =IF(ISERROR((N17/P17)*1000),"",(N17/P17)*1000) | Q17: =VLOOKUP(A17,'MVA-IPI'!A:AD,30,FALSE) -> 0 | R17: =IF($B$4="AM",0,IF($B$4="AP",0,IF($B$4="RR",0,(B17*Q17)))) -> 0 | S17: =IF($B$4="AP",(B17/0.88*$S$8),IF(T17=0%,0,IF($B$4="AM",(B17/0.88*$S$8),IF(T17=0%,0,IF($B$4="RR",(B17/0.88*$S$8),IF(T17=0%,0,B17*$S$8)))))) -> 0 | T17: =IF($C$4="GRUPO 1",VLOOKUP(A17,'MVA-grupos'!$A$9:$B$128,2,FALSE),IF($C$4="GRUPO 2",VLOOKUP(A17,'MVA-grupos'!$A$9:$D$128,4,FALSE),IF($C$4="GRUPO 3",VLOOKUP(A17,'MVA-grupos'!$A$10:$F$128,6,FALSE),IF($C$4="Grupo 4",VLOOKUP(A17,'MVA-grupos'!$A$9:$H$128,8,FALSE))))) -> 0 | U17: =IF(T17=0%,0,(B17+R17)*T17+(B17+R17)) -> 0 | V17: =(U17*$V$8)-S17 -> 0 | X17: =A17 -> BRAZIMIL ECONÔMICA 15L PPQ BRANCO NEVE | Y17: =+C17 -> 0 | Z17: =IF(ISERROR(Y17*N17),"",Y17*N17) -> 0 | AA17: =IF(ISERROR(IF(E$7="X",Y17*E17,Y17*F17)),"",IF(E$7="X",Y17*E17,Y17*F17)) -> 0 | AB17: =IF(ISERROR(Z17/AA17),"",Z17/AA17) | AE17: 0.06 | AF17: =+'Frete_Regiao-Impostos'!A38 -> 0 | AG17: =+'Frete_Regiao-Impostos'!B38 -> 0 | AH17: =+'Frete_Regiao-Impostos'!C38 -> 0 | AI17: =+'Frete_Regiao-Impostos'!D38 -> 0 | AP17: =Peso!B17 -> 18.7
A18: BRAZIMIL ECONÔMICA 12L BALDE BRANCO NEVE | B18: 0 | D18: =IF($F$7="x",IF(F18=0,0,N18/F18),IF($E$7="x",IF(F18=0,0,N18/E18),"")) -> 0 | E18: =+B18*(-B$5+100%) -> 0 | F18: =IF(B18=0,0,E18-H18) -> 0 | G18: =VLOOKUP(A18,Custo!A:B,2,0) -> 25.763717 | H18: =(VLOOKUP(A18,Peso!$A$10:$B$148,2,0))*($B$6/1000) -> 1.44 | I18: =IF($I$7="X",AE18,0%) -> 0.05 | J18: =+B18*I18 -> 0 | L18: =+B18*K18 -> 0 | M18: =+G18+H18+J18+L18 -> 27.203717 | N18: =+E18-M18 -> -27.203717 | O18: =IF(ISERROR((N18/P18)*1000),"",(N18/P18)*1000) | Q18: =VLOOKUP(A18,'MVA-IPI'!A:AD,30,FALSE) -> 0 | R18: =IF($B$4="AM",0,IF($B$4="AP",0,IF($B$4="RR",0,(B18*Q18)))) -> 0 | S18: =IF($B$4="AP",(B18/0.88*$S$8),IF(T18=0%,0,IF($B$4="AM",(B18/0.88*$S$8),IF(T18=0%,0,IF($B$4="RR",(B18/0.88*$S$8),IF(T18=0%,0,B18*$S$8)))))) -> 0 | T18: =IF($C$4="GRUPO 1",VLOOKUP(A18,'MVA-grupos'!$A$9:$B$128,2,FALSE),IF($C$4="GRUPO 2",VLOOKUP(A18,'MVA-grupos'!$A$9:$D$128,4,FALSE),IF($C$4="GRUPO 3",VLOOKUP(A18,'MVA-grupos'!$A$10:$F$128,6,FALSE),IF($C$4="Grupo 4",VLOOKUP(A18,'MVA-grupos'!$A$9:$H$128,8,FALSE))))) -> 0 | U18: =IF(T18=0%,0,(B18+R18)*T18+(B18+R18)) -> 0 | V18: =(U18*$V$8)-S18 -> 0 | X18: =A18 -> BRAZIMIL ECONÔMICA 12L BALDE BRANCO NEVE | Y18: =+C18 -> 0 | Z18: =IF(ISERROR(Y18*N18),"",Y18*N18) -> 0 | AA18: =IF(ISERROR(IF(E$7="X",Y18*E18,Y18*F18)),"",IF(E$7="X",Y18*E18,Y18*F18)) -> 0 | AB18: =IF(ISERROR(Z18/AA18),"",Z18/AA18) | AE18: 0.05 | AF18: =+'Frete_Regiao-Impostos'!A39 -> 0 | AG18: =+'Frete_Regiao-Impostos'!B39 -> 0 | AH18: =+'Frete_Regiao-Impostos'!C39 -> 0 | AI18: =+'Frete_Regiao-Impostos'!D39 -> 0 | AP18: =Peso!B18 -> 14.4
A19: BRAZIMIL ECONÔMICA 15L BALDE BRANCO NEVE | B19: 58 | D19: =IF($F$7="x",IF(F19=0,0,N19/F19),IF($E$7="x",IF(F19=0,0,N19/E19),"")) -> 0.30387761 | E19: =+B19*(-B$5+100%) -> 53.94 | F19: =IF(B19=0,0,E19-H19) -> 52.07 | G19: =VLOOKUP(A19,Custo!A:B,2,0) -> 32.778842 | H19: =(VLOOKUP(A19,Peso!$A$10:$B$148,2,0))*($B$6/1000) -> 1.87 | I19: =IF($I$7="X",AE19,0%) -> 0.05 | J19: =+B19*I19 -> 2.9 | K19: =IF($B$2="X",$C$2,0) -> 0 | L19: =+B19*K19 -> 0 | M19: =+G19+H19+J19+L19 -> 37.548842 | N19: =+E19-M19 -> 16.391158 | O19: =IF(ISERROR((N19/P19)*1000),"",(N19/P19)*1000) | Q19: =VLOOKUP(A19,'MVA-IPI'!A:AD,30,FALSE) -> 0 | R19: =IF($B$4="AM",0,IF($B$4="AP",0,IF($B$4="RR",0,(B19*Q19)))) -> 0 | S19: =IF($B$4="AP",(B19/0.88*$S$8),IF(T19=0%,0,IF($B$4="AM",(B19/0.88*$S$8),IF(T19=0%,0,IF($B$4="RR",(B19/0.88*$S$8),IF(T19=0%,0,B19*$S$8)))))) -> 0 | T19: =IF($C$4="GRUPO 1",VLOOKUP(A19,'MVA-grupos'!$A$9:$B$128,2,FALSE),IF($C$4="GRUPO 2",VLOOKUP(A19,'MVA-grupos'!$A$9:$D$128,4,FALSE),IF($C$4="GRUPO 3",VLOOKUP(A19,'MVA-grupos'!$A$10:$F$128,6,FALSE),IF($C$4="Grupo 4",VLOOKUP(A19,'MVA-grupos'!$A$9:$H$128,8,FALSE))))) -> 0 | U19: =IF(T19=0%,0,(B19+R19)*T19+(B19+R19)) -> 0 | V19: =(U19*$V$8)-S19 -> 0 | X19: =A19 -> BRAZIMIL ECONÔMICA 15L BALDE BRANCO NEVE | Y19: =+C19 -> 0 | Z19: =IF(ISERROR(Y19*N19),"",Y19*N19) -> 0 | AA19: =IF(ISERROR(IF(E$7="X",Y19*E19,Y19*F19)),"",IF(E$7="X",Y19*E19,Y19*F19)) -> 0 | AB19: =IF(ISERROR(Z19/AA19),"",Z19/AA19) | AE19: 0.05 | AF19: =+'Frete_Regiao-Impostos'!A10 -> 0 | AG19: =+'Frete_Regiao-Impostos'!B10 -> 0 | AH19: =+'Frete_Regiao-Impostos'!C10 -> 0 | AI19: =+'Frete_Regiao-Impostos'!D10 -> 0 | AP19: =Peso!B19 -> 18.7
A20: BRAZIMIL ECONÔMICA 15L BALDE COR | B20: 69.9 | D20: =IF($F$7="x",IF(F20=0,0,N20/F20),IF($E$7="x",IF(F20=0,0,N20/E20),"")) -> 0.4675206 | E20: =+B20*(-B$5+100%) -> 65.007 | F20: =IF(B20=0,0,E20-H20) -> 63.307 | G20: =VLOOKUP(A20,Custo!A:B,2,0) -> 29.419889 | H20: =(VLOOKUP(A20,Peso!$A$10:$B$148,2,0))*($B$6/1000) -> 1.7 | I20: =IF($I$7="X",AE20,0%) -> 0.05 | J20: =+B20*I20 -> 3.495 | K20: =IF($B$2="X",$C$2,0) -> 0 | L20: =+B20*K20 -> 0 | M20: =+G20+H20+J20+L20 -> 34.614889 | N20: =+E20-M20 -> 30.392111 | O20: =IF(ISERROR((N20/P20)*1000),"",(N20/P20)*1000) | Q20: =VLOOKUP(A20,'MVA-IPI'!A:AD,30,FALSE) -> 0 | R20: =IF($B$4="AM",0,IF($B$4="AP",0,IF($B$4="RR",0,(B20*Q20)))) -> 0 | S20: =IF($B$4="AP",(B20/0.88*$S$8),IF(T20=0%,0,IF($B$4="AM",(B20/0.88*$S$8),IF(T20=0%,0,IF($B$4="RR",(B20/0.88*$S$8),IF(T20=0%,0,B20*$S$8)))))) -> 0 | T20: =IF($C$4="GRUPO 1",VLOOKUP(A20,'MVA-grupos'!$A$9:$B$128,2,FALSE),IF($C$4="GRUPO 2",VLOOKUP(A20,'MVA-grupos'!$A$9:$D$128,4,FALSE),IF($C$4="GRUPO 3",VLOOKUP(A20,'MVA-grupos'!$A$10:$F$128,6,FALSE),IF($C$4="Grupo 4",VLOOKUP(A20,'MVA-grupos'!$A$9:$H$128,8,FALSE))))) -> 0 | U20: =IF(T20=0%,0,(B20+R20)*T20+(B20+R20)) -> 0 | V20: =(U20*$V$8)-S20 -> 0 | X20: =A20 -> BRAZIMIL ECONÔMICA 15L BALDE COR | Y20: =+C20 -> 0 | Z20: =IF(ISERROR(Y20*N20),"",Y20*N20) -> 0 | AA20: =IF(ISERROR(IF(E$7="X",Y20*E20,Y20*F20)),"",IF(E$7="X",Y20*E20,Y20*F20)) -> 0 | AB20: =IF(ISERROR(Z20/AA20),"",Z20/AA20) | AE20: 0.05 | AF20: =+'Frete_Regiao-Impostos'!A11 -> 0 | AG20: =+'Frete_Regiao-Impostos'!B11 -> 0 | AH20: =+'Frete_Regiao-Impostos'!C11 -> 0 | AI20: =+'Frete_Regiao-Impostos'!D11 -> 0 | AP20: =Peso!B20 -> 17
A21: BRAZIMIL EXTERNA 3,0L | D21: =AB21 | X21: =A21 -> BRAZIMIL EXTERNA 3,0L | Z21: =SUM(Z22:Z23) -> 0 | AA21: =SUM(AA22:AA23) -> 0 | AB21: =IF(ISERROR(Z21/AA21),"",Z21/AA21) | AC21: 0.25 | AF21: =+'Frete_Regiao-Impostos'!A12 -> 0 | AG21: =+'Frete_Regiao-Impostos'!B12 -> 0 | AH21: =+'Frete_Regiao-Impostos'!C12 -> 0 | AI21: =+'Frete_Regiao-Impostos'!D12 -> 0 | AP21: =Peso!B21 -> 0
A22: BRAZIMIL EXTERNA 3,0L BALDE BRANCO NEVE | B22: 26 | D22: =IF($F$7="x",IF(F22=0,0,N22/F22),IF($E$7="x",IF(F22=0,0,N22/E22),"")) -> 0.46348735 | E22: =+B22*(-B$5+100%) -> 24.18 | F22: =IF(B22=0,0,E22-H22) -> 23.76 | G22: =VLOOKUP(A22,Custo!A:B,2,0) -> 11.252876 | H22: =(VLOOKUP(A22,Peso!$A$10:$B$148,2,0))*($B$6/1000) -> 0.42 | I22: =IF($I$7="X",AE22,0%) -> 0.05 | J22: =+B22*I22 -> 1.3 | K22: =IF($B$2="X",$C$2,0) -> 0 | L22: =+B22*K22 -> 0 | M22: =+G22+H22+J22+L22 -> 12.972876 | N22: =+E22-M22 -> 11.207124 | O22: =IF(ISERROR((N22/P22)*1000),"",(N22/P22)*1000) | Q22: =VLOOKUP(A22,'MVA-IPI'!A:AD,30,FALSE) -> 0 | R22: =IF($B$4="AM",0,IF($B$4="AP",0,IF($B$4="RR",0,(B22*Q22)))) -> 0 | S22: =IF($B$4="AP",(B22/0.88*$S$8),IF(T22=0%,0,IF($B$4="AM",(B22/0.88*$S$8),IF(T22=0%,0,IF($B$4="RR",(B22/0.88*$S$8),IF(T22=0%,0,B22*$S$8)))))) -> 0 | T22: =IF($C$4="GRUPO 1",VLOOKUP(A22,'MVA-grupos'!$A$9:$B$128,2,FALSE),IF($C$4="GRUPO 2",VLOOKUP(A22,'MVA-grupos'!$A$9:$D$128,4,FALSE),IF($C$4="GRUPO 3",VLOOKUP(A22,'MVA-grupos'!$A$10:$F$128,6,FALSE),IF($C$4="Grupo 4",VLOOKUP(A22,'MVA-grupos'!$A$9:$H$128,8,FALSE))))) -> 0 | U22: =IF(T22=0%,0,(B22+R22)*T22+(B22+R22)) -> 0 | V22: =(U22*$V$8)-S22 -> 0 | X22: =A22 -> BRAZIMIL EXTERNA 3,0L BALDE BRANCO NEVE | Y22: =+C22 -> 0 | Z22: =IF(ISERROR(Y22*N22),"",Y22*N22) -> 0 | AA22: =IF(ISERROR(IF(E$7="X",Y22*E22,Y22*F22)),"",IF(E$7="X",Y22*E22,Y22*F22)) -> 0 | AB22: =IF(ISERROR(Z22/AA22),"",Z22/AA22) | AE22: 0.05 | AF22: =+'Frete_Regiao-Impostos'!A13 -> 0 | AG22: =+'Frete_Regiao-Impostos'!B13 -> 0 | AH22: =+'Frete_Regiao-Impostos'!C13 -> 0 | AI22: =+'Frete_Regiao-Impostos'!D13 -> 0 | AP22: =Peso!B22 -> 4.2
A23: BRAZIMIL EXTERNA 3,0L BALDE COR | B23: 24.2 | D23: =IF($F$7="x",IF(F23=0,0,N23/F23),IF($E$7="x",IF(F23=0,0,N23/E23),"")) -> 0.51154588 | E23: =+B23*(-B$5+100%) -> 22.506 | F23: =IF(B23=0,0,E23-H23) -> 22.116 | G23: =VLOOKUP(A23,Custo!A:B,2,0) -> 9.3931485 | H23: =(VLOOKUP(A23,Peso!$A$10:$B$148,2,0))*($B$6/1000) -> 0.39 | I23: =IF($I$7="X",AE23,0%) -> 0.05 | J23: =+B23*I23 -> 1.21 | K23: =IF($B$2="X",$C$2,0) -> 0 | L23: =+B23*K23 -> 0 | M23: =+G23+H23+J23+L23 -> 10.993148 | N23: =+E23-M23 -> 11.512852 | O23: =IF(ISERROR((N23/P23)*1000),"",(N23/P23)*1000) | Q23: =VLOOKUP(A23,'MVA-IPI'!A:AD,30,FALSE) -> 0 | R23: =IF($B$4="AM",0,IF($B$4="AP",0,IF($B$4="RR",0,(B23*Q23)))) -> 0 | S23: =IF($B$4="AP",(B23/0.88*$S$8),IF(T23=0%,0,IF($B$4="AM",(B23/0.88*$S$8),IF(T23=0%,0,IF($B$4="RR",(B23/0.88*$S$8),IF(T23=0%,0,B23*$S$8)))))) -> 0 | T23: =IF($C$4="GRUPO 1",VLOOKUP(A23,'MVA-grupos'!$A$9:$B$128,2,FALSE),IF($C$4="GRUPO 2",VLOOKUP(A23,'MVA-grupos'!$A$9:$D$128,4,FALSE),IF($C$4="GRUPO 3",VLOOKUP(A23,'MVA-grupos'!$A$10:$F$128,6,FALSE),IF($C$4="Grupo 4",VLOOKUP(A23,'MVA-grupos'!$A$9:$H$128,8,FALSE))))) -> 0 | U23: =IF(T23=0%,0,(B23+R23)*T23+(B23+R23)) -> 0 | V23: =(U23*$V$8)-S23 -> 0 | X23: =A23 -> BRAZIMIL EXTERNA 3,0L BALDE COR | Y23: =+C23 -> 0 | Z23: =IF(ISERROR(Y23*N23),"",Y23*N23) -> 0 | AA23: =IF(ISERROR(IF(E$7="X",Y23*E23,Y23*F23)),"",IF(E$7="X",Y23*E23,Y23*F23)) -> 0 | AB23: =IF(ISERROR(Z23/AA23),"",Z23/AA23) | AE23: 0.05 | AF23: =+'Frete_Regiao-Impostos'!A14 -> 0 | AG23: =+'Frete_Regiao-Impostos'!B14 -> 0 | AH23: =+'Frete_Regiao-Impostos'!C14 -> 0 | AI23: =+'Frete_Regiao-Impostos'!D14 -> 0 | AP23: =Peso!B23 -> 3.9
A24: BRAZIMIL EXTERNA 15L | D24: =AB24 | X24: =A24 -> BRAZIMIL EXTERNA 15L | Z24: =SUM(Z25:Z26) -> 0 | AA24: =SUM(AA25:AA26) -> 0 | AB24: =IF(ISERROR(Z24/AA24),"",Z24/AA24) | AC24: 0.25 | AF24: =+'Frete_Regiao-Impostos'!A15 -> 0 | AG24: =+'Frete_Regiao-Impostos'!B15 -> 0 | AH24: =+'Frete_Regiao-Impostos'!C15 -> 0 | AI24: =+'Frete_Regiao-Impostos'!D15 -> 0 | AP24: =Peso!B24 -> 0
A25: BRAZIMIL EXTERNA 15L BALDE BRANCO NEVE | B25: 94 | D25: =IF($F$7="x",IF(F25=0,0,N25/F25),IF($E$7="x",IF(F25=0,0,N25/E25),"")) -> 0.30961014 | E25: =+B25*(-B$5+100%) -> 87.42 | F25: =IF(B25=0,0,E25-H25) -> 85.52 | G25: =VLOOKUP(A25,Custo!A:B,2,0) -> 53.753882 | H25: =(VLOOKUP(A25,Peso!$A$10:$B$148,2,0))*($B$6/1000) -> 1.9 | I25: =IF($I$7="X",AE25,0%) -> 0.05 | J25: =+B25*I25 -> 4.7 | K25: =IF($B$2="X",$C$2,0) -> 0 | L25: =+B25*K25 -> 0 | M25: =+G25+H25+J25+L25 -> 60.353882 | N25: =+E25-M25 -> 27.066118 | O25: =IF(ISERROR((N25/P25)*1000),"",(N25/P25)*1000) | Q25: =VLOOKUP(A25,'MVA-IPI'!A:AD,30,FALSE) -> 0 | R25: =IF($B$4="AM",0,IF($B$4="AP",0,IF($B$4="RR",0,(B25*Q25)))) -> 0 | S25: =IF($B$4="AP",(B25/0.88*$S$8),IF(T25=0%,0,IF($B$4="AM",(B25/0.88*$S$8),IF(T25=0%,0,IF($B$4="RR",(B25/0.88*$S$8),IF(T25=0%,0,B25*$S$8)))))) -> 0 | T25: =IF($C$4="GRUPO 1",VLOOKUP(A25,'MVA-grupos'!$A$9:$B$128,2,FALSE),IF($C$4="GRUPO 2",VLOOKUP(A25,'MVA-grupos'!$A$9:$D$128,4,FALSE),IF($C$4="GRUPO 3",VLOOKUP(A25,'MVA-grupos'!$A$10:$F$128,6,FALSE),IF($C$4="Grupo 4",VLOOKUP(A25,'MVA-grupos'!$A$9:$H$128,8,FALSE))))) -> 0 | U25: =IF(T25=0%,0,(B25+R25)*T25+(B25+R25)) -> 0 | V25: =(U25*$V$8)-S25 -> 0 | X25: =A25 -> BRAZIMIL EXTERNA 15L BALDE BRANCO NEVE | Y25: =+C25 -> 0 | Z25: =IF(ISERROR(Y25*N25),"",Y25*N25) -> 0 | AA25: =IF(ISERROR(IF(E$7="X",Y25*E25,Y25*F25)),"",IF(E$7="X",Y25*E25,Y25*F25)) -> 0 | AB25: =IF(ISERROR(Z25/AA25),"",Z25/AA25) | AE25: 0.05 | AF25: =+'Frete_Regiao-Impostos'!A16 -> 0 | AG25: =+'Frete_Regiao-Impostos'!B16 -> 0 | AH25: =+'Frete_Regiao-Impostos'!C16 -> 0 | AI25: =+'Frete_Regiao-Impostos'!D16 -> 0 | AP25: =Peso!B25 -> 19
A26: BRAZIMIL EXTERNA 15L BALDE COR | B26: 90.11 | D26: =IF($F$7="x",IF(F26=0,0,N26/F26),IF($E$7="x",IF(F26=0,0,N26/E26),"")) -> 0.42543208 | E26: =+B26*(-B$5+100%) -> 83.8023 | F26: =IF(B26=0,0,E26-H26) -> 82.1023 | G26: =VLOOKUP(A26,Custo!A:B,2,0) -> 41.944613 | H26: =(VLOOKUP(A26,Peso!$A$10:$B$148,2,0))*($B$6/1000) -> 1.7 | I26: =IF($I$7="X",AE26,0%) -> 0.05 | J26: =+B26*I26 -> 4.5055 | K26: =IF($B$2="X",$C$2,0) -> 0 | L26: =+B26*K26 -> 0 | M26: =+G26+H26+J26+L26 -> 48.150113 | N26: =+E26-M26 -> 35.652187 | O26: =IF(ISERROR((N26/P26)*1000),"",(N26/P26)*1000) | Q26: =VLOOKUP(A26,'MVA-IPI'!A:AD,30,FALSE) -> 0 | R26: =IF($B$4="AM",0,IF($B$4="AP",0,IF($B$4="RR",0,(B26*Q26)))) -> 0 | S26: =IF($B$4="AP",(B26/0.88*$S$8),IF(T26=0%,0,IF($B$4="AM",(B26/0.88*$S$8),IF(T26=0%,0,IF($B$4="RR",(B26/0.88*$S$8),IF(T26=0%,0,B26*$S$8)))))) -> 0 | T26: =IF($C$4="GRUPO 1",VLOOKUP(A26,'MVA-grupos'!$A$9:$B$128,2,FALSE),IF($C$4="GRUPO 2",VLOOKUP(A26,'MVA-grupos'!$A$9:$D$128,4,FALSE),IF($C$4="GRUPO 3",VLOOKUP(A26,'MVA-grupos'!$A$10:$F$128,6,FALSE),IF($C$4="Grupo 4",VLOOKUP(A26,'MVA-grupos'!$A$9:$H$128,8,FALSE))))) -> 0 | U26: =IF(T26=0%,0,(B26+R26)*T26+(B26+R26)) -> 0 | V26: =(U26*$V$8)-S26 -> 0 | X26: =A26 -> BRAZIMIL EXTERNA 15L BALDE COR | Y26: =+C26 -> 0 | Z26: =IF(ISERROR(Y26*N26),"",Y26*N26) -> 0 | AA26: =IF(ISERROR(IF(E$7="X",Y26*E26,Y26*F26)),"",IF(E$7="X",Y26*E26,Y26*F26)) -> 0 | AB26: =IF(ISERROR(Z26/AA26),"",Z26/AA26) | AE26: 0.05 | AF26: =+'Frete_Regiao-Impostos'!A17 -> 0 | AG26: =+'Frete_Regiao-Impostos'!B17 -> 0 | AH26: =+'Frete_Regiao-Impostos'!C17 -> 0 | AI26: =+'Frete_Regiao-Impostos'!D17 -> 0 | AP26: =Peso!B26 -> 17
A27: BRAZIMIL SEMI BRILHO 3,0L | D27: =AB27 | X27: =A27 -> BRAZIMIL SEMI BRILHO 3,0L | Z27: =SUM(Z28:Z29) -> 0 | AA27: =SUM(AA28:AA29) -> 0 | AB27: =IF(ISERROR(Z27/AA27),"",Z27/AA27) | AC27: 0.25 | AF27: =+'Frete_Regiao-Impostos'!A18 -> 0 | AG27: =+'Frete_Regiao-Impostos'!B18 -> 0 | AH27: =+'Frete_Regiao-Impostos'!C18 -> 0 | AI27: =+'Frete_Regiao-Impostos'!D18 -> 0 | AP27: =Peso!B27 -> 0
A28: BRAZIMIL SEMI BRILHO 3,0L BALDE BRANCO NEVE | B28: 43 | D28: =IF($F$7="x",IF(F28=0,0,N28/F28),IF($E$7="x",IF(F28=0,0,N28/E28),"")) -> 0.64685165 | E28: =+B28*(-B$5+100%) -> 39.99 | F28: =IF(B28=0,0,E28-H28) -> 39.63 | G28: =VLOOKUP(A28,Custo!A:B,2,0) -> 11.612403 | H28: =(VLOOKUP(A28,Peso!$A$10:$B$148,2,0))*($B$6/1000) -> 0.36 | I28: =IF($I$7="X",AE28,0%) -> 0.05 | J28: =+B28*I28 -> 2.15 | K28: =IF($B$2="X",$C$2,0) -> 0 | L28: =+B28*K28 -> 0 | M28: =+G28+H28+J28+L28 -> 14.122403 | N28: =+E28-M28 -> 25.867597 | O28: =IF(ISERROR((N28/P28)*1000),"",(N28/P28)*1000) | Q28: =VLOOKUP(A28,'MVA-IPI'!A:AD,30,FALSE) -> 0 | R28: =IF($B$4="AM",0,IF($B$4="AP",0,IF($B$4="RR",0,(B28*Q28)))) -> 0 | S28: =IF($B$4="AP",(B28/0.88*$S$8),IF(T28=0%,0,IF($B$4="AM",(B28/0.88*$S$8),IF(T28=0%,0,IF($B$4="RR",(B28/0.88*$S$8),IF(T28=0%,0,B28*$S$8)))))) -> 0 | T28: =IF($C$4="GRUPO 1",VLOOKUP(A28,'MVA-grupos'!$A$9:$B$128,2,FALSE),IF($C$4="GRUPO 2",VLOOKUP(A28,'MVA-grupos'!$A$9:$D$128,4,FALSE),IF($C$4="GRUPO 3",VLOOKUP(A28,'MVA-grupos'!$A$10:$F$128,6,FALSE),IF($C$4="Grupo 4",VLOOKUP(A28,'MVA-grupos'!$A$9:$H$128,8,FALSE))))) -> 0 | U28: =IF(T28=0%,0,(B28+R28)*T28+(B28+R28)) -> 0 | V28: =(U28*$V$8)-S28 -> 0 | X28: =A28 -> BRAZIMIL SEMI BRILHO 3,0L BALDE BRANCO NEVE | Y28: =+C28 -> 0 | Z28: =IF(ISERROR(Y28*N28),"",Y28*N28) -> 0 | AA28: =IF(ISERROR(IF(E$7="X",Y28*E28,Y28*F28)),"",IF(E$7="X",Y28*E28,Y28*F28)) -> 0 | AB28: =IF(ISERROR(Z28/AA28),"",Z28/AA28) | AE28: 0.05 | AF28: =+'Frete_Regiao-Impostos'!A19 -> 0 | AG28: =+'Frete_Regiao-Impostos'!B19 -> 0 | AH28: =+'Frete_Regiao-Impostos'!C19 -> 0 | AI28: =+'Frete_Regiao-Impostos'!D19 -> 0 | AP28: =Peso!B28 -> 3.6
A29: BRAZIMIL SEMI BRILHO 3,0L BALDE COR | B29: 35 | D29: =IF($F$7="x",IF(F29=0,0,N29/F29),IF($E$7="x",IF(F29=0,0,N29/E29),"")) -> 0.47050906 | E29: =+B29*(-B$5+100%) -> 32.55 | F29: =IF(B29=0,0,E29-H29) -> 32.2 | G29: =VLOOKUP(A29,Custo!A:B,2,0) -> 15.13493 | H29: =(VLOOKUP(A29,Peso!$A$10:$B$148,2,0))*($B$6/1000) -> 0.35 | I29: =IF($I$7="X",AE29,0%) -> 0.05 | J29: =+B29*I29 -> 1.75 | K29: =IF($B$2="X",$C$2,0) -> 0 | L29: =+B29*K29 -> 0 | M29: =+G29+H29+J29+L29 -> 17.23493 | N29: =+E29-M29 -> 15.31507 | O29: =IF(ISERROR((N29/P29)*1000),"",(N29/P29)*1000) | Q29: =VLOOKUP(A29,'MVA-IPI'!A:AD,30,FALSE) -> 0 | R29: =IF($B$4="AM",0,IF($B$4="AP",0,IF($B$4="RR",0,(B29*Q29)))) -> 0 | S29: =IF($B$4="AP",(B29/0.88*$S$8),IF(T29=0%,0,IF($B$4="AM",(B29/0.88*$S$8),IF(T29=0%,0,IF($B$4="RR",(B29/0.88*$S$8),IF(T29=0%,0,B29*$S$8)))))) -> 0 | T29: =IF($C$4="GRUPO 1",VLOOKUP(A29,'MVA-grupos'!$A$9:$B$128,2,FALSE),IF($C$4="GRUPO 2",VLOOKUP(A29,'MVA-grupos'!$A$9:$D$128,4,FALSE),IF($C$4="GRUPO 3",VLOOKUP(A29,'MVA-grupos'!$A$10:$F$128,6,FALSE),IF($C$4="Grupo 4",VLOOKUP(A29,'MVA-grupos'!$A$9:$H$128,8,FALSE))))) -> 0 | U29: =IF(T29=0%,0,(B29+R29)*T29+(B29+R29)) -> 0 | V29: =(U29*$V$8)-S29 -> 0 | X29: =A29 -> BRAZIMIL SEMI BRILHO 3,0L BALDE COR | Y29: =+C29 -> 0 | Z29: =IF(ISERROR(Y29*N29),"",Y29*N29) -> 0 | AA29: =IF(ISERROR(IF(E$7="X",Y29*E29,Y29*F29)),"",IF(E$7="X",Y29*E29,Y29*F29)) -> 0 | AB29: =IF(ISERROR(Z29/AA29),"",Z29/AA29) | AE29: 0.05 | AF29: =+'Frete_Regiao-Impostos'!A20 -> 0 | AG29: =+'Frete_Regiao-Impostos'!B20 -> 0 | AH29: =+'Frete_Regiao-Impostos'!C20 -> 0 | AI29: =+'Frete_Regiao-Impostos'!D20 -> 0 | AP29: =Peso!B29 -> 3.5
A30: BRAZIMIL SEMI BRILHO 15L | D30: =AB30 | X30: =A30 -> BRAZIMIL SEMI BRILHO 15L | Z30: =SUM(Z31:Z32) -> 0 | AA30: =SUM(AA31:AA32) -> 0 | AB30: =IF(ISERROR(Z30/AA30),"",Z30/AA30) | AC30: 0.25 | AF30: =+'Frete_Regiao-Impostos'!A21 -> 0 | AG30: =+'Frete_Regiao-Impostos'!B21 -> 0 | AH30: =+'Frete_Regiao-Impostos'!C21 -> 0 | AI30: =+'Frete_Regiao-Impostos'!D21 -> 0 | AP30: =Peso!B30 -> 0
A31: BRAZIMIL SEMI BRILHO 15L BALDE BRANCO NEVE | B31: 170 | D31: =IF($F$7="x",IF(F31=0,0,N31/F31),IF($E$7="x",IF(F31=0,0,N31/E31),"")) -> 0.54095942 | E31: =+B31*(-B$5+100%) -> 158.1 | F31: =IF(B31=0,0,E31-H31) -> 156.59 | G31: =VLOOKUP(A31,Custo!A:B,2,0) -> 54.064315 | H31: =(VLOOKUP(A31,Peso!$A$10:$B$148,2,0))*($B$6/1000) -> 1.51 | I31: =IF($I$7="X",AE31,0%) -> 0.05 | J31: =+B31*I31 -> 8.5 | K31: 0.05 | L31: =+B31*K31 -> 8.5 | M31: =+G31+H31+J31+L31 -> 72.574315 | N31: =+E31-M31 -> 85.525685 | O31: =IF(ISERROR((N31/P31)*1000),"",(N31/P31)*1000) | Q31: =VLOOKUP(A31,'MVA-IPI'!A:AD,30,FALSE) -> 0 | R31: =IF($B$4="AM",0,IF($B$4="AP",0,IF($B$4="RR",0,(B31*Q31)))) -> 0 | S31: =IF($B$4="AP",(B31/0.88*$S$8),IF(T31=0%,0,IF($B$4="AM",(B31/0.88*$S$8),IF(T31=0%,0,IF($B$4="RR",(B31/0.88*$S$8),IF(T31=0%,0,B31*$S$8)))))) -> 0 | T31: =IF($C$4="GRUPO 1",VLOOKUP(A31,'MVA-grupos'!$A$9:$B$128,2,FALSE),IF($C$4="GRUPO 2",VLOOKUP(A31,'MVA-grupos'!$A$9:$D$128,4,FALSE),IF($C$4="GRUPO 3",VLOOKUP(A31,'MVA-grupos'!$A$10:$F$128,6,FALSE),IF($C$4="Grupo 4",VLOOKUP(A31,'MVA-grupos'!$A$9:$H$128,8,FALSE))))) -> 0 | U31: =IF(T31=0%,0,(B31+R31)*T31+(B31+R31)) -> 0 | V31: =(U31*$V$8)-S31 -> 0 | X31: =A31 -> BRAZIMIL SEMI BRILHO 15L BALDE BRANCO NEVE | Y31: =+C31 -> 0 | Z31: =IF(ISERROR(Y31*N31),"",Y31*N31) -> 0 | AA31: =IF(ISERROR(IF(E$7="X",Y31*E31,Y31*F31)),"",IF(E$7="X",Y31*E31,Y31*F31)) -> 0 | AB31: =IF(ISERROR(Z31/AA31),"",Z31/AA31) | AE31: 0.05 | AF31: =+'Frete_Regiao-Impostos'!A22 -> 0 | AG31: =+'Frete_Regiao-Impostos'!B22 -> 0 | AH31: =+'Frete_Regiao-Impostos'!C22 -> 0 | AI31: =+'Frete_Regiao-Impostos'!D22 -> 0 | AP31: =Peso!B32 -> 15.1
A32: BRAZIMIL SEMI BRILHO 15L BALDE COR | B32: 170 | D32: =IF($F$7="x",IF(F32=0,0,N32/F32),IF($E$7="x",IF(F32=0,0,N32/E32),"")) -> 0.4666107 | E32: =+B32*(-B$5+100%) -> 158.1 | F32: =IF(B32=0,0,E32-H32) -> 156.59 | G32: =VLOOKUP(A32,Custo!A:B,2,0) -> 74.318848 | H32: =(VLOOKUP(A32,Peso!$A$10:$B$148,2,0))*($B$6/1000) -> 1.51 | I32: =IF($I$7="X",AE32,0%) -> 0.05 | J32: =+B32*I32 -> 8.5 | K32: =IF($B$2="X",$C$2,0) -> 0 | L32: =+B32*K32 -> 0 | M32: =+G32+H32+J32+L32 -> 84.328848 | N32: =+E32-M32 -> 73.771152 | O32: =IF(ISERROR((N32/P32)*1000),"",(N32/P32)*1000) | Q32: =VLOOKUP(A32,'MVA-IPI'!A:AD,30,FALSE) -> 0 | R32: =IF($B$4="AM",0,IF($B$4="AP",0,IF($B$4="RR",0,(B32*Q32)))) -> 0 | S32: =IF($B$4="AP",(B32/0.88*$S$8),IF(T32=0%,0,IF($B$4="AM",(B32/0.88*$S$8),IF(T32=0%,0,IF($B$4="RR",(B32/0.88*$S$8),IF(T32=0%,0,B32*$S$8)))))) -> 0 | T32: =IF($C$4="GRUPO 1",VLOOKUP(A32,'MVA-grupos'!$A$9:$B$128,2,FALSE),IF($C$4="GRUPO 2",VLOOKUP(A32,'MVA-grupos'!$A$9:$D$128,4,FALSE),IF($C$4="GRUPO 3",VLOOKUP(A32,'MVA-grupos'!$A$10:$F$128,6,FALSE),IF($C$4="Grupo 4",VLOOKUP(A32,'MVA-grupos'!$A$9:$H$128,8,FALSE))))) -> 0 | U32: =IF(T32=0%,0,(B32+R32)*T32+(B32+R32)) -> 0 | V32: =(U32*$V$8)-S32 -> 0 | X32: =A32 -> BRAZIMIL SEMI BRILHO 15L BALDE COR | Y32: =+C32 -> 0 | Z32: =IF(ISERROR(Y32*N32),"",Y32*N32) -> 0 | AA32: =IF(ISERROR(IF(E$7="X",Y32*E32,Y32*F32)),"",IF(E$7="X",Y32*E32,Y32*F32)) -> 0 | AB32: =IF(ISERROR(Z32/AA32),"",Z32/AA32) | AE32: 0.05 | AF32: =+'Frete_Regiao-Impostos'!A23 -> 0 | AG32: =+'Frete_Regiao-Impostos'!B23 -> 0 | AH32: =+'Frete_Regiao-Impostos'!C23 -> 0 | AI32: =+'Frete_Regiao-Impostos'!D23 -> 0 | AP32: =Peso!B33 -> 15.1
A33: BRAZIMIL TINTA PISO 3,0L | D33: =AB33 | X33: =A33 -> BRAZIMIL TINTA PISO 3,0L | Z33: =SUM(Z34:Z35) -> 0 | AA33: =SUM(AA34:AA35) -> 0 | AB33: =IF(ISERROR(Z33/AA33),"",Z33/AA33) | AC33: 0.25 | AF33: =+'Frete_Regiao-Impostos'!A24 -> 0 | AG33: =+'Frete_Regiao-Impostos'!B24 -> 0 | AH33: =+'Frete_Regiao-Impostos'!C24 -> 0 | AI33: =+'Frete_Regiao-Impostos'!D24 -> 0 | AP33: =Peso!B34 -> 0
A34: BRAZIMIL TINTA PISO 3,0L BALDE BRANCO NEVE | B34: 30 | D34: =IF($F$7="x",IF(F34=0,0,N34/F34),IF($E$7="x",IF(F34=0,0,N34/E34),"")) -> 0.26174171 | E34: =+B34*(-B$5+100%) -> 27.9 | F34: =IF(B34=0,0,E34-H34) -> 27.53 | G34: =VLOOKUP(A34,Custo!A:B,2,0) -> 18.727406 | H34: =(VLOOKUP(A34,Peso!$A$10:$B$148,2,0))*($B$6/1000) -> 0.37 | I34: =IF($I$7="X",AE34,0%) -> 0.05 | J34: =+B34*I34 -> 1.5 | K34: =IF($B$2="X",$C$2,0) -> 0 | L34: =+B34*K34 -> 0 | M34: =+G34+H34+J34+L34 -> 20.597406 | N34: =+E34-M34 -> 7.3025937 | O34: =IF(ISERROR((N34/P34)*1000),"",(N34/P34)*1000) | Q34: =VLOOKUP(A34,'MVA-IPI'!A:AD,30,FALSE) -> 0 | R34: =IF($B$4="AM",0,IF($B$4="AP",0,IF($B$4="RR",0,(B34*Q34)))) -> 0 | S34: =IF($B$4="AP",(B34/0.88*$S$8),IF(T34=0%,0,IF($B$4="AM",(B34/0.88*$S$8),IF(T34=0%,0,IF($B$4="RR",(B34/0.88*$S$8),IF(T34=0%,0,B34*$S$8)))))) -> 0 | T34: =IF($C$4="GRUPO 1",VLOOKUP(A34,'MVA-grupos'!$A$9:$B$128,2,FALSE),IF($C$4="GRUPO 2",VLOOKUP(A34,'MVA-grupos'!$A$9:$D$128,4,FALSE),IF($C$4="GRUPO 3",VLOOKUP(A34,'MVA-grupos'!$A$10:$F$128,6,FALSE),IF($C$4="Grupo 4",VLOOKUP(A34,'MVA-grupos'!$A$9:$H$128,8,FALSE))))) -> 0 | U34: =IF(T34=0%,0,(B34+R34)*T34+(B34+R34)) -> 0 | V34: =(U34*$V$8)-S34 -> 0 | X34: =A34 -> BRAZIMIL TINTA PISO 3,0L BALDE BRANCO NEVE | Y34: =+C34 -> 0 | Z34: =IF(ISERROR(Y34*N34),"",Y34*N34) -> 0 | AA34: =IF(ISERROR(IF(E$7="X",Y34*E34,Y34*F34)),"",IF(E$7="X",Y34*E34,Y34*F34)) -> 0 | AB34: =IF(ISERROR(Z34/AA34),"",Z34/AA34) | AE34: 0.05 | AF34: =+'Frete_Regiao-Impostos'!A25 -> Manaus CIF | AG34: =+'Frete_Regiao-Impostos'!B25 -> 100 | AH34: =+'Frete_Regiao-Impostos'!C25 -> 0.07 | AI34: =+'Frete_Regiao-Impostos'!D25 -> AM | AP34: =Peso!B35 -> 3.7
A35: BRAZIMIL TINTA PISO 3,0L BALDE COR | B35: 28.5 | D35: =IF($F$7="x",IF(F35=0,0,N35/F35),IF($E$7="x",IF(F35=0,0,N35/E35),"")) -> 0.27313443 | E35: =+B35*(-B$5+100%) -> 26.505 | F35: =IF(B35=0,0,E35-H35) -> 26.145 | G35: =VLOOKUP(A35,Custo!A:B,2,0) -> 17.480572 | H35: =(VLOOKUP(A35,Peso!$A$10:$B$148,2,0))*($B$6/1000) -> 0.36 | I35: =IF($I$7="X",AE35,0%) -> 0.05 | J35: =+B35*I35 -> 1.425 | K35: =IF($B$2="X",$C$2,0) -> 0 | L35: =+B35*K35 -> 0 | M35: =+G35+H35+J35+L35 -> 19.265572 | N35: =+E35-M35 -> 7.239428 | O35: =IF(ISERROR((N35/P35)*1000),"",(N35/P35)*1000) | Q35: =VLOOKUP(A35,'MVA-IPI'!A:AD,30,FALSE) -> 0 | R35: =IF($B$4="AM",0,IF($B$4="AP",0,IF($B$4="RR",0,(B35*Q35)))) -> 0 | S35: =IF($B$4="AP",(B35/0.88*$S$8),IF(T35=0%,0,IF($B$4="AM",(B35/0.88*$S$8),IF(T35=0%,0,IF($B$4="RR",(B35/0.88*$S$8),IF(T35=0%,0,B35*$S$8)))))) -> 0 | T35: =IF($C$4="GRUPO 1",VLOOKUP(A35,'MVA-grupos'!$A$9:$B$128,2,FALSE),IF($C$4="GRUPO 2",VLOOKUP(A35,'MVA-grupos'!$A$9:$D$128,4,FALSE),IF($C$4="GRUPO 3",VLOOKUP(A35,'MVA-grupos'!$A$10:$F$128,6,FALSE),IF($C$4="Grupo 4",VLOOKUP(A35,'MVA-grupos'!$A$9:$H$128,8,FALSE))))) -> 0 | U35: =IF(T35=0%,0,(B35+R35)*T35+(B35+R35)) -> 0 | V35: =(U35*$V$8)-S35 -> 0 | X35: =A35 -> BRAZIMIL TINTA PISO 3,0L BALDE COR | Y35: =+C35 -> 0 | Z35: =IF(ISERROR(Y35*N35),"",Y35*N35) -> 0 | AA35: =IF(ISERROR(IF(E$7="X",Y35*E35,Y35*F35)),"",IF(E$7="X",Y35*E35,Y35*F35)) -> 0 | AB35: =IF(ISERROR(Z35/AA35),"",Z35/AA35) | AE35: 0.05 | AF35: =+'Frete_Regiao-Impostos'!A26 -> 0 | AG35: =+'Frete_Regiao-Impostos'!B26 -> 0 | AH35: =+'Frete_Regiao-Impostos'!C26 -> 0 | AI35: =+'Frete_Regiao-Impostos'!D26 -> 0 | AP35: =Peso!B36 -> 3.6
A36: BRAZIMIL TINTA PISO 15L | D36: =AB36 | X36: =A36 -> BRAZIMIL TINTA PISO 15L | Z36: =SUM(Z37:Z38) -> 0 | AA36: =SUM(AA37:AA38) -> 0 | AB36: =IF(ISERROR(Z36/AA36),"",Z36/AA36) | AC36: 0.25 | AF36: =+'Frete_Regiao-Impostos'!A27 -> Manaus - FOB | AG36: =+'Frete_Regiao-Impostos'!B27 -> 0 | AH36: =+'Frete_Regiao-Impostos'!C27 -> 0.07 | AI36: =+'Frete_Regiao-Impostos'!D27 -> AM | AP36: =Peso!B37 -> 0
A37: BRAZIMIL TINTA PISO 15L BALDE BRANCO NEVE | B37: 130 | D37: =IF($F$7="x",IF(F37=0,0,N37/F37),IF($E$7="x",IF(F37=0,0,N37/E37),"")) -> 0.083538953 | E37: =+B37*(-B$5+100%) -> 120.9 | F37: =IF(B37=0,0,E37-H37) -> 119.3 | G37: =VLOOKUP(A37,Custo!A:B,2,0) -> 102.70014 | H37: =(VLOOKUP(A37,Peso!$A$10:$B$148,2,0))*($B$6/1000) -> 1.6 | I37: =IF($I$7="X",AE37,0%) -> 0.05 | J37: =+B37*I37 -> 6.5 | K37: =IF($B$2="X",$C$2,0) -> 0 | L37: =+B37*K37 -> 0 | M37: =+G37+H37+J37+L37 -> 110.80014 | N37: =+E37-M37 -> 10.099859 | O37: =IF(ISERROR((N37/P37)*1000),"",(N37/P37)*1000) | Q37: =VLOOKUP(A37,'MVA-IPI'!A:AD,30,FALSE) -> 0 | R37: =IF($B$4="AM",0,IF($B$4="AP",0,IF($B$4="RR",0,(B37*Q37)))) -> 0 | S37: =IF($B$4="AP",(B37/0.88*$S$8),IF(T37=0%,0,IF($B$4="AM",(B37/0.88*$S$8),IF(T37=0%,0,IF($B$4="RR",(B37/0.88*$S$8),IF(T37=0%,0,B37*$S$8)))))) -> 0 | T37: =IF($C$4="GRUPO 1",VLOOKUP(A37,'MVA-grupos'!$A$9:$B$128,2,FALSE),IF($C$4="GRUPO 2",VLOOKUP(A37,'MVA-grupos'!$A$9:$D$128,4,FALSE),IF($C$4="GRUPO 3",VLOOKUP(A37,'MVA-grupos'!$A$10:$F$128,6,FALSE),IF($C$4="Grupo 4",VLOOKUP(A37,'MVA-grupos'!$A$9:$H$128,8,FALSE))))) -> 0 | U37: =IF(T37=0%,0,(B37+R37)*T37+(B37+R37)) -> 0 | V37: =(U37*$V$8)-S37 -> 0 | X37: =A37 -> BRAZIMIL TINTA PISO 15L BALDE BRANCO NEVE | Y37: =+C37 -> 0 | Z37: =IF(ISERROR(Y37*N37),"",Y37*N37) -> 0 | AA37: =IF(ISERROR(IF(E$7="X",Y37*E37,Y37*F37)),"",IF(E$7="X",Y37*E37,Y37*F37)) -> 0 | AB37: =IF(ISERROR(Z37/AA37),"",Z37/AA37) | AE37: 0.05 | AF37: =+'Frete_Regiao-Impostos'!A28 -> Manaus - INTERIOR PIS COFINS | AG37: =+'Frete_Regiao-Impostos'!B28 -> 0 | AH37: =+'Frete_Regiao-Impostos'!C28 -> 0.1065 | AI37: =+'Frete_Regiao-Impostos'!D28 -> AM | AP37: =Peso!B38 -> 16
A38: BRAZIMIL TINTA PISO 15L BALDE COR | B38: 108 | D38: =IF($F$7="x",IF(F38=0,0,N38/F38),IF($E$7="x",IF(F38=0,0,N38/E38),"")) -> -0.032127247 | E38: =+B38*(-B$5+100%) -> 100.44 | F38: =IF(B38=0,0,E38-H38) -> 98.86 | G38: =VLOOKUP(A38,Custo!A:B,2,0) -> 96.686861 | H38: =(VLOOKUP(A38,Peso!$A$10:$B$148,2,0))*($B$6/1000) -> 1.58 | I38: =IF($I$7="X",AE38,0%) -> 0.05 | J38: =+B38*I38 -> 5.4 | K38: =IF($B$2="X",$C$2,0) -> 0 | L38: =+B38*K38 -> 0 | M38: =+G38+H38+J38+L38 -> 103.66686 | N38: =+E38-M38 -> -3.2268607 | O38: =IF(ISERROR((N38/P38)*1000),"",(N38/P38)*1000) | Q38: =VLOOKUP(A38,'MVA-IPI'!A:AD,30,FALSE) -> 0 | R38: =IF($B$4="AM",0,IF($B$4="AP",0,IF($B$4="RR",0,(B38*Q38)))) -> 0 | S38: =IF($B$4="AP",(B38/0.88*$S$8),IF(T38=0%,0,IF($B$4="AM",(B38/0.88*$S$8),IF(T38=0%,0,IF($B$4="RR",(B38/0.88*$S$8),IF(T38=0%,0,B38*$S$8)))))) -> 0 | T38: =IF($C$4="GRUPO 1",VLOOKUP(A38,'MVA-grupos'!$A$9:$B$128,2,FALSE),IF($C$4="GRUPO 2",VLOOKUP(A38,'MVA-grupos'!$A$9:$D$128,4,FALSE),IF($C$4="GRUPO 3",VLOOKUP(A38,'MVA-grupos'!$A$10:$F$128,6,FALSE),IF($C$4="Grupo 4",VLOOKUP(A38,'MVA-grupos'!$A$9:$H$128,8,FALSE))))) -> 0 | U38: =IF(T38=0%,0,(B38+R38)*T38+(B38+R38)) -> 0 | V38: =(U38*$V$8)-S38 -> 0 | X38: =A38 -> BRAZIMIL TINTA PISO 15L BALDE COR | Y38: =+C38 -> 0 | Z38: =IF(ISERROR(Y38*N38),"",Y38*N38) -> 0 | AA38: =IF(ISERROR(IF(E$7="X",Y38*E38,Y38*F38)),"",IF(E$7="X",Y38*E38,Y38*F38)) -> 0 | AB38: =IF(ISERROR(Z38/AA38),"",Z38/AA38) | AE38: 0.05 | AF38: =+'Frete_Regiao-Impostos'!A29 -> Manaus - INTERIOR S/ PIS COFINS | AG38: =+'Frete_Regiao-Impostos'!B29 -> 0 | AH38: =+'Frete_Regiao-Impostos'!C29 -> 0.07 | AI38: =+'Frete_Regiao-Impostos'!D29 -> AM | AP38: =Peso!B39 -> 15.8
A39: BRAZIMIL SELADOR ACRIL 3,0L | D39: =AB39 | X39: =A39 -> BRAZIMIL SELADOR ACRIL 3,0L | Z39: =SUM(Z40:Z41) -> 0 | AA39: =SUM(AA40:AA41) -> 0 | AB39: =IF(ISERROR(Z39/AA39),"",Z39/AA39) | AC39: 0.25 | AF39: =+'Frete_Regiao-Impostos'!A30 -> 0 | AG39: =+'Frete_Regiao-Impostos'!B30 -> 0 | AH39: =+'Frete_Regiao-Impostos'!C30 -> 0 | AI39: =+'Frete_Regiao-Impostos'!D30 -> 0 | AP39: =Peso!B40 -> 0
A40: BRAZIMIL SELADOR ACRIL 3,0L REFIL PIGMENTADO | B40: 0 | D40: =IF($F$7="x",IF(F40=0,0,N40/F40),IF($E$7="x",IF(F40=0,0,N40/E40),"")) -> 0 | E40: =+B40*(-B$5+100%) -> 0 | F40: =IF(B40=0,0,E40-H40) -> 0 | G40: =VLOOKUP(A40,Custo!A:B,2,0) -> 3.2667289 | H40: =(VLOOKUP(A40,Peso!$A$10:$B$148,2,0))*($B$6/1000) -> 0.385 | I40: =IF($I$7="X",AE40,0%) -> 0.05 | J40: =+B40*I40 -> 0 | K40: =IF($B$2="X",$C$2,0) -> 0 | L40: =+B40*K40 -> 0 | M40: =+G40+H40+J40+L40 -> 3.6517289 | N40: =+E40-M40 -> -3.6517289 | O40: =IF(ISERROR((N40/P40)*1000),"",(N40/P40)*1000) | Q40: =VLOOKUP(A40,'MVA-IPI'!A:AD,30,FALSE) -> 0 | R40: =IF($B$4="AM",0,IF($B$4="AP",0,IF($B$4="RR",0,(B40*Q40)))) -> 0 | S40: =IF($B$4="AP",(B40/0.88*$S$8),IF(T40=0%,0,IF($B$4="AM",(B40/0.88*$S$8),IF(T40=0%,0,IF($B$4="RR",(B40/0.88*$S$8),IF(T40=0%,0,B40*$S$8)))))) -> 0 | T40: =IF($C$4="GRUPO 1",VLOOKUP(A40,'MVA-grupos'!$A$9:$B$128,2,FALSE),IF($C$4="GRUPO 2",VLOOKUP(A40,'MVA-grupos'!$A$9:$D$128,4,FALSE),IF($C$4="GRUPO 3",VLOOKUP(A40,'MVA-grupos'!$A$10:$F$128,6,FALSE),IF($C$4="Grupo 4",VLOOKUP(A40,'MVA-grupos'!$A$9:$H$128,8,FALSE))))) -> 0 | U40: =IF(T40=0%,0,(B40+R40)*T40+(B40+R40)) -> 0 | V40: =(U40*$V$8)-S40 -> 0 | X40: =A40 -> BRAZIMIL SELADOR ACRIL 3,0L REFIL PIGMENTADO | Y40: =+C40 -> 0 | Z40: =IF(ISERROR(Y40*N40),"",Y40*N40) -> 0 | AA40: =IF(ISERROR(IF(E$7="X",Y40*E40,Y40*F40)),"",IF(E$7="X",Y40*E40,Y40*F40)) -> 0 | AB40: =IF(ISERROR(Z40/AA40),"",Z40/AA40) | AE40: 0.05 | AF40: =+'Frete_Regiao-Impostos'!A31 -> 0 | AG40: =+'Frete_Regiao-Impostos'!B31 -> 0 | AH40: =+'Frete_Regiao-Impostos'!C31 -> 0 | AI40: =+'Frete_Regiao-Impostos'!D31 -> 0 | AP40: =Peso!B41 -> 3.85
A41: BRAZIMIL SELADOR ACRIL 3,0L BALDE PIGMENTADO | B41: 17.99 | D41: =IF($F$7="x",IF(F41=0,0,N41/F41),IF($E$7="x",IF(F41=0,0,N41/E41),"")) -> 0.51931306 | E41: =+B41*(-B$5+100%) -> 16.7307 | F41: =IF(B41=0,0,E41-H41) -> 16.3257 | G41: =VLOOKUP(A41,Custo!A:B,2,0) -> 6.7377289 | H41: =(VLOOKUP(A41,Peso!$A$10:$B$148,2,0))*($B$6/1000) -> 0.405 | I41: =IF($I$7="X",AE41,0%) -> 0.05 | J41: =+B41*I41 -> 0.8995 | K41: =IF($B$2="X",$C$2,0) -> 0 | L41: =+B41*K41 -> 0 | M41: =+G41+H41+J41+L41 -> 8.0422289 | N41: =+E41-M41 -> 8.6884711 | O41: =IF(ISERROR((N41/P41)*1000),"",(N41/P41)*1000) | Q41: =VLOOKUP(A41,'MVA-IPI'!A:AD,30,FALSE) -> 0 | R41: =IF($B$4="AM",0,IF($B$4="AP",0,IF($B$4="RR",0,(B41*Q41)))) -> 0 | S41: =IF($B$4="AP",(B41/0.88*$S$8),IF(T41=0%,0,IF($B$4="AM",(B41/0.88*$S$8),IF(T41=0%,0,IF($B$4="RR",(B41/0.88*$S$8),IF(T41=0%,0,B41*$S$8)))))) -> 0 | T41: =IF($C$4="GRUPO 1",VLOOKUP(A41,'MVA-grupos'!$A$9:$B$128,2,FALSE),IF($C$4="GRUPO 2",VLOOKUP(A41,'MVA-grupos'!$A$9:$D$128,4,FALSE),IF($C$4="GRUPO 3",VLOOKUP(A41,'MVA-grupos'!$A$10:$F$128,6,FALSE),IF($C$4="Grupo 4",VLOOKUP(A41,'MVA-grupos'!$A$9:$H$128,8,FALSE))))) -> 0 | U41: =IF(T41=0%,0,(B41+R41)*T41+(B41+R41)) -> 0 | V41: =(U41*$V$8)-S41 -> 0 | X41: =A41 -> BRAZIMIL SELADOR ACRIL 3,0L BALDE PIGMENTADO | Y41: =+C41 -> 0 | Z41: =IF(ISERROR(Y41*N41),"",Y41*N41) -> 0 | AA41: =IF(ISERROR(IF(E$7="X",Y41*E41,Y41*F41)),"",IF(E$7="X",Y41*E41,Y41*F41)) -> 0 | AB41: =IF(ISERROR(Z41/AA41),"",Z41/AA41) | AE41: 0.05 | AF41: =+'Frete_Regiao-Impostos'!A32 -> 0 | AG41: =+'Frete_Regiao-Impostos'!B32 -> 0 | AH41: =+'Frete_Regiao-Impostos'!C32 -> 0 | AI41: =+'Frete_Regiao-Impostos'!D32 -> 0 | AP41: =Peso!B42 -> 4.05
A42: BRAZIMIL SELADOR ACRIL 15L | D42: =AB42 | I42: =IF($I$7="X",AE42,0%) -> 0.04 | X42: =A42 -> BRAZIMIL SELADOR ACRIL 15L | Z42: =SUM(Z43:Z43) -> 0 | AA42: =SUM(AA43:AA43) -> 0 | AB42: =IF(ISERROR(Z42/AA42),"",Z42/AA42) | AC42: 0.25 | AE42: 0.04 | AF42: =+'Frete_Regiao-Impostos'!A33 -> 0 | AG42: =+'Frete_Regiao-Impostos'!B33 -> 0 | AH42: =+'Frete_Regiao-Impostos'!C33 -> 0 | AI42: =+'Frete_Regiao-Impostos'!D33 -> 0 | AP42: =Peso!B43 -> 0
A43: BRAZIMIL SELADOR ACRIL 15L BALDE PIGMENTADO | B43: 51 | D43: =IF($F$7="x",IF(F43=0,0,N43/F43),IF($E$7="x",IF(F43=0,0,N43/E43),"")) -> 0.38610082 | E43: =+B43*(-B$5+100%) -> 47.43 | F43: =IF(B43=0,0,E43-H43) -> 45.63 | G43: =VLOOKUP(A43,Custo!A:B,2,0) -> 24.767238 | H43: =(VLOOKUP(A43,Peso!$A$10:$B$148,2,0))*($B$6/1000) -> 1.8 | I43: =IF($I$7="X",AE43,0%) -> 0.05 | J43: =+B43*I43 -> 2.55 | K43: =IF($B$2="X",$C$2,0) -> 0 | L43: =+B43*K43 -> 0 | M43: =+G43+H43+J43+L43 -> 29.117238 | N43: =+E43-M43 -> 18.312762 | O43: =IF(ISERROR((N43/P43)*1000),"",(N43/P43)*1000) | Q43: =VLOOKUP(A43,'MVA-IPI'!A:AD,30,FALSE) -> 0 | R43: =IF($B$4="AM",0,IF($B$4="AP",0,IF($B$4="RR",0,(B43*Q43)))) -> 0 | S43: =IF($B$4="AP",(B43/0.88*$S$8),IF(T43=0%,0,IF($B$4="AM",(B43/0.88*$S$8),IF(T43=0%,0,IF($B$4="RR",(B43/0.88*$S$8),IF(T43=0%,0,B43*$S$8)))))) -> 0 | T43: =IF($C$4="GRUPO 1",VLOOKUP(A43,'MVA-grupos'!$A$9:$B$128,2,FALSE),IF($C$4="GRUPO 2",VLOOKUP(A43,'MVA-grupos'!$A$9:$D$128,4,FALSE),IF($C$4="GRUPO 3",VLOOKUP(A43,'MVA-grupos'!$A$10:$F$128,6,FALSE),IF($C$4="Grupo 4",VLOOKUP(A43,'MVA-grupos'!$A$9:$H$128,8,FALSE))))) -> 0 | U43: =IF(T43=0%,0,(B43+R43)*T43+(B43+R43)) -> 0 | V43: =(U43*$V$8)-S43 -> 0 | X43: =A43 -> BRAZIMIL SELADOR ACRIL 15L BALDE PIGMENTADO | Y43: =+C43 -> 0 | Z43: =IF(ISERROR(Y43*N43),"",Y43*N43) -> 0 | AA43: =IF(ISERROR(IF(E$7="X",Y43*E43,Y43*F43)),"",IF(E$7="X",Y43*E43,Y43*F43)) -> 0 | AB43: =IF(ISERROR(Z43/AA43),"",Z43/AA43) | AE43: 0.05 | AF43: =+'Frete_Regiao-Impostos'!A35 -> 0 | AG43: =+'Frete_Regiao-Impostos'!B35 -> 0 | AH43: =+'Frete_Regiao-Impostos'!C35 -> 0 | AI43: =+'Frete_Regiao-Impostos'!D35 -> 0 | AP43: =Peso!B45 -> 18
A44: LIQUIBRILHO 3,0L | D44: =AB44 | I44: =IF($I$7="X",AE44,0%) -> 0.02 | X44: =A44 -> LIQUIBRILHO 3,0L | Z44: =SUM(Z45) -> 0 | AA44: =SUM(AA45) -> 0 | AB44: =IF(ISERROR(Z44/AA44),"",Z44/AA44) | AC44: 0.25 | AE44: 0.02 | AF44: =+'Frete_Regiao-Impostos'!A36 -> 0 | AG44: =+'Frete_Regiao-Impostos'!B36 -> 0 | AH44: =+'Frete_Regiao-Impostos'!C36 -> 0 | AI44: =+'Frete_Regiao-Impostos'!D36 -> 0 | AP44: =Peso!B46 -> 0
A45: LIQUIBRILHO 3,0L BALDE INCOLOR | B45: 32 | D45: =IF($F$7="x",IF(F45=0,0,N45/F45),IF($E$7="x",IF(F45=0,0,N45/E45),"")) -> 0.46007776 | E45: =+B45*(-B$5+100%) -> 29.76 | F45: =IF(B45=0,0,E45-H45) -> 29.4415 | G45: =VLOOKUP(A45,Custo!A:B,2,0) -> 14.149586 | H45: =(VLOOKUP(A45,Peso!$A$10:$B$148,2,0))*($B$6/1000) -> 0.3185 | I45: =IF($I$7="X",AE45,0%) -> 0.05 | J45: =+B45*I45 -> 1.6 | K45: =IF($B$2="X",$C$2,0) -> 0 | L45: =+B45*K45 -> 0 | M45: =+G45+H45+J45+L45 -> 16.068086 | N45: =+E45-M45 -> 13.691914 | O45: =IF(ISERROR((N45/P45)*1000),"",(N45/P45)*1000) | Q45: =VLOOKUP(A45,'MVA-IPI'!A:AD,30,FALSE) -> 0 | R45: =IF($B$4="AM",0,IF($B$4="AP",0,IF($B$4="RR",0,(B45*Q45)))) -> 0 | S45: =IF($B$4="AP",(B45/0.88*$S$8),IF(T45=0%,0,IF($B$4="AM",(B45/0.88*$S$8),IF(T45=0%,0,IF($B$4="RR",(B45/0.88*$S$8),IF(T45=0%,0,B45*$S$8)))))) -> 0 | T45: =IF($C$4="GRUPO 1",VLOOKUP(A45,'MVA-grupos'!$A$9:$B$128,2,FALSE),IF($C$4="GRUPO 2",VLOOKUP(A45,'MVA-grupos'!$A$9:$D$128,4,FALSE),IF($C$4="GRUPO 3",VLOOKUP(A45,'MVA-grupos'!$A$10:$F$128,6,FALSE),IF($C$4="Grupo 4",VLOOKUP(A45,'MVA-grupos'!$A$9:$H$128,8,FALSE))))) -> 0 | U45: =IF(T45=0%,0,(B45+R45)*T45+(B45+R45)) -> 0 | V45: =(U45*$V$8)-S45 -> 0 | X45: =A45 -> LIQUIBRILHO 3,0L BALDE INCOLOR | Y45: =+C45 -> 0 | Z45: =IF(ISERROR(Y45*N45),"",Y45*N45) -> 0 | AA45: =IF(ISERROR(IF(E$7="X",Y45*E45,Y45*F45)),"",IF(E$7="X",Y45*E45,Y45*F45)) -> 0 | AB45: =IF(ISERROR(Z45/AA45),"",Z45/AA45) | AE45: 0.05 | AF45: =+'Frete_Regiao-Impostos'!A37 -> 0 | AG45: =+'Frete_Regiao-Impostos'!B37 -> 0 | AH45: =+'Frete_Regiao-Impostos'!C37 -> 0 | AI45: =+'Frete_Regiao-Impostos'!D37 -> 0 | AP45: =Peso!B47 -> 3.185
A46: LIQUIBRILHO 15L | D46: =AB46 | I46: =IF($I$7="X",AE46,0%) -> 0.02 | X46: =A46 -> LIQUIBRILHO 15L | Z46: =SUM(Z47) -> 0 | AA46: =SUM(AA47) -> 0 | AB46: =IF(ISERROR(Z46/AA46),"",Z46/AA46) | AC46: 0.25 | AE46: 0.02 | AF46: =+'Frete_Regiao-Impostos'!A40 -> 0 | AG46: =+'Frete_Regiao-Impostos'!B40 -> 0 | AH46: =+'Frete_Regiao-Impostos'!C40 -> 0 | AI46: =+'Frete_Regiao-Impostos'!D40 -> 0 | AP46: =Peso!B48 -> 0
A47: LIQUIBRILHO 15L BALDE INCOLOR | B47: 135 | D47: =IF($F$7="x",IF(F47=0,0,N47/F47),IF($E$7="x",IF(F47=0,0,N47/E47),"")) -> 0.4127405 | E47: =+B47*(-B$5+100%) -> 125.55 | F47: =IF(B47=0,0,E47-H47) -> 124.2 | G47: =VLOOKUP(A47,Custo!A:B,2,0) -> 65.63043 | H47: =(VLOOKUP(A47,Peso!$A$10:$B$148,2,0))*($B$6/1000) -> 1.35 | I47: =IF($I$7="X",AE47,0%) -> 0.05 | J47: =+B47*I47 -> 6.75 | K47: =IF($B$2="X",$C$2,0) -> 0 | L47: =+B47*K47 -> 0 | M47: =+G47+H47+J47+L47 -> 73.73043 | N47: =+E47-M47 -> 51.81957 | O47: =IF(ISERROR((N47/P47)*1000),"",(N47/P47)*1000) | Q47: =VLOOKUP(A47,'MVA-IPI'!A:AD,30,FALSE) -> 0 | R47: =IF($B$4="AM",0,IF($B$4="AP",0,IF($B$4="RR",0,(B47*Q47)))) -> 0 | S47: =IF($B$4="AP",(B47/0.88*$S$8),IF(T47=0%,0,IF($B$4="AM",(B47/0.88*$S$8),IF(T47=0%,0,IF($B$4="RR",(B47/0.88*$S$8),IF(T47=0%,0,B47*$S$8)))))) -> 0 | T47: =IF($C$4="GRUPO 1",VLOOKUP(A47,'MVA-grupos'!$A$9:$B$128,2,FALSE),IF($C$4="GRUPO 2",VLOOKUP(A47,'MVA-grupos'!$A$9:$D$128,4,FALSE),IF($C$4="GRUPO 3",VLOOKUP(A47,'MVA-grupos'!$A$10:$F$128,6,FALSE),IF($C$4="Grupo 4",VLOOKUP(A47,'MVA-grupos'!$A$9:$H$128,8,FALSE))))) -> 0 | U47: =IF(T47=0%,0,(B47+R47)*T47+(B47+R47)) -> 0 | V47: =(U47*$V$8)-S47 -> 0 | X47: =A47 -> LIQUIBRILHO 15L BALDE INCOLOR | Y47: =+C47 -> 0 | Z47: =IF(ISERROR(Y47*N47),"",Y47*N47) -> 0 | AA47: =IF(ISERROR(IF(E$7="X",Y47*E47,Y47*F47)),"",IF(E$7="X",Y47*E47,Y47*F47)) -> 0 | AB47: =IF(ISERROR(Z47/AA47),"",Z47/AA47) | AE47: 0.05 | AF47: =+'Frete_Regiao-Impostos'!A41 -> 0 | AG47: =+'Frete_Regiao-Impostos'!B41 -> 0 | AH47: =+'Frete_Regiao-Impostos'!C41 -> 0 | AI47: =+'Frete_Regiao-Impostos'!D41 -> 0 | AP47: =Peso!B49 -> 13.5
A48: MASSAS / TEXTURAS | D48: =AB48 | X48: MASSAS / TEXTURAS | Z48: =Z49+Z58+Z66+Z71 -> 0 | AA48: =AA49+AA58+AA66+AA71 -> 0 | AB48: =IF(ISERROR(Z48/AA48),"",Z48/AA48) | AC48: 0.25 | AF48: =+'Frete_Regiao-Impostos'!A42 -> 0 | AG48: =+'Frete_Regiao-Impostos'!B42 -> 0 | AH48: =+'Frete_Regiao-Impostos'!C42 -> 0 | AI48: =+'Frete_Regiao-Impostos'!D42 -> 0 | AP48: =Peso!B50 -> 0
A49: BRAZIMIL CORRIDA | D49: =AB49 | X49: =A49 -> BRAZIMIL CORRIDA | Z49: =SUM(Z50:Z57) -> 0 | AA49: =SUM(AA50:AA57) -> 0 | AB49: =IF(ISERROR(Z49/AA49),"",Z49/AA49) | AC49: 0.25 | AF49: =+'Frete_Regiao-Impostos'!A43 -> 0 | AG49: =+'Frete_Regiao-Impostos'!B43 -> 0 | AH49: =+'Frete_Regiao-Impostos'!C43 -> 0 | AI49: =+'Frete_Regiao-Impostos'!D43 -> 0 | AP49: =Peso!B51 -> 0
A50: BRAZIMIL CORRIDA POTE 1KG | B50: 5.5 | D50: =IF($F$7="x",IF(F50=0,0,N50/F50),IF($E$7="x",IF(F50=0,0,N50/E50),"")) -> 0.70123236 | E50: =+B50*(-B$5+100%) -> 5.115 | F50: =IF(B50=0,0,E50-H50) -> 5.011 | G50: =VLOOKUP(A50,Custo!A:B,2,0) -> 1.1491965 | H50: =(VLOOKUP(A50,Peso!$A$10:$B$148,2,0))*($B$6/1000) -> 0.104 | I50: =IF($I$7="X",AE50,0%) -> 0.05 | J50: =+B50*I50 -> 0.275 | K50: =IF($B$2="X",$C$2,0) -> 0 | L50: =+B50*K50 -> 0 | M50: =+G50+H50+J50+L50 -> 1.5281965 | N50: =+E50-M50 -> 3.5868035 | O50: =IF(ISERROR((N50/P50)*100),"",(N50/P50)*100) | Q50: =VLOOKUP(A50,'MVA-IPI'!A:AD,30,FALSE) -> 0.02 | R50: =IF($B$4="AM",0,IF($B$4="AP",0,IF($B$4="RR",0,(B50*Q50)))) -> 0 | S50: =IF($B$4="AP",(B50/0.88*$S$8),IF(T50=0%,0,IF($B$4="AM",(B50/0.88*$S$8),IF(T50=0%,0,IF($B$4="RR",(B50/0.88*$S$8),IF(T50=0%,0,B50*$S$8)))))) -> 0 | T50: =IF($C$4="GRUPO 1",VLOOKUP(A50,'MVA-grupos'!$A$9:$B$128,2,FALSE),IF($C$4="GRUPO 2",VLOOKUP(A50,'MVA-grupos'!$A$9:$D$128,4,FALSE),IF($C$4="GRUPO 3",VLOOKUP(A50,'MVA-grupos'!$A$10:$F$128,6,FALSE),IF($C$4="Grupo 4",VLOOKUP(A50,'MVA-grupos'!$A$9:$H$128,8,FALSE))))) -> 0 | U50: =IF(T50=0%,0,(B50+R50)*T50+(B50+R50)) -> 0 | V50: =(U50*$V$8)-S50 -> 0 | X50: =A50 -> BRAZIMIL CORRIDA POTE 1KG | Y50: =+C50 -> 0 | Z50: =IF(ISERROR(Y50*N50),"",Y50*N50) -> 0 | AA50: =IF(ISERROR(IF(E$7="X",Y50*E50,Y50*F50)),"",IF(E$7="X",Y50*E50,Y50*F50)) -> 0 | AB50: =IF(ISERROR(Z50/AA50),"",Z50/AA50) | AE50: 0.05 | AF50: =+'Frete_Regiao-Impostos'!A44 -> 0 | AG50: =+'Frete_Regiao-Impostos'!B44 -> 0 | AH50: =+'Frete_Regiao-Impostos'!C44 -> 0 | AI50: =+'Frete_Regiao-Impostos'!D44 -> 0 | AP50: =Peso!B52 -> 1.04
A51: BRAZIMIL CORRIDA GALÃO 5KG | B51: 14.9 | D51: =IF($F$7="x",IF(F51=0,0,N51/F51),IF($E$7="x",IF(F51=0,0,N51/E51),"")) -> 0.4386765 | E51: =+B51*(-B$5+100%) -> 13.857 | F51: =IF(B51=0,0,E51-H51) -> 13.3385 | G51: =VLOOKUP(A51,Custo!A:B,2,0) -> 6.5147597 | H51: =(VLOOKUP(A51,Peso!$A$10:$B$148,2,0))*($B$6/1000) -> 0.5185 | I51: =IF($I$7="X",AE51,0%) -> 0.05 | J51: =+B51*I51 -> 0.745 | K51: =IF($B$2="X",$C$2,0) -> 0 | L51: =+B51*K51 -> 0 | M51: =+G51+H51+J51+L51 -> 7.7782597 | N51: =+E51-M51 -> 6.0787403 | O51: =IF(ISERROR((N51/P51)*100),"",(N51/P51)*100) | Q51: =VLOOKUP(A51,'MVA-IPI'!A:AD,30,FALSE) -> 0.02 | R51: =IF($B$4="AM",0,IF($B$4="AP",0,IF($B$4="RR",0,(B51*Q51)))) -> 0 | S51: =IF($B$4="AP",(B51/0.88*$S$8),IF(T51=0%,0,IF($B$4="AM",(B51/0.88*$S$8),IF(T51=0%,0,IF($B$4="RR",(B51/0.88*$S$8),IF(T51=0%,0,B51*$S$8)))))) -> 0 | T51: =IF($C$4="GRUPO 1",VLOOKUP(A51,'MVA-grupos'!$A$9:$B$128,2,FALSE),IF($C$4="GRUPO 2",VLOOKUP(A51,'MVA-grupos'!$A$9:$D$128,4,FALSE),IF($C$4="GRUPO 3",VLOOKUP(A51,'MVA-grupos'!$A$10:$F$128,6,FALSE),IF($C$4="Grupo 4",VLOOKUP(A51,'MVA-grupos'!$A$9:$H$128,8,FALSE))))) -> 0 | U51: =IF(T51=0%,0,(B51+R51)*T51+(B51+R51)) -> 0 | V51: =(U51*$V$8)-S51 -> 0 | X51: =A51 -> BRAZIMIL CORRIDA GALÃO 5KG | Y51: =+C51 -> 0 | Z51: =IF(ISERROR(Y51*N51),"",Y51*N51) -> 0 | AA51: =IF(ISERROR(IF(E$7="X",Y51*E51,Y51*F51)),"",IF(E$7="X",Y51*E51,Y51*F51)) -> 0 | AB51: =IF(ISERROR(Z51/AA51),"",Z51/AA51) | AE51: 0.05 | AF51: =+'Frete_Regiao-Impostos'!A45 -> 0 | AG51: =+'Frete_Regiao-Impostos'!B45 -> 0 | AH51: =+'Frete_Regiao-Impostos'!C45 -> 0 | AI51: =+'Frete_Regiao-Impostos'!D45 -> 0 | AP51: =Peso!B53 -> 5.185
A52: BRAZIMIL CORRIDA SACO VALV 10 KG | B52: 11 | D52: =IF($F$7="x",IF(F52=0,0,N52/F52),IF($E$7="x",IF(F52=0,0,N52/E52),"")) -> 0.27896068 | E52: =+B52*(-B$5+100%) -> 10.23 | F52: =IF(B52=0,0,E52-H52) -> 9.225 | G52: =VLOOKUP(A52,Custo!A:B,2,0) -> 5.8212323 | H52: =(VLOOKUP(A52,Peso!$A$10:$B$148,2,0))*($B$6/1000) -> 1.005 | I52: =IF($I$7="X",AE52,0%) -> 0.05 | J52: =+B52*I52 -> 0.55 | K52: =IF($B$2="X",$C$2,0) -> 0 | L52: =+B52*K52 -> 0 | M52: =+G52+H52+J52+L52 -> 7.3762323 | N52: =+E52-M52 -> 2.8537677 | O52: =IF(ISERROR((N52/P52)*100),"",(N52/P52)*100) | Q52: =VLOOKUP(A52,'MVA-IPI'!A:AD,30,FALSE) -> 0.02 | R52: =IF($B$4="AM",0,IF($B$4="AP",0,IF($B$4="RR",0,(B52*Q52)))) -> 0 | S52: =IF($B$4="AP",(B52/0.88*$S$8),IF(T52=0%,0,IF($B$4="AM",(B52/0.88*$S$8),IF(T52=0%,0,IF($B$4="RR",(B52/0.88*$S$8),IF(T52=0%,0,B52*$S$8)))))) -> 0 | T52: =IF($C$4="GRUPO 1",VLOOKUP(A52,'MVA-grupos'!$A$9:$B$128,2,FALSE),IF($C$4="GRUPO 2",VLOOKUP(A52,'MVA-grupos'!$A$9:$D$128,4,FALSE),IF($C$4="GRUPO 3",VLOOKUP(A52,'MVA-grupos'!$A$10:$F$128,6,FALSE),IF($C$4="Grupo 4",VLOOKUP(A52,'MVA-grupos'!$A$9:$H$128,8,FALSE))))) -> 0 | U52: =IF(T52=0%,0,(B52+R52)*T52+(B52+R52)) -> 0 | V52: =(U52*$V$8)-S52 -> 0 | X52: =A52 -> BRAZIMIL CORRIDA SACO VALV 10 KG | Y52: =+C52 -> 0 | Z52: =IF(ISERROR(Y52*N52),"",Y52*N52) -> 0 | AA52: =IF(ISERROR(IF(E$7="X",Y52*E52,Y52*F52)),"",IF(E$7="X",Y52*E52,Y52*F52)) -> 0 | AB52: =IF(ISERROR(Z52/AA52),"",Z52/AA52) | AE52: 0.05 | AF52: =+'Frete_Regiao-Impostos'!A46 -> 0 | AG52: =+'Frete_Regiao-Impostos'!B46 -> 0 | AH52: =+'Frete_Regiao-Impostos'!C46 -> 0 | AI52: =+'Frete_Regiao-Impostos'!D46 -> 0 | AP52: =Peso!B54 -> 10.05
A53: BRAZIMIL CORRIDA BALDE 20KG | B53: 36.5 | D53: =IF($F$7="x",IF(F53=0,0,N53/F53),IF($E$7="x",IF(F53=0,0,N53/E53),"")) -> 0.25417591 | E53: =+B53*(-B$5+100%) -> 33.945 | F53: =IF(B53=0,0,E53-H53) -> 31.881 | G53: =VLOOKUP(A53,Custo!A:B,2,0) -> 21.427999 | H53: =(VLOOKUP(A53,Peso!$A$10:$B$148,2,0))*($B$6/1000) -> 2.064 | I53: =IF($I$7="X",AE53,0%) -> 0.05 | J53: =+B53*I53 -> 1.825 | K53: =IF($B$2="X",$C$2,0) -> 0 | L53: =+B53*K53 -> 0 | M53: =+G53+H53+J53+L53 -> 25.316999 | N53: =+E53-M53 -> 8.6280011 | O53: =IF(ISERROR((N53/P53)*100),"",(N53/P53)*100) | Q53: =VLOOKUP(A53,'MVA-IPI'!A:AD,30,FALSE) -> 0.02 | R53: =IF($B$4="AM",0,IF($B$4="AP",0,IF($B$4="RR",0,(B53*Q53)))) -> 0 | S53: =IF($B$4="AP",(B53/0.88*$S$8),IF(T53=0%,0,IF($B$4="AM",(B53/0.88*$S$8),IF(T53=0%,0,IF($B$4="RR",(B53/0.88*$S$8),IF(T53=0%,0,B53*$S$8)))))) -> 0 | T53: =IF($C$4="GRUPO 1",VLOOKUP(A53,'MVA-grupos'!$A$9:$B$128,2,FALSE),IF($C$4="GRUPO 2",VLOOKUP(A53,'MVA-grupos'!$A$9:$D$128,4,FALSE),IF($C$4="GRUPO 3",VLOOKUP(A53,'MVA-grupos'!$A$10:$F$128,6,FALSE),IF($C$4="Grupo 4",VLOOKUP(A53,'MVA-grupos'!$A$9:$H$128,8,FALSE))))) -> 0 | U53: =IF(T53=0%,0,(B53+R53)*T53+(B53+R53)) -> 0 | V53: =(U53*$V$8)-S53 -> 0 | X53: =A53 -> BRAZIMIL CORRIDA BALDE 20KG | Y53: =+C53 -> 0 | Z53: =IF(ISERROR(Y53*N53),"",Y53*N53) -> 0 | AA53: =IF(ISERROR(IF(E$7="X",Y53*E53,Y53*F53)),"",IF(E$7="X",Y53*E53,Y53*F53)) -> 0 | AB53: =IF(ISERROR(Z53/AA53),"",Z53/AA53) | AE53: 0.05 | AF53: =+'Frete_Regiao-Impostos'!A50 -> 0 | AG53: =+'Frete_Regiao-Impostos'!B50 -> 0 | AH53: =+'Frete_Regiao-Impostos'!C50 -> 0 | AI53: =+'Frete_Regiao-Impostos'!D50 -> 0 | AP53: =Peso!B58 -> 20.64
A54: BRAZIMIL CORRIDA BALDE 25KG | B54: 0 | D54: =IF($F$7="x",IF(F54=0,0,N54/F54),IF($E$7="x",IF(F54=0,0,N54/E54),"")) -> 0 | E54: =+B54*(-B$5+100%) -> 0 | F54: =IF(B54=0,0,E54-H54) -> 0 | G54: =VLOOKUP(A54,Custo!A:B,2,0) -> 22.679956 | H54: =(VLOOKUP(A54,Peso!$A$10:$B$148,2,0))*($B$6/1000) -> 2.564 | I54: =IF($I$7="X",AE54,0%) -> 0.05 | J54: =+B54*I54 -> 0 | K54: =IF($B$2="X",$C$2,0) -> 0 | L54: =+B54*K54 -> 0 | M54: =+G54+H54+J54+L54 -> 25.243956 | N54: =+E54-M54 -> -25.243956 | O54: =IF(ISERROR((N54/P54)*100),"",(N54/P54)*100) | Q54: =VLOOKUP(A54,'MVA-IPI'!A:AD,30,FALSE) -> 0.02 | R54: =IF($B$4="AM",0,IF($B$4="AP",0,IF($B$4="RR",0,(B54*Q54)))) -> 0 | S54: =IF($B$4="AP",(B54/0.88*$S$8),IF(T54=0%,0,IF($B$4="AM",(B54/0.88*$S$8),IF(T54=0%,0,IF($B$4="RR",(B54/0.88*$S$8),IF(T54=0%,0,B54*$S$8)))))) -> 0 | T54: =IF($C$4="GRUPO 1",VLOOKUP(A54,'MVA-grupos'!$A$9:$B$128,2,FALSE),IF($C$4="GRUPO 2",VLOOKUP(A54,'MVA-grupos'!$A$9:$D$128,4,FALSE),IF($C$4="GRUPO 3",VLOOKUP(A54,'MVA-grupos'!$A$10:$F$128,6,FALSE),IF($C$4="Grupo 4",VLOOKUP(A54,'MVA-grupos'!$A$9:$H$128,8,FALSE))))) -> 0 | U54: =IF(T54=0%,0,(B54+R54)*T54+(B54+R54)) -> 0 | V54: =(U54*$V$8)-S54 -> 0 | X54: =A54 -> BRAZIMIL CORRIDA BALDE 25KG | Y54: =+C54 -> 0 | Z54: =IF(ISERROR(Y54*N54),"",Y54*N54) -> 0 | AA54: =IF(ISERROR(IF(E$7="X",Y54*E54,Y54*F54)),"",IF(E$7="X",Y54*E54,Y54*F54)) -> 0 | AB54: =IF(ISERROR(Z54/AA54),"",Z54/AA54) | AE54: 0.05 | AF54: =+'Frete_Regiao-Impostos'!A51 -> 0 | AG54: =+'Frete_Regiao-Impostos'!B51 -> 0 | AH54: =+'Frete_Regiao-Impostos'!C51 -> 0 | AI54: =+'Frete_Regiao-Impostos'!D51 -> 0 | AP54: =Peso!B59 -> 25.64
A55: BRAZIMIL CORRIDA SACO VALV 25KG | B55: 22.04 | D55: =IF($F$7="x",IF(F55=0,0,N55/F55),IF($E$7="x",IF(F55=0,0,N55/E55),"")) -> 0.82412232 | E55: =+B55*(-B$5+100%) -> 20.4972 | F55: =IF(B55=0,0,E55-H55) -> 17.9942 | G55: =VLOOKUP(A55,Custo!A:B,2,0) -> 0 | H55: =(VLOOKUP(A55,Peso!$A$10:$B$148,2,0))*($B$6/1000) -> 2.503 | I55: =IF($I$7="X",AE55,0%) -> 0.05 | J55: =+B55*I55 -> 1.102 | M55: =+G55+H55+J55 -> 3.605 | N55: =+E55-M55 -> 16.8922 | O55: =IF(ISERROR((N55/P55)*100),"",(N55/P55)*100) | Q55: =VLOOKUP(A55,'MVA-IPI'!A:AD,30,FALSE) -> 0.02 | R55: =IF($B$4="AM",0,IF($B$4="AP",0,IF($B$4="RR",0,(B55*Q55)))) -> 0 | S55: =IF($B$4="AP",(B55/0.88*$S$8),IF(T55=0%,0,IF($B$4="AM",(B55/0.88*$S$8),IF(T55=0%,0,IF($B$4="RR",(B55/0.88*$S$8),IF(T55=0%,0,B55*$S$8)))))) -> 0 | T55: =IF($C$4="GRUPO 1",VLOOKUP(A55,'MVA-grupos'!$A$9:$B$128,2,FALSE),IF($C$4="GRUPO 2",VLOOKUP(A55,'MVA-grupos'!$A$9:$D$128,4,FALSE),IF($C$4="GRUPO 3",VLOOKUP(A55,'MVA-grupos'!$A$10:$F$128,6,FALSE),IF($C$4="Grupo 4",VLOOKUP(A55,'MVA-grupos'!$A$9:$H$128,8,FALSE))))) -> 0 | U55: =IF(T55=0%,0,(B55+R55)*T55+(B55+R55)) -> 0 | V55: =(U55*$V$8)-S55 -> 0 | X55: =A55 -> BRAZIMIL CORRIDA SACO VALV 25KG | Y55: =+C55 -> 0 | Z55: =IF(ISERROR(Y55*N55),"",Y55*N55) -> 0 | AA55: =IF(ISERROR(IF(E$7="X",Y55*E55,Y55*F55)),"",IF(E$7="X",Y55*E55,Y55*F55)) -> 0 | AB55: =IF(ISERROR(Z55/AA55),"",Z55/AA55) | AE55: 0.05 | AF55: =+'Frete_Regiao-Impostos'!A47 -> 0 | AG55: =+'Frete_Regiao-Impostos'!B47 -> 0 | AH55: =+'Frete_Regiao-Impostos'!C47 -> 0 | AI55: =+'Frete_Regiao-Impostos'!D47 -> 0 | AP55: =Peso!B55 -> 25.03
A56: BRAZIMIL CORRIDA PPQ 20KG | B56: 20.98 | D56: =IF($F$7="x",IF(F56=0,0,N56/F56),IF($E$7="x",IF(F56=0,0,N56/E56),"")) -> 0.83978597 | E56: =+B56*(-B$5+100%) -> 19.5114 | F56: =IF(B56=0,0,E56-H56) -> 17.4344 | G56: =VLOOKUP(A56,Custo!A:B,2,0) -> 0 | H56: =(VLOOKUP(A56,Peso!$A$10:$B$148,2,0))*($B$6/1000) -> 2.077 | I56: =IF($I$7="X",AE56,0%) -> 0.05 | J56: =+B56*I56 -> 1.049 | M56: =+G56+H56+J56 -> 3.126 | N56: =+E56-M56 -> 16.3854 | O56: =IF(ISERROR((N56/P56)*100),"",(N56/P56)*100) | Q56: =VLOOKUP(A56,'MVA-IPI'!A:AD,30,FALSE) -> 0.02 | R56: =IF($B$4="AM",0,IF($B$4="AP",0,IF($B$4="RR",0,(B56*Q56)))) -> 0 | S56: =IF($B$4="AP",(B56/0.88*$S$8),IF(T56=0%,0,IF($B$4="AM",(B56/0.88*$S$8),IF(T56=0%,0,IF($B$4="RR",(B56/0.88*$S$8),IF(T56=0%,0,B56*$S$8)))))) -> 0 | T56: =IF($C$4="GRUPO 1",VLOOKUP(A56,'MVA-grupos'!$A$9:$B$128,2,FALSE),IF($C$4="GRUPO 2",VLOOKUP(A56,'MVA-grupos'!$A$9:$D$128,4,FALSE),IF($C$4="GRUPO 3",VLOOKUP(A56,'MVA-grupos'!$A$10:$F$128,6,FALSE),IF($C$4="Grupo 4",VLOOKUP(A56,'MVA-grupos'!$A$9:$H$128,8,FALSE))))) -> 0 | U56: =IF(T56=0%,0,(B56+R56)*T56+(B56+R56)) -> 0 | V56: =(U56*$V$8)-S56 -> 0 | X56: =A56 -> BRAZIMIL CORRIDA PPQ 20KG | Y56: =+C56 -> 0 | Z56: =IF(ISERROR(Y56*N56),"",Y56*N56) -> 0 | AA56: =IF(ISERROR(IF(E$7="X",Y56*E56,Y56*F56)),"",IF(E$7="X",Y56*E56,Y56*F56)) -> 0 | AB56: =IF(ISERROR(Z56/AA56),"",Z56/AA56) | AE56: 0.05 | AF56: =+'Frete_Regiao-Impostos'!A48 -> 0 | AG56: =+'Frete_Regiao-Impostos'!B48 -> 0 | AH56: =+'Frete_Regiao-Impostos'!C48 -> 0 | AI56: =+'Frete_Regiao-Impostos'!D48 -> 0 | AP56: =Peso!B56 -> 20.77
A57: BRAZIMIL CORRIDA PPQ 25KG | B57: 20 | D57: =IF($F$7="x",IF(F57=0,0,N57/F57),IF($E$7="x",IF(F57=0,0,N57/E57),"")) -> 0.80768817 | E57: =+B57*(-B$5+100%) -> 18.6 | F57: =IF(B57=0,0,E57-H57) -> 16.023 | G57: =VLOOKUP(A57,Custo!A:B,2,0) -> 0 | H57: =(VLOOKUP(A57,Peso!$A$10:$B$148,2,0))*($B$6/1000) -> 2.577 | I57: =IF($I$7="X",AE57,0%) -> 0.05 | J57: =+B57*I57 -> 1 | M57: =+G57+H57+J57 -> 3.577 | N57: =+E57-M57 -> 15.023 | O57: =IF(ISERROR((N57/P57)*100),"",(N57/P57)*100) | Q57: =VLOOKUP(A57,'MVA-IPI'!A:AD,30,FALSE) -> 0.02 | R57: =IF($B$4="AM",0,IF($B$4="AP",0,IF($B$4="RR",0,(B57*Q57)))) -> 0 | S57: =IF($B$4="AP",(B57/0.88*$S$8),IF(T57=0%,0,IF($B$4="AM",(B57/0.88*$S$8),IF(T57=0%,0,IF($B$4="RR",(B57/0.88*$S$8),IF(T57=0%,0,B57*$S$8)))))) -> 0 | T57: =IF($C$4="GRUPO 1",VLOOKUP(A57,'MVA-grupos'!$A$9:$B$128,2,FALSE),IF($C$4="GRUPO 2",VLOOKUP(A57,'MVA-grupos'!$A$9:$D$128,4,FALSE),IF($C$4="GRUPO 3",VLOOKUP(A57,'MVA-grupos'!$A$10:$F$128,6,FALSE),IF($C$4="Grupo 4",VLOOKUP(A57,'MVA-grupos'!$A$9:$H$128,8,FALSE))))) -> 0 | U57: =IF(T57=0%,0,(B57+R57)*T57+(B57+R57)) -> 0 | V57: =(U57*$V$8)-S57 -> 0 | X57: =A57 -> BRAZIMIL CORRIDA PPQ 25KG | Y57: =+C57 -> 0 | Z57: =IF(ISERROR(Y57*N57),"",Y57*N57) -> 0 | AA57: =IF(ISERROR(IF(E$7="X",Y57*E57,Y57*F57)),"",IF(E$7="X",Y57*E57,Y57*F57)) -> 0 | AB57: =IF(ISERROR(Z57/AA57),"",Z57/AA57) | AE57: 0.05 | AF57: =+'Frete_Regiao-Impostos'!A49 -> 0 | AG57: =+'Frete_Regiao-Impostos'!B49 -> 0 | AH57: =+'Frete_Regiao-Impostos'!C49 -> 0 | AI57: =+'Frete_Regiao-Impostos'!D49 -> 0 | AP57: =Peso!B57 -> 25.77
A58: BRAZIMIL ACRILICA | D58: =AB58 | X58: =A58 -> BRAZIMIL ACRILICA | Z58: =SUM(Z59:Z65) -> 0 | AA58: =SUM(AA59:AA65) -> 0 | AB58: =IF(ISERROR(Z58/AA58),"",Z58/AA58) | AC58: 0.25 | AF58: =+'Frete_Regiao-Impostos'!A52 -> 0 | AG58: =+'Frete_Regiao-Impostos'!B52 -> 0 | AH58: =+'Frete_Regiao-Impostos'!C52 -> 0 | AI58: =+'Frete_Regiao-Impostos'!D52 -> 0 | AP58: =Peso!B60 -> 0
A59: BRAZIMIL ACRILICA POTE 1KG | B59: 6 | D59: =IF($F$7="x",IF(F59=0,0,N59/F59),IF($E$7="x",IF(F59=0,0,N59/E59),"")) -> 0.46854646 | E59: =+B59*(-B$5+100%) -> 5.58 | F59: =IF(B59=0,0,E59-H59) -> 5.476 | G59: =VLOOKUP(A59,Custo!A:B,2,0) -> 2.5615108 | H59: =(VLOOKUP(A59,Peso!$A$10:$B$148,2,0))*($B$6/1000) -> 0.104 | I59: =IF($I$7="X",AE59,0%) -> 0.05 | J59: =+B59*I59 -> 0.3 | K59: =IF($B$2="X",$C$2,0) -> 0 | L59: =+B59*K59 -> 0 | M59: =+G59+H59+J59+L59 -> 2.9655108 | N59: =+E59-M59 -> 2.6144892 | O59: =IF(ISERROR((N59/P59)*100),"",(N59/P59)*100) | Q59: =VLOOKUP(A59,'MVA-IPI'!A:AD,30,FALSE) -> 0.02 | R59: =IF($B$4="AM",0,IF($B$4="AP",0,IF($B$4="RR",0,(B59*Q59)))) -> 0 | S59: =IF($B$4="AP",(B59/0.88*$S$8),IF(T59=0%,0,IF($B$4="AM",(B59/0.88*$S$8),IF(T59=0%,0,IF($B$4="RR",(B59/0.88*$S$8),IF(T59=0%,0,B59*$S$8)))))) -> 0 | T59: =IF($C$4="GRUPO 1",VLOOKUP(A59,'MVA-grupos'!$A$9:$B$128,2,FALSE),IF($C$4="GRUPO 2",VLOOKUP(A59,'MVA-grupos'!$A$9:$D$128,4,FALSE),IF($C$4="GRUPO 3",VLOOKUP(A59,'MVA-grupos'!$A$10:$F$128,6,FALSE),IF($C$4="Grupo 4",VLOOKUP(A59,'MVA-grupos'!$A$9:$H$128,8,FALSE))))) -> 0 | U59: =IF(T59=0%,0,(B59+R59)*T59+(B59+R59)) -> 0 | V59: =(U59*$V$8)-S59 -> 0 | X59: =A59 -> BRAZIMIL ACRILICA POTE 1KG | Y59: =+C59 -> 0 | Z59: =IF(ISERROR(Y59*N59),"",Y59*N59) -> 0 | AA59: =IF(ISERROR(IF(E$7="X",Y59*E59,Y59*F59)),"",IF(E$7="X",Y59*E59,Y59*F59)) -> 0 | AB59: =IF(ISERROR(Z59/AA59),"",Z59/AA59) | AE59: 0.05 | AF59: =+'Frete_Regiao-Impostos'!A53 -> 0 | AG59: =+'Frete_Regiao-Impostos'!B53 -> 0 | AH59: =+'Frete_Regiao-Impostos'!C53 -> 0 | AI59: =+'Frete_Regiao-Impostos'!D53 -> 0 | AP59: =Peso!B61 -> 1.04
A60: BRAZIMIL ACRILICA GALÃO 5KG | B60: 19.16 | D60: =IF($F$7="x",IF(F60=0,0,N60/F60),IF($E$7="x",IF(F60=0,0,N60/E60),"")) -> 0.33047618 | E60: =+B60*(-B$5+100%) -> 17.8188 | F60: =IF(B60=0,0,E60-H60) -> 17.3003 | G60: =VLOOKUP(A60,Custo!A:B,2,0) -> 10.453611 | H60: =(VLOOKUP(A60,Peso!$A$10:$B$148,2,0))*($B$6/1000) -> 0.5185 | I60: =IF($I$7="X",AE60,0%) -> 0.05 | J60: =+B60*I60 -> 0.958 | K60: =IF($B$2="X",$C$2,0) -> 0 | L60: =+B60*K60 -> 0 | M60: =+G60+H60+J60+L60 -> 11.930111 | N60: =+E60-M60 -> 5.888689 | O60: =IF(ISERROR((N60/P60)*100),"",(N60/P60)*100) | Q60: =VLOOKUP(A60,'MVA-IPI'!A:AD,30,FALSE) -> 0.02 | R60: =IF($B$4="AM",0,IF($B$4="AP",0,IF($B$4="RR",0,(B60*Q60)))) -> 0 | S60: =IF($B$4="AP",(B60/0.88*$S$8),IF(T60=0%,0,IF($B$4="AM",(B60/0.88*$S$8),IF(T60=0%,0,IF($B$4="RR",(B60/0.88*$S$8),IF(T60=0%,0,B60*$S$8)))))) -> 0 | T60: =IF($C$4="GRUPO 1",VLOOKUP(A60,'MVA-grupos'!$A$9:$B$128,2,FALSE),IF($C$4="GRUPO 2",VLOOKUP(A60,'MVA-grupos'!$A$9:$D$128,4,FALSE),IF($C$4="GRUPO 3",VLOOKUP(A60,'MVA-grupos'!$A$10:$F$128,6,FALSE),IF($C$4="Grupo 4",VLOOKUP(A60,'MVA-grupos'!$A$9:$H$128,8,FALSE))))) -> 0 | U60: =IF(T60=0%,0,(B60+R60)*T60+(B60+R60)) -> 0 | V60: =(U60*$V$8)-S60 -> 0 | X60: =A60 -> BRAZIMIL ACRILICA GALÃO 5KG | Y60: =+C60 -> 0 | Z60: =IF(ISERROR(Y60*N60),"",Y60*N60) -> 0 | AA60: =IF(ISERROR(IF(E$7="X",Y60*E60,Y60*F60)),"",IF(E$7="X",Y60*E60,Y60*F60)) -> 0 | AB60: =IF(ISERROR(Z60/AA60),"",Z60/AA60) | AE60: 0.05 | AF60: =+'Frete_Regiao-Impostos'!A54 -> 0 | AG60: =+'Frete_Regiao-Impostos'!B54 -> 0 | AH60: =+'Frete_Regiao-Impostos'!C54 -> 0 | AI60: =+'Frete_Regiao-Impostos'!D54 -> 0 | AP60: =Peso!B62 -> 5.185
A61: BRAZIMIL ACRILICA SACO VALV 10,0KG | B61: 27 | D61: =IF($F$7="x",IF(F61=0,0,N61/F61),IF($E$7="x",IF(F61=0,0,N61/E61),"")) -> 0.39315795 | E61: =+B61*(-B$5+100%) -> 25.11 | F61: =IF(B61=0,0,E61-H61) -> 24.105 | G61: =VLOOKUP(A61,Custo!A:B,2,0) -> 12.882804 | H61: =(VLOOKUP(A61,Peso!$A$10:$B$148,2,0))*($B$6/1000) -> 1.005 | I61: =IF($I$7="X",AE61,0%) -> 0.05 | J61: =+B61*I61 -> 1.35 | K61: =IF($B$2="X",$C$2,0) -> 0 | L61: =+B61*K61 -> 0 | M61: =+G61+H61+J61+L61 -> 15.237804 | N61: =+E61-M61 -> 9.8721962 | O61: =IF(ISERROR((N61/P61)*100),"",(N61/P61)*100) | Q61: =VLOOKUP(A61,'MVA-IPI'!A:AD,30,FALSE) -> 0.02 | R61: =IF($B$4="AM",0,IF($B$4="AP",0,IF($B$4="RR",0,(B61*Q61)))) -> 0 | S61: =IF($B$4="AP",(B61/0.88*$S$8),IF(T61=0%,0,IF($B$4="AM",(B61/0.88*$S$8),IF(T61=0%,0,IF($B$4="RR",(B61/0.88*$S$8),IF(T61=0%,0,B61*$S$8)))))) -> 0 | T61: =IF($C$4="GRUPO 1",VLOOKUP(A61,'MVA-grupos'!$A$9:$B$128,2,FALSE),IF($C$4="GRUPO 2",VLOOKUP(A61,'MVA-grupos'!$A$9:$D$128,4,FALSE),IF($C$4="GRUPO 3",VLOOKUP(A61,'MVA-grupos'!$A$10:$F$128,6,FALSE),IF($C$4="Grupo 4",VLOOKUP(A61,'MVA-grupos'!$A$9:$H$128,8,FALSE))))) -> 0 | U61: =IF(T61=0%,0,(B61+R61)*T61+(B61+R61)) -> 0 | V61: =(U61*$V$8)-S61 -> 0 | X61: =A61 -> BRAZIMIL ACRILICA SACO VALV 10,0KG | Y61: =+C61 -> 0 | Z61: =IF(ISERROR(Y61*N61),"",Y61*N61) -> 0 | AA61: =IF(ISERROR(IF(E$7="X",Y61*E61,Y61*F61)),"",IF(E$7="X",Y61*E61,Y61*F61)) -> 0 | AB61: =IF(ISERROR(Z61/AA61),"",Z61/AA61) | AE61: 0.05 | AP61: =Peso!B63 -> 10.05
A62: BRAZIMIL ACRILICA BALDE 20KG | B62: 62.26 | D62: =IF($F$7="x",IF(F62=0,0,N62/F62),IF($E$7="x",IF(F62=0,0,N62/E62),"")) -> 0.2884619 | E62: =+B62*(-B$5+100%) -> 57.9018 | F62: =IF(B62=0,0,E62-H62) -> 55.8318 | G62: =VLOOKUP(A62,Custo!A:B,2,0) -> 36.016337 | H62: =(VLOOKUP(A62,Peso!$A$10:$B$148,2,0))*($B$6/1000) -> 2.07 | I62: =IF($I$7="X",AE62,0%) -> 0.05 | J62: =+B62*I62 -> 3.113 | K62: =IF($B$2="X",$C$2,0) -> 0 | L62: =+B62*K62 -> 0 | M62: =+G62+H62+J62+L62 -> 41.199337 | N62: =+E62-M62 -> 16.702463 | O62: =IF(ISERROR((N62/P62)*100),"",(N62/P62)*100) | Q62: =VLOOKUP(A62,'MVA-IPI'!A:AD,30,FALSE) -> 0.02 | R62: =IF($B$4="AM",0,IF($B$4="AP",0,IF($B$4="RR",0,(B62*Q62)))) -> 0 | S62: =IF($B$4="AP",(B62/0.88*$S$8),IF(T62=0%,0,IF($B$4="AM",(B62/0.88*$S$8),IF(T62=0%,0,IF($B$4="RR",(B62/0.88*$S$8),IF(T62=0%,0,B62*$S$8)))))) -> 0 | T62: =IF($C$4="GRUPO 1",VLOOKUP(A62,'MVA-grupos'!$A$9:$B$128,2,FALSE),IF($C$4="GRUPO 2",VLOOKUP(A62,'MVA-grupos'!$A$9:$D$128,4,FALSE),IF($C$4="GRUPO 3",VLOOKUP(A62,'MVA-grupos'!$A$10:$F$128,6,FALSE),IF($C$4="Grupo 4",VLOOKUP(A62,'MVA-grupos'!$A$9:$H$128,8,FALSE))))) -> 0 | U62: =IF(T62=0%,0,(B62+R62)*T62+(B62+R62)) -> 0 | V62: =(U62*$V$8)-S62 -> 0 | X62: =A62 -> BRAZIMIL ACRILICA BALDE 20KG | Y62: =+C62 -> 0 | Z62: =IF(ISERROR(Y62*N62),"",Y62*N62) -> 0 | AA62: =IF(ISERROR(IF(E$7="X",Y62*E62,Y62*F62)),"",IF(E$7="X",Y62*E62,Y62*F62)) -> 0 | AB62: =IF(ISERROR(Z62/AA62),"",Z62/AA62) | AE62: 0.05 | AP62: =Peso!B66 -> 20.7
A63: BRAZIMIL ACRILICA PPQ 20KG | B63: 42.09 | D63: =IF($F$7="x",IF(F63=0,0,N63/F63),IF($E$7="x",IF(F63=0,0,N63/E63),"")) -> 0.89317566 | E63: =+B63*(-B$5+100%) -> 39.1437 | F63: =IF(B63=0,0,E63-H63) -> 37.0667 | G63: =VLOOKUP(A63,Custo!A:B,2,0) -> 0 | H63: =(VLOOKUP(A63,Peso!$A$10:$B$148,2,0))*($B$6/1000) -> 2.077 | I63: =IF($I$7="X",AE63,0%) -> 0.05 | J63: =+B63*I63 -> 2.1045 | M63: =+G63+H63+J63 -> 4.1815 | N63: =+E63-M63 -> 34.9622 | O63: =IF(ISERROR((N63/P63)*100),"",(N63/P63)*100) | Q63: =VLOOKUP(A63,'MVA-IPI'!A:AD,30,FALSE) -> 0.02 | R63: =IF($B$4="AM",0,IF($B$4="AP",0,IF($B$4="RR",0,(B63*Q63)))) -> 0 | S63: =IF($B$4="AP",(B63/0.88*$S$8),IF(T63=0%,0,IF($B$4="AM",(B63/0.88*$S$8),IF(T63=0%,0,IF($B$4="RR",(B63/0.88*$S$8),IF(T63=0%,0,B63*$S$8)))))) -> 0 | T63: =IF($C$4="GRUPO 1",VLOOKUP(A63,'MVA-grupos'!$A$9:$B$128,2,FALSE),IF($C$4="GRUPO 2",VLOOKUP(A63,'MVA-grupos'!$A$9:$D$128,4,FALSE),IF($C$4="GRUPO 3",VLOOKUP(A63,'MVA-grupos'!$A$10:$F$128,6,FALSE),IF($C$4="Grupo 4",VLOOKUP(A63,'MVA-grupos'!$A$9:$H$128,8,FALSE))))) -> 0 | U63: =IF(T63=0%,0,(B63+R63)*T63+(B63+R63)) -> 0 | V63: =(U63*$V$8)-S63 -> 0 | X63: =A63 -> BRAZIMIL ACRILICA PPQ 20KG | Y63: =+C63 -> 0 | Z63: =IF(ISERROR(Y63*N63),"",Y63*N63) -> 0 | AA63: =IF(ISERROR(IF(E$7="X",Y63*E63,Y63*F63)),"",IF(E$7="X",Y63*E63,Y63*F63)) -> 0 | AB63: =IF(ISERROR(Z63/AA63),"",Z63/AA63) | AE63: 0.05 | AP63: =Peso!B64 -> 20.77
A64: BRAZIMIL ACRILICA PPQ 25KG | B64: 53.11 | D64: =IF($F$7="x",IF(F64=0,0,N64/F64),IF($E$7="x",IF(F64=0,0,N64/E64),"")) -> 0.89406243 | E64: =+B64*(-B$5+100%) -> 49.3923 | F64: =IF(B64=0,0,E64-H64) -> 46.8153 | G64: =VLOOKUP(A64,Custo!A:B,2,0) -> 0 | H64: =(VLOOKUP(A64,Peso!$A$10:$B$148,2,0))*($B$6/1000) -> 2.577 | I64: =IF($I$7="X",AE64,0%) -> 0.05 | J64: =+B64*I64 -> 2.6555 | M64: =+G64+H64+J64 -> 5.2325 | N64: =+E64-M64 -> 44.1598 | O64: =IF(ISERROR((N64/P64)*100),"",(N64/P64)*100) | Q64: =VLOOKUP(A64,'MVA-IPI'!A:AD,30,FALSE) -> 0.02 | R64: =IF($B$4="AM",0,IF($B$4="AP",0,IF($B$4="RR",0,(B64*Q64)))) -> 0 | S64: =IF($B$4="AP",(B64/0.88*$S$8),IF(T64=0%,0,IF($B$4="AM",(B64/0.88*$S$8),IF(T64=0%,0,IF($B$4="RR",(B64/0.88*$S$8),IF(T64=0%,0,B64*$S$8)))))) -> 0 | T64: =IF($C$4="GRUPO 1",VLOOKUP(A64,'MVA-grupos'!$A$9:$B$128,2,FALSE),IF($C$4="GRUPO 2",VLOOKUP(A64,'MVA-grupos'!$A$9:$D$128,4,FALSE),IF($C$4="GRUPO 3",VLOOKUP(A64,'MVA-grupos'!$A$10:$F$128,6,FALSE),IF($C$4="Grupo 4",VLOOKUP(A64,'MVA-grupos'!$A$9:$H$128,8,FALSE))))) -> 0 | U64: =IF(T64=0%,0,(B64+R64)*T64+(B64+R64)) -> 0 | V64: =(U64*$V$8)-S64 -> 0 | X64: =A64 -> BRAZIMIL ACRILICA PPQ 25KG | Y64: =+C64 -> 0 | Z64: =IF(ISERROR(Y64*N64),"",Y64*N64) -> 0 | AA64: =IF(ISERROR(IF(E$7="X",Y64*E64,Y64*F64)),"",IF(E$7="X",Y64*E64,Y64*F64)) -> 0 | AB64: =IF(ISERROR(Z64/AA64),"",Z64/AA64) | AE64: 0.05 | AP64: =Peso!B65 -> 25.77
A65: BRAZIMIL ACRILICA BALDE 25KG | B65: 0 | D65: =IF($F$7="x",IF(F65=0,0,N65/F65),IF($E$7="x",IF(F65=0,0,N65/E65),"")) -> 0 | E65: =+B65*(-B$5+100%) -> 0 | F65: =IF(B65=0,0,E65-H65) -> 0 | G65: =VLOOKUP(A65,Custo!A:B,2,0) -> 40.333884 | H65: =(VLOOKUP(A65,Peso!$A$10:$B$148,2,0))*($B$6/1000) -> 2.564 | I65: =IF($I$7="X",AE65,0%) -> 0.05 | J65: =+B65*I65 -> 0 | K65: =IF($B$2="X",$C$2,0) -> 0 | L65: =+B65*K65 -> 0 | M65: =+G65+H65+J65+L65 -> 42.897884 | N65: =+E65-M65 -> -42.897884 | O65: =IF(ISERROR((N65/P65)*100),"",(N65/P65)*100) | Q65: =VLOOKUP(A65,'MVA-IPI'!A:AD,30,FALSE) -> 0.02 | R65: =IF($B$4="AM",0,IF($B$4="AP",0,IF($B$4="RR",0,(B65*Q65)))) -> 0 | S65: =IF($B$4="AP",(B65/0.88*$S$8),IF(T65=0%,0,IF($B$4="AM",(B65/0.88*$S$8),IF(T65=0%,0,IF($B$4="RR",(B65/0.88*$S$8),IF(T65=0%,0,B65*$S$8)))))) -> 0 | T65: =IF($C$4="GRUPO 1",VLOOKUP(A65,'MVA-grupos'!$A$9:$B$128,2,FALSE),IF($C$4="GRUPO 2",VLOOKUP(A65,'MVA-grupos'!$A$9:$D$128,4,FALSE),IF($C$4="GRUPO 3",VLOOKUP(A65,'MVA-grupos'!$A$10:$F$128,6,FALSE),IF($C$4="Grupo 4",VLOOKUP(A65,'MVA-grupos'!$A$9:$H$128,8,FALSE))))) -> 0 | U65: =IF(T65=0%,0,(B65+R65)*T65+(B65+R65)) -> 0 | V65: =(U65*$V$8)-S65 -> 0 | X65: =A65 -> BRAZIMIL ACRILICA BALDE 25KG | Y65: =+C65 -> 0 | Z65: =IF(ISERROR(Y65*N65),"",Y65*N65) -> 0 | AA65: =IF(ISERROR(IF(E$7="X",Y65*E65,Y65*F65)),"",IF(E$7="X",Y65*E65,Y65*F65)) -> 0 | AB65: =IF(ISERROR(Z65/AA65),"",Z65/AA65) | AE65: 0.05 | AP65: =Peso!B67 -> 25.64
A66: BRAZIMIL TEXT. LISA | D66: =AB66 | X66: =A66 -> BRAZIMIL TEXT. LISA | Z66: =SUM(Z67:Z70) -> 0 | AA66: =SUM(AA67:AA70) -> 0 | AB66: =IF(ISERROR(Z66/AA66),"",Z66/AA66) | AC66: 0.25 | AE66: 0.05 | AP66: =Peso!B68 -> 0
A67: BRAZIMIL TEXT. LISA GALÃO 5KG | B67: 0 | D67: =IF($F$7="x",IF(F67=0,0,N67/F67),IF($E$7="x",IF(F67=0,0,N67/E67),"")) -> 0 | E67: =+B67*(-B$5+100%) -> 0 | F67: =IF(B67=0,0,E67-H67) -> 0 | G67: =VLOOKUP(A67,Custo!A:B,2,0) -> 0 | H67: =(VLOOKUP(A67,Peso!$A$10:$B$148,2,0))*($B$6/1000) -> 0.516 | I67: =IF($I$7="X",AE67,0%) -> 0.05 | J67: =+B67*I67 -> 0 | K67: =IF($B$2="X",$C$2,0) -> 0 | L67: =+B67*K67 -> 0 | M67: =+G67+H67+J67+L67 -> 0.516 | N67: =+E67-M67 -> -0.516 | O67: =IF(ISERROR((N67/P67)*1000),"",(N67/P67)*1000) | Q67: =VLOOKUP(A67,'MVA-IPI'!A:AD,30,FALSE) -> 0 | R67: =IF($B$4="AM",0,IF($B$4="AP",0,IF($B$4="RR",0,(B67*Q67)))) -> 0 | S67: =IF($B$4="AP",(B67/0.88*$S$8),IF(T67=0%,0,IF($B$4="AM",(B67/0.88*$S$8),IF(T67=0%,0,IF($B$4="RR",(B67/0.88*$S$8),IF(T67=0%,0,B67*$S$8)))))) -> 0 | T67: =IF($C$4="GRUPO 1",VLOOKUP(A67,'MVA-grupos'!$A$9:$B$128,2,FALSE),IF($C$4="GRUPO 2",VLOOKUP(A67,'MVA-grupos'!$A$9:$D$128,4,FALSE),IF($C$4="GRUPO 3",VLOOKUP(A67,'MVA-grupos'!$A$10:$F$128,6,FALSE),IF($C$4="Grupo 4",VLOOKUP(A67,'MVA-grupos'!$A$9:$H$128,8,FALSE))))) -> 0 | U67: =IF(T67=0%,0,(B67+R67)*T67+(B67+R67)) -> 0 | V67: =(U67*$V$8)-S67 -> 0 | X67: =A67 -> BRAZIMIL TEXT. LISA GALÃO 5KG | Y67: =+C67 -> 0 | Z67: =IF(ISERROR(Y67*N67),"",Y67*N67) -> 0 | AA67: =IF(ISERROR(IF(E$7="X",Y67*E67,Y67*F67)),"",IF(E$7="X",Y67*E67,Y67*F67)) -> 0 | AB67: =IF(ISERROR(Z67/AA67),"",Z67/AA67) | AE67: 0.05 | AP67: =Peso!B69 -> 5.16
A68: BRAZIMIL TEXT. LISA SACO VALV 12,5KG | B68: 0 | D68: =IF($F$7="x",IF(F68=0,0,N68/F68),IF($E$7="x",IF(F68=0,0,N68/E68),"")) -> 0 | E68: =+B68*(-B$5+100%) -> 0 | F68: =IF(B68=0,0,E68-H68) -> 0 | G68: =VLOOKUP(A68,Custo!A:B,2,0) -> 15.460622 | H68: =(VLOOKUP(A68,Peso!$A$10:$B$148,2,0))*($B$6/1000) -> 1.254 | I68: =IF($I$7="X",AE68,0%) -> 0.05 | J68: =+B68*I68 -> 0 | K68: =IF($B$2="X",$C$2,0) -> 0 | L68: =+B68*K68 -> 0 | M68: =+G68+H68+J68+L68 -> 16.714622 | N68: =+E68-M68 -> -16.714622 | O68: =IF(ISERROR((N68/P68)*1000),"",(N68/P68)*1000) | Q68: =VLOOKUP(A68,'MVA-IPI'!A:AD,30,FALSE) -> 0 | R68: =IF($B$4="AM",0,IF($B$4="AP",0,IF($B$4="RR",0,(B68*Q68)))) -> 0 | S68: =IF($B$4="AP",(B68/0.88*$S$8),IF(T68=0%,0,IF($B$4="AM",(B68/0.88*$S$8),IF(T68=0%,0,IF($B$4="RR",(B68/0.88*$S$8),IF(T68=0%,0,B68*$S$8)))))) -> 0 | T68: =IF($C$4="GRUPO 1",VLOOKUP(A68,'MVA-grupos'!$A$9:$B$128,2,FALSE),IF($C$4="GRUPO 2",VLOOKUP(A68,'MVA-grupos'!$A$9:$D$128,4,FALSE),IF($C$4="GRUPO 3",VLOOKUP(A68,'MVA-grupos'!$A$10:$F$128,6,FALSE),IF($C$4="Grupo 4",VLOOKUP(A68,'MVA-grupos'!$A$9:$H$128,8,FALSE))))) -> 0 | U68: =IF(T68=0%,0,(B68+R68)*T68+(B68+R68)) -> 0 | V68: =(U68*$V$8)-S68 -> 0 | X68: =A68 -> BRAZIMIL TEXT. LISA SACO VALV 12,5KG | Y68: =+C68 -> 0 | Z68: =IF(ISERROR(Y68*N68),"",Y68*N68) -> 0 | AA68: =IF(ISERROR(IF(E$7="X",Y68*E68,Y68*F68)),"",IF(E$7="X",Y68*E68,Y68*F68)) -> 0 | AB68: =IF(ISERROR(Z68/AA68),"",Z68/AA68) | AE68: 0.05 | AP68: =Peso!B70 -> 12.54
A69: BRAZIMIL TEXT. LISA PPQ 25KG | B69: 0 | D69: =IF($F$7="x",IF(F69=0,0,N69/F69),IF($E$7="x",IF(F69=0,0,N69/E69),"")) -> 0 | E69: =+B69*(-B$5+100%) -> 0 | F69: =IF(B69=0,0,E69-H69) -> 0 | G69: =VLOOKUP(A69,Custo!A:B,2,0) -> 0 | H69: =(VLOOKUP(A69,Peso!$A$10:$B$148,2,0))*($B$6/1000) -> 2.577 | I69: =IF($I$7="X",AE69,0%) -> 0.05 | J69: =+B69*I69 -> 0 | K69: =IF($B$2="X",$C$2,0) -> 0 | L69: =+B69*K69 -> 0 | M69: =+G69+H69+J69+L69 -> 2.577 | N69: =+E69-M69 -> -2.577 | O69: =IF(ISERROR((N69/P69)*1000),"",(N69/P69)*1000) | Q69: =VLOOKUP(A69,'MVA-IPI'!A:AD,30,FALSE) -> 0 | R69: =IF($B$4="AM",0,IF($B$4="AP",0,IF($B$4="RR",0,(B69*Q69)))) -> 0 | S69: =IF($B$4="AP",(B69/0.88*$S$8),IF(T69=0%,0,IF($B$4="AM",(B69/0.88*$S$8),IF(T69=0%,0,IF($B$4="RR",(B69/0.88*$S$8),IF(T69=0%,0,B69*$S$8)))))) -> 0 | T69: =IF($C$4="GRUPO 1",VLOOKUP(A69,'MVA-grupos'!$A$9:$B$128,2,FALSE),IF($C$4="GRUPO 2",VLOOKUP(A69,'MVA-grupos'!$A$9:$D$128,4,FALSE),IF($C$4="GRUPO 3",VLOOKUP(A69,'MVA-grupos'!$A$10:$F$128,6,FALSE),IF($C$4="Grupo 4",VLOOKUP(A69,'MVA-grupos'!$A$9:$H$128,8,FALSE))))) -> 0 | U69: =IF(T69=0%,0,(B69+R69)*T69+(B69+R69)) -> 0 | V69: =(U69*$V$8)-S69 -> 0 | X69: =A69 -> BRAZIMIL TEXT. LISA PPQ 25KG | Y69: =+C69 -> 0 | Z69: =IF(ISERROR(Y69*N69),"",Y69*N69) -> 0 | AA69: =IF(ISERROR(IF(E$7="X",Y69*E69,Y69*F69)),"",IF(E$7="X",Y69*E69,Y69*F69)) -> 0 | AB69: =IF(ISERROR(Z69/AA69),"",Z69/AA69) | AE69: 0.05 | AP69: =Peso!B71 -> 25.77
A70: BRAZIMIL TEXT. LISA BALDE 25KG | B70: 0 | D70: =IF($F$7="x",IF(F70=0,0,N70/F70),IF($E$7="x",IF(F70=0,0,N70/E70),"")) -> 0 | E70: =+B70*(-B$5+100%) -> 0 | F70: =IF(B70=0,0,E70-H70) -> 0 | G70: =VLOOKUP(A70,Custo!A:B,2,0) -> 46.778431 | H70: =(VLOOKUP(A70,Peso!$A$10:$B$148,2,0))*($B$6/1000) -> 2.564 | I70: =IF($I$7="X",AE70,0%) -> 0.05 | J70: =+B70*I70 -> 0 | K70: =IF($B$2="X",$C$2,0) -> 0 | L70: =+B70*K70 -> 0 | M70: =+G70+H70+J70+L70 -> 49.342431 | N70: =+E70-M70 -> -49.342431 | O70: =IF(ISERROR((N70/P70)*1000),"",(N70/P70)*1000) | Q70: =VLOOKUP(A70,'MVA-IPI'!A:AD,30,FALSE) -> 0 | R70: =IF($B$4="AM",0,IF($B$4="AP",0,IF($B$4="RR",0,(B70*Q70)))) -> 0 | S70: =IF($B$4="AP",(B70/0.88*$S$8),IF(T70=0%,0,IF($B$4="AM",(B70/0.88*$S$8),IF(T70=0%,0,IF($B$4="RR",(B70/0.88*$S$8),IF(T70=0%,0,B70*$S$8)))))) -> 0 | T70: =IF($C$4="GRUPO 1",VLOOKUP(A70,'MVA-grupos'!$A$9:$B$128,2,FALSE),IF($C$4="GRUPO 2",VLOOKUP(A70,'MVA-grupos'!$A$9:$D$128,4,FALSE),IF($C$4="GRUPO 3",VLOOKUP(A70,'MVA-grupos'!$A$10:$F$128,6,FALSE),IF($C$4="Grupo 4",VLOOKUP(A70,'MVA-grupos'!$A$9:$H$128,8,FALSE))))) -> 0 | U70: =IF(T70=0%,0,(B70+R70)*T70+(B70+R70)) -> 0 | V70: =(U70*$V$8)-S70 -> 0 | X70: =A70 -> BRAZIMIL TEXT. LISA BALDE 25KG | Y70: =+C70 -> 0 | Z70: =IF(ISERROR(Y70*N70),"",Y70*N70) -> 0 | AA70: =IF(ISERROR(IF(E$7="X",Y70*E70,Y70*F70)),"",IF(E$7="X",Y70*E70,Y70*F70)) -> 0 | AB70: =IF(ISERROR(Z70/AA70),"",Z70/AA70) | AE70: 0.05 | AP70: =Peso!B72 -> 25.64
A71: BRAZIMIL TEXT. RÚSTICA | D71: =AB71 | I71: =IF($I$7="X",AE71,0%) -> 0 | X71: =A71 -> BRAZIMIL TEXT. RÚSTICA | Z71: =SUM(Z72:Z75) -> 0 | AA71: =SUM(AA72:AA75) -> 0 | AB71: =IF(ISERROR(Z71/AA71),"",Z71/AA71) | AC71: 0.25 | AP71: =Peso!B73 -> 0
A72: BRAZIMIL TEXT. RÚSTICA GALÃO 5KG | B72: 14.44 | D72: =IF($F$7="x",IF(F72=0,0,N72/F72),IF($E$7="x",IF(F72=0,0,N72/E72),"")) -> 0.90781283 | E72: =+B72*(-B$5+100%) -> 13.4292 | F72: =IF(B72=0,0,E72-H72) -> 12.9132 | G72: =VLOOKUP(A72,Custo!A:B,2,0) -> 0 | H72: =(VLOOKUP(A72,Peso!$A$10:$B$148,2,0))*($B$6/1000) -> 0.516 | I72: =IF($I$7="X",AE72,0%) -> 0.05 | J72: =+B72*I72 -> 0.722 | M72: =+G72+H72+J72 -> 1.238 | N72: =+E72-M72 -> 12.1912 | O72: =IF(ISERROR((N72/P72)*1000),"",(N72/P72)*1000) | Q72: =VLOOKUP(A72,'MVA-IPI'!A:AD,30,FALSE) -> 0 | R72: =IF($B$4="AM",0,IF($B$4="AP",0,IF($B$4="RR",0,(B72*Q72)))) -> 0 | S72: =IF($B$4="AP",(B72/0.88*$S$8),IF(T72=0%,0,IF($B$4="AM",(B72/0.88*$S$8),IF(T72=0%,0,IF($B$4="RR",(B72/0.88*$S$8),IF(T72=0%,0,B72*$S$8)))))) -> 0 | T72: =IF($C$4="GRUPO 1",VLOOKUP(A72,'MVA-grupos'!$A$9:$B$128,2,FALSE),IF($C$4="GRUPO 2",VLOOKUP(A72,'MVA-grupos'!$A$9:$D$128,4,FALSE),IF($C$4="GRUPO 3",VLOOKUP(A72,'MVA-grupos'!$A$10:$F$128,6,FALSE),IF($C$4="Grupo 4",VLOOKUP(A72,'MVA-grupos'!$A$9:$H$128,8,FALSE))))) -> 0 | U72: =IF(T72=0%,0,(B72+R72)*T72+(B72+R72)) -> 0 | V72: =(U72*$V$8)-S72 -> 0 | X72: =A72 -> BRAZIMIL TEXT. RÚSTICA GALÃO 5KG | Y72: =+C72 -> 0 | Z72: =IF(ISERROR(Y72*N72),"",Y72*N72) -> 0 | AA72: =IF(ISERROR(IF(E$7="X",Y72*E72,Y72*F72)),"",IF(E$7="X",Y72*E72,Y72*F72)) -> 0 | AB72: =IF(ISERROR(Z72/AA72),"",Z72/AA72) | AE72: 0.05 | AP72: =Peso!B74 -> 5.16
A73: BRAZIMIL TEXT. RÚSTICA SACO VALV 12,5KG | B73: 14.44 | D73: =IF($F$7="x",IF(F73=0,0,N73/F73),IF($E$7="x",IF(F73=0,0,N73/E73),"")) -> 0.85285795 | E73: =+B73*(-B$5+100%) -> 13.4292 | F73: =IF(B73=0,0,E73-H73) -> 12.1752 | G73: =VLOOKUP(A73,Custo!A:B,2,0) -> 0 | H73: =(VLOOKUP(A73,Peso!$A$10:$B$148,2,0))*($B$6/1000) -> 1.254 | I73: =IF($I$7="X",AE73,0%) -> 0.05 | J73: =+B73*I73 -> 0.722 | M73: =+G73+H73+J73 -> 1.976 | N73: =+E73-M73 -> 11.4532 | O73: =IF(ISERROR((N73/P73)*1000),"",(N73/P73)*1000) | Q73: =VLOOKUP(A73,'MVA-IPI'!A:AD,30,FALSE) -> 0 | R73: =IF($B$4="AM",0,IF($B$4="AP",0,IF($B$4="RR",0,(B73*Q73)))) -> 0 | S73: =IF($B$4="AP",(B73/0.88*$S$8),IF(T73=0%,0,IF($B$4="AM",(B73/0.88*$S$8),IF(T73=0%,0,IF($B$4="RR",(B73/0.88*$S$8),IF(T73=0%,0,B73*$S$8)))))) -> 0 | T73: =IF($C$4="GRUPO 1",VLOOKUP(A73,'MVA-grupos'!$A$9:$B$128,2,FALSE),IF($C$4="GRUPO 2",VLOOKUP(A73,'MVA-grupos'!$A$9:$D$128,4,FALSE),IF($C$4="GRUPO 3",VLOOKUP(A73,'MVA-grupos'!$A$10:$F$128,6,FALSE),IF($C$4="Grupo 4",VLOOKUP(A73,'MVA-grupos'!$A$9:$H$128,8,FALSE))))) -> 0 | U73: =IF(T73=0%,0,(B73+R73)*T73+(B73+R73)) -> 0 | V73: =(U73*$V$8)-S73 -> 0 | X73: =A73 -> BRAZIMIL TEXT. RÚSTICA SACO VALV 12,5KG | Y73: =+C73 -> 0 | Z73: =IF(ISERROR(Y73*N73),"",Y73*N73) -> 0 | AA73: =IF(ISERROR(IF(E$7="X",Y73*E73,Y73*F73)),"",IF(E$7="X",Y73*E73,Y73*F73)) -> 0 | AB73: =IF(ISERROR(Z73/AA73),"",Z73/AA73) | AE73: 0.05 | AP73: =Peso!B75 -> 12.54
A74: BRAZIMIL TEXT. RÚSTICA PPQ 25KG | B74: 14.44 | D74: =IF($F$7="x",IF(F74=0,0,N74/F74),IF($E$7="x",IF(F74=0,0,N74/E74),"")) -> 0.75434129 | E74: =+B74*(-B$5+100%) -> 13.4292 | F74: =IF(B74=0,0,E74-H74) -> 10.8522 | G74: =VLOOKUP(A74,Custo!A:B,2,0) -> 0 | H74: =(VLOOKUP(A74,Peso!$A$10:$B$148,2,0))*($B$6/1000) -> 2.577 | I74: =IF($I$7="X",AE74,0%) -> 0.05 | J74: =+B74*I74 -> 0.722 | M74: =+G74+H74+J74 -> 3.299 | N74: =+E74-M74 -> 10.1302 | O74: =IF(ISERROR((N74/P74)*1000),"",(N74/P74)*1000) | Q74: =VLOOKUP(A74,'MVA-IPI'!A:AD,30,FALSE) -> 0 | R74: =IF($B$4="AM",0,IF($B$4="AP",0,IF($B$4="RR",0,(B74*Q74)))) -> 0 | S74: =IF($B$4="AP",(B74/0.88*$S$8),IF(T74=0%,0,IF($B$4="AM",(B74/0.88*$S$8),IF(T74=0%,0,IF($B$4="RR",(B74/0.88*$S$8),IF(T74=0%,0,B74*$S$8)))))) -> 0 | T74: =IF($C$4="GRUPO 1",VLOOKUP(A74,'MVA-grupos'!$A$9:$B$128,2,FALSE),IF($C$4="GRUPO 2",VLOOKUP(A74,'MVA-grupos'!$A$9:$D$128,4,FALSE),IF($C$4="GRUPO 3",VLOOKUP(A74,'MVA-grupos'!$A$10:$F$128,6,FALSE),IF($C$4="Grupo 4",VLOOKUP(A74,'MVA-grupos'!$A$9:$H$128,8,FALSE))))) -> 0 | U74: =IF(T74=0%,0,(B74+R74)*T74+(B74+R74)) -> 0 | V74: =(U74*$V$8)-S74 -> 0 | X74: =A74 -> BRAZIMIL TEXT. RÚSTICA PPQ 25KG | Y74: =+C74 -> 0 | Z74: =IF(ISERROR(Y74*N74),"",Y74*N74) -> 0 | AA74: =IF(ISERROR(IF(E$7="X",Y74*E74,Y74*F74)),"",IF(E$7="X",Y74*E74,Y74*F74)) -> 0 | AB74: =IF(ISERROR(Z74/AA74),"",Z74/AA74) | AE74: 0.05 | AP74: =Peso!B76 -> 25.77
A75: BRAZIMIL TEXT. RÚSTICA BALDE 25KG | B75: 72.46 | D75: =IF($F$7="x",IF(F75=0,0,N75/F75),IF($E$7="x",IF(F75=0,0,N75/E75),"")) -> 0.90818813 | E75: =+B75*(-B$5+100%) -> 67.3878 | F75: =IF(B75=0,0,E75-H75) -> 64.8238 | G75: =VLOOKUP(A75,Custo!A:B,2,0) -> 0 | H75: =(VLOOKUP(A75,Peso!$A$10:$B$148,2,0))*($B$6/1000) -> 2.564 | I75: =IF($I$7="X",AE75,0%) -> 0.05 | J75: =+B75*I75 -> 3.623 | M75: =+G75+H75+J75 -> 6.187 | N75: =+E75-M75 -> 61.2008 | O75: =IF(ISERROR((N75/P75)*1000),"",(N75/P75)*1000) | Q75: =VLOOKUP(A75,'MVA-IPI'!A:AD,30,FALSE) -> 0 | R75: =IF($B$4="AM",0,IF($B$4="AP",0,IF($B$4="RR",0,(B75*Q75)))) -> 0 | S75: =IF($B$4="AP",(B75/0.88*$S$8),IF(T75=0%,0,IF($B$4="AM",(B75/0.88*$S$8),IF(T75=0%,0,IF($B$4="RR",(B75/0.88*$S$8),IF(T75=0%,0,B75*$S$8)))))) -> 0 | T75: =IF($C$4="GRUPO 1",VLOOKUP(A75,'MVA-grupos'!$A$9:$B$128,2,FALSE),IF($C$4="GRUPO 2",VLOOKUP(A75,'MVA-grupos'!$A$9:$D$128,4,FALSE),IF($C$4="GRUPO 3",VLOOKUP(A75,'MVA-grupos'!$A$10:$F$128,6,FALSE),IF($C$4="Grupo 4",VLOOKUP(A75,'MVA-grupos'!$A$9:$H$128,8,FALSE))))) -> 0 | U75: =IF(T75=0%,0,(B75+R75)*T75+(B75+R75)) -> 0 | V75: =(U75*$V$8)-S75 -> 0 | X75: =A75 -> BRAZIMIL TEXT. RÚSTICA BALDE 25KG | Y75: =+C75 -> 0 | Z75: =IF(ISERROR(Y75*N75),"",Y75*N75) -> 0 | AA75: =IF(ISERROR(IF(E$7="X",Y75*E75,Y75*F75)),"",IF(E$7="X",Y75*E75,Y75*F75)) -> 0 | AB75: =IF(ISERROR(Z75/AA75),"",Z75/AA75) | AE75: 0.05 | AP75: =Peso!B77 -> 25.64
A76: TINTAS BASE SOLVENTE | D76: =AB76 | X76: TINTAS BASE SOLVENTE | Z76: =Z77+Z83+Z89+Z92+Z95+Z99+Z103+Z105 -> 0 | AA76: =AA77+AA83+AA89+AA92+AA95+AA99+AA103+AA105 -> 0 | AB76: =IF(ISERROR(Z76/AA76),"",Z76/AA76) | AC76: 0.25 | AP76: =Peso!B78 -> 0
A77: BRAZIMIL ESMALTE SINTÉTICO 0,75L | D77: =AB77 | X77: =A77 -> BRAZIMIL ESMALTE SINTÉTICO 0,75L | Z77: =SUM(Z78:Z82) -> 0 | AA77: =SUM(AA78:AA82) -> 0 | AB77: =IF(ISERROR(Z77/AA77),"",Z77/AA77) | AC77: 0.25 | AP77: =Peso!B79 -> 0
A78: BRAZIMIL ESMALTE SINTÉTICO 0,75L LATA ALUMÍNIO | B78: 27.2 | D78: =IF($F$7="x",IF(F78=0,0,N78/F78),IF($E$7="x",IF(F78=0,0,N78/E78),"")) -> 0.30931412 | E78: =+B78*(-B$5+100%) -> 25.296 | F78: =IF(B78=0,0,E78-H78) -> 25.211 | G78: =VLOOKUP(A78,Custo!A:B,2,0) -> 16.02659 | H78: =(VLOOKUP(A78,Peso!$A$10:$B$148,2,0))*($B$6/1000) -> 0.085 | I78: =IF($I$7="X",AE78,0%) -> 0.05 | J78: =+B78*I78 -> 1.36 | M78: =+G78+H78+J78 -> 17.47159 | N78: =+E78-M78 -> 7.82441 | O78: =IF(ISERROR((N78/P78)*100),"",(N78/P78)*100) | Q78: =VLOOKUP(A78,'MVA-IPI'!A:AD,30,FALSE) -> 0 | R78: =IF($B$4="AM",0,IF($B$4="AP",0,IF($B$4="RR",0,(B78*Q78)))) -> 0 | S78: =IF($B$4="AP",(B78/0.88*$S$8),IF(T78=0%,0,IF($B$4="AM",(B78/0.88*$S$8),IF(T78=0%,0,IF($B$4="RR",(B78/0.88*$S$8),IF(T78=0%,0,B78*$S$8)))))) -> 0 | T78: =IF($C$4="GRUPO 1",VLOOKUP(A78,'MVA-grupos'!$A$9:$B$128,2,FALSE),IF($C$4="GRUPO 2",VLOOKUP(A78,'MVA-grupos'!$A$9:$D$128,4,FALSE),IF($C$4="GRUPO 3",VLOOKUP(A78,'MVA-grupos'!$A$10:$F$128,6,FALSE),IF($C$4="Grupo 4",VLOOKUP(A78,'MVA-grupos'!$A$9:$H$128,8,FALSE))))) -> 0 | U78: =IF(T78=0%,0,(B78+R78)*T78+(B78+R78)) -> 0 | V78: =(U78*$V$8)-S78 -> 0 | X78: =A78 -> BRAZIMIL ESMALTE SINTÉTICO 0,75L LATA ALUMÍNIO | Y78: =+C78 -> 0 | Z78: =IF(ISERROR(Y78*N78),"",Y78*N78) -> 0 | AA78: =IF(ISERROR(IF(E$7="X",Y78*E78,Y78*F78)),"",IF(E$7="X",Y78*E78,Y78*F78)) -> 0 | AB78: =IF(ISERROR(Z78/AA78),"",Z78/AA78) | AE78: 0.05 | AP78: =Peso!B80 -> 0.85
A79: BRAZIMIL ESMALTE SINTÉTICO 0,75L LATA ALUMÍNIO | B79: 16.11 | D79: =IF($F$7="x",IF(F79=0,0,N79/F79),IF($E$7="x",IF(F79=0,0,N79/E79),"")) -> -0.12913838 | E79: =+B79*(-B$5+100%) -> 14.9823 | F79: =IF(B79=0,0,E79-H79) -> 14.8973 | G79: =VLOOKUP(A79,Custo!A:B,2,0) -> 16.02659 | H79: =(VLOOKUP(A79,Peso!$A$10:$B$148,2,0))*($B$6/1000) -> 0.085 | I79: =IF($I$7="X",AE79,0%) -> 0.05 | J79: =+B79*I79 -> 0.8055 | K79: =IF($B$2="X",$C$2,0) -> 0 | L79: =+B79*K79 -> 0 | M79: =+G79+H79+J79+L79 -> 16.91709 | N79: =+E79-M79 -> -1.93479 | O79: =IF(ISERROR((N79/P79)*100),"",(N79/P79)*100) | Q79: =VLOOKUP(A79,'MVA-IPI'!A:AD,30,FALSE) -> 0 | R79: =IF($B$4="AM",0,IF($B$4="AP",0,IF($B$4="RR",0,(B79*Q79)))) -> 0 | S79: =IF($B$4="AP",(B79/0.88*$S$8),IF(T79=0%,0,IF($B$4="AM",(B79/0.88*$S$8),IF(T79=0%,0,IF($B$4="RR",(B79/0.88*$S$8),IF(T79=0%,0,B79*$S$8)))))) -> 0 | T79: =IF($C$4="GRUPO 1",VLOOKUP(A79,'MVA-grupos'!$A$9:$B$128,2,FALSE),IF($C$4="GRUPO 2",VLOOKUP(A79,'MVA-grupos'!$A$9:$D$128,4,FALSE),IF($C$4="GRUPO 3",VLOOKUP(A79,'MVA-grupos'!$A$10:$F$128,6,FALSE),IF($C$4="Grupo 4",VLOOKUP(A79,'MVA-grupos'!$A$9:$H$128,8,FALSE))))) -> 0 | U79: =IF(T79=0%,0,(B79+R79)*T79+(B79+R79)) -> 0 | V79: =(U79*$V$8)-S79 -> 0 | X79: =A79 -> BRAZIMIL ESMALTE SINTÉTICO 0,75L LATA ALUMÍNIO | Y79: =+C79 -> 0 | Z79: =IF(ISERROR(Y79*N79),"",Y79*N79) -> 0 | AA79: =IF(ISERROR(IF(E$7="X",Y79*E79,Y79*F79)),"",IF(E$7="X",Y79*E79,Y79*F79)) -> 0 | AB79: =IF(ISERROR(Z79/AA79),"",Z79/AA79) | AE79: 0.05 | AP79: =Peso!B81 -> 1.05
A80: BRAZIMIL ESMALTE SINTÉTICO 0,75L LATA BRANCO | B80: 200 | D80: =IF($F$7="x",IF(F80=0,0,N80/F80),IF($E$7="x",IF(F80=0,0,N80/E80),"")) -> 0.89157225 | E80: =+B80*(-B$5+100%) -> 186 | F80: =IF(B80=0,0,E80-H80) -> 185.895 | G80: =VLOOKUP(A80,Custo!A:B,2,0) -> 10.062562 | H80: =(VLOOKUP(A80,Peso!$A$10:$B$148,2,0))*($B$6/1000) -> 0.105 | I80: =IF($I$7="X",AE80,0%) -> 0.05 | J80: =+B80*I80 -> 10 | K80: =IF($B$2="X",$C$2,0) -> 0 | L80: =+B80*K80 -> 0 | M80: =+G80+H80+J80+L80 -> 20.167562 | N80: =+E80-M80 -> 165.83244 | O80: =IF(ISERROR((N80/P80)*100),"",(N80/P80)*100) | Q80: =VLOOKUP(A80,'MVA-IPI'!A:AD,30,FALSE) -> 0 | R80: =IF($B$4="AM",0,IF($B$4="AP",0,IF($B$4="RR",0,(B80*Q80)))) -> 0 | S80: =IF($B$4="AP",(B80/0.88*$S$8),IF(T80=0%,0,IF($B$4="AM",(B80/0.88*$S$8),IF(T80=0%,0,IF($B$4="RR",(B80/0.88*$S$8),IF(T80=0%,0,B80*$S$8)))))) -> 0 | T80: =IF($C$4="GRUPO 1",VLOOKUP(A80,'MVA-grupos'!$A$9:$B$128,2,FALSE),IF($C$4="GRUPO 2",VLOOKUP(A80,'MVA-grupos'!$A$9:$D$128,4,FALSE),IF($C$4="GRUPO 3",VLOOKUP(A80,'MVA-grupos'!$A$10:$F$128,6,FALSE),IF($C$4="Grupo 4",VLOOKUP(A80,'MVA-grupos'!$A$9:$H$128,8,FALSE))))) -> 0 | U80: =IF(T80=0%,0,(B80+R80)*T80+(B80+R80)) -> 0 | V80: =(U80*$V$8)-S80 -> 0 | X80: =A80 -> BRAZIMIL ESMALTE SINTÉTICO 0,75L LATA BRANCO | Y80: =+C80 -> 0 | Z80: =IF(ISERROR(Y80*N80),"",Y80*N80) -> 0 | AA80: =IF(ISERROR(IF(E$7="X",Y80*E80,Y80*F80)),"",IF(E$7="X",Y80*E80,Y80*F80)) -> 0 | AB80: =IF(ISERROR(Z80/AA80),"",Z80/AA80) | AE80: 0.05 | AP80: =Peso!B82 -> 19
A81: BRAZIMIL ESMALTE SINTÉTICO 0,75L LATA PRETO | B81: 16.866 | D81: =IF($F$7="x",IF(F81=0,0,N81/F81),IF($E$7="x",IF(F81=0,0,N81/E81),"")) -> 0.30153094 | E81: =+B81*(-B$5+100%) -> 15.68538 | F81: =IF(B81=0,0,E81-H81) -> 13.78538 | G81: =VLOOKUP(A81,Custo!A:B,2,0) -> 8.2124527 | H81: =(VLOOKUP(A81,Peso!$A$10:$B$148,2,0))*($B$6/1000) -> 1.9 | I81: =IF($I$7="X",AE81,0%) -> 0.05 | J81: =+B81*I81 -> 0.8433 | M81: =+G81+H81+J81 -> 10.955753 | N81: =+E81-M81 -> 4.7296273 | O81: =IF(ISERROR((N81/P81)*100),"",(N81/P81)*100) | Q81: =VLOOKUP(A81,'MVA-IPI'!A:AD,30,FALSE) -> 0 | R81: =IF($B$4="AM",0,IF($B$4="AP",0,IF($B$4="RR",0,(B81*Q81)))) -> 0 | S81: =IF($B$4="AP",(B81/0.88*$S$8),IF(T81=0%,0,IF($B$4="AM",(B81/0.88*$S$8),IF(T81=0%,0,IF($B$4="RR",(B81/0.88*$S$8),IF(T81=0%,0,B81*$S$8)))))) -> 0 | T81: =IF($C$4="GRUPO 1",VLOOKUP(A81,'MVA-grupos'!$A$9:$B$128,2,FALSE),IF($C$4="GRUPO 2",VLOOKUP(A81,'MVA-grupos'!$A$9:$D$128,4,FALSE),IF($C$4="GRUPO 3",VLOOKUP(A81,'MVA-grupos'!$A$10:$F$128,6,FALSE),IF($C$4="Grupo 4",VLOOKUP(A81,'MVA-grupos'!$A$9:$H$128,8,FALSE))))) -> 0 | U81: =IF(T81=0%,0,(B81+R81)*T81+(B81+R81)) -> 0 | V81: =(U81*$V$8)-S81 -> 0 | X81: =A81 -> BRAZIMIL ESMALTE SINTÉTICO 0,75L LATA PRETO | Y81: =+C81 -> 0 | Z81: =IF(ISERROR(Y81*N81),"",Y81*N81) -> 0 | AA81: =IF(ISERROR(IF(E$7="X",Y81*E81,Y81*F81)),"",IF(E$7="X",Y81*E81,Y81*F81)) -> 0 | AB81: =IF(ISERROR(Z81/AA81),"",Z81/AA81) | AE81: 0.05 | AP81: =Peso!B83 -> 0.85
A82: BRAZIMIL ESMALTE SINTÉTICO 0,75L LATA COR | B82: 16.866 | D82: =IF($F$7="x",IF(F82=0,0,N82/F82),IF($E$7="x",IF(F82=0,0,N82/E82),"")) -> 0.38738079 | E82: =+B82*(-B$5+100%) -> 15.68538 | F82: =IF(B82=0,0,E82-H82) -> 15.60038 | G82: =VLOOKUP(A82,Custo!A:B,2,0) -> 8.6808652 | H82: =(VLOOKUP(A82,Peso!$A$10:$B$148,2,0))*($B$6/1000) -> 0.085 | I82: =IF($I$7="X",AE82,0%) -> 0.05 | J82: =+B82*I82 -> 0.8433 | M82: =+G82+H82+J82 -> 9.6091652 | N82: =+E82-M82 -> 6.0762148 | O82: =IF(ISERROR((N82/P82)*100),"",(N82/P82)*100) | Q82: =VLOOKUP(A82,'MVA-IPI'!A:AD,30,FALSE) -> 0 | R82: =IF($B$4="AM",0,IF($B$4="AP",0,IF($B$4="RR",0,(B82*Q82)))) -> 0 | S82: =IF($B$4="AP",(B82/0.88*$S$8),IF(T82=0%,0,IF($B$4="AM",(B82/0.88*$S$8),IF(T82=0%,0,IF($B$4="RR",(B82/0.88*$S$8),IF(T82=0%,0,B82*$S$8)))))) -> 0 | T82: =IF($C$4="GRUPO 1",VLOOKUP(A82,'MVA-grupos'!$A$9:$B$128,2,FALSE),IF($C$4="GRUPO 2",VLOOKUP(A82,'MVA-grupos'!$A$9:$D$128,4,FALSE),IF($C$4="GRUPO 3",VLOOKUP(A82,'MVA-grupos'!$A$10:$F$128,6,FALSE),IF($C$4="Grupo 4",VLOOKUP(A82,'MVA-grupos'!$A$9:$H$128,8,FALSE))))) -> 0 | U82: =IF(T82=0%,0,(B82+R82)*T82+(B82+R82)) -> 0 | V82: =(U82*$V$8)-S82 -> 0 | X82: =A82 -> BRAZIMIL ESMALTE SINTÉTICO 0,75L LATA COR | Y82: =+C82 -> 0 | Z82: =IF(ISERROR(Y82*N82),"",Y82*N82) -> 0 | AA82: =IF(ISERROR(IF(E$7="X",Y82*E82,Y82*F82)),"",IF(E$7="X",Y82*E82,Y82*F82)) -> 0 | AB82: =IF(ISERROR(Z82/AA82),"",Z82/AA82) | AE82: 0.05 | AP82: =Peso!B84 -> 1.05
A83: BRAZIMIL ESMALTE SINTÉTICO 3,0L | D83: =AB83 | X83: =A83 -> BRAZIMIL ESMALTE SINTÉTICO 3,0L | Z83: =SUM(Z84:Z88) -> 0 | AA83: =SUM(AA84:AA88) -> 0 | AB83: =IF(ISERROR(Z83/AA83),"",Z83/AA83) | AC83: 0.25 | AP83: =Peso!B85 -> 0
A84: BRAZIMIL ESMALTE SINTÉTICO 3,0L LATA ALUMÍNIO | B84: 99 | D84: =IF($F$7="x",IF(F84=0,0,N84/F84),IF($E$7="x",IF(F84=0,0,N84/E84),"")) -> 0.309604 | E84: =+B84*(-B$5+100%) -> 92.07 | F84: =IF(B84=0,0,E84-H84) -> 91.76 | G84: =VLOOKUP(A84,Custo!A:B,2,0) -> 58.30476 | H84: =(VLOOKUP(A84,Peso!$A$10:$B$148,2,0))*($B$6/1000) -> 0.31 | I84: =IF($I$7="X",AE84,0%) -> 0.05 | J84: =+B84*I84 -> 4.95 | M84: =+G84+H84+J84 -> 63.56476 | N84: =+E84-M84 -> 28.50524 | O84: =IF(ISERROR((N84/P84)*100),"",(N84/P84)*100) | Q84: =VLOOKUP(A84,'MVA-IPI'!A:AD,30,FALSE) -> 0 | R84: =IF($B$4="AM",0,IF($B$4="AP",0,IF($B$4="RR",0,(B84*Q84)))) -> 0 | S84: =IF($B$4="AP",(B84/0.88*$S$8),IF(T84=0%,0,IF($B$4="AM",(B84/0.88*$S$8),IF(T84=0%,0,IF($B$4="RR",(B84/0.88*$S$8),IF(T84=0%,0,B84*$S$8)))))) -> 0 | T84: =IF($C$4="GRUPO 1",VLOOKUP(A84,'MVA-grupos'!$A$9:$B$128,2,FALSE),IF($C$4="GRUPO 2",VLOOKUP(A84,'MVA-grupos'!$A$9:$D$128,4,FALSE),IF($C$4="GRUPO 3",VLOOKUP(A84,'MVA-grupos'!$A$10:$F$128,6,FALSE),IF($C$4="Grupo 4",VLOOKUP(A84,'MVA-grupos'!$A$9:$H$128,8,FALSE))))) -> 0 | U84: =IF(T84=0%,0,(B84+R84)*T84+(B84+R84)) -> 0 | V84: =(U84*$V$8)-S84 -> 0 | X84: =A84 -> BRAZIMIL ESMALTE SINTÉTICO 3,0L LATA ALUMÍNIO | Y84: =+C84 -> 0 | Z84: =IF(ISERROR(Y84*N84),"",Y84*N84) -> 0 | AA84: =IF(ISERROR(IF(E$7="X",Y84*E84,Y84*F84)),"",IF(E$7="X",Y84*E84,Y84*F84)) -> 0 | AB84: =IF(ISERROR(Z84/AA84),"",Z84/AA84) | AE84: 0.05 | AP84: =Peso!B86 -> 3.1
A85: BRAZIMIL ESMALTE SINTÉTICO 3,0L LATA BRANCO | B85: 52.26 | D85: =IF($F$7="x",IF(F85=0,0,N85/F85),IF($E$7="x",IF(F85=0,0,N85/E85),"")) -> 0.22105253 | E85: =+B85*(-B$5+100%) -> 48.6018 | F85: =IF(B85=0,0,E85-H85) -> 48.2668 | G85: =VLOOKUP(A85,Custo!A:B,2,0) -> 34.910249 | H85: =(VLOOKUP(A85,Peso!$A$10:$B$148,2,0))*($B$6/1000) -> 0.335 | I85: =IF($I$7="X",AE85,0%) -> 0.05 | J85: =+B85*I85 -> 2.613 | K85: =IF($B$2="X",$C$2,0) -> 0 | L85: =+B85*K85 -> 0 | M85: =+G85+H85+J85+L85 -> 37.858249 | N85: =+E85-M85 -> 10.743551 | O85: =IF(ISERROR((N85/P85)*100),"",(N85/P85)*100) | Q85: =VLOOKUP(A85,'MVA-IPI'!A:AD,30,FALSE) -> 0 | R85: =IF($B$4="AM",0,IF($B$4="AP",0,IF($B$4="RR",0,(B85*Q85)))) -> 0 | S85: =IF($B$4="AP",(B85/0.88*$S$8),IF(T85=0%,0,IF($B$4="AM",(B85/0.88*$S$8),IF(T85=0%,0,IF($B$4="RR",(B85/0.88*$S$8),IF(T85=0%,0,B85*$S$8)))))) -> 0 | T85: =IF($C$4="GRUPO 1",VLOOKUP(A85,'MVA-grupos'!$A$9:$B$128,2,FALSE),IF($C$4="GRUPO 2",VLOOKUP(A85,'MVA-grupos'!$A$9:$D$128,4,FALSE),IF($C$4="GRUPO 3",VLOOKUP(A85,'MVA-grupos'!$A$10:$F$128,6,FALSE),IF($C$4="Grupo 4",VLOOKUP(A85,'MVA-grupos'!$A$9:$H$128,8,FALSE))))) -> 0 | U85: =IF(T85=0%,0,(B85+R85)*T85+(B85+R85)) -> 0 | V85: =(U85*$V$8)-S85 -> 0 | X85: =A85 -> BRAZIMIL ESMALTE SINTÉTICO 3,0L LATA BRANCO | Y85: =+C85 -> 0 | Z85: =IF(ISERROR(Y85*N85),"",Y85*N85) -> 0 | AA85: =IF(ISERROR(IF(E$7="X",Y85*E85,Y85*F85)),"",IF(E$7="X",Y85*E85,Y85*F85)) -> 0 | AB85: =IF(ISERROR(Z85/AA85),"",Z85/AA85) | AE85: 0.05 | AP85: =Peso!B87 -> 3.35
A86: BRAZIMIL ESMALTE SINTÉTICO 3,0L LATA PRETO | B86: 39.9 | D86: =IF($F$7="x",IF(F86=0,0,N86/F86),IF($E$7="x",IF(F86=0,0,N86/E86),"")) -> 0.19584416 | E86: =+B86*(-B$5+100%) -> 37.107 | F86: =IF(B86=0,0,E86-H86) -> 36.772 | G86: =VLOOKUP(A86,Custo!A:B,2,0) -> 27.509811 | H86: =(VLOOKUP(A86,Peso!$A$10:$B$148,2,0))*($B$6/1000) -> 0.335 | I86: =IF($I$7="X",AE86,0%) -> 0.05 | J86: =+B86*I86 -> 1.995 | M86: =+G86+H86+J86 -> 29.839811 | N86: =+E86-M86 -> 7.2671893 | O86: =IF(ISERROR((N86/P86)*100),"",(N86/P86)*100) | Q86: =VLOOKUP(A86,'MVA-IPI'!A:AD,30,FALSE) -> 0 | R86: =IF($B$4="AM",0,IF($B$4="AP",0,IF($B$4="RR",0,(B86*Q86)))) -> 0 | S86: =IF($B$4="AP",(B86/0.88*$S$8),IF(T86=0%,0,IF($B$4="AM",(B86/0.88*$S$8),IF(T86=0%,0,IF($B$4="RR",(B86/0.88*$S$8),IF(T86=0%,0,B86*$S$8)))))) -> 0 | T86: =IF($C$4="GRUPO 1",VLOOKUP(A86,'MVA-grupos'!$A$9:$B$128,2,FALSE),IF($C$4="GRUPO 2",VLOOKUP(A86,'MVA-grupos'!$A$9:$D$128,4,FALSE),IF($C$4="GRUPO 3",VLOOKUP(A86,'MVA-grupos'!$A$10:$F$128,6,FALSE),IF($C$4="Grupo 4",VLOOKUP(A86,'MVA-grupos'!$A$9:$H$128,8,FALSE))))) -> 0 | U86: =IF(T86=0%,0,(B86+R86)*T86+(B86+R86)) -> 0 | V86: =(U86*$V$8)-S86 -> 0 | X86: =A86 -> BRAZIMIL ESMALTE SINTÉTICO 3,0L LATA PRETO | Y86: =+C86 -> 0 | Z86: =IF(ISERROR(Y86*N86),"",Y86*N86) -> 0 | AA86: =IF(ISERROR(IF(E$7="X",Y86*E86,Y86*F86)),"",IF(E$7="X",Y86*E86,Y86*F86)) -> 0 | AB86: =IF(ISERROR(Z86/AA86),"",Z86/AA86) | AE86: 0.05 | AP86: =Peso!B88 -> 3.35
A87: BRAZIMIL ESMALTE SINTÉTICO 3,0L LATA COR | B87: 46.9 | D87: =IF($F$7="x",IF(F87=0,0,N87/F87),IF($E$7="x",IF(F87=0,0,N87/E87),"")) -> 0.26488615 | E87: =+B87*(-B$5+100%) -> 43.617 | F87: =IF(B87=0,0,E87-H87) -> 43.282 | G87: =VLOOKUP(A87,Custo!A:B,2,0) -> 29.383461 | H87: =(VLOOKUP(A87,Peso!$A$10:$B$148,2,0))*($B$6/1000) -> 0.335 | I87: =IF($I$7="X",AE87,0%) -> 0.05 | J87: =+B87*I87 -> 2.345 | M87: =+G87+H87+J87 -> 32.063461 | N87: =+E87-M87 -> 11.553539 | O87: =IF(ISERROR((N87/P87)*100),"",(N87/P87)*100) | Q87: =VLOOKUP(A87,'MVA-IPI'!A:AD,30,FALSE) -> 0 | R87: =IF($B$4="AM",0,IF($B$4="AP",0,IF($B$4="RR",0,(B87*Q87)))) -> 0 | S87: =IF($B$4="AP",(B87/0.88*$S$8),IF(T87=0%,0,IF($B$4="AM",(B87/0.88*$S$8),IF(T87=0%,0,IF($B$4="RR",(B87/0.88*$S$8),IF(T87=0%,0,B87*$S$8)))))) -> 0 | T87: =IF($C$4="GRUPO 1",VLOOKUP(A87,'MVA-grupos'!$A$9:$B$128,2,FALSE),IF($C$4="GRUPO 2",VLOOKUP(A87,'MVA-grupos'!$A$9:$D$128,4,FALSE),IF($C$4="GRUPO 3",VLOOKUP(A87,'MVA-grupos'!$A$10:$F$128,6,FALSE),IF($C$4="Grupo 4",VLOOKUP(A87,'MVA-grupos'!$A$9:$H$128,8,FALSE))))) -> 0 | U87: =IF(T87=0%,0,(B87+R87)*T87+(B87+R87)) -> 0 | V87: =(U87*$V$8)-S87 -> 0 | X87: =A87 -> BRAZIMIL ESMALTE SINTÉTICO 3,0L LATA COR | Y87: =+C87 -> 0 | Z87: =IF(ISERROR(Y87*N87),"",Y87*N87) -> 0 | AA87: =IF(ISERROR(IF(E$7="X",Y87*E87,Y87*F87)),"",IF(E$7="X",Y87*E87,Y87*F87)) -> 0 | AB87: =IF(ISERROR(Z87/AA87),"",Z87/AA87) | AE87: 0.05 | AP87: =Peso!B89 -> 3.35
A88: BRAZIMIL ESMALTE SINTÉTICO 3,0L LATA FOSCO | B88: 54.5 | D88: =IF($F$7="x",IF(F88=0,0,N88/F88),IF($E$7="x",IF(F88=0,0,N88/E88),"")) -> 0.31534313 | E88: =+B88*(-B$5+100%) -> 50.685 | F88: =IF(B88=0,0,E88-H88) -> 50.325 | G88: =VLOOKUP(A88,Custo!A:B,2,0) -> 31.616833 | H88: =(VLOOKUP(A88,Peso!$A$10:$B$148,2,0))*($B$6/1000) -> 0.36 | I88: =IF($I$7="X",AE88,0%) -> 0.05 | J88: =+B88*I88 -> 2.725 | M88: =+G88+H88+J88 -> 34.701833 | N88: =+E88-M88 -> 15.983167 | O88: =IF(ISERROR((N88/P88)*100),"",(N88/P88)*100) | Q88: =VLOOKUP(A88,'MVA-IPI'!A:AD,30,FALSE) -> 0 | R88: =IF($B$4="AM",0,IF($B$4="AP",0,IF($B$4="RR",0,(B88*Q88)))) -> 0 | S88: =IF($B$4="AP",(B88/0.88*$S$8),IF(T88=0%,0,IF($B$4="AM",(B88/0.88*$S$8),IF(T88=0%,0,IF($B$4="RR",(B88/0.88*$S$8),IF(T88=0%,0,B88*$S$8)))))) -> 0 | T88: =IF($C$4="GRUPO 1",VLOOKUP(A88,'MVA-grupos'!$A$9:$B$128,2,FALSE),IF($C$4="GRUPO 2",VLOOKUP(A88,'MVA-grupos'!$A$9:$D$128,4,FALSE),IF($C$4="GRUPO 3",VLOOKUP(A88,'MVA-grupos'!$A$10:$F$128,6,FALSE),IF($C$4="Grupo 4",VLOOKUP(A88,'MVA-grupos'!$A$9:$H$128,8,FALSE))))) -> 0 | U88: =IF(T88=0%,0,(B88+R88)*T88+(B88+R88)) -> 0 | V88: =(U88*$V$8)-S88 -> 0 | X88: =A88 -> BRAZIMIL ESMALTE SINTÉTICO 3,0L LATA FOSCO | Y88: =+C88 -> 0 | Z88: =IF(ISERROR(Y88*N88),"",Y88*N88) -> 0 | AA88: =IF(ISERROR(IF(E$7="X",Y88*E88,Y88*F88)),"",IF(E$7="X",Y88*E88,Y88*F88)) -> 0 | AB88: =IF(ISERROR(Z88/AA88),"",Z88/AA88) | AE88: 0.05 | AP88: =Peso!B90 -> 3.6 | AW88: =+AV88/$AU$6 -> #DIV/0!
A89: BRAZIMIL VERNIZ 0,75L | D89: =AB89 | X89: =A89 -> BRAZIMIL VERNIZ 0,75L | Z89: =SUM(Z90:Z91) -> 0 | AA89: =SUM(AA90:AA91) -> 0 | AB89: =IF(ISERROR(Z89/AA89),"",Z89/AA89) | AC89: 0.25 | AP89: =Peso!B91 -> 0 | AW89: =+AV89/$AU$6 -> #DIV/0!
A90: BRAZIMIL VERNIZ 0,75L LATA INCOLOR | B90: 20.5 | D90: =IF($F$7="x",IF(F90=0,0,N90/F90),IF($E$7="x",IF(F90=0,0,N90/E90),"")) -> 0.34650842 | E90: =+B90*(-B$5+100%) -> 19.065 | F90: =IF(B90=0,0,E90-H90) -> 18.98 | G90: =VLOOKUP(A90,Custo!A:B,2,0) -> 11.348817 | H90: =(VLOOKUP(A90,Peso!$A$10:$B$148,2,0))*($B$6/1000) -> 0.085 | I90: =IF($I$7="X",AE90,0%) -> 0.05 | J90: =+B90*I90 -> 1.025 | K90: =IF($B$2="X",$C$2,0) -> 0 | L90: =+B90*K90 -> 0 | M90: =+G90+H90+J90+L90 -> 12.458817 | N90: =+E90-M90 -> 6.6061831 | O90: =IF(ISERROR((N90/P90)*100),"",(N90/P90)*100) | Q90: =VLOOKUP(A90,'MVA-IPI'!A:AD,30,FALSE) -> 0 | R90: =IF($B$4="AM",0,IF($B$4="AP",0,IF($B$4="RR",0,(B90*Q90)))) -> 0 | S90: =IF($B$4="AP",(B90/0.88*$S$8),IF(T90=0%,0,IF($B$4="AM",(B90/0.88*$S$8),IF(T90=0%,0,IF($B$4="RR",(B90/0.88*$S$8),IF(T90=0%,0,B90*$S$8)))))) -> 0 | T90: =IF($C$4="GRUPO 1",VLOOKUP(A90,'MVA-grupos'!$A$9:$B$128,2,FALSE),IF($C$4="GRUPO 2",VLOOKUP(A90,'MVA-grupos'!$A$9:$D$128,4,FALSE),IF($C$4="GRUPO 3",VLOOKUP(A90,'MVA-grupos'!$A$10:$F$128,6,FALSE),IF($C$4="Grupo 4",VLOOKUP(A90,'MVA-grupos'!$A$9:$H$128,8,FALSE))))) -> 0 | U90: =IF(T90=0%,0,(B90+R90)*T90+(B90+R90)) -> 0 | V90: =(U90*$V$8)-S90 -> 0 | X90: =A90 -> BRAZIMIL VERNIZ 0,75L LATA INCOLOR | Y90: =+C90 -> 0 | Z90: =IF(ISERROR(Y90*N90),"",Y90*N90) -> 0 | AA90: =IF(ISERROR(IF(E$7="X",Y90*E90,Y90*F90)),"",IF(E$7="X",Y90*E90,Y90*F90)) -> 0 | AB90: =IF(ISERROR(Z90/AA90),"",Z90/AA90) | AE90: 0.05 | AP90: =Peso!B92 -> 0.85 | AW90: =+AV90/$AU$6 -> #DIV/0!
A91: BRAZIMIL VERNIZ 0,75L LATA PIGMENTADO | B91: 20.5 | D91: =IF($F$7="x",IF(F91=0,0,N91/F91),IF($E$7="x",IF(F91=0,0,N91/E91),"")) -> 0.42991476 | E91: =+B91*(-B$5+100%) -> 19.065 | F91: =IF(B91=0,0,E91-H91) -> 18.98 | G91: =VLOOKUP(A91,Custo!A:B,2,0) -> 9.7586751 | H91: =(VLOOKUP(A91,Peso!$A$10:$B$148,2,0))*($B$6/1000) -> 0.085 | I91: =IF($I$7="X",AE91,0%) -> 0.05 | J91: =+B91*I91 -> 1.025 | K91: =IF($B$2="X",$C$2,0) -> 0 | L91: =+B91*K91 -> 0 | M91: =+G91+H91+J91+L91 -> 10.868675 | N91: =+E91-M91 -> 8.1963249 | O91: =IF(ISERROR((N91/P91)*100),"",(N91/P91)*100) | Q91: =VLOOKUP(A91,'MVA-IPI'!A:AD,30,FALSE) -> 0 | R91: =IF($B$4="AM",0,IF($B$4="AP",0,IF($B$4="RR",0,(B91*Q91)))) -> 0 | S91: =IF($B$4="AP",(B91/0.88*$S$8),IF(T91=0%,0,IF($B$4="AM",(B91/0.88*$S$8),IF(T91=0%,0,IF($B$4="RR",(B91/0.88*$S$8),IF(T91=0%,0,B91*$S$8)))))) -> 0 | T91: =IF($C$4="GRUPO 1",VLOOKUP(A91,'MVA-grupos'!$A$9:$B$128,2,FALSE),IF($C$4="GRUPO 2",VLOOKUP(A91,'MVA-grupos'!$A$9:$D$128,4,FALSE),IF($C$4="GRUPO 3",VLOOKUP(A91,'MVA-grupos'!$A$10:$F$128,6,FALSE),IF($C$4="Grupo 4",VLOOKUP(A91,'MVA-grupos'!$A$9:$H$128,8,FALSE))))) -> 0 | U91: =IF(T91=0%,0,(B91+R91)*T91+(B91+R91)) -> 0 | V91: =(U91*$V$8)-S91 -> 0 | X91: =A91 -> BRAZIMIL VERNIZ 0,75L LATA PIGMENTADO | Y91: =+C91 -> 0 | Z91: =IF(ISERROR(Y91*N91),"",Y91*N91) -> 0 | AA91: =IF(ISERROR(IF(E$7="X",Y91*E91,Y91*F91)),"",IF(E$7="X",Y91*E91,Y91*F91)) -> 0 | AB91: =IF(ISERROR(Z91/AA91),"",Z91/AA91) | AE91: 0.05 | AP91: =Peso!B93 -> 0.85 | AW91: =+AV91/$AU$6 -> #DIV/0!
A92: BRAZIMIL VERNIZ 3,0L | D92: =AB92 | X92: =A92 -> BRAZIMIL VERNIZ 3,0L | Z92: =SUM(Z93:Z94) -> 0 | AA92: =SUM(AA93:AA94) -> 0 | AB92: =IF(ISERROR(Z92/AA92),"",Z92/AA92) | AC92: 0.25 | AP92: =Peso!B94 -> 0 | AW92: =+AV92/$AU$6 -> #DIV/0!
A93: BRAZIMIL VERNIZ 3,0L LATA INCOLOR | B93: 63 | D93: =IF($F$7="x",IF(F93=0,0,N93/F93),IF($E$7="x",IF(F93=0,0,N93/E93),"")) -> 0.26517037 | E93: =+B93*(-B$5+100%) -> 58.59 | F93: =IF(B93=0,0,E93-H93) -> 58.28 | G93: =VLOOKUP(A93,Custo!A:B,2,0) -> 39.593668 | H93: =(VLOOKUP(A93,Peso!$A$10:$B$148,2,0))*($B$6/1000) -> 0.31 | I93: =IF($I$7="X",AE93,0%) -> 0.05 | J93: =+B93*I93 -> 3.15 | K93: =IF($B$2="X",$C$2,0) -> 0 | L93: =+B93*K93 -> 0 | M93: =+G93+H93+J93+L93 -> 43.053668 | N93: =+E93-M93 -> 15.536332 | O93: =IF(ISERROR((N93/P93)*100),"",(N93/P93)*100) | Q93: =VLOOKUP(A93,'MVA-IPI'!A:AD,30,FALSE) -> 0 | R93: =IF($B$4="AM",0,IF($B$4="AP",0,IF($B$4="RR",0,(B93*Q93)))) -> 0 | S93: =IF($B$4="AP",(B93/0.88*$S$8),IF(T93=0%,0,IF($B$4="AM",(B93/0.88*$S$8),IF(T93=0%,0,IF($B$4="RR",(B93/0.88*$S$8),IF(T93=0%,0,B93*$S$8)))))) -> 0 | T93: =IF($C$4="GRUPO 1",VLOOKUP(A93,'MVA-grupos'!$A$9:$B$128,2,FALSE),IF($C$4="GRUPO 2",VLOOKUP(A93,'MVA-grupos'!$A$9:$D$128,4,FALSE),IF($C$4="GRUPO 3",VLOOKUP(A93,'MVA-grupos'!$A$10:$F$128,6,FALSE),IF($C$4="Grupo 4",VLOOKUP(A93,'MVA-grupos'!$A$9:$H$128,8,FALSE))))) -> 0 | U93: =IF(T93=0%,0,(B93+R93)*T93+(B93+R93)) -> 0 | V93: =(U93*$V$8)-S93 -> 0 | X93: =A93 -> BRAZIMIL VERNIZ 3,0L LATA INCOLOR | Y93: =+C93 -> 0 | Z93: =IF(ISERROR(Y93*N93),"",Y93*N93) -> 0 | AA93: =IF(ISERROR(IF(E$7="X",Y93*E93,Y93*F93)),"",IF(E$7="X",Y93*E93,Y93*F93)) -> 0 | AB93: =IF(ISERROR(Z93/AA93),"",Z93/AA93) | AE93: 0.05 | AP93: =Peso!B95 -> 3.1 | AW93: =+AV93/$AU$6 -> #DIV/0!
A94: BRAZIMIL VERNIZ 3,0L LATA PIGMENTADO | B94: 63 | D94: =IF($F$7="x",IF(F94=0,0,N94/F94),IF($E$7="x",IF(F94=0,0,N94/E94),"")) -> 0.33524451 | E94: =+B94*(-B$5+100%) -> 58.59 | F94: =IF(B94=0,0,E94-H94) -> 58.28 | G94: =VLOOKUP(A94,Custo!A:B,2,0) -> 35.488024 | H94: =(VLOOKUP(A94,Peso!$A$10:$B$148,2,0))*($B$6/1000) -> 0.31 | I94: =IF($I$7="X",AE94,0%) -> 0.05 | J94: =+B94*I94 -> 3.15 | K94: =IF($B$2="X",$C$2,0) -> 0 | L94: =+B94*K94 -> 0 | M94: =+G94+H94+J94+L94 -> 38.948024 | N94: =+E94-M94 -> 19.641976 | O94: =IF(ISERROR((N94/P94)*100),"",(N94/P94)*100) | Q94: =VLOOKUP(A94,'MVA-IPI'!A:AD,30,FALSE) -> 0 | R94: =IF($B$4="AM",0,IF($B$4="AP",0,IF($B$4="RR",0,(B94*Q94)))) -> 0 | S94: =IF($B$4="AP",(B94/0.88*$S$8),IF(T94=0%,0,IF($B$4="AM",(B94/0.88*$S$8),IF(T94=0%,0,IF($B$4="RR",(B94/0.88*$S$8),IF(T94=0%,0,B94*$S$8)))))) -> 0 | T94: =IF($C$4="GRUPO 1",VLOOKUP(A94,'MVA-grupos'!$A$9:$B$128,2,FALSE),IF($C$4="GRUPO 2",VLOOKUP(A94,'MVA-grupos'!$A$9:$D$128,4,FALSE),IF($C$4="GRUPO 3",VLOOKUP(A94,'MVA-grupos'!$A$10:$F$128,6,FALSE),IF($C$4="Grupo 4",VLOOKUP(A94,'MVA-grupos'!$A$9:$H$128,8,FALSE))))) -> 0 | U94: =IF(T94=0%,0,(B94+R94)*T94+(B94+R94)) -> 0 | V94: =(U94*$V$8)-S94 -> 0 | X94: =A94 -> BRAZIMIL VERNIZ 3,0L LATA PIGMENTADO | Y94: =+C94 -> 0 | Z94: =IF(ISERROR(Y94*N94),"",Y94*N94) -> 0 | AA94: =IF(ISERROR(IF(E$7="X",Y94*E94,Y94*F94)),"",IF(E$7="X",Y94*E94,Y94*F94)) -> 0 | AB94: =IF(ISERROR(Z94/AA94),"",Z94/AA94) | AE94: 0.05 | AP94: =Peso!B96 -> 3.1 | AW94: =+AV94/$AU$6 -> #DIV/0!
A95: BRAZIMIL ZARCÃO 0,75L | D95: =AB95 | X95: =A95 -> BRAZIMIL ZARCÃO 0,75L | Z95: =SUM(Z96:Z98) -> 0 | AA95: =SUM(AA96:AA98) -> 0 | AB95: =IF(ISERROR(Z95/AA95),"",Z95/AA95) | AC95: 0.25 | AP95: =Peso!B97 -> 0 | AW95: =+AV95/$AU$6 -> #DIV/0!
A96: BRAZIMIL ZARCÃO 0,75L LATA BRANCO | B96: 15.9 | D96: =IF($F$7="x",IF(F96=0,0,N96/F96),IF($E$7="x",IF(F96=0,0,N96/E96),"")) -> 0.49336219 | E96: =+B96*(-B$5+100%) -> 14.787 | F96: =IF(B96=0,0,E96-H96) -> 14.685 | G96: =VLOOKUP(A96,Custo!A:B,2,0) -> 6.5946532 | H96: =(VLOOKUP(A96,Peso!$A$10:$B$148,2,0))*($B$6/1000) -> 0.102 | I96: =IF($I$7="X",AE96,0%) -> 0.05 | J96: =+B96*I96 -> 0.795 | K96: =IF($B$2="X",$C$2,0) -> 0 | L96: =+B96*K96 -> 0 | M96: =+G96+H96+J96+L96 -> 7.4916532 | N96: =+E96-M96 -> 7.2953468 | O96: =IF(ISERROR((N96/P96)*100),"",(N96/P96)*100) | Q96: =VLOOKUP(A96,'MVA-IPI'!A:AD,30,FALSE) -> 0 | R96: =IF($B$4="AM",0,IF($B$4="AP",0,IF($B$4="RR",0,(B96*Q96)))) -> 0 | S96: =IF($B$4="AP",(B96/0.88*$S$8),IF(T96=0%,0,IF($B$4="AM",(B96/0.88*$S$8),IF(T96=0%,0,IF($B$4="RR",(B96/0.88*$S$8),IF(T96=0%,0,B96*$S$8)))))) -> 0 | T96: =IF($C$4="GRUPO 1",VLOOKUP(A96,'MVA-grupos'!$A$9:$B$128,2,FALSE),IF($C$4="GRUPO 2",VLOOKUP(A96,'MVA-grupos'!$A$9:$D$128,4,FALSE),IF($C$4="GRUPO 3",VLOOKUP(A96,'MVA-grupos'!$A$10:$F$128,6,FALSE),IF($C$4="Grupo 4",VLOOKUP(A96,'MVA-grupos'!$A$9:$H$128,8,FALSE))))) -> 0 | U96: =IF(T96=0%,0,(B96+R96)*T96+(B96+R96)) -> 0 | V96: =(U96*$V$8)-S96 -> 0 | X96: =A96 -> BRAZIMIL ZARCÃO 0,75L LATA BRANCO | Y96: =+C96 -> 0 | Z96: =IF(ISERROR(Y96*N96),"",Y96*N96) -> 0 | AA96: =IF(ISERROR(IF(E$7="X",Y96*E96,Y96*F96)),"",IF(E$7="X",Y96*E96,Y96*F96)) -> 0 | AB96: =IF(ISERROR(Z96/AA96),"",Z96/AA96) | AE96: 0.05 | AP96: =Peso!B98 -> 1.02 | AW96: =+AV96/$AU$6 -> #DIV/0!
A97: BRAZIMIL ZARCÃO 0,75L LATA CINZA | B97: 14.9 | D97: =IF($F$7="x",IF(F97=0,0,N97/F97),IF($E$7="x",IF(F97=0,0,N97/E97),"")) -> 0.46296794 | E97: =+B97*(-B$5+100%) -> 13.857 | F97: =IF(B97=0,0,E97-H97) -> 13.755 | G97: =VLOOKUP(A97,Custo!A:B,2,0) -> 6.5946532 | H97: =(VLOOKUP(A97,Peso!$A$10:$B$148,2,0))*($B$6/1000) -> 0.102 | I97: =IF($I$7="X",AE97,0%) -> 0.05 | J97: =+B97*I97 -> 0.745 | K97: =IF($B$2="X",$C$2,0) -> 0 | L97: =+B97*K97 -> 0 | M97: =+G97+H97+J97+L97 -> 7.4416532 | N97: =+E97-M97 -> 6.4153468 | O97: =IF(ISERROR((N97/P97)*100),"",(N97/P97)*100) | Q97: =VLOOKUP(A97,'MVA-IPI'!A:AD,30,FALSE) -> 0 | R97: =IF($B$4="AM",0,IF($B$4="AP",0,IF($B$4="RR",0,(B97*Q97)))) -> 0 | S97: =IF($B$4="AP",(B97/0.88*$S$8),IF(T97=0%,0,IF($B$4="AM",(B97/0.88*$S$8),IF(T97=0%,0,IF($B$4="RR",(B97/0.88*$S$8),IF(T97=0%,0,B97*$S$8)))))) -> 0 | T97: =IF($C$4="GRUPO 1",VLOOKUP(A97,'MVA-grupos'!$A$9:$B$128,2,FALSE),IF($C$4="GRUPO 2",VLOOKUP(A97,'MVA-grupos'!$A$9:$D$128,4,FALSE),IF($C$4="GRUPO 3",VLOOKUP(A97,'MVA-grupos'!$A$10:$F$128,6,FALSE),IF($C$4="Grupo 4",VLOOKUP(A97,'MVA-grupos'!$A$9:$H$128,8,FALSE))))) -> 0 | U97: =IF(T97=0%,0,(B97+R97)*T97+(B97+R97)) -> 0 | V97: =(U97*$V$8)-S97 -> 0 | X97: =A97 -> BRAZIMIL ZARCÃO 0,75L LATA CINZA | Y97: =+C97 -> 0 | Z97: =IF(ISERROR(Y97*N97),"",Y97*N97) -> 0 | AA97: =IF(ISERROR(IF(E$7="X",Y97*E97,Y97*F97)),"",IF(E$7="X",Y97*E97,Y97*F97)) -> 0 | AB97: =IF(ISERROR(Z97/AA97),"",Z97/AA97) | AE97: 0.05 | AP97: =Peso!B99 -> 1.02 | AW97: =+AV97/$AU$6 -> #DIV/0!
A98: BRAZIMIL ZARCÃO 0,75L LATA COR | B98: 14 | D98: =IF($F$7="x",IF(F98=0,0,N98/F98),IF($E$7="x",IF(F98=0,0,N98/E98),"")) -> 0.43190067 | E98: =+B98*(-B$5+100%) -> 13.02 | F98: =IF(B98=0,0,E98-H98) -> 12.918 | G98: =VLOOKUP(A98,Custo!A:B,2,0) -> 6.5946532 | H98: =(VLOOKUP(A98,Peso!$A$10:$B$148,2,0))*($B$6/1000) -> 0.102 | I98: =IF($I$7="X",AE98,0%) -> 0.05 | J98: =+B98*I98 -> 0.7 | K98: =IF($B$2="X",$C$2,0) -> 0 | L98: =+B98*K98 -> 0 | M98: =+G98+H98+J98+L98 -> 7.3966532 | N98: =+E98-M98 -> 5.6233468 | O98: =IF(ISERROR((N98/P98)*100),"",(N98/P98)*100) | Q98: =VLOOKUP(A98,'MVA-IPI'!A:AD,30,FALSE) -> 0 | R98: =IF($B$4="AM",0,IF($B$4="AP",0,IF($B$4="RR",0,(B98*Q98)))) -> 0 | S98: =IF($B$4="AP",(B98/0.88*$S$8),IF(T98=0%,0,IF($B$4="AM",(B98/0.88*$S$8),IF(T98=0%,0,IF($B$4="RR",(B98/0.88*$S$8),IF(T98=0%,0,B98*$S$8)))))) -> 0 | T98: =IF($C$4="GRUPO 1",VLOOKUP(A98,'MVA-grupos'!$A$9:$B$128,2,FALSE),IF($C$4="GRUPO 2",VLOOKUP(A98,'MVA-grupos'!$A$9:$D$128,4,FALSE),IF($C$4="GRUPO 3",VLOOKUP(A98,'MVA-grupos'!$A$10:$F$128,6,FALSE),IF($C$4="Grupo 4",VLOOKUP(A98,'MVA-grupos'!$A$9:$H$128,8,FALSE))))) -> 0 | U98: =IF(T98=0%,0,(B98+R98)*T98+(B98+R98)) -> 0 | V98: =(U98*$V$8)-S98 -> 0 | X98: =A98 -> BRAZIMIL ZARCÃO 0,75L LATA COR | Y98: =+C98 -> 0 | Z98: =IF(ISERROR(Y98*N98),"",Y98*N98) -> 0 | AA98: =IF(ISERROR(IF(E$7="X",Y98*E98,Y98*F98)),"",IF(E$7="X",Y98*E98,Y98*F98)) -> 0 | AB98: =IF(ISERROR(Z98/AA98),"",Z98/AA98) | AE98: 0.05 | AP98: =Peso!B100 -> 1.02 | AW98: =+AV98/$AU$6 -> #DIV/0!
A99: BRAZIMIL ZARCÃO 3,0L | D99: =AB99 | X99: =A99 -> BRAZIMIL ZARCÃO 3,0L | Z99: =SUM(Z100:Z102) -> 0 | AA99: =SUM(AA100:AA102) -> 0 | AB99: =IF(ISERROR(Z99/AA99),"",Z99/AA99) | AC99: 0.25 | AP99: =Peso!B101 -> 0
A100: BRAZIMIL ZARCÃO 3,0L LATA BRANCO | B100: 46.9 | D100: =IF($F$7="x",IF(F100=0,0,N100/F100),IF($E$7="x",IF(F100=0,0,N100/E100),"")) -> -1.1145931 | E100: =+B100*(-B$5+100%) -> 43.617 | F100: =IF(B100=0,0,E100-H100) -> 43.267 | G100: =VLOOKUP(A100,Custo!A:B,2,0) -> 89.537208 | H100: =(VLOOKUP(A100,Peso!$A$10:$B$148,2,0))*($B$6/1000) -> 0.35 | I100: =IF($I$7="X",AE100,0%) -> 0.05 | J100: =+B100*I100 -> 2.345 | K100: =IF($B$2="X",$C$2,0) -> 0 | L100: =+B100*K100 -> 0 | M100: =+G100+H100+J100+L100 -> 92.232208 | N100: =+E100-M100 -> -48.615208 | O100: =IF(ISERROR((N100/P100)*1000),"",(N100/P100)*1000) | Q100: =VLOOKUP(A100,'MVA-IPI'!A:AD,30,FALSE) -> 0 | R100: =IF($B$4="AM",0,IF($B$4="AP",0,IF($B$4="RR",0,(B100*Q100)))) -> 0 | S100: =IF($B$4="AP",(B100/0.88*$S$8),IF(T100=0%,0,IF($B$4="AM",(B100/0.88*$S$8),IF(T100=0%,0,IF($B$4="RR",(B100/0.88*$S$8),IF(T100=0%,0,B100*$S$8)))))) -> 0 | T100: =IF($C$4="GRUPO 1",VLOOKUP(A100,'MVA-grupos'!$A$9:$B$128,2,FALSE),IF($C$4="GRUPO 2",VLOOKUP(A100,'MVA-grupos'!$A$9:$D$128,4,FALSE),IF($C$4="GRUPO 3",VLOOKUP(A100,'MVA-grupos'!$A$10:$F$128,6,FALSE),IF($C$4="Grupo 4",VLOOKUP(A100,'MVA-grupos'!$A$9:$H$128,8,FALSE))))) -> 0 | U100: =IF(T100=0%,0,(B100+R100)*T100+(B100+R100)) -> 0 | V100: =(U100*$V$8)-S100 -> 0 | X100: =A100 -> BRAZIMIL ZARCÃO 3,0L LATA BRANCO | Y100: =+C100 -> 0 | Z100: =IF(ISERROR(Y100*N100),"",Y100*N100) -> 0 | AA100: =IF(ISERROR(IF(E$7="X",Y100*E100,Y100*F100)),"",IF(E$7="X",Y100*E100,Y100*F100)) -> 0 | AB100: =IF(ISERROR(Z100/AA100),"",Z100/AA100) | AE100: 0.05 | AP100: =Peso!B102 -> 3.5
A101: BRAZIMIL ZARCÃO 3,0L LATA CINZA | B101: 45.55 | D101: =IF($F$7="x",IF(F101=0,0,N101/F101),IF($E$7="x",IF(F101=0,0,N101/E101),"")) -> 0.45222636 | E101: =+B101*(-B$5+100%) -> 42.3615 | F101: =IF(B101=0,0,E101-H101) -> 42.0115 | G101: =VLOOKUP(A101,Custo!A:B,2,0) -> 20.577013 | H101: =(VLOOKUP(A101,Peso!$A$10:$B$148,2,0))*($B$6/1000) -> 0.35 | I101: =IF($I$7="X",AE101,0%) -> 0.05 | J101: =+B101*I101 -> 2.2775 | K101: =IF($B$2="X",$C$2,0) -> 0 | L101: =+B101*K101 -> 0 | M101: =+G101+H101+J101+L101 -> 23.204513 | N101: =+E101-M101 -> 19.156987 | O101: =IF(ISERROR((N101/P101)*1000),"",(N101/P101)*1000) | Q101: =VLOOKUP(A101,'MVA-IPI'!A:AD,30,FALSE) -> 0 | R101: =IF($B$4="AM",0,IF($B$4="AP",0,IF($B$4="RR",0,(B101*Q101)))) -> 0 | S101: =IF($B$4="AP",(B101/0.88*$S$8),IF(T101=0%,0,IF($B$4="AM",(B101/0.88*$S$8),IF(T101=0%,0,IF($B$4="RR",(B101/0.88*$S$8),IF(T101=0%,0,B101*$S$8)))))) -> 0 | T101: =IF($C$4="GRUPO 1",VLOOKUP(A101,'MVA-grupos'!$A$9:$B$128,2,FALSE),IF($C$4="GRUPO 2",VLOOKUP(A101,'MVA-grupos'!$A$9:$D$128,4,FALSE),IF($C$4="GRUPO 3",VLOOKUP(A101,'MVA-grupos'!$A$10:$F$128,6,FALSE),IF($C$4="Grupo 4",VLOOKUP(A101,'MVA-grupos'!$A$9:$H$128,8,FALSE))))) -> 0 | U101: =IF(T101=0%,0,(B101+R101)*T101+(B101+R101)) -> 0 | V101: =(U101*$V$8)-S101 -> 0 | X101: =A101 -> BRAZIMIL ZARCÃO 3,0L LATA CINZA | Y101: =+C101 -> 0 | Z101: =IF(ISERROR(Y101*N101),"",Y101*N101) -> 0 | AA101: =IF(ISERROR(IF(E$7="X",Y101*E101,Y101*F101)),"",IF(E$7="X",Y101*E101,Y101*F101)) -> 0 | AB101: =IF(ISERROR(Z101/AA101),"",Z101/AA101) | AE101: 0.05 | AP101: =Peso!B103 -> 3.5
...

Sheet Custo
A9: Produto | B9: CUSTO
A10: TINTAS BASE ÁGUA
A11: BRAZIMIL ECONOMICA 3,0L
A12: BRAZIMIL ECONÔMICA 3,0L REFIL BRANCO NEVE | B12: ='[5]CUSTO ESPELHO'!$B4 -> 4.4992833
A13: BRAZIMIL ECONÔMICA 3,0L REFIL COR | B13: ='[5]CUSTO ESPELHO'!$B5 -> 3.9825213
A14: BRAZIMIL ECONÔMICA 3,0L GALÃO BRANCO NEVE | B14: ='[5]CUSTO ESPELHO'!$B6 -> 7.9702833
A15: BRAZIMIL ECONÔMICA 3,0L GALÃO COR | B15: ='[5]CUSTO ESPELHO'!$B7 -> 7.4535213
A16: BRAZIMIL ECONÔMICA 15L
A17: BRAZIMIL ECONÔMICA 15L PPQ BRANCO NEVE | B17: ='[2]CUSTO ESPELHO'!B17 -> 0
A18: BRAZIMIL ECONÔMICA 12L BALDE BRANCO NEVE | B18: ='[1]CUSTO ESPELHO'!$B18 -> 25.763717
A19: BRAZIMIL ECONÔMICA 15L BALDE BRANCO NEVE | B19: ='[5]CUSTO ESPELHO'!$B11 -> 32.778842
A20: BRAZIMIL ECONÔMICA 15L BALDE COR | B20: ='[5]CUSTO ESPELHO'!$B12 -> 29.419889
A21: BRAZIMIL EXTERNA 3,0L
A22: BRAZIMIL EXTERNA 3,0L BALDE BRANCO NEVE | B22: ='[5]CUSTO ESPELHO'!$B14 -> 11.252876
A23: BRAZIMIL EXTERNA 3,0L BALDE COR | B23: ='[5]CUSTO ESPELHO'!$B15 -> 9.3931485
A24: BRAZIMIL EXTERNA 15L
A25: BRAZIMIL EXTERNA 15L BALDE BRANCO NEVE | B25: ='[5]CUSTO ESPELHO'!$B17 -> 53.753882
A26: BRAZIMIL EXTERNA 15L BALDE COR | B26: ='[5]CUSTO ESPELHO'!$B18 -> 41.944613
A27: BRAZIMIL SEMI BRILHO 3,0L
A28: BRAZIMIL SEMI BRILHO 3,0L BALDE BRANCO NEVE | B28: ='[5]CUSTO ESPELHO'!$B20 -> 11.612403
A29: BRAZIMIL SEMI BRILHO 3,0L BALDE COR | B29: ='[5]CUSTO ESPELHO'!$B21 -> 15.13493
A30: BRAZIMIL SEMI BRILHO 15L
A31: BRAZIMIL SEMI BRILHO 12L BALDE BRANCO NEVE | B31: ='[5]CUSTO ESPELHO'!$B23 -> 35.219452
A32: BRAZIMIL SEMI BRILHO 15L BALDE BRANCO NEVE | B32: ='[5]CUSTO ESPELHO'!$B24 -> 54.064315
A33: BRAZIMIL SEMI BRILHO 15L BALDE COR | B33: ='[5]CUSTO ESPELHO'!$B25 -> 74.318848
A34: BRAZIMIL TINTA PISO 3,0L
A35: BRAZIMIL TINTA PISO 3,0L BALDE BRANCO NEVE | B35: ='[5]CUSTO ESPELHO'!$B27 -> 18.727406
A36: BRAZIMIL TINTA PISO 3,0L BALDE COR | B36: ='[5]CUSTO ESPELHO'!$B28 -> 17.480572
A37: BRAZIMIL TINTA PISO 15L
A38: BRAZIMIL TINTA PISO 15L BALDE BRANCO NEVE | B38: ='[5]CUSTO ESPELHO'!$B30 -> 102.70014
A39: BRAZIMIL TINTA PISO 15L BALDE COR | B39: ='[5]CUSTO ESPELHO'!$B31 -> 96.686861
A40: BRAZIMIL SELADOR ACRIL 3,0L
A41: BRAZIMIL SELADOR ACRIL 3,0L REFIL PIGMENTADO | B41: ='[5]CUSTO ESPELHO'!$B33 -> 3.2667289
A42: BRAZIMIL SELADOR ACRIL 3,0L BALDE PIGMENTADO | B42: ='[5]CUSTO ESPELHO'!$B34 -> 6.7377289
A43: BRAZIMIL SELADOR ACRIL 15L
A44: BRAZIMIL SELADOR ACRIL 12L PIGMENTADO | B44: ='[5]CUSTO ESPELHO'!$B36 -> 11.78179
A45: BRAZIMIL SELADOR ACRIL 15L BALDE PIGMENTADO | B45: ='[5]CUSTO ESPELHO'!$B37 -> 24.767238
A46: LIQUIBRILHO 3,0L
A47: LIQUIBRILHO 3,0L BALDE INCOLOR | B47: ='[1]CUSTO ESPELHO'!$B47 -> 14.149586
A48: LIQUIBRILHO 15L
A49: LIQUIBRILHO 15L BALDE INCOLOR | B49: ='[1]CUSTO ESPELHO'!$B49 -> 65.63043
A50: MASSAS / TEXTURAS
A51: BRAZIMIL CORRIDA
A52: BRAZIMIL CORRIDA POTE 1KG | B52: ='[1]CUSTO ESPELHO'!$B52 -> 1.1491965
A53: BRAZIMIL CORRIDA GALÃO 5KG | B53: ='[5]CUSTO ESPELHO'!$B45 -> 6.5147597
A54: BRAZIMIL CORRIDA SACO VALV 10 KG | B54: ='[1]CUSTO ESPELHO'!$B54 -> 5.8212323
A55: BRAZIMIL CORRIDA SACO VALV 25KG
A56: BRAZIMIL CORRIDA PPQ 20KG
A57: BRAZIMIL CORRIDA PPQ 25KG
A58: BRAZIMIL CORRIDA BALDE 20KG | B58: ='[5]CUSTO ESPELHO'!$B50 -> 21.427999
A59: BRAZIMIL CORRIDA BALDE 25KG | B59: ='[1]CUSTO ESPELHO'!$B59 -> 22.679956
A60: BRAZIMIL ACRILICA
A61: BRAZIMIL ACRILICA POTE 1KG | B61: ='[1]CUSTO ESPELHO'!$B61 -> 2.5615108
A62: BRAZIMIL ACRILICA GALÃO 5KG | B62: ='[5]CUSTO ESPELHO'!$B54 -> 10.453611
A63: BRAZIMIL ACRILICA SACO VALV 10,0KG | B63: ='[1]CUSTO ESPELHO'!$B63 -> 12.882804
A64: BRAZIMIL ACRILICA PPQ 20KG | B64: ='[3]CUSTO ESPELHO'!$B64 -> 0
A65: BRAZIMIL ACRILICA PPQ 25KG | B65: ='[3]CUSTO ESPELHO'!$B65 -> 0
A66: BRAZIMIL ACRILICA BALDE 20KG | B66: ='[5]CUSTO ESPELHO'!$B58 -> 36.016337
A67: BRAZIMIL ACRILICA BALDE 25KG | B67: ='[1]CUSTO ESPELHO'!$B67 -> 40.333884
A68: BRAZIMIL TEXT. LISA
A69: BRAZIMIL TEXT. LISA GALÃO 5KG | B69: ='[4]CUSTO ESPELHO'!$B69 -> 0
A70: BRAZIMIL TEXT. LISA SACO VALV 12,5KG | B70: ='[1]CUSTO ESPELHO'!$B70 -> 15.460622
A71: BRAZIMIL TEXT. LISA PPQ 25KG | B71: ='[4]CUSTO ESPELHO'!$B71 -> 0
A72: BRAZIMIL TEXT. LISA BALDE 25KG | B72: ='[1]CUSTO ESPELHO'!$B72 -> 46.778431
A73: BRAZIMIL TEXT. RÚSTICA
A74: BRAZIMIL TEXT. RÚSTICA GALÃO 5KG | B74: ='[1]CUSTO ESPELHO'!$B74 -> 0
A75: BRAZIMIL TEXT. RÚSTICA SACO VALV 12,5KG | B75: ='[1]CUSTO ESPELHO'!$B75 -> 0
A76: BRAZIMIL TEXT. RÚSTICA PPQ 25KG | B76: ='[1]CUSTO ESPELHO'!$B76 -> 0
A77: BRAZIMIL TEXT. RÚSTICA BALDE 25KG | B77: ='[1]CUSTO ESPELHO'!$B77 -> 0
A78: TINTAS BASE SOLVENTE
A79: BRAZIMIL ESMALTE SINTÉTICO 0,75L
A80: BRAZIMIL ESMALTE SINTÉTICO 0,75L LATA ALUMÍNIO | B80: ='[1]CUSTO ESPELHO'!$B80 -> 16.02659
A81: BRAZIMIL ESMALTE SINTÉTICO 0,75L LATA BRANCO | B81: ='[5]CUSTO ESPELHO'!$B73 -> 10.062562
A82: BRAZIMIL ESMALTE SINTÉTICO 0,75L LATA PRETO | B82: ='[5]CUSTO ESPELHO'!$B74 -> 8.2124527
A83: BRAZIMIL ESMALTE SINTÉTICO 0,75L LATA COR | B83: ='[5]CUSTO ESPELHO'!$B75 -> 8.6808652
A84: BRAZIMIL ESMALTE SINTÉTICO 0,75L LATA FOSCO
A85: BRAZIMIL ESMALTE SINTÉTICO 3,0L
A86: BRAZIMIL ESMALTE SINTÉTICO 3,0L LATA ALUMÍNIO | B86: ='[1]CUSTO ESPELHO'!$B86 -> 58.30476
A87: BRAZIMIL ESMALTE SINTÉTICO 3,0L LATA BRANCO | B87: ='[5]CUSTO ESPELHO'!$B79 -> 34.910249
A88: BRAZIMIL ESMALTE SINTÉTICO 3,0L LATA PRETO | B88: ='[5]CUSTO ESPELHO'!$B80 -> 27.509811
A89: BRAZIMIL ESMALTE SINTÉTICO 3,0L LATA COR | B89: ='[5]CUSTO ESPELHO'!$B81 -> 29.383461
A90: BRAZIMIL ESMALTE SINTÉTICO 3,0L LATA FOSCO | B90: ='[1]CUSTO ESPELHO'!$B90 -> 31.616833
A91: BRAZIMIL VERNIZ 0,75L | D91: 2370
A92: BRAZIMIL VERNIZ 0,75L LATA INCOLOR | B92: ='[1]CUSTO ESPELHO'!$B92 -> 11.348817 | D92: =D91*0.95 -> 2251.5
A93: BRAZIMIL VERNIZ 0,75L LATA PIGMENTADO | B93: ='[1]CUSTO ESPELHO'!$B93 -> 9.7586751
A94: BRAZIMIL VERNIZ 3,0L
A95: BRAZIMIL VERNIZ 3,0L LATA INCOLOR | B95: ='[1]CUSTO ESPELHO'!$B95 -> 39.593668
A96: BRAZIMIL VERNIZ 3,0L LATA PIGMENTADO | B96: ='[1]CUSTO ESPELHO'!$B96 -> 35.488024
A97: BRAZIMIL ZARCÃO 0,75L
A98: BRAZIMIL ZARCÃO 0,75L LATA BRANCO | B98: ='[1]CUSTO ESPELHO'!$B98 -> 6.5946532
A99: BRAZIMIL ZARCÃO 0,75L LATA CINZA | B99: ='[1]CUSTO ESPELHO'!$B99 -> 6.5946532
A100: BRAZIMIL ZARCÃO 0,75L LATA COR | B100: ='[1]CUSTO ESPELHO'!$B100 -> 6.5946532
A101: BRAZIMIL ZARCÃO 3,0L
A102: BRAZIMIL ZARCÃO 3,0L LATA BRANCO | B102: ='[1]CUSTO ESPELHO'!$B102 -> 89.537208
A103: BRAZIMIL ZARCÃO 3,0L LATA CINZA | B103: ='[1]CUSTO ESPELHO'!$B103 -> 20.577013
A104: BRAZIMIL ZARCÃO 18L LATA COR | B104: ='[1]CUSTO ESPELHO'!$B104 -> 89.537208
A105: BRAZIMIL SELADOR P/ MAD. 0,75L
A106: BRAZIMIL SELADOR P/ MAD. 0,75L LATA INCOLOR | B106: ='[1]CUSTO ESPELHO'!$B106 -> 11.117213
A107: BRAZIMIL SELADOR P/ MAD. 3,0L
A108: BRAZIMIL SELADOR P/ MAD. 3,0L LATA INCOLOR | B108: ='[1]CUSTO ESPELHO'!$B108 -> 38.667252
...

Sheet Peso
A9: Produto | B9: PESO BRUTO
A10: TINTAS BASE ÁGUA
A11: BRAZIMIL ECONOMICA 3,0L
A12: BRAZIMIL ECONÔMICA 3,0L REFIL BRANCO NEVE | B12: 3.85
A13: BRAZIMIL ECONÔMICA 3,0L REFIL COR | B13: 3.35
A14: BRAZIMIL ECONÔMICA 3,0L GALÃO BRANCO NEVE | B14: 4
A15: BRAZIMIL ECONÔMICA 3,0L GALÃO COR | B15: 3.5
A16: BRAZIMIL ECONÔMICA 15L
A17: BRAZIMIL ECONÔMICA 15L PPQ BRANCO NEVE | B17: 18.7
A18: BRAZIMIL ECONÔMICA 12L BALDE BRANCO NEVE | B18: =12*1.2 -> 14.4
A19: BRAZIMIL ECONÔMICA 15L BALDE BRANCO NEVE | B19: 18.7
A20: BRAZIMIL ECONÔMICA 15L BALDE COR | B20: 17
A21: BRAZIMIL EXTERNA 3,0L
A22: BRAZIMIL EXTERNA 3,0L BALDE BRANCO NEVE | B22: 4.2
A23: BRAZIMIL EXTERNA 3,0L BALDE COR | B23: 3.9
A24: BRAZIMIL EXTERNA 15L
A25: BRAZIMIL EXTERNA 15L BALDE BRANCO NEVE | B25: 19
A26: BRAZIMIL EXTERNA 15L BALDE COR | B26: 17
A27: BRAZIMIL SEMI BRILHO 3,0L
A28: BRAZIMIL SEMI BRILHO 3,0L BALDE BRANCO NEVE | B28: 3.6
A29: BRAZIMIL SEMI BRILHO 3,0L BALDE COR | B29: 3.5
A30: BRAZIMIL SEMI BRILHO 15L
A31: BRAZIMIL SEMI BRILHO 12L BALDE BRANCO NEVE | B31: 12.5
A32: BRAZIMIL SEMI BRILHO 15L BALDE BRANCO NEVE | B32: 15.1
A33: BRAZIMIL SEMI BRILHO 15L BALDE COR | B33: 15.1
A34: BRAZIMIL TINTA PISO 3,0L
A35: BRAZIMIL TINTA PISO 3,0L BALDE BRANCO NEVE | B35: 3.7
A36: BRAZIMIL TINTA PISO 3,0L BALDE COR | B36: 3.6
A37: BRAZIMIL TINTA PISO 15L
A38: BRAZIMIL TINTA PISO 15L BALDE BRANCO NEVE | B38: 16
A39: BRAZIMIL TINTA PISO 15L BALDE COR | B39: 15.8
A40: BRAZIMIL SELADOR ACRIL 3,0L
A41: BRAZIMIL SELADOR ACRIL 3,0L REFIL PIGMENTADO | B41: 3.85
A42: BRAZIMIL SELADOR ACRIL 3,0L BALDE PIGMENTADO | B42: 4.05
A43: BRAZIMIL SELADOR ACRIL 15L
A44: BRAZIMIL SELADOR ACRIL 12L PIGMENTADO | B44: 13
A45: BRAZIMIL SELADOR ACRIL 15L BALDE PIGMENTADO | B45: 18
A46: LIQUIBRILHO 3,0L
A47: LIQUIBRILHO 3,0L BALDE INCOLOR | B47: 3.185
A48: LIQUIBRILHO 15L
A49: LIQUIBRILHO 15L BALDE INCOLOR | B49: 13.5
A50: MASSAS / TEXTURAS
A51: BRAZIMIL CORRIDA
A52: BRAZIMIL CORRIDA POTE 1KG | B52: 1.04
A53: BRAZIMIL CORRIDA GALÃO 5KG | B53: 5.185
A54: BRAZIMIL CORRIDA SACO VALV 10 KG | B54: 10.05
A55: BRAZIMIL CORRIDA SACO VALV 25KG | B55: 25.03
A56: BRAZIMIL CORRIDA PPQ 20KG | B56: 20.77
A57: BRAZIMIL CORRIDA PPQ 25KG | B57: 25.77
A58: BRAZIMIL CORRIDA BALDE 20KG | B58: 20.64
A59: BRAZIMIL CORRIDA BALDE 25KG | B59: 25.64
A60: BRAZIMIL ACRILICA
A61: BRAZIMIL ACRILICA POTE 1KG | B61: 1.04
A62: BRAZIMIL ACRILICA GALÃO 5KG | B62: 5.185
A63: BRAZIMIL ACRILICA SACO VALV 10,0KG | B63: 10.05
A64: BRAZIMIL ACRILICA PPQ 20KG | B64: 20.77
A65: BRAZIMIL ACRILICA PPQ 25KG | B65: 25.77
A66: BRAZIMIL ACRILICA BALDE 20KG | B66: 20.7
A67: BRAZIMIL ACRILICA BALDE 25KG | B67: 25.64
A68: BRAZIMIL TEXT. LISA
A69: BRAZIMIL TEXT. LISA GALÃO 5KG | B69: 5.16
A70: BRAZIMIL TEXT. LISA SACO VALV 12,5KG | B70: 12.54
A71: BRAZIMIL TEXT. LISA PPQ 25KG | B71: 25.77
A72: BRAZIMIL TEXT. LISA BALDE 25KG | B72: 25.64
A73: BRAZIMIL TEXT. RÚSTICA
A74: BRAZIMIL TEXT. RÚSTICA GALÃO 5KG | B74: 5.16
A75: BRAZIMIL TEXT. RÚSTICA SACO VALV 12,5KG | B75: 12.54
A76: BRAZIMIL TEXT. RÚSTICA PPQ 25KG | B76: 25.77
A77: BRAZIMIL TEXT. RÚSTICA BALDE 25KG | B77: 25.64
A78: TINTAS BASE SOLVENTE
A79: BRAZIMIL ESMALTE SINTÉTICO 0,75L
A80: BRAZIMIL ESMALTE SINTÉTICO 0,75L LATA ALUMÍNIO | B80: 0.85 | C80: BRAZIMIL ESMALTE SINTÉTICO 0,75L LATA ALUMÍNIO
A81: BRAZIMIL ESMALTE SINTÉTICO 0,75L LATA BRANCO | B81: 1.05 | C81: BRAZIMIL ESMALTE SINTÉTICO 0,75L LATA BRANCO
A82: BRAZIMIL ESMALTE SINTÉTICO 0,75L LATA PRETO | B82: 19 | C82: BRAZIMIL ESMALTE SINTÉTICO 0,75L LATA PRETO
A83: BRAZIMIL ESMALTE SINTÉTICO 0,75L LATA COR | B83: 0.85 | C83: BRAZIMIL ESMALTE SINTÉTICO 0,75L LATA COR
A84: BRAZIMIL ESMALTE SINTÉTICO 0,75L LATA FOSCO | B84: 1.05 | C84: BRAZIMIL ESMALTE SINTÉTICO 0,75L LATA FOSCO
A85: BRAZIMIL ESMALTE SINTÉTICO 3,0L
A86: BRAZIMIL ESMALTE SINTÉTICO 3,0L LATA ALUMÍNIO | B86: 3.1
A87: BRAZIMIL ESMALTE SINTÉTICO 3,0L LATA BRANCO | B87: 3.35
A88: BRAZIMIL ESMALTE SINTÉTICO 3,0L LATA PRETO | B88: 3.35
A89: BRAZIMIL ESMALTE SINTÉTICO 3,0L LATA COR | B89: 3.35
A90: BRAZIMIL ESMALTE SINTÉTICO 3,0L LATA FOSCO | B90: 3.6
A91: BRAZIMIL VERNIZ 0,75L
A92: BRAZIMIL VERNIZ 0,75L LATA INCOLOR | B92: 0.85
A93: BRAZIMIL VERNIZ 0,75L LATA PIGMENTADO | B93: 0.85
A94: BRAZIMIL VERNIZ 3,0L
A95: BRAZIMIL VERNIZ 3,0L LATA INCOLOR | B95: 3.1
A96: BRAZIMIL VERNIZ 3,0L LATA PIGMENTADO | B96: 3.1
A97: BRAZIMIL ZARCÃO 0,75L
A98: BRAZIMIL ZARCÃO 0,75L LATA BRANCO | B98: 1.02
A99: BRAZIMIL ZARCÃO 0,75L LATA CINZA | B99: 1.02
A100: BRAZIMIL ZARCÃO 0,75L LATA COR | B100: 1.02
A101: BRAZIMIL ZARCÃO 3,0L
A102: BRAZIMIL ZARCÃO 3,0L LATA BRANCO | B102: 3.5
A103: BRAZIMIL ZARCÃO 3,0L LATA CINZA | B103: 3.5
A104: BRAZIMIL ZARCÃO 18L LATA COR | B104: 20.5
A105: BRAZIMIL SELADOR P/ MAD. 0,75L
A106: BRAZIMIL SELADOR P/ MAD. 0,75L LATA INCOLOR | B106: 0.85
A107: BRAZIMIL SELADOR P/ MAD. 3,0L
A108: BRAZIMIL SELADOR P/ MAD. 3,0L LATA INCOLOR | B108: 3.1
...

Sheet MVA-grupos
A9: Produto / Grupo ST | B9: GRUPO 1 | D9: GRUPO 2 | F9: GRUPO 3 | H9: GRUPO 4
A10: TINTAS BASE ÁGUA
A11: BRAZIMIL ECONOMICA 3,0L
A12: BRAZIMIL ECONÔMICA 3,0L REFIL BRANCO NEVE | B12: ='MVA-IPI'!O12 -> 0.485 | D12: ='MVA-IPI'!B12 -> 0.485 | F12: ='MVA-IPI'!N12 -> 0.4667 | H12: ='MVA-IPI'!AB12 -> 0
A13: BRAZIMIL ECONÔMICA 3,0L REFIL COR | B13: ='MVA-IPI'!O13 -> 0.485 | D13: ='MVA-IPI'!B13 -> 0.485 | F13: ='MVA-IPI'!N13 -> 0.4667 | H13: ='MVA-IPI'!AB13 -> 0
A14: BRAZIMIL ECONÔMICA 3,0L GALÃO BRANCO NEVE | B14: ='MVA-IPI'!O14 -> 0.485 | D14: ='MVA-IPI'!B14 -> 0.485 | F14: ='MVA-IPI'!N14 -> 0.4667 | H14: ='MVA-IPI'!AB14 -> 0
A15: BRAZIMIL ECONÔMICA 3,0L GALÃO COR | B15: ='MVA-IPI'!O15 -> 0.485 | D15: ='MVA-IPI'!B15 -> 0.485 | F15: ='MVA-IPI'!N15 -> 0.4667 | H15: ='MVA-IPI'!AB15 -> 0
A16: BRAZIMIL ECONÔMICA 15L
A17: BRAZIMIL ECONÔMICA 15L PPQ BRANCO NEVE | B17: ='MVA-IPI'!O17 -> 0.485 | D17: ='MVA-IPI'!B17 -> 0.485 | F17: ='MVA-IPI'!N17 -> 0.4667 | H17: ='MVA-IPI'!AB17 -> 0
A18: BRAZIMIL ECONÔMICA 12L BALDE BRANCO NEVE | B18: ='MVA-IPI'!O18 -> 0.485 | D18: ='MVA-IPI'!B18 -> 0.485 | F18: ='MVA-IPI'!N18 -> 0.4667 | H18: ='MVA-IPI'!AB18 -> 0
A19: BRAZIMIL ECONÔMICA 15L BALDE BRANCO NEVE | B19: ='MVA-IPI'!O19 -> 0.485 | D19: ='MVA-IPI'!B19 -> 0.485 | F19: ='MVA-IPI'!N19 -> 0.4667 | H19: ='MVA-IPI'!AB19 -> 0
A20: BRAZIMIL ECONÔMICA 15L BALDE COR | B20: ='MVA-IPI'!O20 -> 0.485 | D20: ='MVA-IPI'!B20 -> 0.485 | F20: ='MVA-IPI'!N20 -> 0.4667 | H20: ='MVA-IPI'!AB20 -> 0
A21: BRAZIMIL EXTERNA 3,0L
A22: BRAZIMIL EXTERNA 3,0L BALDE BRANCO NEVE | B22: ='MVA-IPI'!O22 -> 0.485 | D22: ='MVA-IPI'!B22 -> 0.485 | F22: ='MVA-IPI'!N22 -> 0.4667 | H22: ='MVA-IPI'!AB22 -> 0
A23: BRAZIMIL EXTERNA 3,0L BALDE COR | B23: ='MVA-IPI'!O23 -> 0.485 | D23: ='MVA-IPI'!B23 -> 0.485 | F23: ='MVA-IPI'!N23 -> 0.4667 | H23: ='MVA-IPI'!AB23 -> 0
A24: BRAZIMIL EXTERNA 15L
A25: BRAZIMIL EXTERNA 15L BALDE BRANCO NEVE | B25: ='MVA-IPI'!O25 -> 0.485 | D25: ='MVA-IPI'!B25 -> 0.485 | F25: ='MVA-IPI'!N25 -> 0.4667 | H25: ='MVA-IPI'!AB25 -> 0
A26: BRAZIMIL EXTERNA 15L BALDE COR | B26: ='MVA-IPI'!O26 -> 0.485 | D26: ='MVA-IPI'!B26 -> 0.485 | F26: ='MVA-IPI'!N26 -> 0.4667 | H26: ='MVA-IPI'!AB26 -> 0
A27: BRAZIMIL SEMI BRILHO 3,0L
A28: BRAZIMIL SEMI BRILHO 3,0L BALDE BRANCO NEVE | B28: ='MVA-IPI'!O28 -> 0.485 | D28: ='MVA-IPI'!B28 -> 0.485 | F28: ='MVA-IPI'!N28 -> 0.4667 | H28: ='MVA-IPI'!AB28 -> 0
A29: BRAZIMIL SEMI BRILHO 3,0L BALDE COR | B29: ='MVA-IPI'!O29 -> 0.485 | D29: ='MVA-IPI'!B29 -> 0.485 | F29: ='MVA-IPI'!N29 -> 0.4667 | H29: ='MVA-IPI'!AB29 -> 0
A30: BRAZIMIL SEMI BRILHO 15L
A31: BRAZIMIL SEMI BRILHO 12L BALDE BRANCO NEVE | B31: ='MVA-IPI'!O31 -> 0.485 | D31: ='MVA-IPI'!B31 -> 0.485 | F31: ='MVA-IPI'!N31 -> 0.4667 | H31: ='MVA-IPI'!AB31 -> 0
A32: BRAZIMIL SEMI BRILHO 15L BALDE BRANCO NEVE | B32: ='MVA-IPI'!O32 -> 0.485 | D32: ='MVA-IPI'!B32 -> 0.485 | F32: ='MVA-IPI'!N32 -> 0.4667 | H32: ='MVA-IPI'!AB32 -> 0
A33: BRAZIMIL SEMI BRILHO 15L BALDE COR | B33: ='MVA-IPI'!O33 -> 0.485 | D33: ='MVA-IPI'!B33 -> 0.485 | F33: ='MVA-IPI'!N33 -> 0.4667 | H33: ='MVA-IPI'!AB33 -> 0
A34: BRAZIMIL TINTA PISO 3,0L
A35: BRAZIMIL TINTA PISO 3,0L BALDE BRANCO NEVE | B35: ='MVA-IPI'!O35 -> 0.485 | D35: ='MVA-IPI'!B35 -> 0.485 | F35: ='MVA-IPI'!N35 -> 0.4667 | H35: ='MVA-IPI'!AB35 -> 0
A36: BRAZIMIL TINTA PISO 3,0L BALDE COR | B36: ='MVA-IPI'!O36 -> 0.485 | D36: ='MVA-IPI'!B36 -> 0.485 | F36: ='MVA-IPI'!N36 -> 0.4667 | H36: ='MVA-IPI'!AB36 -> 0
A37: BRAZIMIL TINTA PISO 15L
A38: BRAZIMIL TINTA PISO 15L BALDE BRANCO NEVE | B38: ='MVA-IPI'!O38 -> 0.485 | D38: ='MVA-IPI'!B38 -> 0.485 | F38: ='MVA-IPI'!N38 -> 0.4667 | H38: ='MVA-IPI'!AB38 -> 0
A39: BRAZIMIL TINTA PISO 15L BALDE COR | B39: ='MVA-IPI'!O39 -> 0.485 | D39: ='MVA-IPI'!B39 -> 0.485 | F39: ='MVA-IPI'!N39 -> 0.4667 | H39: ='MVA-IPI'!AB39 -> 0
A40: BRAZIMIL SELADOR ACRIL 3,0L
A41: BRAZIMIL SELADOR ACRIL 3,0L REFIL PIGMENTADO | B41: ='MVA-IPI'!O41 -> 0.485 | D41: ='MVA-IPI'!B41 -> 0.485 | F41: ='MVA-IPI'!N41 -> 0.4667 | H41: ='MVA-IPI'!AB41 -> 0
A42: BRAZIMIL SELADOR ACRIL 3,0L BALDE PIGMENTADO | B42: ='MVA-IPI'!O42 -> 0.485 | D42: ='MVA-IPI'!B42 -> 0.485 | F42: ='MVA-IPI'!N42 -> 0.4667 | H42: ='MVA-IPI'!AB42 -> 0
A43: BRAZIMIL SELADOR ACRIL 15L
A44: BRAZIMIL SELADOR ACRIL 12L PIGMENTADO | B44: ='MVA-IPI'!O44 -> 0.485 | D44: ='MVA-IPI'!B44 -> 0.485 | F44: ='MVA-IPI'!N44 -> 0.4667 | H44: ='MVA-IPI'!AB44 -> 0
A45: BRAZIMIL SELADOR ACRIL 15L BALDE PIGMENTADO | B45: ='MVA-IPI'!O45 -> 0.485 | D45: ='MVA-IPI'!B45 -> 0.485 | F45: ='MVA-IPI'!N45 -> 0.4667 | H45: ='MVA-IPI'!AB45 -> 0
A46: LIQUIBRILHO 3,0L
A47: LIQUIBRILHO 3,0L BALDE INCOLOR | B47: ='MVA-IPI'!O47 -> 0.485 | D47: ='MVA-IPI'!B47 -> 0.485 | F47: ='MVA-IPI'!N47 -> 0.4667 | H47: ='MVA-IPI'!AB47 -> 0
A48: LIQUIBRILHO 15L
A49: LIQUIBRILHO 15L BALDE INCOLOR | B49: ='MVA-IPI'!O49 -> 0.485 | D49: ='MVA-IPI'!B49 -> 0.485 | F49: ='MVA-IPI'!N49 -> 0.4667 | H49: ='MVA-IPI'!AB49 -> 0
A50: MASSAS / TEXTURAS
A51: BRAZIMIL CORRIDA
A52: BRAZIMIL CORRIDA POTE 1KG | B52: ='MVA-IPI'!O52 -> 0 | D52: ='MVA-IPI'!B52 -> 0 | F52: ='MVA-IPI'!N52 -> 0 | H52: ='MVA-IPI'!AB52 -> 0
A53: BRAZIMIL CORRIDA GALÃO 5KG | B53: ='MVA-IPI'!O53 -> 0 | D53: ='MVA-IPI'!B53 -> 0 | F53: ='MVA-IPI'!N53 -> 0 | H53: ='MVA-IPI'!AB53 -> 0
A54: BRAZIMIL CORRIDA SACO VALV 10 KG | B54: ='MVA-IPI'!O54 -> 0 | D54: ='MVA-IPI'!B54 -> 0 | F54: ='MVA-IPI'!N54 -> 0 | H54: ='MVA-IPI'!AB54 -> 0
A55: BRAZIMIL CORRIDA SACO VALV 25KG | B55: ='MVA-IPI'!O55 -> 0 | D55: ='MVA-IPI'!B55 -> 0 | F55: ='MVA-IPI'!N55 -> 0 | H55: ='MVA-IPI'!AB55 -> 0
A56: BRAZIMIL CORRIDA PPQ 20KG | B56: ='MVA-IPI'!O56 -> 0 | D56: ='MVA-IPI'!B56 -> 0 | F56: ='MVA-IPI'!N56 -> 0 | H56: ='MVA-IPI'!AB56 -> 0
A57: BRAZIMIL CORRIDA PPQ 25KG | B57: ='MVA-IPI'!O57 -> 0 | D57: ='MVA-IPI'!B57 -> 0 | F57: ='MVA-IPI'!N57 -> 0 | H57: ='MVA-IPI'!AB57 -> 0
A58: BRAZIMIL CORRIDA BALDE 20KG | B58: ='MVA-IPI'!O58 -> 0 | D58: ='MVA-IPI'!B58 -> 0 | F58: ='MVA-IPI'!N58 -> 0 | H58: ='MVA-IPI'!AB58 -> 0
A59: BRAZIMIL CORRIDA BALDE 25KG | B59: ='MVA-IPI'!O59 -> 0 | D59: ='MVA-IPI'!B59 -> 0 | F59: ='MVA-IPI'!N59 -> 0 | H59: ='MVA-IPI'!AB59 -> 0
A60: BRAZIMIL ACRILICA
A61: BRAZIMIL ACRILICA POTE 1KG | B61: ='MVA-IPI'!O61 -> 0 | D61: ='MVA-IPI'!B61 -> 0 | F61: ='MVA-IPI'!N61 -> 0 | H61: ='MVA-IPI'!AB61 -> 0
A62: BRAZIMIL ACRILICA GALÃO 5KG | B62: ='MVA-IPI'!O62 -> 0 | D62: ='MVA-IPI'!B62 -> 0 | F62: ='MVA-IPI'!N62 -> 0 | H62: ='MVA-IPI'!AB62 -> 0
A63: BRAZIMIL ACRILICA SACO VALV 10,0KG | B63: ='MVA-IPI'!O63 -> 0 | D63: ='MVA-IPI'!B63 -> 0 | F63: ='MVA-IPI'!N63 -> 0 | H63: ='MVA-IPI'!AB63 -> 0
A64: BRAZIMIL ACRILICA PPQ 20KG | B64: ='MVA-IPI'!O64 -> 0 | D64: ='MVA-IPI'!B64 -> 0 | F64: ='MVA-IPI'!N64 -> 0 | H64: ='MVA-IPI'!AB64 -> 0
A65: BRAZIMIL ACRILICA PPQ 25KG | B65: ='MVA-IPI'!O65 -> 0 | D65: ='MVA-IPI'!B65 -> 0 | F65: ='MVA-IPI'!N65 -> 0 | H65: ='MVA-IPI'!AB65 -> 0
A66: BRAZIMIL ACRILICA BALDE 20KG | B66: ='MVA-IPI'!O66 -> 0 | D66: ='MVA-IPI'!B66 -> 0 | F66: ='MVA-IPI'!N66 -> 0 | H66: ='MVA-IPI'!AB66 -> 0
A67: BRAZIMIL ACRILICA BALDE 25KG | B67: ='MVA-IPI'!O67 -> 0 | D67: ='MVA-IPI'!B67 -> 0 | F67: ='MVA-IPI'!N67 -> 0 | H67: ='MVA-IPI'!AB67 -> 0
A68: BRAZIMIL TEXT. LISA
A69: BRAZIMIL TEXT. LISA GALÃO 5KG | B69: ='MVA-IPI'!O69 -> 0 | D69: ='MVA-IPI'!B69 -> 0 | F69: ='MVA-IPI'!N69 -> 0 | H69: ='MVA-IPI'!AB69 -> 0
A70: BRAZIMIL TEXT. LISA SACO VALV 12,5KG | B70: ='MVA-IPI'!O70 -> 0 | D70: ='MVA-IPI'!B70 -> 0 | F70: ='MVA-IPI'!N70 -> 0 | H70: ='MVA-IPI'!AB70 -> 0
A71: BRAZIMIL TEXT. LISA PPQ 25KG | B71: ='MVA-IPI'!O71 -> 0 | D71: ='MVA-IPI'!B71 -> 0 | F71: ='MVA-IPI'!N71 -> 0 | H71: ='MVA-IPI'!AB71 -> 0
A72: BRAZIMIL TEXT. LISA BALDE 25KG | B72: ='MVA-IPI'!O72 -> 0 | D72: ='MVA-IPI'!B72 -> 0 | F72: ='MVA-IPI'!N72 -> 0 | H72: ='MVA-IPI'!AB72 -> 0
A73: BRAZIMIL TEXT. RÚSTICA
A74: BRAZIMIL TEXT. RÚSTICA GALÃO 5KG | B74: ='MVA-IPI'!O74 -> 0 | D74: ='MVA-IPI'!B74 -> 0 | F74: ='MVA-IPI'!N74 -> 0 | H74: ='MVA-IPI'!AB74 -> 0
A75: BRAZIMIL TEXT. RÚSTICA SACO VALV 12,5KG | B75: ='MVA-IPI'!O75 -> 0 | D75: ='MVA-IPI'!B75 -> 0 | F75: ='MVA-IPI'!N75 -> 0 | H75: ='MVA-IPI'!AB75 -> 0
A76: BRAZIMIL TEXT. RÚSTICA PPQ 25KG | B76: ='MVA-IPI'!O76 -> 0 | D76: ='MVA-IPI'!B76 -> 0 | F76: ='MVA-IPI'!N76 -> 0 | H76: ='MVA-IPI'!AB76 -> 0
A77: BRAZIMIL TEXT. RÚSTICA BALDE 25KG | B77: ='MVA-IPI'!O77 -> 0 | D77: ='MVA-IPI'!B77 -> 0 | F77: ='MVA-IPI'!N77 -> 0 | H77: ='MVA-IPI'!AB77 -> 0
A78: TINTAS BASE SOLVENTE
A79: BRAZIMIL ESMALTE SINTÉTICO 0,75L
A80: BRAZIMIL ESMALTE SINTÉTICO 0,75L LATA ALUMÍNIO | B80: ='MVA-IPI'!O80 -> 0.485 | D80: ='MVA-IPI'!B80 -> 0.485 | F80: ='MVA-IPI'!N80 -> 0.4667 | H80: ='MVA-IPI'!AB80 -> 0
A81: BRAZIMIL ESMALTE SINTÉTICO 0,75L LATA BRANCO | B81: ='MVA-IPI'!O81 -> 0.485 | D81: ='MVA-IPI'!B81 -> 0.485 | F81: ='MVA-IPI'!N81 -> 0.4667 | H81: ='MVA-IPI'!AB81 -> 0
A82: BRAZIMIL ESMALTE SINTÉTICO 0,75L LATA PRETO | B82: ='MVA-IPI'!O82 -> 0.485 | D82: ='MVA-IPI'!B82 -> 0.485 | F82: ='MVA-IPI'!N82 -> 0.4667 | H82: ='MVA-IPI'!AB82 -> 0
A83: BRAZIMIL ESMALTE SINTÉTICO 0,75L LATA COR | B83: ='MVA-IPI'!O83 -> 0.485 | D83: ='MVA-IPI'!B83 -> 0.485 | F83: ='MVA-IPI'!N83 -> 0.4667 | H83: ='MVA-IPI'!AB83 -> 0
A84: BRAZIMIL ESMALTE SINTÉTICO 0,75L LATA FOSCO | B84: ='MVA-IPI'!O84 -> 0.485 | D84: ='MVA-IPI'!B84 -> 0.485 | F84: ='MVA-IPI'!N84 -> 0.4667 | H84: ='MVA-IPI'!AB84 -> 0
A85: BRAZIMIL ESMALTE SINTÉTICO 3,0L
A86: BRAZIMIL ESMALTE SINTÉTICO 3,0L LATA ALUMÍNIO | B86: ='MVA-IPI'!O86 -> 0.485 | D86: ='MVA-IPI'!B86 -> 0.485 | F86: ='MVA-IPI'!N86 -> 0.4667 | H86: ='MVA-IPI'!AB86 -> 0
A87: BRAZIMIL ESMALTE SINTÉTICO 3,0L LATA BRANCO | B87: ='MVA-IPI'!O87 -> 0.485 | D87: ='MVA-IPI'!B87 -> 0.485 | F87: ='MVA-IPI'!N87 -> 0.4667 | H87: ='MVA-IPI'!AB87 -> 0
A88: BRAZIMIL ESMALTE SINTÉTICO 3,0L LATA PRETO | B88: ='MVA-IPI'!O88 -> 0.485 | D88: ='MVA-IPI'!B88 -> 0.485 | F88: ='MVA-IPI'!N88 -> 0.4667 | H88: ='MVA-IPI'!AB88 -> 0
A89: BRAZIMIL ESMALTE SINTÉTICO 3,0L LATA COR | B89: ='MVA-IPI'!O89 -> 0.485 | D89: ='MVA-IPI'!B89 -> 0.485 | F89: ='MVA-IPI'!N89 -> 0.4667 | H89: ='MVA-IPI'!AB89 -> 0
A90: BRAZIMIL ESMALTE SINTÉTICO 3,0L LATA FOSCO | B90: ='MVA-IPI'!O90 -> 0.485 | D90: ='MVA-IPI'!B90 -> 0.485 | F90: ='MVA-IPI'!N90 -> 0.4667 | H90: ='MVA-IPI'!AB90 -> 0
A91: BRAZIMIL VERNIZ 0,75L
A92: BRAZIMIL VERNIZ 0,75L LATA INCOLOR | B92: ='MVA-IPI'!O92 -> 0.485 | D92: ='MVA-IPI'!B92 -> 0.485 | F92: ='MVA-IPI'!N92 -> 0.4667 | H92: ='MVA-IPI'!AB92 -> 0
A93: BRAZIMIL VERNIZ 0,75L LATA PIGMENTADO | B93: ='MVA-IPI'!O93 -> 0.485 | D93: ='MVA-IPI'!B93 -> 0.485 | F93: ='MVA-IPI'!N93 -> 0.4667 | H93: ='MVA-IPI'!AB93 -> 0
A94: BRAZIMIL VERNIZ 3,0L
A95: BRAZIMIL VERNIZ 3,0L LATA INCOLOR | B95: ='MVA-IPI'!O95 -> 0.485 | D95: ='MVA-IPI'!B95 -> 0.485 | F95: ='MVA-IPI'!N95 -> 0.4667 | H95: ='MVA-IPI'!AB95 -> 0
A96: BRAZIMIL VERNIZ 3,0L LATA PIGMENTADO | B96: ='MVA-IPI'!O96 -> 0.485 | D96: ='MVA-IPI'!B96 -> 0.485 | F96: ='MVA-IPI'!N96 -> 0.4667 | H96: ='MVA-IPI'!AB96 -> 0
A97: BRAZIMIL ZARCÃO 0,75L
A98: BRAZIMIL ZARCÃO 0,75L LATA BRANCO | B98: ='MVA-IPI'!O98 -> 0.485 | D98: ='MVA-IPI'!B98 -> 0.485 | F98: ='MVA-IPI'!N98 -> 0.4667 | H98: ='MVA-IPI'!AB98 -> 0
A99: BRAZIMIL ZARCÃO 0,75L LATA CINZA | B99: ='MVA-IPI'!O99 -> 0.485 | D99: ='MVA-IPI'!B99 -> 0.485 | F99: ='MVA-IPI'!N99 -> 0.4667 | H99: ='MVA-IPI'!AB99 -> 0
A100: BRAZIMIL ZARCÃO 0,75L LATA COR | B100: ='MVA-IPI'!O100 -> 0.485 | D100: ='MVA-IPI'!B100 -> 0.485 | F100: ='MVA-IPI'!N100 -> 0.4667 | H100: ='MVA-IPI'!AB100 -> 0
A101: BRAZIMIL ZARCÃO 3,0L
A102: BRAZIMIL ZARCÃO 3,0L LATA BRANCO | B102: ='MVA-IPI'!O102 -> 0.485 | D102: ='MVA-IPI'!B102 -> 0.485 | F102: ='MVA-IPI'!N102 -> 0.4667 | H102: ='MVA-IPI'!AB102 -> 0
A103: BRAZIMIL ZARCÃO 3,0L LATA CINZA | B103: ='MVA-IPI'!O103 -> 0.485 | D103: ='MVA-IPI'!B103 -> 0.485 | F103: ='MVA-IPI'!N103 -> 0.4667 | H103: ='MVA-IPI'!AB103 -> 0
A104: BRAZIMIL ZARCÃO 18L LATA COR | B104: ='MVA-IPI'!O104 -> 0.485 | D104: ='MVA-IPI'!B104 -> 0.485 | F104: ='MVA-IPI'!N104 -> 0.4667 | H104: ='MVA-IPI'!AB104 -> 0
A105: BRAZIMIL SELADOR P/ MAD. 0,75L
A106: BRAZIMIL SELADOR P/ MAD. 0,75L LATA INCOLOR | B106: ='MVA-IPI'!O106 -> 0.485 | D106: ='MVA-IPI'!B106 -> 0.485 | F106: ='MVA-IPI'!N106 -> 0.4667 | H106: ='MVA-IPI'!AB106 -> 0
A107: BRAZIMIL SELADOR P/ MAD. 3,0L
A108: BRAZIMIL SELADOR P/ MAD. 3,0L LATA INCOLOR | B108: ='MVA-IPI'!O108 -> 0.485 | D108: ='MVA-IPI'!B108 -> 0.485 | F108: ='MVA-IPI'!N108 -> 0.4667 | H108: ='MVA-IPI'!AB108 -> 0
...

Sheet MVA-IPI
A2: ICMS - ALIQUOTA PB | B2: =B138 -> 0.12 | C2: =C138 -> 0.12 | D2: =D138 -> 0.12 | E2: =E138 -> 0.12 | F2: =F138 -> 0.12 | G2: =G138 -> 0.12 | H2: =H138 -> 0.12 | I2: =I138 -> 0.12 | ... AB2: =AB138 -> 0.12
A3: ICMS ST - ALIQ. INTERNA DE CADA ESTADO | B3: =B139 -> 0.2 | C3: =C139 -> 0.19 | D3: =D139 -> 0.19 | E3: =E139 -> 0.2 | F3: =F139 -> 0.205 | G3: =G139 -> 0.205 | H3: =H139 -> 0.18 | I3: =I139 -> 0.17 | ... AB3: =AB139 -> 0.2
B7: MVA - MARGEM DE VALOR AGREGADO - %
A9: Produto / Estados Destino | B9: CE | C9: AC | D9: AL | E9: AM | F9: AP | G9: BA | H9: DF | I9: ES | J9: GO | K9: MA | L9: MT | M9: MS | N9: PA | O9: PB | P9: PE | Q9: PI | R9: RN | S9: RS | T9: RR | U9: RO | V9: SC | W9: SE | X9: TO | Y9: MG | Z9: PR | AA9: SP | AB9: RJ
A10: TINTAS BASE ÁGUA | B10: G1 | D10: G2 | E10: G2 | F10: G2 | G10: G2 | K10: G2 | N10: G3 | O10: G2 | P10: G2 | Q10: G2 | R10: G2 | T10: G3 | X10: G2 | AD10: Alíquota IPI
A11: BRAZIMIL ECONOMICA 3,0L
A12: BRAZIMIL ECONÔMICA 3,0L REFIL BRANCO NEVE | B12: 0.485 | D12: 0.4667 | E12: 0.485 | F12: 0.4943 | G12: 0.4943 | K12: 0.5231 | N12: 0.4667 | O12: 0.485 | P12: 0.4943 | Q12: 0.5038 | R12: 0.4488 | T12: 0.4314 | X12: 0.4488 | AD12: 0
A13: BRAZIMIL ECONÔMICA 3,0L REFIL COR | B13: 0.485 | D13: 0.4667 | E13: 0.485 | F13: 0.4943 | G13: 0.4943 | K13: 0.5231 | N13: 0.4667 | O13: 0.485 | P13: 0.4943 | Q13: 0.5038 | R13: 0.4488 | T13: 0.4314 | X13: 0.4488 | AD13: 0
A14: BRAZIMIL ECONÔMICA 3,0L GALÃO BRANCO NEVE | B14: 0.485 | D14: 0.4667 | E14: 0.485 | F14: 0.4943 | G14: 0.4943 | K14: 0.5231 | N14: 0.4667 | O14: 0.485 | P14: 0.4943 | Q14: 0.5038 | R14: 0.4488 | T14: 0.4314 | X14: 0.4488 | AD14: 0
A15: BRAZIMIL ECONÔMICA 3,0L GALÃO COR | B15: 0.485 | D15: 0.4667 | E15: 0.485 | F15: 0.4943 | G15: 0.4943 | K15: 0.5231 | N15: 0.4667 | O15: 0.485 | P15: 0.4943 | Q15: 0.5038 | R15: 0.4488 | T15: 0.4314 | X15: 0.4488 | AD15: 0
A16: BRAZIMIL ECONÔMICA 15L
A17: BRAZIMIL ECONÔMICA 15L PPQ BRANCO NEVE | B17: 0.485 | D17: 0.4667 | E17: 0.485 | F17: 0.4943 | G17: 0.4943 | K17: 0.5231 | N17: 0.4667 | O17: 0.485 | P17: 0.4943 | Q17: 0.5038 | R17: 0.4488 | T17: 0.4314 | X17: 0.4488 | AD17: 0
A18: BRAZIMIL ECONÔMICA 12L BALDE BRANCO NEVE | B18: 0.485 | D18: 0.4667 | E18: 0.485 | F18: 0.4943 | G18: 0.4943 | K18: 0.5231 | N18: 0.4667 | O18: 0.485 | P18: 0.4943 | Q18: 0.5038 | R18: 0.4488 | T18: 0.4314 | X18: 0.4488 | AD18: 0
A19: BRAZIMIL ECONÔMICA 15L BALDE BRANCO NEVE | B19: 0.485 | D19: 0.4667 | E19: 0.485 | F19: 0.4943 | G19: 0.4943 | K19: 0.5231 | N19: 0.4667 | O19: 0.485 | P19: 0.4943 | Q19: 0.5038 | R19: 0.4488 | T19: 0.4314 | X19: 0.4488 | AD19: 0
A20: BRAZIMIL ECONÔMICA 15L BALDE COR | B20: 0.485 | D20: 0.4667 | E20: 0.485 | F20: 0.4943 | G20: 0.4943 | K20: 0.5231 | N20: 0.4667 | O20: 0.485 | P20: 0.4943 | Q20: 0.5038 | R20: 0.4488 | T20: 0.4314 | X20: 0.4488 | AD20: 0
A21: BRAZIMIL EXTERNA 3,0L
A22: BRAZIMIL EXTERNA 3,0L BALDE BRANCO NEVE | B22: 0.485 | D22: 0.4667 | E22: 0.485 | F22: 0.4943 | G22: 0.4943 | K22: 0.5231 | N22: 0.4667 | O22: 0.485 | P22: 0.4943 | Q22: 0.5038 | R22: 0.4488 | T22: 0.4314 | X22: 0.4488 | AD22: 0
A23: BRAZIMIL EXTERNA 3,0L BALDE COR | B23: 0.485 | D23: 0.4667 | E23: 0.485 | F23: 0.4943 | G23: 0.4943 | K23: 0.5231 | N23: 0.4667 | O23: 0.485 | P23: 0.4943 | Q23: 0.5038 | R23: 0.4488 | T23: 0.4314 | X23: 0.4488 | AD23: 0
A24: BRAZIMIL EXTERNA 15L
A25: BRAZIMIL EXTERNA 15L BALDE BRANCO NEVE | B25: 0.485 | D25: 0.4667 | E25: 0.485 | F25: 0.4943 | G25: 0.4943 | K25: 0.5231 | N25: 0.4667 | O25: 0.485 | P25: 0.4943 | Q25: 0.5038 | R25: 0.4488 | T25: 0.4314 | X25: 0.4488 | AD25: 0
A26: BRAZIMIL EXTERNA 15L BALDE COR | B26: 0.485 | D26: 0.4667 | E26: 0.485 | F26: 0.4943 | G26: 0.4943 | K26: 0.5231 | N26: 0.4667 | O26: 0.485 | P26: 0.4943 | Q26: 0.5038 | R26: 0.4488 | T26: 0.4314 | X26: 0.4488 | AD26: 0
A27: BRAZIMIL SEMI BRILHO 3,0L
A28: BRAZIMIL SEMI BRILHO 3,0L BALDE BRANCO NEVE | B28: 0.485 | D28: 0.4667 | E28: 0.485 | F28: 0.4943 | G28: 0.4943 | K28: 0.5231 | N28: 0.4667 | O28: 0.485 | P28: 0.4943 | Q28: 0.5038 | R28: 0.4488 | T28: 0.4314 | X28: 0.4488 | AD28: 0
A29: BRAZIMIL SEMI BRILHO 3,0L BALDE COR | B29: 0.485 | D29: 0.4667 | E29: 0.485 | F29: 0.4943 | G29: 0.4943 | K29: 0.5231 | N29: 0.4667 | O29: 0.485 | P29: 0.4943 | Q29: 0.5038 | R29: 0.4488 | T29: 0.4314 | X29: 0.4488 | AD29: 0
A30: BRAZIMIL SEMI BRILHO 15L
A31: BRAZIMIL SEMI BRILHO 12L BALDE BRANCO NEVE | B31: 0.485 | D31: 0.4667 | E31: 0.485 | F31: 0.4943 | G31: 0.4943 | K31: 0.5231 | N31: 0.4667 | O31: 0.485 | P31: 0.4943 | Q31: 0.5038 | R31: 0.4488 | T31: 0.4314 | X31: 0.4488 | AD31: 0
A32: BRAZIMIL SEMI BRILHO 15L BALDE BRANCO NEVE | B32: 0.485 | D32: 0.4667 | E32: 0.485 | F32: 0.4943 | G32: 0.4943 | K32: 0.5231 | N32: 0.4667 | O32: 0.485 | P32: 0.4943 | Q32: 0.5038 | R32: 0.4488 | T32: 0.4314 | X32: 0.4488 | AD32: 0
A33: BRAZIMIL SEMI BRILHO 15L BALDE COR | B33: 0.485 | D33: 0.4667 | E33: 0.485 | F33: 0.4943 | G33: 0.4943 | K33: 0.5231 | N33: 0.4667 | O33: 0.485 | P33: 0.4943 | Q33: 0.5038 | R33: 0.4488 | T33: 0.4314 | X33: 0.4488 | AD33: 0
A34: BRAZIMIL TINTA PISO 3,0L
A35: BRAZIMIL TINTA PISO 3,0L BALDE BRANCO NEVE | B35: 0.485 | D35: 0.4667 | E35: 0.485 | F35: 0.4943 | G35: 0.4943 | K35: 0.5231 | N35: 0.4667 | O35: 0.485 | P35: 0.4943 | Q35: 0.5038 | R35: 0.4488 | T35: 0.4314 | X35: 0.4488 | AD35: 0
A36: BRAZIMIL TINTA PISO 3,0L BALDE COR | B36: 0.485 | D36: 0.4667 | E36: 0.485 | F36: 0.4943 | G36: 0.4943 | K36: 0.5231 | N36: 0.4667 | O36: 0.485 | P36: 0.4943 | Q36: 0.5038 | R36: 0.4488 | T36: 0.4314 | X36: 0.4488 | AD36: 0
A37: BRAZIMIL TINTA PISO 15L
A38: BRAZIMIL TINTA PISO 15L BALDE BRANCO NEVE | B38: 0.485 | D38: 0.4667 | E38: 0.485 | F38: 0.4943 | G38: 0.4943 | K38: 0.5231 | N38: 0.4667 | O38: 0.485 | P38: 0.4943 | Q38: 0.5038 | R38: 0.4488 | T38: 0.4314 | X38: 0.4488 | AD38: 0
A39: BRAZIMIL TINTA PISO 15L BALDE COR | B39: 0.485 | D39: 0.4667 | E39: 0.485 | F39: 0.4943 | G39: 0.4943 | K39: 0.5231 | N39: 0.4667 | O39: 0.485 | P39: 0.4943 | Q39: 0.5038 | R39: 0.4488 | T39: 0.4314 | X39: 0.4488 | AD39: 0
A40: BRAZIMIL SELADOR ACRIL 3,0L
A41: BRAZIMIL SELADOR ACRIL 3,0L REFIL PIGMENTADO | B41: 0.485 | D41: 0.4667 | E41: 0.485 | F41: 0.4943 | G41: 0.4943 | K41: 0.5231 | N41: 0.4667 | O41: 0.485 | P41: 0.4943 | Q41: 0.5038 | R41: 0.4488 | T41: 0.4314 | X41: 0.4488 | AD41: 0
A42: BRAZIMIL SELADOR ACRIL 3,0L BALDE PIGMENTADO | B42: 0.485 | D42: 0.4667 | E42: 0.485 | F42: 0.4943 | G42: 0.4943 | K42: 0.5231 | N42: 0.4667 | O42: 0.485 | P42: 0.4943 | Q42: 0.5038 | R42: 0.4488 | T42: 0.4314 | X42: 0.4488 | AD42: 0
A43: BRAZIMIL SELADOR ACRIL 15L
A44: BRAZIMIL SELADOR ACRIL 12L PIGMENTADO | B44: 0.485 | D44: 0.4667 | E44: 0.485 | F44: 0.4943 | G44: 0.4943 | K44: 0.5231 | N44: 0.4667 | O44: 0.485 | P44: 0.4943 | Q44: 0.5038 | R44: 0.4488 | T44: 0.4314 | X44: 0.4488 | AD44: 0
A45: BRAZIMIL SELADOR ACRIL 15L BALDE PIGMENTADO | B45: 0.485 | D45: 0.4667 | E45: 0.485 | F45: 0.4943 | G45: 0.4943 | K45: 0.5231 | N45: 0.4667 | O45: 0.485 | P45: 0.4943 | Q45: 0.5038 | R45: 0.4488 | T45: 0.4314 | X45: 0.4488 | AD45: 0
A46: LIQUIBRILHO 3,0L
A47: LIQUIBRILHO 3,0L BALDE INCOLOR | B47: 0.485 | D47: 0.4667 | E47: 0.485 | F47: 0.4943 | G47: 0.4943 | K47: 0.5231 | N47: 0.4667 | O47: 0.485 | P47: 0.4943 | Q47: 0.5038 | R47: 0.4488 | T47: 0.4314 | X47: 0.4488 | AD47: 0
A48: LIQUIBRILHO 15L
A49: LIQUIBRILHO 15L BALDE INCOLOR | B49: 0.485 | D49: 0.4667 | E49: 0.485 | F49: 0.4943 | G49: 0.4943 | K49: 0.5231 | N49: 0.4667 | O49: 0.485 | P49: 0.4943 | Q49: 0.5038 | R49: 0.4488 | T49: 0.4314 | X49: 0.4488 | AD49: 0
A50: MASSAS / TEXTURAS
A51: BRAZIMIL CORRIDA
A52: BRAZIMIL CORRIDA POTE 1KG | B52: 0 | D52: 0 | E52: 0 | F52: 0 | G52: 0 | K52: 0 | N52: 0 | O52: 0 | P52: 0 | Q52: 0 | R52: 0 | T52: 0 | X52: 0 | AD52: 0.02
A53: BRAZIMIL CORRIDA GALÃO 5KG | B53: 0 | D53: 0 | E53: 0 | F53: 0 | G53: 0 | K53: 0 | N53: 0 | O53: 0 | P53: 0 | Q53: 0 | R53: 0 | T53: 0 | X53: 0 | AD53: 0.02
A54: BRAZIMIL CORRIDA SACO VALV 10 KG | B54: 0 | D54: 0 | E54: 0 | F54: 0 | G54: 0 | K54: 0 | N54: 0 | O54: 0 | P54: 0 | Q54: 0 | R54: 0 | T54: 0 | X54: 0 | AD54: 0.02
A55: BRAZIMIL CORRIDA SACO VALV 25KG | B55: 0 | D55: 0 | E55: 0 | F55: 0 | G55: 0 | K55: 0 | N55: 0 | O55: 0 | P55: 0 | Q55: 0 | R55: 0 | T55: 0 | X55: 0 | AD55: 0.02
A56: BRAZIMIL CORRIDA PPQ 20KG | B56: 0 | D56: 0 | E56: 0 | F56: 0 | G56: 0 | K56: 0 | N56: 0 | O56: 0 | P56: 0 | Q56: 0 | R56: 0 | T56: 0 | X56: 0 | AD56: 0.02
A57: BRAZIMIL CORRIDA PPQ 25KG | B57: 0 | D57: 0 | E57: 0 | F57: 0 | G57: 0 | K57: 0 | N57: 0 | O57: 0 | P57: 0 | Q57: 0 | R57: 0 | T57: 0 | X57: 0 | AD57: 0.02
A58: BRAZIMIL CORRIDA BALDE 20KG | B58: 0 | D58: 0 | E58: 0 | F58: 0 | G58: 0 | K58: 0 | N58: 0 | O58: 0 | P58: 0 | Q58: 0 | R58: 0 | T58: 0 | X58: 0 | AD58: 0.02
A59: BRAZIMIL CORRIDA BALDE 25KG | B59: 0 | D59: 0 | E59: 0 | F59: 0 | G59: 0 | K59: 0 | N59: 0 | O59: 0 | P59: 0 | Q59: 0 | R59: 0 | T59: 0 | X59: 0 | AD59: 0.02
A60: BRAZIMIL ACRILICA
A61: BRAZIMIL ACRILICA POTE 1KG | B61: 0 | C61: 0 | D61: 0 | E61: 0 | F61: 0 | G61: 0 | K61: 0 | N61: 0 | O61: 0 | P61: 0 | Q61: 0 | R61: 0 | T61: 0 | X61: 0 | AD61: 0.02
A62: BRAZIMIL ACRILICA GALÃO 5KG | B62: 0 | C62: 0 | D62: 0 | E62: 0 | F62: 0 | G62: 0 | K62: 0 | N62: 0 | O62: 0 | P62: 0 | Q62: 0 | R62: 0 | T62: 0 | X62: 0 | AD62: 0.02
A63: BRAZIMIL ACRILICA SACO VALV 10,0KG | B63: 0 | C63: 0 | D63: 0 | E63: 0 | F63: 0 | G63: 0 | K63: 0 | N63: 0 | O63: 0 | P63: 0 | Q63: 0 | R63: 0 | T63: 0 | X63: 0 | AD63: 0.02
A64: BRAZIMIL ACRILICA PPQ 20KG | B64: 0 | C64: 0 | D64: 0 | E64: 0 | F64: 0 | G64: 0 | K64: 0 | N64: 0 | O64: 0 | P64: 0 | Q64: 0 | R64: 0 | T64: 0 | X64: 0 | AD64: 0.02
A65: BRAZIMIL ACRILICA PPQ 25KG | B65: 0 | C65: 0 | D65: 0 | E65: 0 | F65: 0 | G65: 0 | K65: 0 | N65: 0 | O65: 0 | P65: 0 | Q65: 0 | R65: 0 | T65: 0 | X65: 0 | AD65: 0.02
A66: BRAZIMIL ACRILICA BALDE 20KG | B66: 0 | C66: 0 | D66: 0 | E66: 0 | F66: 0 | G66: 0 | K66: 0 | N66: 0 | O66: 0 | P66: 0 | Q66: 0 | R66: 0 | T66: 0 | X66: 0 | AD66: 0.02
A67: BRAZIMIL ACRILICA BALDE 25KG | B67: 0 | C67: 0 | D67: 0 | E67: 0 | F67: 0 | G67: 0 | K67: 0 | N67: 0 | O67: 0 | P67: 0 | Q67: 0 | R67: 0 | T67: 0 | X67: 0 | AD67: 0.02
A68: BRAZIMIL TEXT. LISA
A69: BRAZIMIL TEXT. LISA GALÃO 5KG | B69: 0 | C69: 0 | D69: 0 | E69: 0 | F69: 0 | G69: 0 | K69: 0 | N69: 0 | O69: 0 | P69: 0 | Q69: 0 | R69: 0 | T69: 0 | X69: 0 | AD69: 0
A70: BRAZIMIL TEXT. LISA SACO VALV 12,5KG | B70: 0 | C70: 0 | D70: 0 | E70: 0 | F70: 0 | G70: 0 | K70: 0 | N70: 0 | O70: 0 | P70: 0 | Q70: 0 | R70: 0 | T70: 0 | X70: 0 | AD70: 0
A71: BRAZIMIL TEXT. LISA PPQ 25KG | B71: 0 | C71: 0 | D71: 0 | E71: 0 | F71: 0 | G71: 0 | K71: 0 | N71: 0 | O71: 0 | P71: 0 | Q71: 0 | R71: 0 | T71: 0 | X71: 0 | AD71: 0
A72: BRAZIMIL TEXT. LISA BALDE 25KG | B72: 0 | C72: 0 | D72: 0 | E72: 0 | F72: 0 | G72: 0 | K72: 0 | N72: 0 | O72: 0 | P72: 0 | Q72: 0 | R72: 0 | T72: 0 | X72: 0 | AD72: 0
A73: BRAZIMIL TEXT. RÚSTICA
A74: BRAZIMIL TEXT. RÚSTICA GALÃO 5KG | B74: 0 | C74: 0 | D74: 0 | E74: 0 | F74: 0 | G74: 0 | K74: 0 | N74: 0 | O74: 0 | P74: 0 | Q74: 0 | R74: 0 | T74: 0 | X74: 0 | AD74: 0
A75: BRAZIMIL TEXT. RÚSTICA SACO VALV 12,5KG | B75: 0 | C75: 0 | D75: 0 | E75: 0 | F75: 0 | G75: 0 | K75: 0 | N75: 0 | O75: 0 | P75: 0 | Q75: 0 | R75: 0 | T75: 0 | X75: 0 | AD75: 0
A76: BRAZIMIL TEXT. RÚSTICA PPQ 25KG | B76: 0 | C76: 0 | D76: 0 | E76: 0 | F76: 0 | G76: 0 | K76: 0 | N76: 0 | O76: 0 | P76: 0 | Q76: 0 | R76: 0 | T76: 0 | X76: 0 | AD76: 0
A77: BRAZIMIL TEXT. RÚSTICA BALDE 25KG | B77: 0 | C77: 0 | D77: 0 | E77: 0 | F77: 0 | G77: 0 | K77: 0 | N77: 0 | O77: 0 | P77: 0 | Q77: 0 | R77: 0 | T77: 0 | X77: 0 | AD77: 0
A78: TINTAS BASE SOLVENTE | N78: 0 | O78: 0
A79: BRAZIMIL ESMALTE SINTÉTICO 0,75L
A80: BRAZIMIL ESMALTE SINTÉTICO 0,75L LATA ALUMÍNIO | B80: 0.485 | D80: 0.4667 | E80: 0.485 | F80: 0.4943 | G80: 0.4943 | K80: 0.5231 | N80: 0.4667 | O80: 0.485 | P80: 0.4943 | Q80: 0.5038 | R80: 0.4488 | T80: 0.4314 | X80: 0.4488 | AD80: 0
A81: BRAZIMIL ESMALTE SINTÉTICO 0,75L LATA BRANCO | B81: 0.485 | D81: 0.4667 | E81: 0.485 | F81: 0.4943 | G81: 0.4943 | K81: 0.5231 | N81: 0.4667 | O81: 0.485 | P81: 0.4943 | Q81: 0.5038 | R81: 0.4488 | T81: 0.4314 | X81: 0.4488 | AD81: 0
A82: BRAZIMIL ESMALTE SINTÉTICO 0,75L LATA PRETO | B82: 0.485 | D82: 0.4667 | E82: 0.485 | F82: 0.4943 | G82: 0.4943 | K82: 0.5231 | N82: 0.4667 | O82: 0.485 | P82: 0.4943 | Q82: 0.5038 | R82: 0.4488 | T82: 0.4314 | X82: 0.4488 | AD82: 0
A83: BRAZIMIL ESMALTE SINTÉTICO 0,75L LATA COR | B83: 0.485 | D83: 0.4667 | E83: 0.485 | F83: 0.4943 | G83: 0.4943 | K83: 0.5231 | N83: 0.4667 | O83: 0.485 | P83: 0.4943 | Q83: 0.5038 | R83: 0.4488 | T83: 0.4314 | X83: 0.4488 | AD83: 0
A84: BRAZIMIL ESMALTE SINTÉTICO 0,75L LATA FOSCO | B84: 0.485 | D84: 0.4667 | E84: 0.485 | F84: 0.4943 | G84: 0.4943 | K84: 0.5231 | N84: 0.4667 | O84: 0.485 | P84: 0.4943 | Q84: 0.5038 | R84: 0.4488 | T84: 0.4314 | X84: 0.4488 | AD84: 0
A85: BRAZIMIL ESMALTE SINTÉTICO 3,0L
A86: BRAZIMIL ESMALTE SINTÉTICO 3,0L LATA ALUMÍNIO | B86: 0.485 | D86: 0.4667 | E86: 0.485 | F86: 0.4943 | G86: 0.4943 | K86: 0.5231 | N86: 0.4667 | O86: 0.485 | P86: 0.4943 | Q86: 0.5038 | R86: 0.4488 | T86: 0.4314 | X86: 0.4488 | AD86: 0
A87: BRAZIMIL ESMALTE SINTÉTICO 3,0L LATA BRANCO | B87: 0.485 | D87: 0.4667 | E87: 0.485 | F87: 0.4943 | G87: 0.4943 | K87: 0.5231 | N87: 0.4667 | O87: 0.485 | P87: 0.4943 | Q87: 0.5038 | R87: 0.4488 | T87: 0.4314 | X87: 0.4488 | AD87: 0
A88: BRAZIMIL ESMALTE SINTÉTICO 3,0L LATA PRETO | B88: 0.485 | D88: 0.4667 | E88: 0.485 | F88: 0.4943 | G88: 0.4943 | K88: 0.5231 | N88: 0.4667 | O88: 0.485 | P88: 0.4943 | Q88: 0.5038 | R88: 0.4488 | T88: 0.4314 | X88: 0.4488 | AD88: 0
A89: BRAZIMIL ESMALTE SINTÉTICO 3,0L LATA COR | B89: 0.485 | D89: 0.4667 | E89: 0.485 | F89: 0.4943 | G89: 0.4943 | K89: 0.5231 | N89: 0.4667 | O89: 0.485 | P89: 0.4943 | Q89: 0.5038 | R89: 0.4488 | T89: 0.4314 | X89: 0.4488 | AD89: 0
A90: BRAZIMIL ESMALTE SINTÉTICO 3,0L LATA FOSCO | B90: 0.485 | D90: 0.4667 | E90: 0.485 | F90: 0.4943 | G90: 0.4943 | K90: 0.5231 | N90: 0.4667 | O90: 0.485 | P90: 0.4943 | Q90: 0.5038 | R90: 0.4488 | T90: 0.4314 | X90: 0.4488 | AD90: 0
A91: BRAZIMIL VERNIZ 0,75L
A92: BRAZIMIL VERNIZ 0,75L LATA INCOLOR | B92: 0.485 | D92: 0.4667 | E92: 0.485 | F92: 0.4943 | G92: 0.4943 | K92: 0.5231 | N92: 0.4667 | O92: 0.485 | P92: 0.4943 | Q92: 0.5038 | R92: 0.4488 | T92: 0.4314 | X92: 0.4488 | AD92: 0
A93: BRAZIMIL VERNIZ 0,75L LATA PIGMENTADO | B93: 0.485 | D93: 0.4667 | E93: 0.485 | F93: 0.4943 | G93: 0.4943 | K93: 0.5231 | N93: 0.4667 | O93: 0.485 | P93: 0.4943 | Q93: 0.5038 | R93: 0.4488 | T93: 0.4314 | X93: 0.4488 | AD93: 0
A94: BRAZIMIL VERNIZ 3,0L
A95: BRAZIMIL VERNIZ 3,0L LATA INCOLOR | B95: 0.485 | D95: 0.4667 | E95: 0.485 | F95: 0.4943 | G95: 0.4943 | K95: 0.5231 | N95: 0.4667 | O95: 0.485 | P95: 0.4943 | Q95: 0.5038 | R95: 0.4488 | T95: 0.4314 | X95: 0.4488 | AD95: 0
A96: BRAZIMIL VERNIZ 3,0L LATA PIGMENTADO | B96: 0.485 | D96: 0.4667 | E96: 0.485 | F96: 0.4943 | G96: 0.4943 | K96: 0.5231 | N96: 0.4667 | O96: 0.485 | P96: 0.4943 | Q96: 0.5038 | R96: 0.4488 | T96: 0.4314 | X96: 0.4488 | AD96: 0
A97: BRAZIMIL ZARCÃO 0,75L
A98: BRAZIMIL ZARCÃO 0,75L LATA BRANCO | B98: 0.485 | D98: 0.4667 | E98: 0.485 | F98: 0.4943 | G98: 0.4943 | K98: 0.5231 | N98: 0.4667 | O98: 0.485 | P98: 0.4943 | Q98: 0.5038 | R98: 0.4488 | T98: 0.4314 | X98: 0.4488 | AD98: 0
A99: BRAZIMIL ZARCÃO 0,75L LATA CINZA | B99: 0.485 | D99: 0.4667 | E99: 0.485 | F99: 0.4943 | G99: 0.4943 | K99: 0.5231 | N99: 0.4667 | O99: 0.485 | P99: 0.4943 | Q99: 0.5038 | R99: 0.4488 | T99: 0.4314 | X99: 0.4488 | AD99: 0
A100: BRAZIMIL ZARCÃO 0,75L LATA COR | B100: 0.485 | D100: 0.4667 | E100: 0.485 | F100: 0.4943 | G100: 0.4943 | K100: 0.5231 | N100: 0.4667 | O100: 0.485 | P100: 0.4943 | Q100: 0.5038 | R100: 0.4488 | T100: 0.4314 | X100: 0.4488 | AD100: 0
A101: BRAZIMIL ZARCÃO 3,0L
A102: BRAZIMIL ZARCÃO 3,0L LATA BRANCO | B102: 0.485 | D102: 0.4667 | E102: 0.485 | F102: 0.4943 | G102: 0.4943 | K102: 0.5231 | N102: 0.4667 | O102: 0.485 | P102: 0.4943 | Q102: 0.5038 | R102: 0.4488 | T102: 0.4314 | X102: 0.4488 | AD102: 0
A103: BRAZIMIL ZARCÃO 3,0L LATA CINZA | B103: 0.485 | D103: 0.4667 | E103: 0.485 | F103: 0.4943 | G103: 0.4943 | K103: 0.5231 | N103: 0.4667 | O103: 0.485 | P103: 0.4943 | Q103: 0.5038 | R103: 0.4488 | T103: 0.4314 | X103: 0.4488 | AD103: 0
A104: BRAZIMIL ZARCÃO 18L LATA COR | B104: 0.485 | D104: 0.4667 | E104: 0.485 | F104: 0.4943 | G104: 0.4943 | K104: 0.5231 | N104: 0.4667 | O104: 0.485 | P104: 0.4943 | Q104: 0.5038 | R104: 0.4488 | T104: 0.4314 | X104: 0.4488 | AD104: 0
A105: BRAZIMIL SELADOR P/ MAD. 0,75L
...
